Workbook

Sheet Read Me
A1: Non-metallic pipes: should-cost model
A2: HDPE PE100, PVC-U, PP-R and CPVC pipe, costed from resin to delivered price. Not a vendor price list: every rate is an editable assumption.
A4: Purpose | B4: Estimate the ex-works plus freight price per metre, per kg and per line of extruded plastic pipe. It follows the structure of the metal-pipe cost model: raw material with yield loss and a scrap credit, conversion, testing, margin, payment interest and logistics.
A5: How to use | B5: Enter up to 12 pipe lines on Inputs (family, outside diameter, rating, length required). Prices, extrusion rates and margins are on Rates; change them to your own. Per-line results and the batch total are on Summary; the row-by-row working is on Calc.
A6: Sheets | B6: Inputs: pipe lines and the line to break down. Summary: results per line, batch value and the cost stack of the chosen line. Calc: the working for each line. Rates: family constants, resin prices, wall tables, logistics. Standards: the sizes and ratings the wall rules cover.
A7: Wall thickness | B7: HDPE and PP-R: wall = OD / SDR. PVC-U: wall = P x OD / (2 x design stress + P), with a design stress of 10 MPa. CPVC: ASTM F441 schedule table. The result is never below the family minimum wall and is rounded up to 0.1 mm.
A8: Cost build-up | B8: Weight per metre = pi/4 x (OD^2 - ID^2) x density. Raw material = weight x (1 + yield loss) x resin price x (1 + additives), less a scrap credit for trimmed material recovered as regrind. Conversion = energy + labour + depreciation + other per kg, with a thick-wall surcharge above 10 mm. Testing per kg. Margin on that base, then interest on the payment period, then logistics priced by truck loading (bulk-limited for large diameters).
A9: Conventions | B9: Yellow fill = input. Blue font = a typed assumption you may change. Black = formula. Green fill = key output. Rupees, ex-GST.
A10: Limits | B10: Straight pipe only: no fittings, sockets, fusion or solvent-weld joints, or installation. Resin prices should follow your own purchase prices or the commodity file (typed here, not linked).
A11: Companion | B11: The same model runs in the Should-Cost dashboards (Pipes, plastic family), with a 3D view and a month selector for resin prices.

Sheet Inputs
A1: Pipe lines
A2: Enter up to 12 lines. Blank lines are ignored.
A4: Description | B4: Family | C4: Outside diameter mm | D4: Rating | E4: Length required m
A5: HDPE 110 SDR 11 | B5: HDPE PE100 | C5: 110 | D5: 11 | E5: 20000
A6: HDPE 315 SDR 17 | B6: HDPE PE100 | C6: 315 | D6: 17 | E6: 4000
A7: PVC-U 110 · 0.6 MPa | B7: PVC-U | C7: 110 | D7: 0.6 | E7: 15000
A8: PVC-U 200 · 0.8 MPa | B8: PVC-U | C8: 200 | D8: 0.8 | E8: 6000
A9: PP-R 32 SDR 7.4 | B9: PP-R | C9: 32 | D9: 7.4 | E9: 8000
A10: CPVC 2" SCH 80 | B10: CPVC | C10: 60.33 | D10: 80 | E10: 3000
A18: Rating: SDR number (HDPE, PP-R), pressure class in MPa (PVC-U), or 40 / 80 (CPVC schedule). See Standards.
A20: Line to break down on Summary (1-12) | B20: 1

Sheet Summary
A1: Non-metallic pipes: summary
A4: Description | B4: Family | C4: OD mm | D4: Rating | E4: Wall mm | F4: kg/m | G4: Rs per m | H4: Rs per kg | I4: Length m | J4: Line value Rs
A5: =IF(Calc!C5="","",Calc!B5) -> HDPE 110 SDR 11 | B5: =IF(Calc!C5="","",Calc!C5) -> HDPE PE100 | C5: =IF(Calc!C5="","",Calc!D5) -> 110 | D5: =IF(Calc!C5="","",Calc!E5) -> 11 | E5: =IF(Calc!C5="","",Calc!G5) -> 10 | F5: =IF(Calc!C5="","",Calc!K5) -> 2.984513 | G5: =IF(Calc!C5="","",Calc!X5) -> 437.13526 | H5: =IF(Calc!C5="","",Calc!Y5) -> 146.46787 | I5: =IF(Calc!C5="","",Calc!F5) -> 20000 | J5: =IF(Calc!C5="","",Calc!AB5) -> 8742705.2
A6: =IF(Calc!C6="","",Calc!B6) -> HDPE 315 SDR 17 | B6: =IF(Calc!C6="","",Calc!C6) -> HDPE PE100 | C6: =IF(Calc!C6="","",Calc!D6) -> 315 | D6: =IF(Calc!C6="","",Calc!E6) -> 17 | E6: =IF(Calc!C6="","",Calc!G6) -> 18.6 | F6: =IF(Calc!C6="","",Calc!K6) -> 16.45374 | G6: =IF(Calc!C6="","",Calc!X6) -> 2461.8489 | H6: =IF(Calc!C6="","",Calc!Y6) -> 149.62245 | I6: =IF(Calc!C6="","",Calc!F6) -> 4000 | J6: =IF(Calc!C6="","",Calc!AB6) -> 9847395.6
A7: =IF(Calc!C7="","",Calc!B7) -> PVC-U 110 · 0.6 MPa | B7: =IF(Calc!C7="","",Calc!C7) -> PVC-U | C7: =IF(Calc!C7="","",Calc!D7) -> 110 | D7: =IF(Calc!C7="","",Calc!E7) -> 0.6 | E7: =IF(Calc!C7="","",Calc!G7) -> 3.3 | F7: =IF(Calc!C7="","",Calc!K7) -> 1.5486607 | G7: =IF(Calc!C7="","",Calc!X7) -> 189.9069 | H7: =IF(Calc!C7="","",Calc!Y7) -> 122.62654 | I7: =IF(Calc!C7="","",Calc!F7) -> 15000 | J7: =IF(Calc!C7="","",Calc!AB7) -> 2848603.5
A8: =IF(Calc!C8="","",Calc!B8) -> PVC-U 200 · 0.8 MPa | B8: =IF(Calc!C8="","",Calc!C8) -> PVC-U | C8: =IF(Calc!C8="","",Calc!D8) -> 200 | D8: =IF(Calc!C8="","",Calc!E8) -> 0.8 | E8: =IF(Calc!C8="","",Calc!G8) -> 7.7 | F8: =IF(Calc!C8="","",Calc!K8) -> 6.5125027 | G8: =IF(Calc!C8="","",Calc!X8) -> 806.39356 | H8: =IF(Calc!C8="","",Calc!Y8) -> 123.82238 | I8: =IF(Calc!C8="","",Calc!F8) -> 6000 | J8: =IF(Calc!C8="","",Calc!AB8) -> 4838361.3
A9: =IF(Calc!C9="","",Calc!B9) -> PP-R 32 SDR 7.4 | B9: =IF(Calc!C9="","",Calc!C9) -> PP-R | C9: =IF(Calc!C9="","",Calc!D9) -> 32 | D9: =IF(Calc!C9="","",Calc!E9) -> 7.4 | E9: =IF(Calc!C9="","",Calc!G9) -> 4.4 | F9: =IF(Calc!C9="","",Calc!K9) -> 0.34336351 | G9: =IF(Calc!C9="","",Calc!X9) -> 62.990062 | H9: =IF(Calc!C9="","",Calc!Y9) -> 183.45008 | I9: =IF(Calc!C9="","",Calc!F9) -> 8000 | J9: =IF(Calc!C9="","",Calc!AB9) -> 503920.5
A10: =IF(Calc!C10="","",Calc!B10) -> CPVC 2" SCH 80 | B10: =IF(Calc!C10="","",Calc!C10) -> CPVC | C10: =IF(Calc!C10="","",Calc!D10) -> 60.33 | D10: =IF(Calc!C10="","",Calc!E10) -> 80 | E10: =IF(Calc!C10="","",Calc!G10) -> 5.6 | F10: =IF(Calc!C10="","",Calc!K10) -> 1.4924337 | G10: =IF(Calc!C10="","",Calc!X10) -> 481.91982 | H10: =IF(Calc!C10="","",Calc!Y10) -> 322.9087 | I10: =IF(Calc!C10="","",Calc!F10) -> 3000 | J10: =IF(Calc!C10="","",Calc!AB10) -> 1445759.5
A11: =IF(Calc!C11="","",Calc!B11) | B11: =IF(Calc!C11="","",Calc!C11) | C11: =IF(Calc!C11="","",Calc!D11) | D11: =IF(Calc!C11="","",Calc!E11) | E11: =IF(Calc!C11="","",Calc!G11) | F11: =IF(Calc!C11="","",Calc!K11) | G11: =IF(Calc!C11="","",Calc!X11) | H11: =IF(Calc!C11="","",Calc!Y11) | I11: =IF(Calc!C11="","",Calc!F11) | J11: =IF(Calc!C11="","",Calc!AB11)
A12: =IF(Calc!C12="","",Calc!B12) | B12: =IF(Calc!C12="","",Calc!C12) | C12: =IF(Calc!C12="","",Calc!D12) | D12: =IF(Calc!C12="","",Calc!E12) | E12: =IF(Calc!C12="","",Calc!G12) | F12: =IF(Calc!C12="","",Calc!K12) | G12: =IF(Calc!C12="","",Calc!X12) | H12: =IF(Calc!C12="","",Calc!Y12) | I12: =IF(Calc!C12="","",Calc!F12) | J12: =IF(Calc!C12="","",Calc!AB12)
A13: =IF(Calc!C13="","",Calc!B13) | B13: =IF(Calc!C13="","",Calc!C13) | C13: =IF(Calc!C13="","",Calc!D13) | D13: =IF(Calc!C13="","",Calc!E13) | E13: =IF(Calc!C13="","",Calc!G13) | F13: =IF(Calc!C13="","",Calc!K13) | G13: =IF(Calc!C13="","",Calc!X13) | H13: =IF(Calc!C13="","",Calc!Y13) | I13: =IF(Calc!C13="","",Calc!F13) | J13: =IF(Calc!C13="","",Calc!AB13)
A14: =IF(Calc!C14="","",Calc!B14) | B14: =IF(Calc!C14="","",Calc!C14) | C14: =IF(Calc!C14="","",Calc!D14) | D14: =IF(Calc!C14="","",Calc!E14) | E14: =IF(Calc!C14="","",Calc!G14) | F14: =IF(Calc!C14="","",Calc!K14) | G14: =IF(Calc!C14="","",Calc!X14) | H14: =IF(Calc!C14="","",Calc!Y14) | I14: =IF(Calc!C14="","",Calc!F14) | J14: =IF(Calc!C14="","",Calc!AB14)
A15: =IF(Calc!C15="","",Calc!B15) | B15: =IF(Calc!C15="","",Calc!C15) | C15: =IF(Calc!C15="","",Calc!D15) | D15: =IF(Calc!C15="","",Calc!E15) | E15: =IF(Calc!C15="","",Calc!G15) | F15: =IF(Calc!C15="","",Calc!K15) | G15: =IF(Calc!C15="","",Calc!X15) | H15: =IF(Calc!C15="","",Calc!Y15) | I15: =IF(Calc!C15="","",Calc!F15) | J15: =IF(Calc!C15="","",Calc!AB15)
A16: =IF(Calc!C16="","",Calc!B16) | B16: =IF(Calc!C16="","",Calc!C16) | C16: =IF(Calc!C16="","",Calc!D16) | D16: =IF(Calc!C16="","",Calc!E16) | E16: =IF(Calc!C16="","",Calc!G16) | F16: =IF(Calc!C16="","",Calc!K16) | G16: =IF(Calc!C16="","",Calc!X16) | H16: =IF(Calc!C16="","",Calc!Y16) | I16: =IF(Calc!C16="","",Calc!F16) | J16: =IF(Calc!C16="","",Calc!AB16)
A17: BATCH TOTAL | I17: =SUM(I5:I16) -> 56000 | J17: =SUM(J5:J16) -> 28226746
A18: Batch value (Rs crore) | J18: =J17/10000000 -> 2.8226746
A19: Weighted average Rs per kg | J19: =IFERROR(J17/SUMPRODUCT(I5:I16,F5:F16),0) -> 144.72704
A21: Cost stack of one line
A22: =IFERROR(INDEX(Calc!B5:B16,i_pick)&" · "&INDEX(Calc!C5:C16,i_pick)&" "&INDEX(Calc!D5:D16,i_pick)&" mm","Pick a filled line number on Inputs") -> HDPE 110 SDR 11 · HDPE PE100 110 mm
A23: Component | B23: Rs per m | C23: Share
A24: Raw material, net of scrap credit | B24: =INDEX(Calc!N5:N16,i_pick)+INDEX(Calc!O5:O16,i_pick) -> 333.65721 | C24: =B24/B30 -> 0.76328141
A25: Conversion | B25: =INDEX(Calc!Q5:Q16,i_pick) -> 40.290926 | C25: =B25/B30 -> 0.092170387
A26: Testing and documentation | B26: =INDEX(Calc!R5:R16,i_pick) -> 8.3566365 | C26: =B26/B30 -> 0.019116821
A27: Margin | B27: =INDEX(Calc!Z5:Z16,i_pick) -> 38.230478 | C27: =B27/B30 -> 0.087456861
A28: Payment interest | B28: =INDEX(Calc!AA5:AA16,i_pick) -> 9.4620432 | C28: =B28/B30 -> 0.021645573
A29: Logistics | B29: =INDEX(Calc!W5:W16,i_pick) -> 7.1379603 | C29: =B29/B30 -> 0.016328951
A30: Total per metre | B30: =SUM(B24:B29) -> 437.13526 | C30: =B30/B30 -> 1
A31: Check against Calc | B31: =IF(ABS(B30-INDEX(Calc!X5:X16,i_pick))<0.0001,"OK","MISMATCH") -> OK
A32: Weight per metre (kg) | B32: =INDEX(Calc!K5:K16,i_pick) -> 2.984513
A33: Wall thickness (mm) | B33: =INDEX(Calc!G5:G16,i_pick) -> 10

Sheet Calc
A1: Working, line by line
A2: Rs per metre unless the heading says otherwise.
A4: # | B4: Description | C4: Family | D4: OD mm | E4: Rating | F4: Qty m | G4: Wall mm | H4: ID mm | I4: Density | J4: Area mm2 | K4: kg/m | L4: Raw kg/m (incl. yield loss) | M4: Compound Rs/kg | N4: Raw material Rs/m | O4: Scrap credit Rs/m | P4: Conv. Rs/kg | Q4: Conversion Rs/m | R4: Testing Rs/m | S4: Base Rs/m | T4: Margin % | U4: Interest % | V4: Load factor | W4: Transport Rs/m | X4: Total Rs/m | Y4: Rs per kg | Z4: Margin Rs/m | AA4: Interest Rs/m | AB4: Line value Rs
A5: =1 -> 1 | B5: =IF(Inputs!A5="","",Inputs!A5) -> HDPE 110 SDR 11 | C5: =IF(Inputs!B5="","",Inputs!B5) -> HDPE PE100 | D5: =IF(Inputs!C5="","",Inputs!C5) -> 110 | E5: =IF(Inputs!D5="","",Inputs!D5) -> 11 | F5: =IF(Inputs!E5="",0,Inputs!E5) -> 20000 | G5: =IF(C5="","",ROUNDUP(MAX(INDEX(r_minWall,MATCH(C5,r_famList,0)),IF(C5="CPVC",INDEX(r_cpvcWall,MATCH(D5,r_cpvcOD,0),IF(E5=40,1,2)),IF(C5="PVC-U",E5*D5/(2*r_stressPvc+E5),D5/E5)))*10-0.000000001,0)/10) -> 10 | H5: =IF(C5="","",D5-2*G5) -> 90 | I5: =IF(C5="","",INDEX(r_rho,MATCH(C5,r_famList,0))) -> 0.95 | J5: =IF(C5="","",PI()/4*(D5^2-H5^2)) -> 3141.5927 | K5: =IF(C5="","",J5*I5/1000) -> 2.984513 | L5: =IF(C5="","",K5*(1+r_yieldLoss)) -> 3.0591258 | M5: =IF(C5="","",INDEX(r_resin,MATCH(C5,r_famList,0))*(1+INDEX(r_add,MATCH(C5,r_famList,0)))) -> 111.24 | N5: =IF(C5="","",L5*M5) -> 340.29716 | O5: =IF(C5="","",-(L5-K5)*M5*r_regrind) -> -6.6399446 | P5: =IF(C5="","",(INDEX(r_energy,MATCH(C5,r_famList,0))+INDEX(r_labour,MATCH(C5,r_famList,0))+INDEX(r_deprec,MATCH(C5,r_famList,0))+INDEX(r_other,MATCH(C5,r_famList,0)))*(1+MAX(0,G5-10)*r_thickPct)) -> 13.5 | Q5: =IF(C5="","",K5*P5) -> 40.290926 | R5: =IF(C5="","",K5*(r_hydro+r_docs)) -> 8.3566365 | S5: =IF(C5="","",N5+O5+Q5+R5) -> 382.30478 | T5: =IF(C5="","",INDEX(r_margin,MATCH(C5,r_famList,0))) -> 0.1 | U5: =IF(C5="","",r_intRate/12*r_months) -> 0.0225 | V5: =IF(C5="","",IF(D5<=r_lf1max,r_lf1,IF(D5<=r_lf2max,r_lf2,r_lf3))) -> 0.6 | W5: =IF(C5="","",r_loading/(V5*1000)*L5) -> 7.1379603 | X5: =IF(C5="","",S5*(1+T5)*(1+U5)+W5) -> 437.13526 | Y5: =IF(C5="","",X5/K5) -> 146.46787 | Z5: =IF(C5="","",S5*T5) -> 38.230478 | AA5: =IF(C5="","",S5*(1+T5)*U5) -> 9.4620432 | AB5: =IF(C5="",0,X5*F5) -> 8742705.2
A6: =2 -> 2 | B6: =IF(Inputs!A6="","",Inputs!A6) -> HDPE 315 SDR 17 | C6: =IF(Inputs!B6="","",Inputs!B6) -> HDPE PE100 | D6: =IF(Inputs!C6="","",Inputs!C6) -> 315 | E6: =IF(Inputs!D6="","",Inputs!D6) -> 17 | F6: =IF(Inputs!E6="",0,Inputs!E6) -> 4000 | G6: =IF(C6="","",ROUNDUP(MAX(INDEX(r_minWall,MATCH(C6,r_famList,0)),IF(C6="CPVC",INDEX(r_cpvcWall,MATCH(D6,r_cpvcOD,0),IF(E6=40,1,2)),IF(C6="PVC-U",E6*D6/(2*r_stressPvc+E6),D6/E6)))*10-0.000000001,0)/10) -> 18.6 | H6: =IF(C6="","",D6-2*G6) -> 277.8 | I6: =IF(C6="","",INDEX(r_rho,MATCH(C6,r_famList,0))) -> 0.95 | J6: =IF(C6="","",PI()/4*(D6^2-H6^2)) -> 17319.726 | K6: =IF(C6="","",J6*I6/1000) -> 16.45374 | L6: =IF(C6="","",K6*(1+r_yieldLoss)) -> 16.865083 | M6: =IF(C6="","",INDEX(r_resin,MATCH(C6,r_famList,0))*(1+INDEX(r_add,MATCH(C6,r_famList,0)))) -> 111.24 | N6: =IF(C6="","",L6*M6) -> 1876.0719 | O6: =IF(C6="","",-(L6-K6)*M6*r_regrind) -> -36.60628 | P6: =IF(C6="","",(INDEX(r_energy,MATCH(C6,r_famList,0))+INDEX(r_labour,MATCH(C6,r_famList,0))+INDEX(r_deprec,MATCH(C6,r_famList,0))+INDEX(r_other,MATCH(C6,r_famList,0)))*(1+MAX(0,G6-10)*r_thickPct)) -> 15.2415 | Q6: =IF(C6="","",K6*P6) -> 250.77967 | R6: =IF(C6="","",K6*(r_hydro+r_docs)) -> 46.070471 | S6: =IF(C6="","",N6+O6+Q6+R6) -> 2136.3157 | T6: =IF(C6="","",INDEX(r_margin,MATCH(C6,r_famList,0))) -> 0.1 | U6: =IF(C6="","",r_intRate/12*r_months) -> 0.0225 | V6: =IF(C6="","",IF(D6<=r_lf1max,r_lf1,IF(D6<=r_lf2max,r_lf2,r_lf3))) -> 0.4 | W6: =IF(C6="","",r_loading/(V6*1000)*L6) -> 59.027791 | X6: =IF(C6="","",S6*(1+T6)*(1+U6)+W6) -> 2461.8489 | Y6: =IF(C6="","",X6/K6) -> 149.62245 | Z6: =IF(C6="","",S6*T6) -> 213.63157 | AA6: =IF(C6="","",S6*(1+T6)*U6) -> 52.873814 | AB6: =IF(C6="",0,X6*F6) -> 9847395.6
A7: =3 -> 3 | B7: =IF(Inputs!A7="","",Inputs!A7) -> PVC-U 110 · 0.6 MPa | C7: =IF(Inputs!B7="","",Inputs!B7) -> PVC-U | D7: =IF(Inputs!C7="","",Inputs!C7) -> 110 | E7: =IF(Inputs!D7="","",Inputs!D7) -> 0.6 | F7: =IF(Inputs!E7="",0,Inputs!E7) -> 15000 | G7: =IF(C7="","",ROUNDUP(MAX(INDEX(r_minWall,MATCH(C7,r_famList,0)),IF(C7="CPVC",INDEX(r_cpvcWall,MATCH(D7,r_cpvcOD,0),IF(E7=40,1,2)),IF(C7="PVC-U",E7*D7/(2*r_stressPvc+E7),D7/E7)))*10-0.000000001,0)/10) -> 3.3 | H7: =IF(C7="","",D7-2*G7) -> 103.4 | I7: =IF(C7="","",INDEX(r_rho,MATCH(C7,r_famList,0))) -> 1.4 | J7: =IF(C7="","",PI()/4*(D7^2-H7^2)) -> 1106.1862 | K7: =IF(C7="","",J7*I7/1000) -> 1.5486607 | L7: =IF(C7="","",K7*(1+r_yieldLoss)) -> 1.5873772 | M7: =IF(C7="","",INDEX(r_resin,MATCH(C7,r_famList,0))*(1+INDEX(r_add,MATCH(C7,r_famList,0)))) -> 91.84 | N7: =IF(C7="","",L7*M7) -> 145.78472 | O7: =IF(C7="","",-(L7-K7)*M7*r_regrind) -> -2.8445799 | P7: =IF(C7="","",(INDEX(r_energy,MATCH(C7,r_famList,0))+INDEX(r_labour,MATCH(C7,r_famList,0))+INDEX(r_deprec,MATCH(C7,r_famList,0))+INDEX(r_other,MATCH(C7,r_famList,0)))*(1+MAX(0,G7-10)*r_thickPct)) -> 11.8 | Q7: =IF(C7="","",K7*P7) -> 18.274196 | R7: =IF(C7="","",K7*(r_hydro+r_docs)) -> 4.3362499 | S7: =IF(C7="","",N7+O7+Q7+R7) -> 165.55059 | T7: =IF(C7="","",INDEX(r_margin,MATCH(C7,r_famList,0))) -> 0.1 | U7: =IF(C7="","",r_intRate/12*r_months) -> 0.0225 | V7: =IF(C7="","",IF(D7<=r_lf1max,r_lf1,IF(D7<=r_lf2max,r_lf2,r_lf3))) -> 0.6 | W7: =IF(C7="","",r_loading/(V7*1000)*L7) -> 3.7038801 | X7: =IF(C7="","",S7*(1+T7)*(1+U7)+W7) -> 189.9069 | Y7: =IF(C7="","",X7/K7) -> 122.62654 | Z7: =IF(C7="","",S7*T7) -> 16.555059 | AA7: =IF(C7="","",S7*(1+T7)*U7) -> 4.097377 | AB7: =IF(C7="",0,X7*F7) -> 2848603.5
A8: =4 -> 4 | B8: =IF(Inputs!A8="","",Inputs!A8) -> PVC-U 200 · 0.8 MPa | C8: =IF(Inputs!B8="","",Inputs!B8) -> PVC-U | D8: =IF(Inputs!C8="","",Inputs!C8) -> 200 | E8: =IF(Inputs!D8="","",Inputs!D8) -> 0.8 | F8: =IF(Inputs!E8="",0,Inputs!E8) -> 6000 | G8: =IF(C8="","",ROUNDUP(MAX(INDEX(r_minWall,MATCH(C8,r_famList,0)),IF(C8="CPVC",INDEX(r_cpvcWall,MATCH(D8,r_cpvcOD,0),IF(E8=40,1,2)),IF(C8="PVC-U",E8*D8/(2*r_stressPvc+E8),D8/E8)))*10-0.000000001,0)/10) -> 7.7 | H8: =IF(C8="","",D8-2*G8) -> 184.6 | I8: =IF(C8="","",INDEX(r_rho,MATCH(C8,r_famList,0))) -> 1.4 | J8: =IF(C8="","",PI()/4*(D8^2-H8^2)) -> 4651.7877 | K8: =IF(C8="","",J8*I8/1000) -> 6.5125027 | L8: =IF(C8="","",K8*(1+r_yieldLoss)) -> 6.6753153 | M8: =IF(C8="","",INDEX(r_resin,MATCH(C8,r_famList,0))*(1+INDEX(r_add,MATCH(C8,r_famList,0)))) -> 91.84 | N8: =IF(C8="","",L8*M8) -> 613.06096 | O8: =IF(C8="","",-(L8-K8)*M8*r_regrind) -> -11.962165 | P8: =IF(C8="","",(INDEX(r_energy,MATCH(C8,r_famList,0))+INDEX(r_labour,MATCH(C8,r_famList,0))+INDEX(r_deprec,MATCH(C8,r_famList,0))+INDEX(r_other,MATCH(C8,r_famList,0)))*(1+MAX(0,G8-10)*r_thickPct)) -> 11.8 | Q8: =IF(C8="","",K8*P8) -> 76.847532 | R8: =IF(C8="","",K8*(r_hydro+r_docs)) -> 18.235008 | S8: =IF(C8="","",N8+O8+Q8+R8) -> 696.18133 | T8: =IF(C8="","",INDEX(r_margin,MATCH(C8,r_famList,0))) -> 0.1 | U8: =IF(C8="","",r_intRate/12*r_months) -> 0.0225 | V8: =IF(C8="","",IF(D8<=r_lf1max,r_lf1,IF(D8<=r_lf2max,r_lf2,r_lf3))) -> 0.4 | W8: =IF(C8="","",r_loading/(V8*1000)*L8) -> 23.363604 | X8: =IF(C8="","",S8*(1+T8)*(1+U8)+W8) -> 806.39356 | Y8: =IF(C8="","",X8/K8) -> 123.82238 | Z8: =IF(C8="","",S8*T8) -> 69.618133 | AA8: =IF(C8="","",S8*(1+T8)*U8) -> 17.230488 | AB8: =IF(C8="",0,X8*F8) -> 4838361.3
A9: =5 -> 5 | B9: =IF(Inputs!A9="","",Inputs!A9) -> PP-R 32 SDR 7.4 | C9: =IF(Inputs!B9="","",Inputs!B9) -> PP-R | D9: =IF(Inputs!C9="","",Inputs!C9) -> 32 | E9: =IF(Inputs!D9="","",Inputs!D9) -> 7.4 | F9: =IF(Inputs!E9="",0,Inputs!E9) -> 8000 | G9: =IF(C9="","",ROUNDUP(MAX(INDEX(r_minWall,MATCH(C9,r_famList,0)),IF(C9="CPVC",INDEX(r_cpvcWall,MATCH(D9,r_cpvcOD,0),IF(E9=40,1,2)),IF(C9="PVC-U",E9*D9/(2*r_stressPvc+E9),D9/E9)))*10-0.000000001,0)/10) -> 4.4 | H9: =IF(C9="","",D9-2*G9) -> 23.2 | I9: =IF(C9="","",INDEX(r_rho,MATCH(C9,r_famList,0))) -> 0.9 | J9: =IF(C9="","",PI()/4*(D9^2-H9^2)) -> 381.51501 | K9: =IF(C9="","",J9*I9/1000) -> 0.34336351 | L9: =IF(C9="","",K9*(1+r_yieldLoss)) -> 0.3519476 | M9: =IF(C9="","",INDEX(r_resin,MATCH(C9,r_famList,0))*(1+INDEX(r_add,MATCH(C9,r_famList,0)))) -> 140.4 | N9: =IF(C9="","",L9*M9) -> 49.413443 | O9: =IF(C9="","",-(L9-K9)*M9*r_regrind) -> -0.96416474 | P9: =IF(C9="","",(INDEX(r_energy,MATCH(C9,r_famList,0))+INDEX(r_labour,MATCH(C9,r_famList,0))+INDEX(r_deprec,MATCH(C9,r_famList,0))+INDEX(r_other,MATCH(C9,r_famList,0)))*(1+MAX(0,G9-10)*r_thickPct)) -> 14.2 | Q9: =IF(C9="","",K9*P9) -> 4.8757619 | R9: =IF(C9="","",K9*(r_hydro+r_docs)) -> 0.96141783 | S9: =IF(C9="","",N9+O9+Q9+R9) -> 54.286458 | T9: =IF(C9="","",INDEX(r_margin,MATCH(C9,r_famList,0))) -> 0.12 | U9: =IF(C9="","",r_intRate/12*r_months) -> 0.0225 | V9: =IF(C9="","",IF(D9<=r_lf1max,r_lf1,IF(D9<=r_lf2max,r_lf2,r_lf3))) -> 0.6 | W9: =IF(C9="","",r_loading/(V9*1000)*L9) -> 0.82121106 | X9: =IF(C9="","",S9*(1+T9)*(1+U9)+W9) -> 62.990062 | Y9: =IF(C9="","",X9/K9) -> 183.45008 | Z9: =IF(C9="","",S9*T9) -> 6.5143749 | AA9: =IF(C9="","",S9*(1+T9)*U9) -> 1.3680187 | AB9: =IF(C9="",0,X9*F9) -> 503920.5
A10: =6 -> 6 | B10: =IF(Inputs!A10="","",Inputs!A10) -> CPVC 2" SCH 80 | C10: =IF(Inputs!B10="","",Inputs!B10) -> CPVC | D10: =IF(Inputs!C10="","",Inputs!C10) -> 60.33 | E10: =IF(Inputs!D10="","",Inputs!D10) -> 80 | F10: =IF(Inputs!E10="",0,Inputs!E10) -> 3000 | G10: =IF(C10="","",ROUNDUP(MAX(INDEX(r_minWall,MATCH(C10,r_famList,0)),IF(C10="CPVC",INDEX(r_cpvcWall,MATCH(D10,r_cpvcOD,0),IF(E10=40,1,2)),IF(C10="PVC-U",E10*D10/(2*r_stressPvc+E10),D10/E10)))*10-0.000000001,0)/10) -> 5.6 | H10: =IF(C10="","",D10-2*G10) -> 49.13 | I10: =IF(C10="","",INDEX(r_rho,MATCH(C10,r_famList,0))) -> 1.55 | J10: =IF(C10="","",PI()/4*(D10^2-H10^2)) -> 962.86045 | K10: =IF(C10="","",J10*I10/1000) -> 1.4924337 | L10: =IF(C10="","",K10*(1+r_yieldLoss)) -> 1.5297445 | M10: =IF(C10="","",INDEX(r_resin,MATCH(C10,r_famList,0))*(1+INDEX(r_add,MATCH(C10,r_famList,0)))) -> 253.7 | N10: =IF(C10="","",L10*M10) -> 388.09619 | O10: =IF(C10="","",-(L10-K10)*M10*r_regrind) -> -7.5726086 | P10: =IF(C10="","",(INDEX(r_energy,MATCH(C10,r_famList,0))+INDEX(r_labour,MATCH(C10,r_famList,0))+INDEX(r_deprec,MATCH(C10,r_famList,0))+INDEX(r_other,MATCH(C10,r_famList,0)))*(1+MAX(0,G10-10)*r_thickPct)) -> 17.2 | Q10: =IF(C10="","",K10*P10) -> 25.66986 | R10: =IF(C10="","",K10*(r_hydro+r_docs)) -> 4.1788143 | S10: =IF(C10="","",N10+O10+Q10+R10) -> 410.37225 | T10: =IF(C10="","",INDEX(r_margin,MATCH(C10,r_famList,0))) -> 0.14 | U10: =IF(C10="","",r_intRate/12*r_months) -> 0.0225 | V10: =IF(C10="","",IF(D10<=r_lf1max,r_lf1,IF(D10<=r_lf2max,r_lf2,r_lf3))) -> 0.6 | W10: =IF(C10="","",r_loading/(V10*1000)*L10) -> 3.5694039 | X10: =IF(C10="","",S10*(1+T10)*(1+U10)+W10) -> 481.91982 | Y10: =IF(C10="","",X10/K10) -> 322.9087 | Z10: =IF(C10="","",S10*T10) -> 57.452116 | AA10: =IF(C10="","",S10*(1+T10)*U10) -> 10.526048 | AB10: =IF(C10="",0,X10*F10) -> 1445759.5
A11: =7 -> 7 | B11: =IF(Inputs!A11="","",Inputs!A11) | C11: =IF(Inputs!B11="","",Inputs!B11) | D11: =IF(Inputs!C11="","",Inputs!C11) | E11: =IF(Inputs!D11="","",Inputs!D11) | F11: =IF(Inputs!E11="",0,Inputs!E11) -> 0 | G11: =IF(C11="","",ROUNDUP(MAX(INDEX(r_minWall,MATCH(C11,r_famList,0)),IF(C11="CPVC",INDEX(r_cpvcWall,MATCH(D11,r_cpvcOD,0),IF(E11=40,1,2)),IF(C11="PVC-U",E11*D11/(2*r_stressPvc+E11),D11/E11)))*10-0.000000001,0)/10) | H11: =IF(C11="","",D11-2*G11) | I11: =IF(C11="","",INDEX(r_rho,MATCH(C11,r_famList,0))) | J11: =IF(C11="","",PI()/4*(D11^2-H11^2)) | K11: =IF(C11="","",J11*I11/1000) | L11: =IF(C11="","",K11*(1+r_yieldLoss)) | M11: =IF(C11="","",INDEX(r_resin,MATCH(C11,r_famList,0))*(1+INDEX(r_add,MATCH(C11,r_famList,0)))) | N11: =IF(C11="","",L11*M11) | O11: =IF(C11="","",-(L11-K11)*M11*r_regrind) | P11: =IF(C11="","",(INDEX(r_energy,MATCH(C11,r_famList,0))+INDEX(r_labour,MATCH(C11,r_famList,0))+INDEX(r_deprec,MATCH(C11,r_famList,0))+INDEX(r_other,MATCH(C11,r_famList,0)))*(1+MAX(0,G11-10)*r_thickPct)) | Q11: =IF(C11="","",K11*P11) | R11: =IF(C11="","",K11*(r_hydro+r_docs)) | S11: =IF(C11="","",N11+O11+Q11+R11) | T11: =IF(C11="","",INDEX(r_margin,MATCH(C11,r_famList,0))) | U11: =IF(C11="","",r_intRate/12*r_months) | V11: =IF(C11="","",IF(D11<=r_lf1max,r_lf1,IF(D11<=r_lf2max,r_lf2,r_lf3))) | W11: =IF(C11="","",r_loading/(V11*1000)*L11) | X11: =IF(C11="","",S11*(1+T11)*(1+U11)+W11) | Y11: =IF(C11="","",X11/K11) | Z11: =IF(C11="","",S11*T11) | AA11: =IF(C11="","",S11*(1+T11)*U11) | AB11: =IF(C11="",0,X11*F11) -> 0
A12: =8 -> 8 | B12: =IF(Inputs!A12="","",Inputs!A12) | C12: =IF(Inputs!B12="","",Inputs!B12) | D12: =IF(Inputs!C12="","",Inputs!C12) | E12: =IF(Inputs!D12="","",Inputs!D12) | F12: =IF(Inputs!E12="",0,Inputs!E12) -> 0 | G12: =IF(C12="","",ROUNDUP(MAX(INDEX(r_minWall,MATCH(C12,r_famList,0)),IF(C12="CPVC",INDEX(r_cpvcWall,MATCH(D12,r_cpvcOD,0),IF(E12=40,1,2)),IF(C12="PVC-U",E12*D12/(2*r_stressPvc+E12),D12/E12)))*10-0.000000001,0)/10) | H12: =IF(C12="","",D12-2*G12) | I12: =IF(C12="","",INDEX(r_rho,MATCH(C12,r_famList,0))) | J12: =IF(C12="","",PI()/4*(D12^2-H12^2)) | K12: =IF(C12="","",J12*I12/1000) | L12: =IF(C12="","",K12*(1+r_yieldLoss)) | M12: =IF(C12="","",INDEX(r_resin,MATCH(C12,r_famList,0))*(1+INDEX(r_add,MATCH(C12,r_famList,0)))) | N12: =IF(C12="","",L12*M12) | O12: =IF(C12="","",-(L12-K12)*M12*r_regrind) | P12: =IF(C12="","",(INDEX(r_energy,MATCH(C12,r_famList,0))+INDEX(r_labour,MATCH(C12,r_famList,0))+INDEX(r_deprec,MATCH(C12,r_famList,0))+INDEX(r_other,MATCH(C12,r_famList,0)))*(1+MAX(0,G12-10)*r_thickPct)) | Q12: =IF(C12="","",K12*P12) | R12: =IF(C12="","",K12*(r_hydro+r_docs)) | S12: =IF(C12="","",N12+O12+Q12+R12) | T12: =IF(C12="","",INDEX(r_margin,MATCH(C12,r_famList,0))) | U12: =IF(C12="","",r_intRate/12*r_months) | V12: =IF(C12="","",IF(D12<=r_lf1max,r_lf1,IF(D12<=r_lf2max,r_lf2,r_lf3))) | W12: =IF(C12="","",r_loading/(V12*1000)*L12) | X12: =IF(C12="","",S12*(1+T12)*(1+U12)+W12) | Y12: =IF(C12="","",X12/K12) | Z12: =IF(C12="","",S12*T12) | AA12: =IF(C12="","",S12*(1+T12)*U12) | AB12: =IF(C12="",0,X12*F12) -> 0
A13: =9 -> 9 | B13: =IF(Inputs!A13="","",Inputs!A13) | C13: =IF(Inputs!B13="","",Inputs!B13) | D13: =IF(Inputs!C13="","",Inputs!C13) | E13: =IF(Inputs!D13="","",Inputs!D13) | F13: =IF(Inputs!E13="",0,Inputs!E13) -> 0 | G13: =IF(C13="","",ROUNDUP(MAX(INDEX(r_minWall,MATCH(C13,r_famList,0)),IF(C13="CPVC",INDEX(r_cpvcWall,MATCH(D13,r_cpvcOD,0),IF(E13=40,1,2)),IF(C13="PVC-U",E13*D13/(2*r_stressPvc+E13),D13/E13)))*10-0.000000001,0)/10) | H13: =IF(C13="","",D13-2*G13) | I13: =IF(C13="","",INDEX(r_rho,MATCH(C13,r_famList,0))) | J13: =IF(C13="","",PI()/4*(D13^2-H13^2)) | K13: =IF(C13="","",J13*I13/1000) | L13: =IF(C13="","",K13*(1+r_yieldLoss)) | M13: =IF(C13="","",INDEX(r_resin,MATCH(C13,r_famList,0))*(1+INDEX(r_add,MATCH(C13,r_famList,0)))) | N13: =IF(C13="","",L13*M13) | O13: =IF(C13="","",-(L13-K13)*M13*r_regrind) | P13: =IF(C13="","",(INDEX(r_energy,MATCH(C13,r_famList,0))+INDEX(r_labour,MATCH(C13,r_famList,0))+INDEX(r_deprec,MATCH(C13,r_famList,0))+INDEX(r_other,MATCH(C13,r_famList,0)))*(1+MAX(0,G13-10)*r_thickPct)) | Q13: =IF(C13="","",K13*P13) | R13: =IF(C13="","",K13*(r_hydro+r_docs)) | S13: =IF(C13="","",N13+O13+Q13+R13) | T13: =IF(C13="","",INDEX(r_margin,MATCH(C13,r_famList,0))) | U13: =IF(C13="","",r_intRate/12*r_months) | V13: =IF(C13="","",IF(D13<=r_lf1max,r_lf1,IF(D13<=r_lf2max,r_lf2,r_lf3))) | W13: =IF(C13="","",r_loading/(V13*1000)*L13) | X13: =IF(C13="","",S13*(1+T13)*(1+U13)+W13) | Y13: =IF(C13="","",X13/K13) | Z13: =IF(C13="","",S13*T13) | AA13: =IF(C13="","",S13*(1+T13)*U13) | AB13: =IF(C13="",0,X13*F13) -> 0
A14: =10 -> 10 | B14: =IF(Inputs!A14="","",Inputs!A14) | C14: =IF(Inputs!B14="","",Inputs!B14) | D14: =IF(Inputs!C14="","",Inputs!C14) | E14: =IF(Inputs!D14="","",Inputs!D14) | F14: =IF(Inputs!E14="",0,Inputs!E14) -> 0 | G14: =IF(C14="","",ROUNDUP(MAX(INDEX(r_minWall,MATCH(C14,r_famList,0)),IF(C14="CPVC",INDEX(r_cpvcWall,MATCH(D14,r_cpvcOD,0),IF(E14=40,1,2)),IF(C14="PVC-U",E14*D14/(2*r_stressPvc+E14),D14/E14)))*10-0.000000001,0)/10) | H14: =IF(C14="","",D14-2*G14) | I14: =IF(C14="","",INDEX(r_rho,MATCH(C14,r_famList,0))) | J14: =IF(C14="","",PI()/4*(D14^2-H14^2)) | K14: =IF(C14="","",J14*I14/1000) | L14: =IF(C14="","",K14*(1+r_yieldLoss)) | M14: =IF(C14="","",INDEX(r_resin,MATCH(C14,r_famList,0))*(1+INDEX(r_add,MATCH(C14,r_famList,0)))) | N14: =IF(C14="","",L14*M14) | O14: =IF(C14="","",-(L14-K14)*M14*r_regrind) | P14: =IF(C14="","",(INDEX(r_energy,MATCH(C14,r_famList,0))+INDEX(r_labour,MATCH(C14,r_famList,0))+INDEX(r_deprec,MATCH(C14,r_famList,0))+INDEX(r_other,MATCH(C14,r_famList,0)))*(1+MAX(0,G14-10)*r_thickPct)) | Q14: =IF(C14="","",K14*P14) | R14: =IF(C14="","",K14*(r_hydro+r_docs)) | S14: =IF(C14="","",N14+O14+Q14+R14) | T14: =IF(C14="","",INDEX(r_margin,MATCH(C14,r_famList,0))) | U14: =IF(C14="","",r_intRate/12*r_months) | V14: =IF(C14="","",IF(D14<=r_lf1max,r_lf1,IF(D14<=r_lf2max,r_lf2,r_lf3))) | W14: =IF(C14="","",r_loading/(V14*1000)*L14) | X14: =IF(C14="","",S14*(1+T14)*(1+U14)+W14) | Y14: =IF(C14="","",X14/K14) | Z14: =IF(C14="","",S14*T14) | AA14: =IF(C14="","",S14*(1+T14)*U14) | AB14: =IF(C14="",0,X14*F14) -> 0
A15: =11 -> 11 | B15: =IF(Inputs!A15="","",Inputs!A15) | C15: =IF(Inputs!B15="","",Inputs!B15) | D15: =IF(Inputs!C15="","",Inputs!C15) | E15: =IF(Inputs!D15="","",Inputs!D15) | F15: =IF(Inputs!E15="",0,Inputs!E15) -> 0 | G15: =IF(C15="","",ROUNDUP(MAX(INDEX(r_minWall,MATCH(C15,r_famList,0)),IF(C15="CPVC",INDEX(r_cpvcWall,MATCH(D15,r_cpvcOD,0),IF(E15=40,1,2)),IF(C15="PVC-U",E15*D15/(2*r_stressPvc+E15),D15/E15)))*10-0.000000001,0)/10) | H15: =IF(C15="","",D15-2*G15) | I15: =IF(C15="","",INDEX(r_rho,MATCH(C15,r_famList,0))) | J15: =IF(C15="","",PI()/4*(D15^2-H15^2)) | K15: =IF(C15="","",J15*I15/1000) | L15: =IF(C15="","",K15*(1+r_yieldLoss)) | M15: =IF(C15="","",INDEX(r_resin,MATCH(C15,r_famList,0))*(1+INDEX(r_add,MATCH(C15,r_famList,0)))) | N15: =IF(C15="","",L15*M15) | O15: =IF(C15="","",-(L15-K15)*M15*r_regrind) | P15: =IF(C15="","",(INDEX(r_energy,MATCH(C15,r_famList,0))+INDEX(r_labour,MATCH(C15,r_famList,0))+INDEX(r_deprec,MATCH(C15,r_famList,0))+INDEX(r_other,MATCH(C15,r_famList,0)))*(1+MAX(0,G15-10)*r_thickPct)) | Q15: =IF(C15="","",K15*P15) | R15: =IF(C15="","",K15*(r_hydro+r_docs)) | S15: =IF(C15="","",N15+O15+Q15+R15) | T15: =IF(C15="","",INDEX(r_margin,MATCH(C15,r_famList,0))) | U15: =IF(C15="","",r_intRate/12*r_months) | V15: =IF(C15="","",IF(D15<=r_lf1max,r_lf1,IF(D15<=r_lf2max,r_lf2,r_lf3))) | W15: =IF(C15="","",r_loading/(V15*1000)*L15) | X15: =IF(C15="","",S15*(1+T15)*(1+U15)+W15) | Y15: =IF(C15="","",X15/K15) | Z15: =IF(C15="","",S15*T15) | AA15: =IF(C15="","",S15*(1+T15)*U15) | AB15: =IF(C15="",0,X15*F15) -> 0
A16: =12 -> 12 | B16: =IF(Inputs!A16="","",Inputs!A16) | C16: =IF(Inputs!B16="","",Inputs!B16) | D16: =IF(Inputs!C16="","",Inputs!C16) | E16: =IF(Inputs!D16="","",Inputs!D16) | F16: =IF(Inputs!E16="",0,Inputs!E16) -> 0 | G16: =IF(C16="","",ROUNDUP(MAX(INDEX(r_minWall,MATCH(C16,r_famList,0)),IF(C16="CPVC",INDEX(r_cpvcWall,MATCH(D16,r_cpvcOD,0),IF(E16=40,1,2)),IF(C16="PVC-U",E16*D16/(2*r_stressPvc+E16),D16/E16)))*10-0.000000001,0)/10) | H16: =IF(C16="","",D16-2*G16) | I16: =IF(C16="","",INDEX(r_rho,MATCH(C16,r_famList,0))) | J16: =IF(C16="","",PI()/4*(D16^2-H16^2)) | K16: =IF(C16="","",J16*I16/1000) | L16: =IF(C16="","",K16*(1+r_yieldLoss)) | M16: =IF(C16="","",INDEX(r_resin,MATCH(C16,r_famList,0))*(1+INDEX(r_add,MATCH(C16,r_famList,0)))) | N16: =IF(C16="","",L16*M16) | O16: =IF(C16="","",-(L16-K16)*M16*r_regrind) | P16: =IF(C16="","",(INDEX(r_energy,MATCH(C16,r_famList,0))+INDEX(r_labour,MATCH(C16,r_famList,0))+INDEX(r_deprec,MATCH(C16,r_famList,0))+INDEX(r_other,MATCH(C16,r_famList,0)))*(1+MAX(0,G16-10)*r_thickPct)) | Q16: =IF(C16="","",K16*P16) | R16: =IF(C16="","",K16*(r_hydro+r_docs)) | S16: =IF(C16="","",N16+O16+Q16+R16) | T16: =IF(C16="","",INDEX(r_margin,MATCH(C16,r_famList,0))) | U16: =IF(C16="","",r_intRate/12*r_months) | V16: =IF(C16="","",IF(D16<=r_lf1max,r_lf1,IF(D16<=r_lf2max,r_lf2,r_lf3))) | W16: =IF(C16="","",r_loading/(V16*1000)*L16) | X16: =IF(C16="","",S16*(1+T16)*(1+U16)+W16) | Y16: =IF(C16="","",X16/K16) | Z16: =IF(C16="","",S16*T16) | AA16: =IF(C16="","",S16*(1+T16)*U16) | AB16: =IF(C16="",0,X16*F16) -> 0

Sheet Rates
A1: Rates and constants
A2: Blue = assumption. Each value is a named cell (r_...).
A4: Family | B4: Density g/cm3 | C4: Resin Rs/kg | D4: Additives % of resin | E4: Minimum wall mm | F4: Energy Rs/kg | G4: Labour Rs/kg | H4: Depreciation Rs/kg | I4: Other Rs/kg | J4: Margin
A5: HDPE PE100 | B5: 0.95 | C5: 108 | D5: 0.03 | E5: 2 | F5: 3.6 | G5: 3.2 | H5: 4.5 | I5: 2.2 | J5: 0.1
A6: PVC-U | B6: 1.4 | C6: 82 | D6: 0.12 | E6: 1.6 | F6: 2.8 | G6: 3 | H6: 4 | I6: 2 | J6: 0.1
A7: PP-R | B7: 0.9 | C7: 135 | D7: 0.04 | E7: 1.9 | F7: 3.4 | G7: 3.4 | H7: 5 | I7: 2.4 | J7: 0.12
A8: CPVC | B8: 1.55 | C8: 215 | D8: 0.18 | E8: 1.5 | F8: 4.2 | G8: 4 | H8: 6 | I8: 3 | J8: 0.14
A10: Process constants
A11: PVC-U design stress | B11: 10 | C11: MPa
A12: Yield loss (start-up and trim scrap) | B12: 0.025 | C12: of weight
A13: Value recovered from scrap as regrind | B13: 0.8 | C13: of scrap value
A14: Thick-wall conversion surcharge per mm above 10 mm | B14: 0.015
A15: Hydro-test | B15: 0.8 | C15: Rs/kg
A16: Documentation and inspection | B16: 2 | C16: Rs/kg
A17: Payment period | B17: 3 | C17: months
A18: Interest rate | B18: 0.09 | C18: per year
A19: Logistics
A20: Loading and freight | B20: 1400 | C20: Rs per tonne of truck capacity
A21: Outside diameter up to (class 1) | B21: 110 | C21: mm
A22: Truck loading factor, class 1 | B22: 0.6
A23: Outside diameter up to (class 2) | B23: 315 | C23: mm
A24: Truck loading factor, class 2 | B24: 0.4
A25: Truck loading factor, larger pipes | B25: 0.25
A27: CPVC wall thickness (ASTM F441), mm
A28: Outside diameter mm | B28: NPS | C28: SCH 40 | D28: SCH 80
A29: 21.34 | B29: 1/2" | C29: 2.77 | D29: 3.73
A30: 26.67 | B30: 3/4" | C30: 2.87 | D30: 3.91
A31: 33.4 | B31: 1" | C31: 3.38 | D31: 4.55
A32: 42.16 | B32: 1 1/4" | C32: 3.56 | D32: 4.85
A33: 48.26 | B33: 1 1/2" | C33: 3.68 | D33: 5.08
A34: 60.33 | B34: 2" | C34: 3.91 | D34: 5.54
A35: 73.03 | B35: 2 1/2" | C35: 5.16 | D35: 7.01
A36: 88.9 | B36: 3" | C36: 5.49 | D36: 7.62
A37: 114.3 | B37: 4" | C37: 6.02 | D37: 8.56

Sheet Standards
A1: Sizes and ratings covered
A4: Family | B4: Standard | C4: Outside diameters (mm) and rating to enter
A5: HDPE PE100 | B5: IS 4984 / ISO 4427 | C5: 20, 25, 32, 40, 50, 63, 75, 90, 110, 125, 140, 160, 180, 200, 225, 250, 280, 315, 355, 400, 450, 500, 560, 630. Rating: SDR 33, 26, 21, 17, 13.6, 11, 9, 7.4 (enter the number)
A6: PVC-U | B6: IS 4985 | C6: 63, 75, 90, 110, 125, 140, 160, 180, 200, 225, 250, 280, 315, 355, 400. Rating: Pressure class in MPa: 0.25, 0.4, 0.6, 0.8, 1.0, 1.25
A7: PP-R | B7: DIN 8077 / IS 15801 | C7: 20, 25, 32, 40, 50, 63, 75, 90, 110. Rating: SDR 11 (PN 10), 7.4 (PN 16), 6 (PN 20) (enter the number)
A8: CPVC | B8: ASTM F441 (IPS) | C8: 21.34, 26.67, 33.4, 42.16, 48.26, 60.33, 73.03, 88.9, 114.3. Rating: Schedule 40 or 80 (enter 40 or 80)
