Workbook
Name IQ_CH: 110000
Name IQ_CQ: 5000
Name IQ_CY: 10000
Name IQ_DAILY: 500000
Name IQ_FH: 100000
Name IQ_FQ: 500
Name IQ_FY: 1000
Name IQ_LTM: 2000
Name IQ_MONTH: 15000
Name IQ_NTM: 6000
Name IQ_WEEK: 50000
Name IQ_YTD: 3000

Sheet Summary
C2: Category | D2: Total INR Cr. (as per cost model)
B3: A | C3: Ladder type, perforated type & U-shaped troughs | D3: =SUM('Cable Tray & Accessories'!F8:F17)/10^7 -> 14.100601
B4: B | C4: Bend, TEE & Reducer | D4: =SUM('Cable Tray & Accessories'!F20:F37)/10^7 -> 0.071049789
B5: C | C5: Channel & Cantilever Arm | D5: =SUM('Cable Tray & Accessories'!F39:F43)/10^7 -> 2.7241413
C6: Total | D6: =SUM(D3:D5) -> 16.895792

Sheet Cable Tray & Accessories
A1: 3X800MW NTPC Nabinagar Thermal Project at Bihar State
A2: Supply of Cable Trays & Accessories
A3: Price Schedule
A4: S.No | B4: Item Description | C4: UOM | D4: Total Qty | E4: Unit FOR Rate | F4: Total FOR Value | G4: Remarks
B5: Lump sum price for the design , manufacture, testing at manufacturers works & delivery including packing, transportation to site of the Cable trays & Accessories
A6: A | B6: Cable Tray
A7: A1 | B7: Cable Tray - Ladder Type
A8: i | B8: 600 mm(Wide), 100mm(Height), 2mm(Thickness) | C8: KM | D8: 107 | E8: ='Ladder 600x100x2'!D113*1000 -> 845424.63 | F8: =D8*E8 -> 90460435
A9: II | B9: 300 mm(Wide), 100mm(Height), 2mm(Thickness) | C9: KM | D9: 20 | E9: ='Ladder 300x100x2'!D113*1000 -> 679444.46 | F9: =D9*E9 -> 13588889
A10: iii | B10: 150 mm(Wide), 100mm(Height), 2mm(Thickness) | C10: KM | D10: 8 | E10: ='Ladder 150x100x2'!D113*1000 -> 596454.38 | F10: =D10*E10 -> 4771635
A11: A2 | B11: Cable Tray - Perforated Type
A12: i | B12: 600 mm(Wide), 100mm(Height), 2mm(Thickness) | C12: KM | D12: 13.5 | E12: ='Perforated 600x100x2'!D93*1000 -> 1519478.6 | F12: =D12*E12 -> 20512961
A13: II | B13: 300 mm(Wide), 100mm(Height), 2mm(Thickness) | C13: KM | D13: 5 | E13: ='Perforated 300x100x2'!D93*1000 -> 978059.14 | F13: =D13*E13 -> 4890295.7
A14: iii | B14: 150 mm(Wide), 100mm(Height), 2mm(Thickness) | C14: KM | D14: 5 | E14: ='Perforated 150x100x2'!D93*1000 -> 653207.48 | F14: =D14*E14 -> 3266037.4
A15: A3 | B15: Cable Tray - Troughs, U-Shaped
A16: i | B16: 75 mm(Wide), 25mm(Depth), 2mm(Thickness) | C16: KM | D16: 8 | E16: ='U Trough 75x25x2'!D93*1000 -> 242294 | F16: =D16*E16 -> 1938352
A17: II | B17: 50 mm(Wide), 25mm(Depth), 2mm(Thickness) | C17: KM | D17: 8 | E17: ='U Trough 50x25x2'!D93*1000 -> 197175.71 | F17: =D17*E17 -> 1577405.7
A18: B | B18: Cable Tray - Bend, TEE & Reducer
A19: B1 | B19: Ladder Type Horizontal Bend 90deg Bending Radius 1200mm
A20: i | B20: 600 mm (Wide) - 2.36 m (Approx), 100mm(Height), 2mm(Thickness) | C20: No | D20: 50 | E20: ='H Bend 600x100x2'!D112 -> 1959.6243 | F20: =D20*E20 -> 97981.216
A21: II | B21: 300 mm (Wide) - 2.36 m (Approx), 100mm(Height), 2mm(Thickness) | C21: No | D21: 25 | E21: ='H Bend 300x100x2'!D112 -> 1586.169 | F21: =D21*E21 -> 39654.224
A22: iii | B22: 150 mm (Wide) - 2.12 m (Approx), 100mm(Height), 2mm(Thickness) | C22: No | D22: 25 | E22: ='H Bend 150x100x2'!D112 -> 1399.4413 | F22: =D22*E22 -> 34986.032
A23: B2 | B23: Ladder Type Vertical Bend - 90deg (UP) Bending Radius 1050mm
A24: i | B24: 600 mm (Wide) - 1.9 m (Approx), 100mm(Height), 2mm(Thickness) | C24: No | D24: 25 | E24: ='Vertical bend up 600x100x2'!D112 -> 1654.6227 | F24: =D24*E24 -> 41365.569
A25: II | B25: 300 mm (Wide) - 1.9 m (Approx), 100mm(Height), 2mm(Thickness) | C25: No | D25: 13 | E25: ='Vertical bend up 300x100x2'!D112 -> 1322.6624 | F25: =D25*E25 -> 17194.611
A26: iii | B26: 150 mm (Wide) - 1.9 m (Approx), 100mm(Height), 2mm(Thickness) | C26: No | D26: 13 | E26: ='Vertical bend up 150x100x2'!D112 -> 1156.6822 | F26: =D26*E26 -> 15036.869
A27: B3 | B27: Ladder Type Vertical Bend - 90deg (Down) Bending Radius 1050mm
A28: i | B28: 600 mm (Wide) - 1.9 m (Approx), 100mm(Height), 2mm(Thickness) | C28: No | D28: 25 | E28: ='Vertical bend down 600x100x2'!D112 -> 1654.6227 | F28: =D28*E28 -> 41365.569
A29: II | B29: 300 mm (Wide) - 1.9 m (Approx), 100mm(Height), 2mm(Thickness) | C29: No | D29: 12 | E29: ='Vertical bend down 300x100x2'!D112 -> 1322.6624 | F29: =D29*E29 -> 15871.949
A30: iii | B30: 150 mm (Wide) - 1.9 m (Approx), 100mm(Height), 2mm(Thickness) | C30: No | D30: 12 | E30: ='Vertical bend down 150x100x2'!D112 -> 1156.6822 | F30: =D30*E30 -> 13880.187
A31: B4 | B31: Ladder Type Horizontal - Tee, Bending Radius - 1200mm
A32: i | B32: 600 mm (Wide) - 4.2 m (Approx), 100mm(Height), 2mm(Thickness) | C32: No | D32: 50 | E32: ='Horizontal Tee 600x100x2'!D112 -> 3511.591 | F32: =D32*E32 -> 175579.55
A33: II | B33: 300 mm (Wide) - 3.9 m (Approx), 100mm(Height), 2mm(Thickness) | C33: No | D33: 25 | E33: ='Horizontal Tee 300x100x2'!D112 -> 2806.1753 | F33: =D33*E33 -> 70154.382
A34: iii | B34: 150 mm (Wide) - 3.7 m (Approx), 100mm(Height), 2mm(Thickness) | C34: No | D34: 25 | E34: ='Horizontal Tee 150x100x2'!D112 -> 2453.4674 | F34: =D34*E34 -> 61336.686
A35: B5 | B35: Ladder Type Horizontal - Cross, Bending Radius - 1050mm
A36: i | B36: 600 mm (Wide) - 5.8 m (Approx), 100mm(Height), 2mm(Thickness) | C36: No | D36: 10 | E36: ='Horizontal Cross 600x100x2'!D112 -> 4781.7454 | F36: =D36*E36 -> 47817.454
A37: II | B37: 300 mm (Wide) - 5.8 m (Approx), 100mm(Height), 2mm(Thickness) | C37: No | D37: 10 | E37: ='Horizontal Cross 300x100x2'!D112 -> 3827.3595 | F37: =D37*E37 -> 38273.595
A38: C | B38: Channel & Cantilever Arm
A39: i | B39: C1 Channel - 41mm (Length) X 41mm (Width), 2.5mm (Thickness) | C39: Mtr | D39: 25000 | E39: ='Channel 41x41x2.5'!D91 -> 293.36812 | F39: =D39*E39 -> 7334202.9
A40: II | B40: C2 Channel - 41mm (Length) X 82mm (Width), 2.5mm (Thickness) | C40: Mtr | D40: 22000 | E40: ='Channel 41x82x2.5'!D91 -> 468.1662 | F40: =D40*E40 -> 10299656
A41: iii | B41: Cantilever Arm - 750 MM Length, 2.5mm (Thickness) | C41: No | D41: 15000 | E41: ='Cantilever Arm 750'!D90 -> 220.02609 | F41: =D41*E41 -> 3300391.3
A42: iv | B42: Cantilever Arm - 620 MM Length, 2.5mm (Thickness) | C42: No | D42: 30000 | E42: ='Cantilever Arm 620'!D90 -> 182.03222 | F42: =D42*E42 -> 5460966.6
A43: v | B43: Cantilever Arm - 320 MM Length, 2.5mm (Thickness) | C43: No | D43: 9000 | E43: ='Cantilever Arm 320'!D90 -> 94.021784 | F43: =D43*E43 -> 846196.06
A44: D | B44: Fixing Accessories
A45: i | B45: C1 channel clamp 43mm(Length) x 41mm(Width), 6mm (Thickness) | C45: No | D45: 500 | F45: =D45*E45 -> 0
A46: II | B46: C2 channel clamp - Type-A, 41mm(Length) x 82mm(Width), 6mm (Thickness) | C46: No | D46: 400 | F46: =D46*E46 -> 0
A47: iii | B47: C2 channel clamp - Type-B, 82mm(Length) x 41mm(Width), 6mm (Thickness) | C47: No | D47: 100 | F47: =D47*E47 -> 0
A48: iv | B48: Base plate for C1 channel 100mm (Length) x100mm (Width), 6mm (Thickness) | C48: No | D48: 1500 | F48: =D48*E48 -> 0
A49: v | B49: Base plate for C2 channel- 200mm (Length) x100mm (Width), 6mm (Thickness)ase plate for C2 channel | C49: No | D49: 12000 | F49: =D49*E49 -> 0
A50: vi | B50: Z-Clamp for Cable tray fixing 30mm x 2mm x 50mm, 6mm (Thickness) | C50: No | D50: 75000 | F50: =D50*E50 -> 0
A51: vii | B51: Z-Clamp for earth flat fixing 30mm x 6mm x 50mm, 6mm (Thickness) | C51: No | D51: 11500 | F51: =D51*E51 -> 0
A52: viii | B52: L-Clamp for cable tray fixing 41mm (Length) x 100mm(Width), 6mm (Thickness) | C52: No | D52: 1000 | F52: =D52*E52 -> 0
A53: ix | B53: 150x150x6 mm thick plate | C53: No | D53: 100 | F53: =D53*E53 -> 0
A54: x | B54: Trestle bracket 74mmx81mm, 6mmThickness | C54: No | D54: 100 | F54: =D54*E54 -> 0
A55: xi | B55: Beam Clamp ‘BC1’ 124mmx90mm, | C55: No | D55: 500 | F55: =D55*E55 -> 0
A56: xii | B56: M8 bolt with long spring nut with Hexgon head set screw | C56: No | D56: 10000 | F56: =D56*E56 -> 0
... A58: xiv | B58: M12 bolt with long spring nut with Hexgon head set screw | C58: No | D58: 175250 | F58: =D58*E58 -> 0
A59: Total FOR Value, Excl GST | F59: =SUM(F8:F58) -> 1.6895792e+08

Sheet Backup>

Sheet Horizontal Cross 300x100x2
A1: Cable Tray Costing : Ladder Type Horizontal Cross, Bending Radius 1050 mm
B5: Input for raw material and conversion costs | M5: Cable Tray configuration
B6: Cost of 1 kg of MS (Rs) | D6: 73 | F6: Coating thickness of Zinc (micron) | H6: 86 | M6: Runners | Q6: Rungs
B7: Transportation and handling cost of raw material to vendor shop (% of raw material cost) | D7: 0 | F7: Specific weight of Zinc (kg/m3) | H7: 7135 | M7: Number of runners | O7: 2 | Q7: No of rungs per 2500 meter of runner | U7: 10
B8: Specific weight of MS (kg/m3) | D8: 7850 | F8: Cost of Zinc (Rs/kg) | H8: 425.6 | M8: Tray width (mm) | O8: 300 | Q8: Length of rung (mm) | U8: =O8 -> 300
B9: Cost of engg and fabrication (% of material cost) | D9: 0 | F9: Wastage during galvalization | H9: 0 | M9: Tray Depth (mm) | O9: 100 | Q9: Width of rung (mm) | U9: 50
B10: Quality test and inspection charges (%) | D10: 0 | F10: Recoverable scrap - Ash per meter of tray (%) | H10: 0.12 | M10: Tray thickness (mm) | O10: 2 | Q10: Collar / Height of rung (mm) | U10: 20
B11: Salvage value of scrap for MS plates(% of overall value) | D11: 0.5 | F11: Recoverable scrap - Dross per meter of tray (%) | H11: 0.08 | M11: Tray collar (mm) | O11: 25 | Q11: Thickness of rung (mm) | U11: 2
B12: Wastage allowance during fabrication | D12: 0 | F12: Recoverable scrap salvage value - Ash (%) | H12: 0.26 | M12: Tray length (mm) | O12: 5800 | Q12: No of slots per 40 mm of length | U12: 1
B13: Transportation and handling cost of finished goods to site (Rs/kg) | D13: 0 | F13: Recoverable scrap salvage value - Dross (%) | H13: 0.52 | M13: No of holes per 2500 mm length | O13: 20 | Q13: Length of 1 slot (mm) | U13: 25
B14: Overheads for vendor (%) | D14: 0 | F14: Cost of galvanization (% of material cost) | H14: 0 | M14: Dia of 1 hole (mm) | O14: 10 | Q14: Width of 1 slot (mm) | U14: 10
B15: Profit margin for vendor (%) | D15: 2.5
B16: Cost of contract Performance Bank Guarantee | D16: 0
B17: Labour,Fabrication,Overhead,Profit Margin (INR/ kg) | D17: =6.5*1.2 -> 7.8
B20: Detailed Costing
B21: Cable tray MS material cost | M21: Galvalization
B22: Runner | F22: Rung | M22: Zinc Requirement
B23: Number of runners per meter length | D23: =O7 -> 2 | F23: No of rungs in this fitting (U7 x length / 2500, rounded) | J23: =ROUND(U7*D28/2500,0) -> 23 | M23: Runner | Q23: Rung
B24: Tray width (mm) | D24: =O8 -> 300 | F24: Length of rung (mm) | J24: =U8 -> 300 | M24: Surface area for 1 m length (m2) | O24: =2*(2*(2*D27+D25)/1000*D28/1000) -> 3.48 | Q24: Surface area for 1 rung (m2) | T24: =2*J24/1000*(J25+2*J26)/1000 -> 0.054
B25: Tray Depth (mm) | D25: =O9 -> 100 | F25: Width of rung (mm) | J25: =U9 -> 50 | M25: Surface area holes along thickness for 1 m length (m2) | O25: =D37*3.14*D38/1000*D26/1000*D28/125 -> 0.0582784 | Q25: Surface area of slots along thickness for 1 rung (m2) | T25: =(2*(J38+J39)/1000*D26/1000)*D24/40 -> 0.00105
B26: Tray thickness (mm) | D26: =O10 -> 2 | F26: Collar / Height of rung (mm) | J26: =U10 -> 20 | M26: Top surface area of holes for 1 m length (m2) | O26: =D37*3.14*(D38/2/1000)^2*D28/125 -> 0.072848 | Q26: Top surface area of slots 1 rung (m2) | T26: =J38/1000*J39/1000*D24/40 -> 0.001875
B27: Tray collar (mm) | D27: =O11 -> 25 | F27: Thickness of rung (mm) | J27: =U11 -> 2
B28: Tray length (mm) | D28: =O12 -> 5800 | M28: Overall surface area for 1 meter of runner (m2) | O28: =O24+O25-O26 -> 3.4654304 | Q28: Overall rung surface area for 1 meter of runner (m2) | T28: =(T24+T25-T26)*J23 -> 1.223025
F29: Volume of 1 rung (m3) | J29: =(2*J26+J25)/1000*J24/1000*J27/1000 -> 5.4e-05
F30: Weight of 1 rung (kg) | J30: =J29*D8 -> 0.4239 | M30: Total surface area per meter of cable tray (m2) | O30: =O28+T28 -> 4.6884554
B31: Volume of runner (m3) | D31: =2*(D25+D27*2)/1000*D26/1000*D28/1000 -> 0.00348 | F31: Cost of 1 rung (Rs) | J31: =J30*(D6*(1+D7)) -> 30.9447
B32: Weight of runner per meter length (kg) | D32: =D31*D8 -> 27.318 | F32: Cost of rungs per meter of runner | J32: =J31*J23 -> 711.7281 | M32: Weight of Zinc required for galvanization (kg) | O32: =O30*H6*10^-6*H7 -> 2.8768831
B33: Cost of runner per meter length (Rs) | D33: =D32*(D6*(1+D7)) -> 1994.214 | M33: Wastage during galvalization | O33: =H9 -> 0
M34: Total weight of Zinc required for galvanization (kg) | O34: =(1+O33)*O32 -> 2.8768831
B35: Scrap salvage due to holes / slots | M35: Cost of Zinc galvanization per meter of runner (Rs) | O35: =O34*H8 -> 1224.4015
B36: Runner | F36: Rung
B37: No of holes per 2500 mm length | D37: =O13 -> 20 | F37: No of slots per 40 mm of length | J37: =U12 -> 1 | M37: Recoverable scrap - Ash per meter of tray (kg) | O37: =H10*O32 -> 0.34522597 | Q37: Recoverable scrap salvage - Ash (Rs/kg) | T37: =H12*$H$8 -> 110.656
B38: Dia of 1 hole (mm) | D38: =O14 -> 10 | F38: Length of 1 slot (mm) | J38: =U13 -> 25 | M38: Recoverable scrap - Dross per meter of tray (kg) | O38: =H11*O32 -> 0.23015065 | Q38: Recoverable scrap salvage - Dross (Rs/kg) | T38: =H13*$H$8 -> 221.312
B39: Volume of holes (m3) | D39: =2*D37*3.14*(D38/2/1000)^2*D26/1000 -> 6.28e-06 | F39: Width of 1 slot (mm) | J39: =U14 -> 10 | M39: Salvage value of scrap per meter of cable (Rs) | O39: =O37*T37+O38*T38 -> 89.136426
F40: Volume of 1 slot (m3) | J40: =J38/1000*J39/1000*J27/1000 -> 5e-07
B41: Weight of holes per 2500 mm of runner (kg) | D41: =D39*D8 -> 0.049298 | F41: Volume slots per rung (m3) | J41: =D24/40*J40 -> 3.75e-06 | M41: Net cost of Zinc galvanization per meter of runner (Rs) | O41: =O35-O39 -> 1135.265
B42: Value of scrap generated per meter of runner (Rs) | D42: =D41*D6 -> 3.598754 | F42: Weight of slots per rung (kg) | J42: =J41*D8 -> 0.0294375
B43: Salvage value of scrap (% of overall value) | D43: =D11 -> 0.5 | F43: Weight of slots per 2500mm of runner (kg) | J43: =J42*J23 -> 0.6770625
B44: Salvage value of MS scrap per meter of runner (Rs) | D44: =D42*D43 -> 1.799377 | F44: Value of scrap generated per meter of runner (Rs) | J44: =J43*D6 -> 49.425562
F45: Salvage value of MS scrap per meter of runner (Rs) | J45: =J44*D43 -> 24.712781
B47: Cost of material for 1 m of runner (Rs) | D47: =D33-D44 -> 1992.4146 | F47: Cost of material for rungs per meter of runner (Rs) | J47: =J32-J45 -> 687.01532
B49: Total cost per meter of cable tray (Rs) | D49: =D47+J47 -> 2679.4299
B50: Wastage allowance during fabrication | D50: =D12 -> 0
B51: Net cost per meter of cable tray (Rs) | D51: =(1+D50)*D49 -> 2679.4299
B54: Engineering, Fabrication and Quality & Inspection cost of cable tray | M54: Cost of galvanization
B55: Engineering & Fabrication cost (Rs) | D55: =(D33+J32)*D9 -> 0 | M55: Galvanization cost (Rs) | N55: =O35*H14 -> 0
B56: Quality inspection and testing (Rs) | D56: =(D33+J32)*D10 -> 0
B61: Summary (Cost of cable tray per meter length)
B63: Cost of steel (Rs) | D63: =D51 -> 2679.4299
B64: Cost of raw material for galvanization (Rs) | D64: =O41 -> 1135.265
B65: Cost of fabrication (Rs) | D65: =D55 -> 0
B66: Cost of galvanization (Rs) | D66: =N55 -> 0
B67: Quality inspection and testing (Rs) | D67: =D56 -> 0
B68: Vendor Overheads (Rs) | D68: =SUM(D63:D67)*D14 -> 0
B69: Profit margin for vendor (Rs) | D69: =SUM(D63:D68)*D15 -> 9536.7374
B70: Contract Performance Bank Guarantee (Rs) | D70: =SUM(D63:D69)*D16 -> 0
B71: Transportation and handling to site (Rs) | D71: =(D32+J30*J23-D41-J43)*D13 -> 0
B72: Should be cost (Rs per meter) | D72: =SUM(D63:D71) -> 13351.432
B73: Ex Works Should be cost (Rs per meter) | D73: =SUM(D63:D70) -> 13351.432
B79: Comparison - Cost model viz-a-viz TPL estimations
C81: B5-i: Ladder Type Horizontal Cross, Bending Radius 1050 mm - 600mm(W) X 100mm(H) X 2mm(T), ~5.80 m
B83: Summary (Cost of cable tray - 2500 length)
B85: Cost of steel (Rs) | D85: =D71 -> 0
B86: Cost of raw material for galvanization (Rs) | D86: =O64 -> 0
B87: Cost of fabrication (Rs) | D87: =D75 -> 0
B88: Cost of galvanization (Rs) | D88: =O75 -> 0
B89: Quality inspection and testing (Rs) | D89: =D76 -> 0
B90: Vendor Overheads (Rs) | D90: =SUM(D85:D89)*D36 -> 0
B91: Profit margin for vendor | D91: =SUM(D85:D90)*D37 -> 0
B92: Contract Performance Bank Guarantee (Rs) | D92: =SUM(D85:D91)*D38 -> 0
B93: Transportation and handling to site (Rs) | D93: =(D54-D62-I63)*D35 -> 0
B95: Should be cost | D95: =SUM(D85:D93) -> 0
B96: Ex Works Should be cost | D96: =SUM(D85:D92) -> 0
D97: Suggested model | E97: TPL model
C98: Weight of runner (kg) | D98: =D32 -> 27.318 | E98: ='[1]Old Ladder type (2)'!K33 -> 27.318
C99: Savings due to holes/ slots in runner (kg) | D99: =D41 -> 0.049298 | E99: 0
C100: Weight of rung (kg) | D100: =J30*J23 -> 9.7497 | E100: ='[1]Old Ladder type (2)'!L33 -> 19.4994
C101: Savings due to slots in rung (kg) | D101: =J43 -> 0.6770625 | E101: 0
C102: ="Weight of Coupler plate ("&'[1]Coupler Plate'!N6&"X"&'[1]Coupler Plate'!N7&"X"&'[1]Coupler Plate'!N8&") (kg)" -> Weight of Coupler plate (70X210X2) (kg) | D102: ='[1]Coupler Plate'!D37*2 -> 0.414009 | E102: ='[1]Old Ladder type (2)'!M33 -> 0.46158
C103: Hardware weight (Nut,bolt and washer) (kg) | D103: 0.32 | E103: 0.32 | G103: fixed
C104: Total weight (kg) | D104: =D98-D99+D100-D101+D102+D103 -> 37.075348 | E104: =E98-E99+E100-E101+E102+E103 -> 47.59898 | F104: =(E104-D104)/D104 -> 0.28384444
C105: Cost of steel (INR) | D105: =(D98*D6-D11*D99*D6)+(D100*D6-D11*D101*D6)+('[1]Coupler Plate'!D24-D43*'[1]Coupler Plate'!D34)*D6*2+D103*D6 -> 2734.7489 | E105: =E104*D6 -> 3474.7255
C107: Weight of Zinc required for galvanization (kg) | D107: =5%*D104 -> 1.8537674 | E107: =5%*E104 -> 2.379949 | G107: TPL assumption: 5% of steel weight; zinc weight to be calculated basis coating thickness
C108: Cost of zinc (INR) | D108: =D107*$H$8 -> 788.96342 | E108: =E107*$H$8 -> 1012.9063
C110: Labour,Fabrication,Overhead,Profit Margin (INR) | D110: =(D104+D107)*$D$17 -> 303.6471 | E110: =(E104+E107)*$D$17 -> 389.83565
C112: Total cost (INR) per tray | D112: =D110+D105+D108 -> 3827.3595 | E112: =E110+E105+E108 -> 4877.4675
C113: Cost per meter (INR) per tray | D113: =D112/(O12/1000) -> 659.88956 | E113: =E112/(O12/1000) -> 840.94267
C114: Savings | D114: =(E112-D112)/D112 -> 0.2743688
B118: Comparison table - Summary
D120: TPL | H120: Cost Model
C121: B5-i: Ladder Type Horizontal Cross, Bending Radius 1050 mm, 600mm(W) X 100mm(H), 2mm thk M.S. sheet, ~5.80 m, hot dip galvanised incl. coupler plate
D123: Weight of steel (kg) | E123: Weight of zinc (kg) | F123: Estimated price | H123: Weight of steel (kg) | I123: Weight of zinc (kg) | J123: Estimated price | K123: Price difference
C124: ='[1]Old Ladder type (2)'!B33 -> 600mm(W)X100mm(H) - B5-i horizontal cross | D124: ='[1]Old Ladder type (2)'!Q33 -> 47.59898 | E124: ='[1]Old Ladder type (2)'!U33 -> 2.379949 | F124: ='[1]Old Ladder type (2)'!Z33 -> 4015.6641 | H124: =D104 -> 37.075348 | I124: =D107 -> 1.8537674 | J124: =D112 -> 3827.3595 | K124: =(F124-J124)/J124 -> 0.049199635

Sheet Horizontal Cross 600x100x2
A1: Cable Tray Costing : Ladder Type Horizontal Cross, Bending Radius 1050 mm
B5: Input for raw material and conversion costs | M5: Cable Tray configuration
B6: Cost of 1 kg of MS (Rs) | D6: 73 | F6: Coating thickness of Zinc (micron) | H6: 86 | M6: Runners | Q6: Rungs
B7: Transportation and handling cost of raw material to vendor shop (% of raw material cost) | D7: 0 | F7: Specific weight of Zinc (kg/m3) | H7: 7135 | M7: Number of runners | O7: 2 | Q7: No of rungs per 2500 meter of runner | U7: 10
B8: Specific weight of MS (kg/m3) | D8: 7850 | F8: Cost of Zinc (Rs/kg) | H8: 425.6 | M8: Tray width (mm) | O8: 600 | Q8: Length of rung (mm) | U8: =O8 -> 600
B9: Cost of engg and fabrication (% of material cost) | D9: 0 | F9: Wastage during galvalization | H9: 0 | M9: Tray Depth (mm) | O9: 100 | Q9: Width of rung (mm) | U9: 50
B10: Quality test and inspection charges (%) | D10: 0 | F10: Recoverable scrap - Ash per meter of tray (%) | H10: 0.12 | M10: Tray thickness (mm) | O10: 2 | Q10: Collar / Height of rung (mm) | U10: 20
B11: Salvage value of scrap for MS plates(% of overall value) | D11: 0.5 | F11: Recoverable scrap - Dross per meter of tray (%) | H11: 0.08 | M11: Tray collar (mm) | O11: 25 | Q11: Thickness of rung (mm) | U11: 2
B12: Wastage allowance during fabrication | D12: 0 | F12: Recoverable scrap salvage value - Ash (%) | H12: 0.26 | M12: Tray length (mm) | O12: 5800 | Q12: No of slots per 40 mm of length | U12: 1
B13: Transportation and handling cost of finished goods to site (Rs/kg) | D13: 0 | F13: Recoverable scrap salvage value - Dross (%) | H13: 0.52 | M13: No of holes per 2500 mm length | O13: 20 | Q13: Length of 1 slot (mm) | U13: 25
B14: Overheads for vendor (%) | D14: 0 | F14: Cost of galvanization (% of material cost) | H14: 0 | M14: Dia of 1 hole (mm) | O14: 10 | Q14: Width of 1 slot (mm) | U14: 10
B15: Profit margin for vendor (%) | D15: 2.5
B16: Cost of contract Performance Bank Guarantee | D16: 0
B17: Labour,Fabrication,Overhead,Profit Margin (INR/ kg) | D17: =6.5*1.2 -> 7.8
B20: Detailed Costing
B21: Cable tray MS material cost | M21: Galvalization
B22: Runner | F22: Rung | M22: Zinc Requirement
B23: Number of runners per meter length | D23: =O7 -> 2 | F23: No of rungs in this fitting (U7 x length / 2500, rounded) | J23: =ROUND(U7*D28/2500,0) -> 23 | M23: Runner | Q23: Rung
B24: Tray width (mm) | D24: =O8 -> 600 | F24: Length of rung (mm) | J24: =U8 -> 600 | M24: Surface area for 1 m length (m2) | O24: =2*(2*(2*D27+D25)/1000*D28/1000) -> 3.48 | Q24: Surface area for 1 rung (m2) | T24: =2*J24/1000*(J25+2*J26)/1000 -> 0.108
B25: Tray Depth (mm) | D25: =O9 -> 100 | F25: Width of rung (mm) | J25: =U9 -> 50 | M25: Surface area holes along thickness for 1 m length (m2) | O25: =D37*3.14*D38/1000*D26/1000*D28/125 -> 0.0582784 | Q25: Surface area of slots along thickness for 1 rung (m2) | T25: =(2*(J38+J39)/1000*D26/1000)*D24/40 -> 0.0021
B26: Tray thickness (mm) | D26: =O10 -> 2 | F26: Collar / Height of rung (mm) | J26: =U10 -> 20 | M26: Top surface area of holes for 1 m length (m2) | O26: =D37*3.14*(D38/2/1000)^2*D28/125 -> 0.072848 | Q26: Top surface area of slots 1 rung (m2) | T26: =J38/1000*J39/1000*D24/40 -> 0.00375
B27: Tray collar (mm) | D27: =O11 -> 25 | F27: Thickness of rung (mm) | J27: =U11 -> 2
B28: Tray length (mm) | D28: =O12 -> 5800 | M28: Overall surface area for 1 meter of runner (m2) | O28: =O24+O25-O26 -> 3.4654304 | Q28: Overall rung surface area for 1 meter of runner (m2) | T28: =(T24+T25-T26)*J23 -> 2.44605
F29: Volume of 1 rung (m3) | J29: =(2*J26+J25)/1000*J24/1000*J27/1000 -> 0.000108
F30: Weight of 1 rung (kg) | J30: =J29*D8 -> 0.8478 | M30: Total surface area per meter of cable tray (m2) | O30: =O28+T28 -> 5.9114804
B31: Volume of runner (m3) | D31: =2*(D25+D27*2)/1000*D26/1000*D28/1000 -> 0.00348 | F31: Cost of 1 rung (Rs) | J31: =J30*(D6*(1+D7)) -> 61.8894
B32: Weight of runner per meter length (kg) | D32: =D31*D8 -> 27.318 | F32: Cost of rungs per meter of runner | J32: =J31*J23 -> 1423.4562 | M32: Weight of Zinc required for galvanization (kg) | O32: =O30*H6*10^-6*H7 -> 3.6273435
B33: Cost of runner per meter length (Rs) | D33: =D32*(D6*(1+D7)) -> 1994.214 | M33: Wastage during galvalization | O33: =H9 -> 0
M34: Total weight of Zinc required for galvanization (kg) | O34: =(1+O33)*O32 -> 3.6273435
B35: Scrap salvage due to holes / slots | M35: Cost of Zinc galvanization per meter of runner (Rs) | O35: =O34*H8 -> 1543.7974
B36: Runner | F36: Rung
B37: No of holes per 2500 mm length | D37: =O13 -> 20 | F37: No of slots per 40 mm of length | J37: =U12 -> 1 | M37: Recoverable scrap - Ash per meter of tray (kg) | O37: =H10*O32 -> 0.43528122 | Q37: Recoverable scrap salvage - Ash (Rs/kg) | T37: =H12*$H$8 -> 110.656
B38: Dia of 1 hole (mm) | D38: =O14 -> 10 | F38: Length of 1 slot (mm) | J38: =U13 -> 25 | M38: Recoverable scrap - Dross per meter of tray (kg) | O38: =H11*O32 -> 0.29018748 | Q38: Recoverable scrap salvage - Dross (Rs/kg) | T38: =H13*$H$8 -> 221.312
B39: Volume of holes (m3) | D39: =2*D37*3.14*(D38/2/1000)^2*D26/1000 -> 6.28e-06 | F39: Width of 1 slot (mm) | J39: =U14 -> 10 | M39: Salvage value of scrap per meter of cable (Rs) | O39: =O37*T37+O38*T38 -> 112.38845
F40: Volume of 1 slot (m3) | J40: =J38/1000*J39/1000*J27/1000 -> 5e-07
B41: Weight of holes per 2500 mm of runner (kg) | D41: =D39*D8 -> 0.049298 | F41: Volume slots per rung (m3) | J41: =D24/40*J40 -> 7.5e-06 | M41: Net cost of Zinc galvanization per meter of runner (Rs) | O41: =O35-O39 -> 1431.4089
B42: Value of scrap generated per meter of runner (Rs) | D42: =D41*D6 -> 3.598754 | F42: Weight of slots per rung (kg) | J42: =J41*D8 -> 0.058875
B43: Salvage value of scrap (% of overall value) | D43: =D11 -> 0.5 | F43: Weight of slots per 2500mm of runner (kg) | J43: =J42*J23 -> 1.354125
B44: Salvage value of MS scrap per meter of runner (Rs) | D44: =D42*D43 -> 1.799377 | F44: Value of scrap generated per meter of runner (Rs) | J44: =J43*D6 -> 98.851125
F45: Salvage value of MS scrap per meter of runner (Rs) | J45: =J44*D43 -> 49.425562
B47: Cost of material for 1 m of runner (Rs) | D47: =D33-D44 -> 1992.4146 | F47: Cost of material for rungs per meter of runner (Rs) | J47: =J32-J45 -> 1374.0306
B49: Total cost per meter of cable tray (Rs) | D49: =D47+J47 -> 3366.4453
B50: Wastage allowance during fabrication | D50: =D12 -> 0
B51: Net cost per meter of cable tray (Rs) | D51: =(1+D50)*D49 -> 3366.4453
B54: Engineering, Fabrication and Quality & Inspection cost of cable tray | M54: Cost of galvanization
B55: Engineering & Fabrication cost (Rs) | D55: =(D33+J32)*D9 -> 0 | M55: Galvanization cost (Rs) | N55: =O35*H14 -> 0
B56: Quality inspection and testing (Rs) | D56: =(D33+J32)*D10 -> 0
B61: Summary (Cost of cable tray per meter length)
B63: Cost of steel (Rs) | D63: =D51 -> 3366.4453
B64: Cost of raw material for galvanization (Rs) | D64: =O41 -> 1431.4089
B65: Cost of fabrication (Rs) | D65: =D55 -> 0
B66: Cost of galvanization (Rs) | D66: =N55 -> 0
B67: Quality inspection and testing (Rs) | D67: =D56 -> 0
B68: Vendor Overheads (Rs) | D68: =SUM(D63:D67)*D14 -> 0
B69: Profit margin for vendor (Rs) | D69: =SUM(D63:D68)*D15 -> 11994.635
B70: Contract Performance Bank Guarantee (Rs) | D70: =SUM(D63:D69)*D16 -> 0
B71: Transportation and handling to site (Rs) | D71: =(D32+J30*J23-D41-J43)*D13 -> 0
B72: Should be cost (Rs per meter) | D72: =SUM(D63:D71) -> 16792.49
B73: Ex Works Should be cost (Rs per meter) | D73: =SUM(D63:D70) -> 16792.49
B79: Comparison - Cost model viz-a-viz TPL estimations
C81: B5-i: Ladder Type Horizontal Cross, Bending Radius 1050 mm - 600mm(W) X 100mm(H) X 2mm(T), ~5.80 m
B83: Summary (Cost of cable tray - 2500 length)
B85: Cost of steel (Rs) | D85: =D71 -> 0
B86: Cost of raw material for galvanization (Rs) | D86: =O64 -> 0
B87: Cost of fabrication (Rs) | D87: =D75 -> 0
B88: Cost of galvanization (Rs) | D88: =O75 -> 0
B89: Quality inspection and testing (Rs) | D89: =D76 -> 0
B90: Vendor Overheads (Rs) | D90: =SUM(D85:D89)*D36 -> 0
B91: Profit margin for vendor | D91: =SUM(D85:D90)*D37 -> 0
B92: Contract Performance Bank Guarantee (Rs) | D92: =SUM(D85:D91)*D38 -> 0
B93: Transportation and handling to site (Rs) | D93: =(D54-D62-I63)*D35 -> 0
B95: Should be cost | D95: =SUM(D85:D93) -> 0
B96: Ex Works Should be cost | D96: =SUM(D85:D92) -> 0
D97: Suggested model | E97: TPL model
C98: Weight of runner (kg) | D98: =D32 -> 27.318 | E98: ='[1]Old Ladder type (2)'!K33 -> 27.318
C99: Savings due to holes/ slots in runner (kg) | D99: =D41 -> 0.049298 | E99: 0
C100: Weight of rung (kg) | D100: =J30*J23 -> 19.4994 | E100: ='[1]Old Ladder type (2)'!L33 -> 19.4994
C101: Savings due to slots in rung (kg) | D101: =J43 -> 1.354125 | E101: 0
C102: ="Weight of Coupler plate ("&'[1]Coupler Plate'!N6&"X"&'[1]Coupler Plate'!N7&"X"&'[1]Coupler Plate'!N8&") (kg)" -> Weight of Coupler plate (70X210X2) (kg) | D102: ='[1]Coupler Plate'!D37*2 -> 0.414009 | E102: ='[1]Old Ladder type (2)'!M33 -> 0.46158
C103: Hardware weight (Nut,bolt and washer) (kg) | D103: 0.32 | E103: 0.32 | G103: fixed
C104: Total weight (kg) | D104: =D98-D99+D100-D101+D102+D103 -> 46.147986 | E104: =E98-E99+E100-E101+E102+E103 -> 47.59898 | F104: =(E104-D104)/D104 -> 0.031442196
C105: Cost of steel (INR) | D105: =(D98*D6-D11*D99*D6)+(D100*D6-D11*D101*D6)+('[1]Coupler Plate'!D24-D43*'[1]Coupler Plate'!D34)*D6*2+D103*D6 -> 3421.7643 | E105: =E104*D6 -> 3474.7255
C107: Weight of Zinc required for galvanization (kg) | D107: =5%*D104 -> 2.3073993 | E107: =5%*E104 -> 2.379949 | G107: TPL assumption: 5% of steel weight; zinc weight to be calculated basis coating thickness
C108: Cost of zinc (INR) | D108: =D107*$H$8 -> 982.02914 | E108: =E107*$H$8 -> 1012.9063
C110: Labour,Fabrication,Overhead,Profit Margin (INR) | D110: =(D104+D107)*$D$17 -> 377.95201 | E110: =(E104+E107)*$D$17 -> 389.83565
C112: Total cost (INR) per tray | D112: =D110+D105+D108 -> 4781.7454 | E112: =E110+E105+E108 -> 4877.4675
C113: Cost per meter (INR) per tray | D113: =D112/(O12/1000) -> 824.43886 | E113: =E112/(O12/1000) -> 840.94267
C114: Savings | D114: =(E112-D112)/D112 -> 0.020018229
B118: Comparison table - Summary
D120: TPL | H120: Cost Model
C121: B5-i: Ladder Type Horizontal Cross, Bending Radius 1050 mm, 600mm(W) X 100mm(H), 2mm thk M.S. sheet, ~5.80 m, hot dip galvanised incl. coupler plate
D123: Weight of steel (kg) | E123: Weight of zinc (kg) | F123: Estimated price | H123: Weight of steel (kg) | I123: Weight of zinc (kg) | J123: Estimated price | K123: Price difference
C124: ='[1]Old Ladder type (2)'!B33 -> 600mm(W)X100mm(H) - B5-i horizontal cross | D124: ='[1]Old Ladder type (2)'!Q33 -> 47.59898 | E124: ='[1]Old Ladder type (2)'!U33 -> 2.379949 | F124: ='[1]Old Ladder type (2)'!Z33 -> 4015.6641 | H124: =D104 -> 46.147986 | I124: =D107 -> 2.3073993 | J124: =D112 -> 4781.7454 | K124: =(F124-J124)/J124 -> -0.16020955

Sheet Channel 41x41x2.5
A1: Cable Tray Costing : C1 Channel - 41 mm (W) x 41 mm (D), 2.5 mm thickness
B5: Input for raw material and conversion costs | M5: Channel / cantilever arm configuration
B6: Cost of steel(Rs/kg) | D6: 73 | F6: Coating thickness of Zinc (micron) | H6: 86 | M6: Channel type | O6: Standard strut slotted channel
B7: Transportation and handling cost of raw material to vendor shop (% of raw material cost) | D7: 0 | F7: Specific weight of Zinc (kg/m3) | H7: 7135 | M7: Channel width - back face (mm) | O7: 41
B8: Specific weight of MS (kg/m3) | D8: 7850 | F8: Cost of Zinc (Rs/kg) | H8: 425.6 | M8: Channel depth (mm) | O8: 41
B9: Cost of engg and fabrication (% of material cost) | D9: 0 | F9: Wastage during galvalization | H9: 0 | M9: Channel thickness (mm) | O9: 2.5
B10: Quality test and inspection charges (%) | D10: 0 | F10: Recoverable scrap - Ash per meter of tray (%) | H10: 0.12 | M10: Lip / return of channel (mm) | O10: 9
B11: Salvage value of scrap for MS plates(% of overall value) | D11: 0.3 | F11: Recoverable scrap - Dross per meter of tray (%) | H11: 0.08 | M11: Length (mm) | O11: 1000
B12: Wastage allowance during fabrication | D12: 0 | F12: Recoverable scrap salvage value - Ash (%) | H12: 0.26 | M12: Length of a slot (mm) | O12: 28
B13: Transportation and handling cost of finished goods to site (Rs/kg) | D13: 0 | F13: Recoverable scrap salvage value - Dross (%) | H13: 0.52 | M13: Width of a slot (mm) | O13: 13
B14: Overheads for vendor (%) | D14: 0 | F14: Cost of galvanization (% of material cost) | H14: 0 | M14: Pitch of slots along length (mm) | O14: 50
B15: Profit & overhead margin (INR/kg) | D15: 2.5 | M15: No of slots per channel | O15: =ROUNDDOWN(O11/O14,0) -> 20
B16: Cost of contract Performance Bank Guarantee | D16: 0
B17: Labour & Fabrication Charges (INR/ kg) | D17: =6.5*1.2 -> 7.8
B25: Detailed Costing
B26: Channel MS material cost | M26: Galvalization
M27: Zinc Requirement
B28: Developed (strip) width of channel (mm) | D28: =O7+2*O8+2*O10 -> 141
B29: Cross-section area of channel (mm2) | D29: =D28*O9 -> 352.5 | M29: Gross surface area - both faces (m2) | O29: =2*D28/1000*D30/1000 -> 0.282
B30: Length (mm) | D30: =O11 -> 1000 | M30: Surface area of slots along thickness (m2) | O30: =2*(O12+O13)/1000*O9/1000*D42 -> 0.0041
M31: Top surface area of slots - both faces (m2) | O31: =2*O12/1000*O13/1000*D42 -> 0.01456
B32: Channel thickness (mm) | D32: =O9 -> 2.5
M33: Overall surface area (m2) | O33: =O29+O30-O31 -> 0.27154
B35: Volume of steel (m3) | D35: =D29*D30/10^9 -> 0.0003525 | M35: Total surface area for galvanization (m2) | O35: =O33 -> 0.27154
B36: Weight of steel (kg) | D36: =D35*D8 -> 2.767125
B37: Cost of steel (Rs) | D37: =D36*(D6*(1+D7)) -> 202.00012 | M37: Weight of Zinc required for galvanization (kg) | O37: =O35*H6*10^-6*H7 -> 0.16661966
M38: Wastage during galvalization | O38: =H9 -> 0
B39: Scrap salvage due to slots | M39: Total weight of Zinc required for galvanization (kg) | O39: =(1+O38)*O37 -> 0.16661966
M40: Cost of Zinc galvanization (Rs) | O40: =O39*H8 -> 70.913327
B41: No of slots per channel | D41: =O15 -> 20
B42: Total no of slots | D42: =D41 -> 20 | M42: Recoverable scrap - Ash (kg) | O42: =H10*O37 -> 0.019994359 | Q42: Recoverable scrap salvage - Ash (Rs/kg) | T42: =H12*$H$8 -> 110.656
B43: Total volume of slots (m3) | D43: =D42*O12/1000*O13/1000*O9/1000 -> 1.82e-05 | M43: Recoverable scrap - Dross (kg) | O43: =H11*O37 -> 0.013329573 | Q43: Recoverable scrap salvage - Dross (Rs/kg) | T43: =H13*$H$8 -> 221.312
B44: Weight of slots (kg) | D44: =D43*D8 -> 0.14287 | M44: Salvage value of zinc scrap (Rs) | O44: =O42*T42+O43*T43 -> 5.1624902
B45: Value of scrap generated (Rs) | D45: =D44*D6 -> 10.42951
B46: Salvage value of scrap (% of overall value) | D46: =D11 -> 0.3 | M46: Net cost of Zinc galvanization (Rs) | O46: =O40-O44 -> 65.750837
B47: Salvage value of MS scrap (Rs) | D47: =D45*D46 -> 3.128853
B49: Cost of material (Rs) | D49: =D37-D47 -> 198.87127
B51: Total cost of channel steel (Rs) per metre | D51: =D49 -> 198.87127
B52: Wastage allowance during fabrication | D52: =D12 -> 0
B53: Net cost of channel steel (Rs) per metre | D53: =(1+D52)*D51 -> 198.87127
B56: Engineering, Fabrication and Quality & Inspection cost of cable tray
B57: Engineering & Fabrication cost (Rs) | D57: =D37*D9 -> 0
B58: Quality inspection and testing (Rs) | D58: =D37*D10 -> 0
B61: Cost model - final cost
B65: Summary (Cost per metre)
B67: Cost of steel (Rs) | D67: =D53 -> 198.87127
B68: Cost of raw material for galvanization (Rs) | D68: =O46 -> 65.750837
B69: Cost of fabrication (Rs) | D69: =D57 -> 0
B70: Cost of galvanization (Rs) | D70: =O40*H14 -> 0
B71: Quality inspection and testing (Rs) | D71: =D58 -> 0
B72: Vendor Overheads (Rs) | D72: =SUM(D67:D71)*D14 -> 0
B73: Profit margin for vendor | D73: =SUM(D67:D72)*D15 -> 661.55527
B74: Contract Performance Bank Guarantee (Rs) | D74: =SUM(D67:D73)*D16 -> 0
B75: Transportation and handling to site (Rs) | D75: =(D36-D44)*D13 -> 0
B77: Should be cost | D77: =SUM(D67:D75) -> 926.17738
B78: Ex Works Should be cost | D78: =SUM(D67:D74) -> 926.17738
D79: Cost model
C80: Weight of steel (kg) | D80: =D36 -> 2.767125
C81: Savings due to slots (kg) | D81: =D44 -> 0.14287
C82: Total weight (kg) | D82: =D80-D81 -> 2.624255
C83: Cost of steel (INR) | D83: =(D80-D81*D46)*D6 -> 198.87127
C85: Weight of Zinc required for galvanization (kg) | D85: =O39 -> 0.16661966
C86: Cost of zinc (INR) | D86: =D85*H8-O44 -> 65.750837
C88: Labour,Fabrication,Overhead,Profit Margin (INR) | D88: =(D82+D85)*($D$17+$D$15) -> 28.746009
C90: Total cost (INR) per metre | D90: =D88+D83+D86 -> 293.36812
C91: Cost per metre (INR) | D91: =D90/(D30/1000) -> 293.36812

Sheet Channel 41x82x2.5
A1: Cable Tray Costing : C1 Channel - 41 mm (W) x 41 mm (D), 2.5 mm thickness
B5: Input for raw material and conversion costs | M5: Channel / cantilever arm configuration
B6: Cost of steel(Rs/kg) | D6: 73 | F6: Coating thickness of Zinc (micron) | H6: 86 | M6: Channel type | O6: Standard strut slotted channel
B7: Transportation and handling cost of raw material to vendor shop (% of raw material cost) | D7: 0 | F7: Specific weight of Zinc (kg/m3) | H7: 7135 | M7: Channel width - back face (mm) | O7: 41
B8: Specific weight of MS (kg/m3) | D8: 7850 | F8: Cost of Zinc (Rs/kg) | H8: 425.6 | M8: Channel depth (mm) | O8: 82
B9: Cost of engg and fabrication (% of material cost) | D9: 0 | F9: Wastage during galvalization | H9: 0 | M9: Channel thickness (mm) | O9: 2.5
B10: Quality test and inspection charges (%) | D10: 0 | F10: Recoverable scrap - Ash per meter of tray (%) | H10: 0.12 | M10: Lip / return of channel (mm) | O10: 9
B11: Salvage value of scrap for MS plates(% of overall value) | D11: 0.3 | F11: Recoverable scrap - Dross per meter of tray (%) | H11: 0.08 | M11: Length (mm) | O11: 1000
B12: Wastage allowance during fabrication | D12: 0 | F12: Recoverable scrap salvage value - Ash (%) | H12: 0.26 | M12: Length of a slot (mm) | O12: 28
B13: Transportation and handling cost of finished goods to site (Rs/kg) | D13: 0 | F13: Recoverable scrap salvage value - Dross (%) | H13: 0.52 | M13: Width of a slot (mm) | O13: 13
B14: Overheads for vendor (%) | D14: 0 | F14: Cost of galvanization (% of material cost) | H14: 0 | M14: Pitch of slots along length (mm) | O14: 50
B15: Profit & overhead margin (INR/kg) | D15: 2.5 | M15: No of slots per channel | O15: =ROUNDDOWN(O11/O14,0) -> 20
B16: Cost of contract Performance Bank Guarantee | D16: 0
B17: Labour & Fabrication Charges (INR/ kg) | D17: =6.5*1.2 -> 7.8
B25: Detailed Costing
B26: Channel MS material cost | M26: Galvalization
M27: Zinc Requirement
B28: Developed (strip) width of channel (mm) | D28: =O7+2*O8+2*O10 -> 223
B29: Cross-section area of channel (mm2) | D29: =D28*O9 -> 557.5 | M29: Gross surface area - both faces (m2) | O29: =2*D28/1000*D30/1000 -> 0.446
B30: Length (mm) | D30: =O11 -> 1000 | M30: Surface area of slots along thickness (m2) | O30: =2*(O12+O13)/1000*O9/1000*D42 -> 0.0041
M31: Top surface area of slots - both faces (m2) | O31: =2*O12/1000*O13/1000*D42 -> 0.01456
B32: Channel thickness (mm) | D32: =O9 -> 2.5
M33: Overall surface area (m2) | O33: =O29+O30-O31 -> 0.43554
B35: Volume of steel (m3) | D35: =D29*D30/10^9 -> 0.0005575 | M35: Total surface area for galvanization (m2) | O35: =O33 -> 0.43554
B36: Weight of steel (kg) | D36: =D35*D8 -> 4.376375
B37: Cost of steel (Rs) | D37: =D36*(D6*(1+D7)) -> 319.47538 | M37: Weight of Zinc required for galvanization (kg) | O37: =O35*H6*10^-6*H7 -> 0.2672517
M38: Wastage during galvalization | O38: =H9 -> 0
B39: Scrap salvage due to slots | M39: Total weight of Zinc required for galvanization (kg) | O39: =(1+O38)*O37 -> 0.2672517
M40: Cost of Zinc galvanization (Rs) | O40: =O39*H8 -> 113.74232
B41: No of slots per channel | D41: =O15 -> 20
B42: Total no of slots | D42: =D41 -> 20 | M42: Recoverable scrap - Ash (kg) | O42: =H10*O37 -> 0.032070204 | Q42: Recoverable scrap salvage - Ash (Rs/kg) | T42: =H12*$H$8 -> 110.656
B43: Total volume of slots (m3) | D43: =D42*O12/1000*O13/1000*O9/1000 -> 1.82e-05 | M43: Recoverable scrap - Dross (kg) | O43: =H11*O37 -> 0.021380136 | Q43: Recoverable scrap salvage - Dross (Rs/kg) | T43: =H13*$H$8 -> 221.312
B44: Weight of slots (kg) | D44: =D43*D8 -> 0.14287 | M44: Salvage value of zinc scrap (Rs) | O44: =O42*T42+O43*T43 -> 8.2804411
B45: Value of scrap generated (Rs) | D45: =D44*D6 -> 10.42951
B46: Salvage value of scrap (% of overall value) | D46: =D11 -> 0.3 | M46: Net cost of Zinc galvanization (Rs) | O46: =O40-O44 -> 105.46188
B47: Salvage value of MS scrap (Rs) | D47: =D45*D46 -> 3.128853
B49: Cost of material (Rs) | D49: =D37-D47 -> 316.34652
B51: Total cost of channel steel (Rs) per metre | D51: =D49 -> 316.34652
B52: Wastage allowance during fabrication | D52: =D12 -> 0
B53: Net cost of channel steel (Rs) per metre | D53: =(1+D52)*D51 -> 316.34652
B56: Engineering, Fabrication and Quality & Inspection cost of cable tray
B57: Engineering & Fabrication cost (Rs) | D57: =D37*D9 -> 0
B58: Quality inspection and testing (Rs) | D58: =D37*D10 -> 0
B61: Cost model - final cost
B65: Summary (Cost per metre)
B67: Cost of steel (Rs) | D67: =D53 -> 316.34652
B68: Cost of raw material for galvanization (Rs) | D68: =O46 -> 105.46188
B69: Cost of fabrication (Rs) | D69: =D57 -> 0
B70: Cost of galvanization (Rs) | D70: =O40*H14 -> 0
B71: Quality inspection and testing (Rs) | D71: =D58 -> 0
B72: Vendor Overheads (Rs) | D72: =SUM(D67:D71)*D14 -> 0
B73: Profit margin for vendor | D73: =SUM(D67:D72)*D15 -> 1054.521
B74: Contract Performance Bank Guarantee (Rs) | D74: =SUM(D67:D73)*D16 -> 0
B75: Transportation and handling to site (Rs) | D75: =(D36-D44)*D13 -> 0
B77: Should be cost | D77: =SUM(D67:D75) -> 1476.3294
B78: Ex Works Should be cost | D78: =SUM(D67:D74) -> 1476.3294
D79: Cost model
C80: Weight of steel (kg) | D80: =D36 -> 4.376375
C81: Savings due to slots (kg) | D81: =D44 -> 0.14287
C82: Total weight (kg) | D82: =D80-D81 -> 4.233505
C83: Cost of steel (INR) | D83: =(D80-D81*D46)*D6 -> 316.34652
C85: Weight of Zinc required for galvanization (kg) | D85: =O39 -> 0.2672517
C86: Cost of zinc (INR) | D86: =D85*H8-O44 -> 105.46188
C88: Labour,Fabrication,Overhead,Profit Margin (INR) | D88: =(D82+D85)*($D$17+$D$15) -> 46.357794
C90: Total cost (INR) per metre | D90: =D88+D83+D86 -> 468.1662
C91: Cost per metre (INR) | D91: =D90/(D30/1000) -> 468.1662

Sheet Cantilever Arm 750
A1: Cable Tray Costing Cantilever Arm - 750 mm length, 2.5 mm thk (per piece, arm only - without base plate)
B5: Input for raw material and conversion costs | M5: Cantilever arm configuration
B6: Cost of steel(Rs/kg) | D6: 73 | F6: Coating thickness of Zinc (micron) | H6: 86
B7: Transportation and handling cost of raw material to vendor shop (% of raw material cost) | D7: 0 | F7: Specific weight of Zinc (kg/m3) | H7: 7135 | M7: Arm section - width (mm) | O7: 41
B8: Specific weight of MS (kg/m3) | D8: 7850 | F8: Cost of Zinc (Rs/kg) | H8: 425.6 | M8: Arm section - depth (mm) | O8: 41
B9: Cost of engg and fabrication (% of material cost) | D9: 0 | F9: Wastage during galvalization | H9: 0 | M9: Arm thickness (mm) | O9: 2.5
B10: Quality test and inspection charges (%) | D10: 0 | F10: Recoverable scrap - Ash per meter of tray (%) | H10: 0.12 | M10: Arm section - lip / return (mm) | O10: 9
B11: Salvage value of scrap for MS plates(% of overall value) | D11: 0.3 | F11: Recoverable scrap - Dross per meter of tray (%) | H11: 0.08 | M11: Arm length (mm) | O11: 750
B12: Wastage allowance during fabrication | D12: 0 | F12: Recoverable scrap salvage value - Ash (%) | H12: 0.26 | M12: Length of a slot in arm (mm) | O12: 28
B13: Transportation and handling cost of finished goods to site (Rs/kg) | D13: 0 | F13: Recoverable scrap salvage value - Dross (%) | H13: 0.52 | M13: Width of a slot in arm (mm) | O13: 13
B14: Overheads for vendor (%) | D14: 0 | F14: Cost of galvanization (% of material cost) | H14: 0 | M14: Pitch of slots along arm (mm) | O14: 50
B15: Profit & overhead margin (INR/kg) | D15: 2.5 | M15: No of slots per arm | O15: =ROUNDDOWN(O11/O14,0) -> 15
B16: Cost of contract Performance Bank Guarantee | D16: 0
B17: Labour & Fabrication Charges (INR/ kg) | D17: =6.5*1.2 -> 7.8
B25: Detailed Costing
B26: Cantilever arm MS material cost | M26: Galvalization
M27: Zinc Requirement
B28: Developed (strip) width of arm section (mm) | D28: =O7+2*O8+2*O10 -> 141
B29: Cross-section area of arm (mm2) | D29: =D28*O9 -> 352.5 | M29: Gross surface area - both faces (m2) | O29: =2*D28/1000*D30/1000 -> 0.2115
B30: Arm length (mm) | D30: =O11 -> 750 | M30: Surface area of slots along thickness (m2) | O30: =2*(O12+O13)/1000*O9/1000*D42 -> 0.003075
M31: Top surface area of slots - both faces (m2) | O31: =2*O12/1000*O13/1000*D42 -> 0.01092
B32: Arm thickness (mm) | D32: =O9 -> 2.5
M33: Overall surface area (m2) | O33: =O29+O30-O31 -> 0.203655
B35: Volume of steel in arm (m3) | D35: =D29*D30/10^9 -> 0.000264375 | M35: Total surface area for galvanization (m2) | O35: =O33 -> 0.203655
B36: Weight of arm (kg) | D36: =D35*D8 -> 2.0753438
B37: Cost of steel for arm (Rs) | D37: =D36*(D6*(1+D7)) -> 151.50009 | M37: Weight of Zinc required for galvanization (kg) | O37: =O35*H6*10^-6*H7 -> 0.12496474
M38: Wastage during galvalization | O38: =H9 -> 0
B39: Scrap salvage due to slots | M39: Total weight of Zinc required for galvanization (kg) | O39: =(1+O38)*O37 -> 0.12496474
M40: Cost of Zinc galvanization (Rs) | O40: =O39*H8 -> 53.184995
B41: No of slots per arm | D41: =O15 -> 15
B42: Total no of slots | D42: =D41 -> 15 | M42: Recoverable scrap - Ash (kg) | O42: =H10*O37 -> 0.014995769 | Q42: Recoverable scrap salvage - Ash (Rs/kg) | T42: =H12*$H$8 -> 110.656
B43: Total volume of slots (m3) | D43: =D42*O12/1000*O13/1000*O9/1000 -> 1.365e-05 | M43: Recoverable scrap - Dross (kg) | O43: =H11*O37 -> 0.0099971796 | Q43: Recoverable scrap salvage - Dross (Rs/kg) | T43: =H13*$H$8 -> 221.312
B44: Weight of slots (kg) | D44: =D43*D8 -> 0.1071525 | M44: Salvage value of zinc scrap (Rs) | O44: =O42*T42+O43*T43 -> 3.8718677
B45: Value of scrap generated (Rs) | D45: =D44*D6 -> 7.8221325
B46: Salvage value of scrap (% of overall value) | D46: =D11 -> 0.3 | M46: Net cost of Zinc galvanization (Rs) | O46: =O40-O44 -> 49.313128
B47: Salvage value of MS scrap (Rs) | D47: =D45*D46 -> 2.3466397
B49: Cost of material (Rs) | D49: =D37-D47 -> 149.15345
B51: Total cost of arm steel (Rs) per piece | D51: =D49 -> 149.15345
B52: Wastage allowance during fabrication | D52: =D12 -> 0
B53: Net cost of arm steel (Rs) per piece | D53: =(1+D52)*D51 -> 149.15345
B56: Engineering, Fabrication and Quality & Inspection cost of cable tray
B57: Engineering & Fabrication cost (Rs) | D57: =D37*D9 -> 0
B58: Quality inspection and testing (Rs) | D58: =D37*D10 -> 0
B61: Cost model - final cost (no TPL comparison)
B65: Summary (Cost per piece)
B67: Cost of steel (Rs) | D67: =D53 -> 149.15345
B68: Cost of raw material for galvanization (Rs) | D68: =O46 -> 49.313128
B69: Cost of fabrication (Rs) | D69: =D57 -> 0
B70: Cost of galvanization (Rs) | D70: =O40*H14 -> 0
B71: Quality inspection and testing (Rs) | D71: =D58 -> 0
B72: Vendor Overheads (Rs) | D72: =SUM(D67:D71)*D14 -> 0
B73: Profit margin for vendor | D73: =SUM(D67:D72)*D15 -> 496.16645
B74: Contract Performance Bank Guarantee (Rs) | D74: =SUM(D67:D73)*D16 -> 0
B75: Transportation and handling to site (Rs) | D75: =(D36-D44)*D13 -> 0
B77: Should be cost | D77: =SUM(D67:D75) -> 694.63304
B78: Ex Works Should be cost | D78: =SUM(D67:D74) -> 694.63304
D79: Cost model
C80: Weight of arm (kg) | D80: =D36 -> 2.0753438
C81: Savings due to slots (kg) | D81: =D44 -> 0.1071525
C82: Total weight of arm (kg) | D82: =D80-D81 -> 1.9681913
C83: Cost of steel (INR) | D83: =(D80-D81*D46)*D6 -> 149.15345
C85: Weight of Zinc required for galvanization (kg) | D85: =O39 -> 0.12496474
C86: Cost of zinc (INR) | D86: =D85*H8-O44 -> 49.313128
C88: Labour,Fabrication,Overhead,Profit Margin (INR) | D88: =(D82+D85)*($D$17+$D$15) -> 21.559507
C90: Total cost per cantilever arm (INR) | D90: =D88+D83+D86 -> 220.02609
C91: Cost per metre of arm (INR) | D91: =D90/(D30/1000) -> 293.36812

Sheet Cantilever Arm 620
A1: Cable Tray Costing Cantilever Arm - 750 mm length, 2.5 mm thk (per piece, arm only - without base plate)
B5: Input for raw material and conversion costs | M5: Cantilever arm configuration
B6: Cost of steel(Rs/kg) | D6: 73 | F6: Coating thickness of Zinc (micron) | H6: 86
B7: Transportation and handling cost of raw material to vendor shop (% of raw material cost) | D7: 0 | F7: Specific weight of Zinc (kg/m3) | H7: 7135 | M7: Arm section - width (mm) | O7: 41
B8: Specific weight of MS (kg/m3) | D8: 7850 | F8: Cost of Zinc (Rs/kg) | H8: 425.6 | M8: Arm section - depth (mm) | O8: 41
B9: Cost of engg and fabrication (% of material cost) | D9: 0 | F9: Wastage during galvalization | H9: 0 | M9: Arm thickness (mm) | O9: 2.5
B10: Quality test and inspection charges (%) | D10: 0 | F10: Recoverable scrap - Ash per meter of tray (%) | H10: 0.12 | M10: Arm section - lip / return (mm) | O10: 9
B11: Salvage value of scrap for MS plates(% of overall value) | D11: 0.3 | F11: Recoverable scrap - Dross per meter of tray (%) | H11: 0.08 | M11: Arm length (mm) | O11: 620
B12: Wastage allowance during fabrication | D12: 0 | F12: Recoverable scrap salvage value - Ash (%) | H12: 0.26 | M12: Length of a slot in arm (mm) | O12: 28
B13: Transportation and handling cost of finished goods to site (Rs/kg) | D13: 0 | F13: Recoverable scrap salvage value - Dross (%) | H13: 0.52 | M13: Width of a slot in arm (mm) | O13: 13
B14: Overheads for vendor (%) | D14: 0 | F14: Cost of galvanization (% of material cost) | H14: 0 | M14: Pitch of slots along arm (mm) | O14: 50
B15: Profit & overhead margin (INR/kg) | D15: 2.5 | M15: No of slots per arm | O15: =ROUNDDOWN(O11/O14,0) -> 12
B16: Cost of contract Performance Bank Guarantee | D16: 0
B17: Labour & Fabrication Charges (INR/ kg) | D17: =6.5*1.2 -> 7.8
B25: Detailed Costing
B26: Cantilever arm MS material cost | M26: Galvalization
M27: Zinc Requirement
B28: Developed (strip) width of arm section (mm) | D28: =O7+2*O8+2*O10 -> 141
B29: Cross-section area of arm (mm2) | D29: =D28*O9 -> 352.5 | M29: Gross surface area - both faces (m2) | O29: =2*D28/1000*D30/1000 -> 0.17484
B30: Arm length (mm) | D30: =O11 -> 620 | M30: Surface area of slots along thickness (m2) | O30: =2*(O12+O13)/1000*O9/1000*D42 -> 0.00246
M31: Top surface area of slots - both faces (m2) | O31: =2*O12/1000*O13/1000*D42 -> 0.008736
B32: Arm thickness (mm) | D32: =O9 -> 2.5
M33: Overall surface area (m2) | O33: =O29+O30-O31 -> 0.168564
B35: Volume of steel in arm (m3) | D35: =D29*D30/10^9 -> 0.00021855 | M35: Total surface area for galvanization (m2) | O35: =O33 -> 0.168564
B36: Weight of arm (kg) | D36: =D35*D8 -> 1.7156175
B37: Cost of steel for arm (Rs) | D37: =D36*(D6*(1+D7)) -> 125.24008 | M37: Weight of Zinc required for galvanization (kg) | O37: =O35*H6*10^-6*H7 -> 0.10343256
M38: Wastage during galvalization | O38: =H9 -> 0
B39: Scrap salvage due to slots | M39: Total weight of Zinc required for galvanization (kg) | O39: =(1+O38)*O37 -> 0.10343256
M40: Cost of Zinc galvanization (Rs) | O40: =O39*H8 -> 44.020896
B41: No of slots per arm | D41: =O15 -> 12
B42: Total no of slots | D42: =D41 -> 12 | M42: Recoverable scrap - Ash (kg) | O42: =H10*O37 -> 0.012411907 | Q42: Recoverable scrap salvage - Ash (Rs/kg) | T42: =H12*$H$8 -> 110.656
B43: Total volume of slots (m3) | D43: =D42*O12/1000*O13/1000*O9/1000 -> 1.092e-05 | M43: Recoverable scrap - Dross (kg) | O43: =H11*O37 -> 0.0082746045 | Q43: Recoverable scrap salvage - Dross (Rs/kg) | T43: =H13*$H$8 -> 221.312
B44: Weight of slots (kg) | D44: =D43*D8 -> 0.085722 | M44: Salvage value of zinc scrap (Rs) | O44: =O42*T42+O43*T43 -> 3.2047212
B45: Value of scrap generated (Rs) | D45: =D44*D6 -> 6.257706
B46: Salvage value of scrap (% of overall value) | D46: =D11 -> 0.3 | M46: Net cost of Zinc galvanization (Rs) | O46: =O40-O44 -> 40.816175
B47: Salvage value of MS scrap (Rs) | D47: =D45*D46 -> 1.8773118
B49: Cost of material (Rs) | D49: =D37-D47 -> 123.36277
B51: Total cost of arm steel (Rs) per piece | D51: =D49 -> 123.36277
B52: Wastage allowance during fabrication | D52: =D12 -> 0
B53: Net cost of arm steel (Rs) per piece | D53: =(1+D52)*D51 -> 123.36277
B56: Engineering, Fabrication and Quality & Inspection cost of cable tray
B57: Engineering & Fabrication cost (Rs) | D57: =D37*D9 -> 0
B58: Quality inspection and testing (Rs) | D58: =D37*D10 -> 0
B61: Cost model - final cost (no TPL comparison)
B65: Summary (Cost per piece)
B67: Cost of steel (Rs) | D67: =D53 -> 123.36277
B68: Cost of raw material for galvanization (Rs) | D68: =O46 -> 40.816175
B69: Cost of fabrication (Rs) | D69: =D57 -> 0
B70: Cost of galvanization (Rs) | D70: =O40*H14 -> 0
B71: Quality inspection and testing (Rs) | D71: =D58 -> 0
B72: Vendor Overheads (Rs) | D72: =SUM(D67:D71)*D14 -> 0
B73: Profit margin for vendor | D73: =SUM(D67:D72)*D15 -> 410.44735
B74: Contract Performance Bank Guarantee (Rs) | D74: =SUM(D67:D73)*D16 -> 0
B75: Transportation and handling to site (Rs) | D75: =(D36-D44)*D13 -> 0
B77: Should be cost | D77: =SUM(D67:D75) -> 574.62629
B78: Ex Works Should be cost | D78: =SUM(D67:D74) -> 574.62629
D79: Cost model
C80: Weight of arm (kg) | D80: =D36 -> 1.7156175
C81: Savings due to slots (kg) | D81: =D44 -> 0.085722
C82: Total weight of arm (kg) | D82: =D80-D81 -> 1.6298955
C83: Cost of steel (INR) | D83: =(D80-D81*D46)*D6 -> 123.36277
C85: Weight of Zinc required for galvanization (kg) | D85: =O39 -> 0.10343256
C86: Cost of zinc (INR) | D86: =D85*H8-O44 -> 40.816175
C88: Labour,Fabrication,Overhead,Profit Margin (INR) | D88: =(D82+D85)*($D$17+$D$15) -> 17.853279
C90: Total cost per cantilever arm (INR) | D90: =D88+D83+D86 -> 182.03222
C91: Cost per metre of arm (INR) | D91: =D90/(D30/1000) -> 293.60035

Sheet Cantilever Arm 320
A1: Cable Tray Costing Cantilever Arm - 750 mm length, 2.5 mm thk (per piece, arm only - without base plate)
B5: Input for raw material and conversion costs | M5: Cantilever arm configuration
B6: Cost of steel(Rs/kg) | D6: 73 | F6: Coating thickness of Zinc (micron) | H6: 86
B7: Transportation and handling cost of raw material to vendor shop (% of raw material cost) | D7: 0 | F7: Specific weight of Zinc (kg/m3) | H7: 7135 | M7: Arm section - width (mm) | O7: 41
B8: Specific weight of MS (kg/m3) | D8: 7850 | F8: Cost of Zinc (Rs/kg) | H8: 425.6 | M8: Arm section - depth (mm) | O8: 41
B9: Cost of engg and fabrication (% of material cost) | D9: 0 | F9: Wastage during galvalization | H9: 0 | M9: Arm thickness (mm) | O9: 2.5
B10: Quality test and inspection charges (%) | D10: 0 | F10: Recoverable scrap - Ash per meter of tray (%) | H10: 0.12 | M10: Arm section - lip / return (mm) | O10: 9
B11: Salvage value of scrap for MS plates(% of overall value) | D11: 0.3 | F11: Recoverable scrap - Dross per meter of tray (%) | H11: 0.08 | M11: Arm length (mm) | O11: 320
B12: Wastage allowance during fabrication | D12: 0 | F12: Recoverable scrap salvage value - Ash (%) | H12: 0.26 | M12: Length of a slot in arm (mm) | O12: 28
B13: Transportation and handling cost of finished goods to site (Rs/kg) | D13: 0 | F13: Recoverable scrap salvage value - Dross (%) | H13: 0.52 | M13: Width of a slot in arm (mm) | O13: 13
B14: Overheads for vendor (%) | D14: 0 | F14: Cost of galvanization (% of material cost) | H14: 0 | M14: Pitch of slots along arm (mm) | O14: 50
B15: Profit & overhead margin (INR/kg) | D15: 2.5 | M15: No of slots per arm | O15: =ROUNDDOWN(O11/O14,0) -> 6
B16: Cost of contract Performance Bank Guarantee | D16: 0
B17: Labour & Fabrication Charges (INR/ kg) | D17: =6.5*1.2 -> 7.8
B25: Detailed Costing
B26: Cantilever arm MS material cost | M26: Galvalization
M27: Zinc Requirement
B28: Developed (strip) width of arm section (mm) | D28: =O7+2*O8+2*O10 -> 141
B29: Cross-section area of arm (mm2) | D29: =D28*O9 -> 352.5 | M29: Gross surface area - both faces (m2) | O29: =2*D28/1000*D30/1000 -> 0.09024
B30: Arm length (mm) | D30: =O11 -> 320 | M30: Surface area of slots along thickness (m2) | O30: =2*(O12+O13)/1000*O9/1000*D42 -> 0.00123
M31: Top surface area of slots - both faces (m2) | O31: =2*O12/1000*O13/1000*D42 -> 0.004368
B32: Arm thickness (mm) | D32: =O9 -> 2.5
M33: Overall surface area (m2) | O33: =O29+O30-O31 -> 0.087102
B35: Volume of steel in arm (m3) | D35: =D29*D30/10^9 -> 0.0001128 | M35: Total surface area for galvanization (m2) | O35: =O33 -> 0.087102
B36: Weight of arm (kg) | D36: =D35*D8 -> 0.88548
B37: Cost of steel for arm (Rs) | D37: =D36*(D6*(1+D7)) -> 64.64004 | M37: Weight of Zinc required for galvanization (kg) | O37: =O35*H6*10^-6*H7 -> 0.053446658
M38: Wastage during galvalization | O38: =H9 -> 0
B39: Scrap salvage due to slots | M39: Total weight of Zinc required for galvanization (kg) | O39: =(1+O38)*O37 -> 0.053446658
M40: Cost of Zinc galvanization (Rs) | O40: =O39*H8 -> 22.746898
B41: No of slots per arm | D41: =O15 -> 6
B42: Total no of slots | D42: =D41 -> 6 | M42: Recoverable scrap - Ash (kg) | O42: =H10*O37 -> 0.006413599 | Q42: Recoverable scrap salvage - Ash (Rs/kg) | T42: =H12*$H$8 -> 110.656
B43: Total volume of slots (m3) | D43: =D42*O12/1000*O13/1000*O9/1000 -> 5.46e-06 | M43: Recoverable scrap - Dross (kg) | O43: =H11*O37 -> 0.0042757327 | Q43: Recoverable scrap salvage - Dross (Rs/kg) | T43: =H13*$H$8 -> 221.312
B44: Weight of slots (kg) | D44: =D43*D8 -> 0.042861 | M44: Salvage value of zinc scrap (Rs) | O44: =O42*T42+O43*T43 -> 1.6559742
B45: Value of scrap generated (Rs) | D45: =D44*D6 -> 3.128853
B46: Salvage value of scrap (% of overall value) | D46: =D11 -> 0.3 | M46: Net cost of Zinc galvanization (Rs) | O46: =O40-O44 -> 21.090924
B47: Salvage value of MS scrap (Rs) | D47: =D45*D46 -> 0.9386559
B49: Cost of material (Rs) | D49: =D37-D47 -> 63.701384
B51: Total cost of arm steel (Rs) per piece | D51: =D49 -> 63.701384
B52: Wastage allowance during fabrication | D52: =D12 -> 0
B53: Net cost of arm steel (Rs) per piece | D53: =(1+D52)*D51 -> 63.701384
B56: Engineering, Fabrication and Quality & Inspection cost of cable tray
B57: Engineering & Fabrication cost (Rs) | D57: =D37*D9 -> 0
B58: Quality inspection and testing (Rs) | D58: =D37*D10 -> 0
B61: Cost model - final cost (no TPL comparison)
B65: Summary (Cost per piece)
B67: Cost of steel (Rs) | D67: =D53 -> 63.701384
B68: Cost of raw material for galvanization (Rs) | D68: =O46 -> 21.090924
B69: Cost of fabrication (Rs) | D69: =D57 -> 0
B70: Cost of galvanization (Rs) | D70: =O40*H14 -> 0
B71: Quality inspection and testing (Rs) | D71: =D58 -> 0
B72: Vendor Overheads (Rs) | D72: =SUM(D67:D71)*D14 -> 0
B73: Profit margin for vendor | D73: =SUM(D67:D72)*D15 -> 211.98077
B74: Contract Performance Bank Guarantee (Rs) | D74: =SUM(D67:D73)*D16 -> 0
B75: Transportation and handling to site (Rs) | D75: =(D36-D44)*D13 -> 0
B77: Should be cost | D77: =SUM(D67:D75) -> 296.77308
B78: Ex Works Should be cost | D78: =SUM(D67:D74) -> 296.77308
D79: Cost model
C80: Weight of arm (kg) | D80: =D36 -> 0.88548
C81: Savings due to slots (kg) | D81: =D44 -> 0.042861
C82: Total weight of arm (kg) | D82: =D80-D81 -> 0.842619
C83: Cost of steel (INR) | D83: =(D80-D81*D46)*D6 -> 63.701384
C85: Weight of Zinc required for galvanization (kg) | D85: =O39 -> 0.053446658
C86: Cost of zinc (INR) | D86: =D85*H8-O44 -> 21.090924
C88: Labour,Fabrication,Overhead,Profit Margin (INR) | D88: =(D82+D85)*($D$17+$D$15) -> 9.2294763
C90: Total cost per cantilever arm (INR) | D90: =D88+D83+D86 -> 94.021784
C91: Cost per metre of arm (INR) | D91: =D90/(D30/1000) -> 293.81807

Sheet Horizontal Tee 600x100x2
A1: Cable Tray Costing: Ladder Type Horizontal Tee, Bending Radius 1200 mm
B5: Input for raw material and conversion costs | M5: Cable Tray configuration
B6: Cost of 1 kg of MS (Rs) | D6: 73 | F6: Coating thickness of Zinc (micron) | H6: 86 | M6: Runners | Q6: Rungs
B7: Transportation and handling cost of raw material to vendor shop (% of raw material cost) | D7: 0 | F7: Specific weight of Zinc (kg/m3) | H7: 7135 | M7: Number of runners | O7: 2 | Q7: No of rungs per 2500 meter of runner | U7: 10
B8: Specific weight of MS (kg/m3) | D8: 7850 | F8: Cost of Zinc (Rs/kg) | H8: 425.6 | M8: Tray width (mm) | O8: 600 | Q8: Length of rung (mm) | U8: =O8 -> 600
B9: Cost of engg and fabrication (% of material cost) | D9: 0 | F9: Wastage during galvalization | H9: 0 | M9: Tray Depth (mm) | O9: 100 | Q9: Width of rung (mm) | U9: 50
B10: Quality test and inspection charges (%) | D10: 0 | F10: Recoverable scrap - Ash per meter of tray (%) | H10: 0.12 | M10: Tray thickness (mm) | O10: 2 | Q10: Collar / Height of rung (mm) | U10: 20
B11: Salvage value of scrap for MS plates(% of overall value) | D11: 0.5 | F11: Recoverable scrap - Dross per meter of tray (%) | H11: 0.08 | M11: Tray collar (mm) | O11: 25 | Q11: Thickness of rung (mm) | U11: 2
B12: Wastage allowance during fabrication | D12: 0 | F12: Recoverable scrap salvage value - Ash (%) | H12: 0.26 | M12: Tray length (mm) | O12: 4200 | Q12: No of slots per 40 mm of length | U12: 1
B13: Transportation and handling cost of finished goods to site (Rs/kg) | D13: 0 | F13: Recoverable scrap salvage value - Dross (%) | H13: 0.52 | M13: No of holes per 2500 mm length | O13: 20 | Q13: Length of 1 slot (mm) | U13: 25
B14: Overheads for vendor (%) | D14: 0 | F14: Cost of galvanization (% of material cost) | H14: 0 | M14: Dia of 1 hole (mm) | O14: 10 | Q14: Width of 1 slot (mm) | U14: 10
B15: Profit margin for vendor (%) | D15: 2.5
B16: Cost of contract Performance Bank Guarantee | D16: 0
B17: Labour,Fabrication,Overhead,Profit Margin (INR/ kg) | D17: =6.5*1.2 -> 7.8
B20: Detailed Costing
B21: Cable tray MS material cost | M21: Galvalization
B22: Runner | F22: Rung | M22: Zinc Requirement
B23: Number of runners per meter length | D23: =O7 -> 2 | F23: No of rungs in this fitting (U7 x length / 2500, rounded) | J23: =ROUND(U7*D28/2500,0) -> 17 | M23: Runner | Q23: Rung
B24: Tray width (mm) | D24: =O8 -> 600 | F24: Length of rung (mm) | J24: =U8 -> 600 | M24: Surface area for 1 m length (m2) | O24: =2*(2*(2*D27+D25)/1000*D28/1000) -> 2.52 | Q24: Surface area for 1 rung (m2) | T24: =2*J24/1000*(J25+2*J26)/1000 -> 0.108
B25: Tray Depth (mm) | D25: =O9 -> 100 | F25: Width of rung (mm) | J25: =U9 -> 50 | M25: Surface area holes along thickness for 1 m length (m2) | O25: =D37*3.14*D38/1000*D26/1000*D28/125 -> 0.0422016 | Q25: Surface area of slots along thickness for 1 rung (m2) | T25: =(2*(J38+J39)/1000*D26/1000)*D24/40 -> 0.0021
B26: Tray thickness (mm) | D26: =O10 -> 2 | F26: Collar / Height of rung (mm) | J26: =U10 -> 20 | M26: Top surface area of holes for 1 m length (m2) | O26: =D37*3.14*(D38/2/1000)^2*D28/125 -> 0.052752 | Q26: Top surface area of slots 1 rung (m2) | T26: =J38/1000*J39/1000*D24/40 -> 0.00375
B27: Tray collar (mm) | D27: =O11 -> 25 | F27: Thickness of rung (mm) | J27: =U11 -> 2
B28: Tray length (mm) | D28: =O12 -> 4200 | M28: Overall surface area for 1 meter of runner (m2) | O28: =O24+O25-O26 -> 2.5094496 | Q28: Overall rung surface area for 1 meter of runner (m2) | T28: =(T24+T25-T26)*J23 -> 1.80795
F29: Volume of 1 rung (m3) | J29: =(2*J26+J25)/1000*J24/1000*J27/1000 -> 0.000108
F30: Weight of 1 rung (kg) | J30: =J29*D8 -> 0.8478 | M30: Total surface area per meter of cable tray (m2) | O30: =O28+T28 -> 4.3173996
B31: Volume of runner (m3) | D31: =2*(D25+D27*2)/1000*D26/1000*D28/1000 -> 0.00252 | F31: Cost of 1 rung (Rs) | J31: =J30*(D6*(1+D7)) -> 61.8894
B32: Weight of runner per meter length (kg) | D32: =D31*D8 -> 19.782 | F32: Cost of rungs per meter of runner | J32: =J31*J23 -> 1052.1198 | M32: Weight of Zinc required for galvanization (kg) | O32: =O30*H6*10^-6*H7 -> 2.6491996
B33: Cost of runner per meter length (Rs) | D33: =D32*(D6*(1+D7)) -> 1444.086 | M33: Wastage during galvalization | O33: =H9 -> 0
M34: Total weight of Zinc required for galvanization (kg) | O34: =(1+O33)*O32 -> 2.6491996
B35: Scrap salvage due to holes / slots | M35: Cost of Zinc galvanization per meter of runner (Rs) | O35: =O34*H8 -> 1127.4993
B36: Runner | F36: Rung
B37: No of holes per 2500 mm length | D37: =O13 -> 20 | F37: No of slots per 40 mm of length | J37: =U12 -> 1 | M37: Recoverable scrap - Ash per meter of tray (kg) | O37: =H10*O32 -> 0.31790395 | Q37: Recoverable scrap salvage - Ash (Rs/kg) | T37: =H12*$H$8 -> 110.656
B38: Dia of 1 hole (mm) | D38: =O14 -> 10 | F38: Length of 1 slot (mm) | J38: =U13 -> 25 | M38: Recoverable scrap - Dross per meter of tray (kg) | O38: =H11*O32 -> 0.21193597 | Q38: Recoverable scrap salvage - Dross (Rs/kg) | T38: =H13*$H$8 -> 221.312
B39: Volume of holes (m3) | D39: =2*D37*3.14*(D38/2/1000)^2*D26/1000 -> 6.28e-06 | F39: Width of 1 slot (mm) | J39: =U14 -> 10 | M39: Salvage value of scrap per meter of cable (Rs) | O39: =O37*T37+O38*T38 -> 82.081952
F40: Volume of 1 slot (m3) | J40: =J38/1000*J39/1000*J27/1000 -> 5e-07
B41: Weight of holes per 2500 mm of runner (kg) | D41: =D39*D8 -> 0.049298 | F41: Volume slots per rung (m3) | J41: =D24/40*J40 -> 7.5e-06 | M41: Net cost of Zinc galvanization per meter of runner (Rs) | O41: =O35-O39 -> 1045.4174
B42: Value of scrap generated per meter of runner (Rs) | D42: =D41*D6 -> 3.598754 | F42: Weight of slots per rung (kg) | J42: =J41*D8 -> 0.058875
B43: Salvage value of scrap (% of overall value) | D43: =D11 -> 0.5 | F43: Weight of slots per 2500mm of runner (kg) | J43: =J42*J23 -> 1.000875
B44: Salvage value of MS scrap per meter of runner (Rs) | D44: =D42*D43 -> 1.799377 | F44: Value of scrap generated per meter of runner (Rs) | J44: =J43*D6 -> 73.063875
F45: Salvage value of MS scrap per meter of runner (Rs) | J45: =J44*D43 -> 36.531937
B47: Cost of material for 1 m of runner (Rs) | D47: =D33-D44 -> 1442.2866 | F47: Cost of material for rungs per meter of runner (Rs) | J47: =J32-J45 -> 1015.5879
B49: Total cost per meter of cable tray (Rs) | D49: =D47+J47 -> 2457.8745
B50: Wastage allowance during fabrication | D50: =D12 -> 0
B51: Net cost per meter of cable tray (Rs) | D51: =(1+D50)*D49 -> 2457.8745
B54: Engineering, Fabrication and Quality & Inspection cost of cable tray | M54: Cost of galvanization
B55: Engineering & Fabrication cost (Rs) | D55: =(D33+J32)*D9 -> 0 | M55: Galvanization cost (Rs) | N55: =O35*H14 -> 0
B56: Quality inspection and testing (Rs) | D56: =(D33+J32)*D10 -> 0
B61: Summary (Cost of cable tray per meter length)
B63: Cost of steel (Rs) | D63: =D51 -> 2457.8745
B64: Cost of raw material for galvanization (Rs) | D64: =O41 -> 1045.4174
B65: Cost of fabrication (Rs) | D65: =D55 -> 0
B66: Cost of galvanization (Rs) | D66: =N55 -> 0
B67: Quality inspection and testing (Rs) | D67: =D56 -> 0
B68: Vendor Overheads (Rs) | D68: =SUM(D63:D67)*D14 -> 0
B69: Profit margin for vendor (Rs) | D69: =SUM(D63:D68)*D15 -> 8758.2297
B70: Contract Performance Bank Guarantee (Rs) | D70: =SUM(D63:D69)*D16 -> 0
B71: Transportation and handling to site (Rs) | D71: =(D32+J30*J23-D41-J43)*D13 -> 0
B72: Should be cost (Rs per meter) | D72: =SUM(D63:D71) -> 12261.522
B73: Ex Works Should be cost (Rs per meter) | D73: =SUM(D63:D70) -> 12261.522
B79: Comparison - Cost model viz-a-viz TPL estimations
C81: B4-i: Ladder Type Horizontal Tee, Bending Radius 1200 mm - 600mm(W) X 100mm(H) X 2mm(T), ~4.20 m
B83: Summary (Cost of cable tray - 2500 length)
B85: Cost of steel (Rs) | D85: =D71 -> 0
B86: Cost of raw material for galvanization (Rs) | D86: =O64 -> 0
B87: Cost of fabrication (Rs) | D87: =D75 -> 0
B88: Cost of galvanization (Rs) | D88: =O75 -> 0
B89: Quality inspection and testing (Rs) | D89: =D76 -> 0
B90: Vendor Overheads (Rs) | D90: =SUM(D85:D89)*D36 -> 0
B91: Profit margin for vendor | D91: =SUM(D85:D90)*D37 -> 0
B92: Contract Performance Bank Guarantee (Rs) | D92: =SUM(D85:D91)*D38 -> 0
B93: Transportation and handling to site (Rs) | D93: =(D54-D62-I63)*D35 -> 0
B95: Should be cost | D95: =SUM(D85:D93) -> 0
B96: Ex Works Should be cost | D96: =SUM(D85:D92) -> 0
D97: Suggested model | E97: TPL model
C98: Weight of runner (kg) | D98: =D32 -> 19.782 | E98: ='[1]Old Ladder type (2)'!K30 -> 19.782
C99: Savings due to holes/ slots in runner (kg) | D99: =D41 -> 0.049298 | E99: 0
C100: Weight of rung (kg) | D100: =J30*J23 -> 14.4126 | E100: ='[1]Old Ladder type (2)'!L30 -> 14.4126
C101: Savings due to slots in rung (kg) | D101: =J43 -> 1.000875 | E101: 0
C102: ="Weight of Coupler plate ("&'[1]Coupler Plate'!N6&"X"&'[1]Coupler Plate'!N7&"X"&'[1]Coupler Plate'!N8&") (kg)" -> Weight of Coupler plate (70X210X2) (kg) | D102: ='[1]Coupler Plate'!D37*2 -> 0.414009 | E102: ='[1]Old Ladder type (2)'!M30 -> 0.46158
C103: Hardware weight (Nut,bolt and washer) (kg) | D103: 0.32 | E103: 0.32 | G103: fixed
C104: Total weight (kg) | D104: =D98-D99+D100-D101+D102+D103 -> 33.878436 | E104: =E98-E99+E100-E101+E102+E103 -> 34.97618 | F104: =(E104-D104)/D104 -> 0.03240244
C105: Cost of steel (INR) | D105: =(D98*D6-D11*D99*D6)+(D100*D6-D11*D101*D6)+('[1]Coupler Plate'!D24-D43*'[1]Coupler Plate'!D34)*D6*2+D103*D6 -> 2513.1935 | E105: =E104*D6 -> 2553.2611
C107: Weight of Zinc required for galvanization (kg) | D107: =5%*D104 -> 1.6939218 | E107: =5%*E104 -> 1.748809 | G107: TPL assumption: 5% of steel weight; zinc weight to be calculated basis coating thickness
C108: Cost of zinc (INR) | D108: =D107*$H$8 -> 720.93312 | E108: =E107*$H$8 -> 744.29311
C110: Labour,Fabrication,Overhead,Profit Margin (INR) | D110: =(D104+D107)*$D$17 -> 277.46439 | E110: =(E104+E107)*$D$17 -> 286.45491
C112: Total cost (INR) per tray | D112: =D110+D105+D108 -> 3511.591 | E112: =E110+E105+E108 -> 3584.0092
C113: Cost per meter (INR) per tray | D113: =D112/(O12/1000) -> 836.09309 | E113: =E112/(O12/1000) -> 853.33552
C114: Savings | D114: =(E112-D112)/D112 -> 0.02062261
B118: Comparison table - Summary
D120: TPL | H120: Cost Model
C121: B4-i: Ladder Type Horizontal Tee, Bending Radius 1200 mm, 600mm(W) X 100mm(H), 2mm thk M.S. sheet, ~4.20 m, hot dip galvanised incl. coupler plate
D123: Weight of steel (kg) | E123: Weight of zinc (kg) | F123: Estimated price | H123: Weight of steel (kg) | I123: Weight of zinc (kg) | J123: Estimated price | K123: Price difference
C124: ='[1]Old Ladder type (2)'!B30 -> 600mm(W)X100mm(H) - B4-i horizontal tee | D124: ='[1]Old Ladder type (2)'!Q30 -> 34.97618 | E124: ='[1]Old Ladder type (2)'!U30 -> 1.748809 | F124: ='[1]Old Ladder type (2)'!Z30 -> 2950.7479 | H124: =D104 -> 33.878436 | I124: =D107 -> 1.6939218 | J124: =D112 -> 3511.591 | K124: =(F124-J124)/J124 -> -0.15971195

Sheet Horizontal Tee 300x100x2
A1: Cable Tray Costing: Ladder Type Horizontal Tee, Bending Radius 1200 mm
B5: Input for raw material and conversion costs | M5: Cable Tray configuration
B6: Cost of 1 kg of MS (Rs) | D6: 73 | F6: Coating thickness of Zinc (micron) | H6: 86 | M6: Runners | Q6: Rungs
B7: Transportation and handling cost of raw material to vendor shop (% of raw material cost) | D7: 0 | F7: Specific weight of Zinc (kg/m3) | H7: 7135 | M7: Number of runners | O7: 2 | Q7: No of rungs per 2500 meter of runner | U7: 10
B8: Specific weight of MS (kg/m3) | D8: 7850 | F8: Cost of Zinc (Rs/kg) | H8: 425.6 | M8: Tray width (mm) | O8: 300 | Q8: Length of rung (mm) | U8: =O8 -> 300
B9: Cost of engg and fabrication (% of material cost) | D9: 0 | F9: Wastage during galvalization | H9: 0 | M9: Tray Depth (mm) | O9: 100 | Q9: Width of rung (mm) | U9: 50
B10: Quality test and inspection charges (%) | D10: 0 | F10: Recoverable scrap - Ash per meter of tray (%) | H10: 0.12 | M10: Tray thickness (mm) | O10: 2 | Q10: Collar / Height of rung (mm) | U10: 20
B11: Salvage value of scrap for MS plates(% of overall value) | D11: 0.5 | F11: Recoverable scrap - Dross per meter of tray (%) | H11: 0.08 | M11: Tray collar (mm) | O11: 25 | Q11: Thickness of rung (mm) | U11: 2
B12: Wastage allowance during fabrication | D12: 0 | F12: Recoverable scrap salvage value - Ash (%) | H12: 0.26 | M12: Tray length (mm) | O12: 4200 | Q12: No of slots per 40 mm of length | U12: 1
B13: Transportation and handling cost of finished goods to site (Rs/kg) | D13: 0 | F13: Recoverable scrap salvage value - Dross (%) | H13: 0.52 | M13: No of holes per 2500 mm length | O13: 20 | Q13: Length of 1 slot (mm) | U13: 25
B14: Overheads for vendor (%) | D14: 0 | F14: Cost of galvanization (% of material cost) | H14: 0 | M14: Dia of 1 hole (mm) | O14: 10 | Q14: Width of 1 slot (mm) | U14: 10
B15: Profit margin for vendor (%) | D15: 2.5
B16: Cost of contract Performance Bank Guarantee | D16: 0
B17: Labour,Fabrication,Overhead,Profit Margin (INR/ kg) | D17: =6.5*1.2 -> 7.8
B20: Detailed Costing
B21: Cable tray MS material cost | M21: Galvalization
B22: Runner | F22: Rung | M22: Zinc Requirement
B23: Number of runners per meter length | D23: =O7 -> 2 | F23: No of rungs in this fitting (U7 x length / 2500, rounded) | J23: =ROUND(U7*D28/2500,0) -> 17 | M23: Runner | Q23: Rung
B24: Tray width (mm) | D24: =O8 -> 300 | F24: Length of rung (mm) | J24: =U8 -> 300 | M24: Surface area for 1 m length (m2) | O24: =2*(2*(2*D27+D25)/1000*D28/1000) -> 2.52 | Q24: Surface area for 1 rung (m2) | T24: =2*J24/1000*(J25+2*J26)/1000 -> 0.054
B25: Tray Depth (mm) | D25: =O9 -> 100 | F25: Width of rung (mm) | J25: =U9 -> 50 | M25: Surface area holes along thickness for 1 m length (m2) | O25: =D37*3.14*D38/1000*D26/1000*D28/125 -> 0.0422016 | Q25: Surface area of slots along thickness for 1 rung (m2) | T25: =(2*(J38+J39)/1000*D26/1000)*D24/40 -> 0.00105
B26: Tray thickness (mm) | D26: =O10 -> 2 | F26: Collar / Height of rung (mm) | J26: =U10 -> 20 | M26: Top surface area of holes for 1 m length (m2) | O26: =D37*3.14*(D38/2/1000)^2*D28/125 -> 0.052752 | Q26: Top surface area of slots 1 rung (m2) | T26: =J38/1000*J39/1000*D24/40 -> 0.001875
B27: Tray collar (mm) | D27: =O11 -> 25 | F27: Thickness of rung (mm) | J27: =U11 -> 2
B28: Tray length (mm) | D28: =O12 -> 4200 | M28: Overall surface area for 1 meter of runner (m2) | O28: =O24+O25-O26 -> 2.5094496 | Q28: Overall rung surface area for 1 meter of runner (m2) | T28: =(T24+T25-T26)*J23 -> 0.903975
F29: Volume of 1 rung (m3) | J29: =(2*J26+J25)/1000*J24/1000*J27/1000 -> 5.4e-05
F30: Weight of 1 rung (kg) | J30: =J29*D8 -> 0.4239 | M30: Total surface area per meter of cable tray (m2) | O30: =O28+T28 -> 3.4134246
B31: Volume of runner (m3) | D31: =2*(D25+D27*2)/1000*D26/1000*D28/1000 -> 0.00252 | F31: Cost of 1 rung (Rs) | J31: =J30*(D6*(1+D7)) -> 30.9447
B32: Weight of runner per meter length (kg) | D32: =D31*D8 -> 19.782 | F32: Cost of rungs per meter of runner | J32: =J31*J23 -> 526.0599 | M32: Weight of Zinc required for galvanization (kg) | O32: =O30*H6*10^-6*H7 -> 2.0945115
B33: Cost of runner per meter length (Rs) | D33: =D32*(D6*(1+D7)) -> 1444.086 | M33: Wastage during galvalization | O33: =H9 -> 0
M34: Total weight of Zinc required for galvanization (kg) | O34: =(1+O33)*O32 -> 2.0945115
B35: Scrap salvage due to holes / slots | M35: Cost of Zinc galvanization per meter of runner (Rs) | O35: =O34*H8 -> 891.42408
B36: Runner | F36: Rung
B37: No of holes per 2500 mm length | D37: =O13 -> 20 | F37: No of slots per 40 mm of length | J37: =U12 -> 1 | M37: Recoverable scrap - Ash per meter of tray (kg) | O37: =H10*O32 -> 0.25134138 | Q37: Recoverable scrap salvage - Ash (Rs/kg) | T37: =H12*$H$8 -> 110.656
B38: Dia of 1 hole (mm) | D38: =O14 -> 10 | F38: Length of 1 slot (mm) | J38: =U13 -> 25 | M38: Recoverable scrap - Dross per meter of tray (kg) | O38: =H11*O32 -> 0.16756092 | Q38: Recoverable scrap salvage - Dross (Rs/kg) | T38: =H13*$H$8 -> 221.312
B39: Volume of holes (m3) | D39: =2*D37*3.14*(D38/2/1000)^2*D26/1000 -> 6.28e-06 | F39: Width of 1 slot (mm) | J39: =U14 -> 10 | M39: Salvage value of scrap per meter of cable (Rs) | O39: =O37*T37+O38*T38 -> 64.895673
F40: Volume of 1 slot (m3) | J40: =J38/1000*J39/1000*J27/1000 -> 5e-07
B41: Weight of holes per 2500 mm of runner (kg) | D41: =D39*D8 -> 0.049298 | F41: Volume slots per rung (m3) | J41: =D24/40*J40 -> 3.75e-06 | M41: Net cost of Zinc galvanization per meter of runner (Rs) | O41: =O35-O39 -> 826.52841
B42: Value of scrap generated per meter of runner (Rs) | D42: =D41*D6 -> 3.598754 | F42: Weight of slots per rung (kg) | J42: =J41*D8 -> 0.0294375
B43: Salvage value of scrap (% of overall value) | D43: =D11 -> 0.5 | F43: Weight of slots per 2500mm of runner (kg) | J43: =J42*J23 -> 0.5004375
B44: Salvage value of MS scrap per meter of runner (Rs) | D44: =D42*D43 -> 1.799377 | F44: Value of scrap generated per meter of runner (Rs) | J44: =J43*D6 -> 36.531937
F45: Salvage value of MS scrap per meter of runner (Rs) | J45: =J44*D43 -> 18.265969
B47: Cost of material for 1 m of runner (Rs) | D47: =D33-D44 -> 1442.2866 | F47: Cost of material for rungs per meter of runner (Rs) | J47: =J32-J45 -> 507.79393
B49: Total cost per meter of cable tray (Rs) | D49: =D47+J47 -> 1950.0806
B50: Wastage allowance during fabrication | D50: =D12 -> 0
B51: Net cost per meter of cable tray (Rs) | D51: =(1+D50)*D49 -> 1950.0806
B54: Engineering, Fabrication and Quality & Inspection cost of cable tray | M54: Cost of galvanization
B55: Engineering & Fabrication cost (Rs) | D55: =(D33+J32)*D9 -> 0 | M55: Galvanization cost (Rs) | N55: =O35*H14 -> 0
B56: Quality inspection and testing (Rs) | D56: =(D33+J32)*D10 -> 0
B61: Summary (Cost of cable tray per meter length)
B63: Cost of steel (Rs) | D63: =D51 -> 1950.0806
B64: Cost of raw material for galvanization (Rs) | D64: =O41 -> 826.52841
B65: Cost of fabrication (Rs) | D65: =D55 -> 0
B66: Cost of galvanization (Rs) | D66: =N55 -> 0
B67: Quality inspection and testing (Rs) | D67: =D56 -> 0
B68: Vendor Overheads (Rs) | D68: =SUM(D63:D67)*D14 -> 0
B69: Profit margin for vendor (Rs) | D69: =SUM(D63:D68)*D15 -> 6941.5224
B70: Contract Performance Bank Guarantee (Rs) | D70: =SUM(D63:D69)*D16 -> 0
B71: Transportation and handling to site (Rs) | D71: =(D32+J30*J23-D41-J43)*D13 -> 0
B72: Should be cost (Rs per meter) | D72: =SUM(D63:D71) -> 9718.1314
B73: Ex Works Should be cost (Rs per meter) | D73: =SUM(D63:D70) -> 9718.1314
B79: Comparison - Cost model viz-a-viz TPL estimations
C81: B4-i: Ladder Type Horizontal Tee, Bending Radius 1200 mm - 600mm(W) X 100mm(H) X 2mm(T), ~4.20 m
B83: Summary (Cost of cable tray - 2500 length)
B85: Cost of steel (Rs) | D85: =D71 -> 0
B86: Cost of raw material for galvanization (Rs) | D86: =O64 -> 0
B87: Cost of fabrication (Rs) | D87: =D75 -> 0
B88: Cost of galvanization (Rs) | D88: =O75 -> 0
B89: Quality inspection and testing (Rs) | D89: =D76 -> 0
B90: Vendor Overheads (Rs) | D90: =SUM(D85:D89)*D36 -> 0
B91: Profit margin for vendor | D91: =SUM(D85:D90)*D37 -> 0
B92: Contract Performance Bank Guarantee (Rs) | D92: =SUM(D85:D91)*D38 -> 0
B93: Transportation and handling to site (Rs) | D93: =(D54-D62-I63)*D35 -> 0
B95: Should be cost | D95: =SUM(D85:D93) -> 0
B96: Ex Works Should be cost | D96: =SUM(D85:D92) -> 0
D97: Suggested model | E97: TPL model
C98: Weight of runner (kg) | D98: =D32 -> 19.782 | E98: ='[1]Old Ladder type (2)'!K30 -> 19.782
C99: Savings due to holes/ slots in runner (kg) | D99: =D41 -> 0.049298 | E99: 0
C100: Weight of rung (kg) | D100: =J30*J23 -> 7.2063 | E100: ='[1]Old Ladder type (2)'!L30 -> 14.4126
C101: Savings due to slots in rung (kg) | D101: =J43 -> 0.5004375 | E101: 0
C102: ="Weight of Coupler plate ("&'[1]Coupler Plate'!N6&"X"&'[1]Coupler Plate'!N7&"X"&'[1]Coupler Plate'!N8&") (kg)" -> Weight of Coupler plate (70X210X2) (kg) | D102: ='[1]Coupler Plate'!D37*2 -> 0.414009 | E102: ='[1]Old Ladder type (2)'!M30 -> 0.46158
C103: Hardware weight (Nut,bolt and washer) (kg) | D103: 0.32 | E103: 0.32 | G103: fixed
C104: Total weight (kg) | D104: =D98-D99+D100-D101+D102+D103 -> 27.172573 | E104: =E98-E99+E100-E101+E102+E103 -> 34.97618 | F104: =(E104-D104)/D104 -> 0.28718688
C105: Cost of steel (INR) | D105: =(D98*D6-D11*D99*D6)+(D100*D6-D11*D101*D6)+('[1]Coupler Plate'!D24-D43*'[1]Coupler Plate'!D34)*D6*2+D103*D6 -> 2005.3996 | E105: =E104*D6 -> 2553.2611
C107: Weight of Zinc required for galvanization (kg) | D107: =5%*D104 -> 1.3586287 | E107: =5%*E104 -> 1.748809 | G107: TPL assumption: 5% of steel weight; zinc weight to be calculated basis coating thickness
C108: Cost of zinc (INR) | D108: =D107*$H$8 -> 578.23236 | E108: =E107*$H$8 -> 744.29311
C110: Labour,Fabrication,Overhead,Profit Margin (INR) | D110: =(D104+D107)*$D$17 -> 222.54338 | E110: =(E104+E107)*$D$17 -> 286.45491
C112: Total cost (INR) per tray | D112: =D110+D105+D108 -> 2806.1753 | E112: =E110+E105+E108 -> 3584.0092
C113: Cost per meter (INR) per tray | D113: =D112/(O12/1000) -> 668.13697 | E113: =E112/(O12/1000) -> 853.33552
C114: Savings | D114: =(E112-D112)/D112 -> 0.27718649
B118: Comparison table - Summary
D120: TPL | H120: Cost Model
C121: B4-i: Ladder Type Horizontal Tee, Bending Radius 1200 mm, 600mm(W) X 100mm(H), 2mm thk M.S. sheet, ~4.20 m, hot dip galvanised incl. coupler plate
D123: Weight of steel (kg) | E123: Weight of zinc (kg) | F123: Estimated price | H123: Weight of steel (kg) | I123: Weight of zinc (kg) | J123: Estimated price | K123: Price difference
C124: ='[1]Old Ladder type (2)'!B30 -> 600mm(W)X100mm(H) - B4-i horizontal tee | D124: ='[1]Old Ladder type (2)'!Q30 -> 34.97618 | E124: ='[1]Old Ladder type (2)'!U30 -> 1.748809 | F124: ='[1]Old Ladder type (2)'!Z30 -> 2950.7479 | H124: =D104 -> 27.172573 | I124: =D107 -> 1.3586287 | J124: =D112 -> 2806.1753 | K124: =(F124-J124)/J124 -> 0.051519463

Sheet Horizontal Tee 150x100x2
A1: Cable Tray Costing: Ladder Type Horizontal Tee, Bending Radius 1200 mm
B5: Input for raw material and conversion costs | M5: Cable Tray configuration
B6: Cost of 1 kg of MS (Rs) | D6: 73 | F6: Coating thickness of Zinc (micron) | H6: 86 | M6: Runners | Q6: Rungs
B7: Transportation and handling cost of raw material to vendor shop (% of raw material cost) | D7: 0 | F7: Specific weight of Zinc (kg/m3) | H7: 7135 | M7: Number of runners | O7: 2 | Q7: No of rungs per 2500 meter of runner | U7: 10
B8: Specific weight of MS (kg/m3) | D8: 7850 | F8: Cost of Zinc (Rs/kg) | H8: 425.6 | M8: Tray width (mm) | O8: 150 | Q8: Length of rung (mm) | U8: =O8 -> 150
B9: Cost of engg and fabrication (% of material cost) | D9: 0 | F9: Wastage during galvalization | H9: 0 | M9: Tray Depth (mm) | O9: 100 | Q9: Width of rung (mm) | U9: 50
B10: Quality test and inspection charges (%) | D10: 0 | F10: Recoverable scrap - Ash per meter of tray (%) | H10: 0.12 | M10: Tray thickness (mm) | O10: 2 | Q10: Collar / Height of rung (mm) | U10: 20
B11: Salvage value of scrap for MS plates(% of overall value) | D11: 0.5 | F11: Recoverable scrap - Dross per meter of tray (%) | H11: 0.08 | M11: Tray collar (mm) | O11: 25 | Q11: Thickness of rung (mm) | U11: 2
B12: Wastage allowance during fabrication | D12: 0 | F12: Recoverable scrap salvage value - Ash (%) | H12: 0.26 | M12: Tray length (mm) | O12: 4200 | Q12: No of slots per 40 mm of length | U12: 1
B13: Transportation and handling cost of finished goods to site (Rs/kg) | D13: 0 | F13: Recoverable scrap salvage value - Dross (%) | H13: 0.52 | M13: No of holes per 2500 mm length | O13: 20 | Q13: Length of 1 slot (mm) | U13: 25
B14: Overheads for vendor (%) | D14: 0 | F14: Cost of galvanization (% of material cost) | H14: 0 | M14: Dia of 1 hole (mm) | O14: 10 | Q14: Width of 1 slot (mm) | U14: 10
B15: Profit margin for vendor (%) | D15: 2.5
B16: Cost of contract Performance Bank Guarantee | D16: 0
B17: Labour,Fabrication,Overhead,Profit Margin (INR/ kg) | D17: =6.5*1.2 -> 7.8
B20: Detailed Costing
B21: Cable tray MS material cost | M21: Galvalization
B22: Runner | F22: Rung | M22: Zinc Requirement
B23: Number of runners per meter length | D23: =O7 -> 2 | F23: No of rungs in this fitting (U7 x length / 2500, rounded) | J23: =ROUND(U7*D28/2500,0) -> 17 | M23: Runner | Q23: Rung
B24: Tray width (mm) | D24: =O8 -> 150 | F24: Length of rung (mm) | J24: =U8 -> 150 | M24: Surface area for 1 m length (m2) | O24: =2*(2*(2*D27+D25)/1000*D28/1000) -> 2.52 | Q24: Surface area for 1 rung (m2) | T24: =2*J24/1000*(J25+2*J26)/1000 -> 0.027
B25: Tray Depth (mm) | D25: =O9 -> 100 | F25: Width of rung (mm) | J25: =U9 -> 50 | M25: Surface area holes along thickness for 1 m length (m2) | O25: =D37*3.14*D38/1000*D26/1000*D28/125 -> 0.0422016 | Q25: Surface area of slots along thickness for 1 rung (m2) | T25: =(2*(J38+J39)/1000*D26/1000)*D24/40 -> 0.000525
B26: Tray thickness (mm) | D26: =O10 -> 2 | F26: Collar / Height of rung (mm) | J26: =U10 -> 20 | M26: Top surface area of holes for 1 m length (m2) | O26: =D37*3.14*(D38/2/1000)^2*D28/125 -> 0.052752 | Q26: Top surface area of slots 1 rung (m2) | T26: =J38/1000*J39/1000*D24/40 -> 0.0009375
B27: Tray collar (mm) | D27: =O11 -> 25 | F27: Thickness of rung (mm) | J27: =U11 -> 2
B28: Tray length (mm) | D28: =O12 -> 4200 | M28: Overall surface area for 1 meter of runner (m2) | O28: =O24+O25-O26 -> 2.5094496 | Q28: Overall rung surface area for 1 meter of runner (m2) | T28: =(T24+T25-T26)*J23 -> 0.4519875
F29: Volume of 1 rung (m3) | J29: =(2*J26+J25)/1000*J24/1000*J27/1000 -> 2.7e-05
F30: Weight of 1 rung (kg) | J30: =J29*D8 -> 0.21195 | M30: Total surface area per meter of cable tray (m2) | O30: =O28+T28 -> 2.9614371
B31: Volume of runner (m3) | D31: =2*(D25+D27*2)/1000*D26/1000*D28/1000 -> 0.00252 | F31: Cost of 1 rung (Rs) | J31: =J30*(D6*(1+D7)) -> 15.47235
B32: Weight of runner per meter length (kg) | D32: =D31*D8 -> 19.782 | F32: Cost of rungs per meter of runner | J32: =J31*J23 -> 263.02995 | M32: Weight of Zinc required for galvanization (kg) | O32: =O30*H6*10^-6*H7 -> 1.8171674
B33: Cost of runner per meter length (Rs) | D33: =D32*(D6*(1+D7)) -> 1444.086 | M33: Wastage during galvalization | O33: =H9 -> 0
M34: Total weight of Zinc required for galvanization (kg) | O34: =(1+O33)*O32 -> 1.8171674
B35: Scrap salvage due to holes / slots | M35: Cost of Zinc galvanization per meter of runner (Rs) | O35: =O34*H8 -> 773.38645
B36: Runner | F36: Rung
B37: No of holes per 2500 mm length | D37: =O13 -> 20 | F37: No of slots per 40 mm of length | J37: =U12 -> 1 | M37: Recoverable scrap - Ash per meter of tray (kg) | O37: =H10*O32 -> 0.21806009 | Q37: Recoverable scrap salvage - Ash (Rs/kg) | T37: =H12*$H$8 -> 110.656
B38: Dia of 1 hole (mm) | D38: =O14 -> 10 | F38: Length of 1 slot (mm) | J38: =U13 -> 25 | M38: Recoverable scrap - Dross per meter of tray (kg) | O38: =H11*O32 -> 0.14537339 | Q38: Recoverable scrap salvage - Dross (Rs/kg) | T38: =H13*$H$8 -> 221.312
B39: Volume of holes (m3) | D39: =2*D37*3.14*(D38/2/1000)^2*D26/1000 -> 6.28e-06 | F39: Width of 1 slot (mm) | J39: =U14 -> 10 | M39: Salvage value of scrap per meter of cable (Rs) | O39: =O37*T37+O38*T38 -> 56.302534
F40: Volume of 1 slot (m3) | J40: =J38/1000*J39/1000*J27/1000 -> 5e-07
B41: Weight of holes per 2500 mm of runner (kg) | D41: =D39*D8 -> 0.049298 | F41: Volume slots per rung (m3) | J41: =D24/40*J40 -> 1.875e-06 | M41: Net cost of Zinc galvanization per meter of runner (Rs) | O41: =O35-O39 -> 717.08392
B42: Value of scrap generated per meter of runner (Rs) | D42: =D41*D6 -> 3.598754 | F42: Weight of slots per rung (kg) | J42: =J41*D8 -> 0.01471875
B43: Salvage value of scrap (% of overall value) | D43: =D11 -> 0.5 | F43: Weight of slots per 2500mm of runner (kg) | J43: =J42*J23 -> 0.25021875
B44: Salvage value of MS scrap per meter of runner (Rs) | D44: =D42*D43 -> 1.799377 | F44: Value of scrap generated per meter of runner (Rs) | J44: =J43*D6 -> 18.265969
F45: Salvage value of MS scrap per meter of runner (Rs) | J45: =J44*D43 -> 9.1329844
B47: Cost of material for 1 m of runner (Rs) | D47: =D33-D44 -> 1442.2866 | F47: Cost of material for rungs per meter of runner (Rs) | J47: =J32-J45 -> 253.89697
B49: Total cost per meter of cable tray (Rs) | D49: =D47+J47 -> 1696.1836
B50: Wastage allowance during fabrication | D50: =D12 -> 0
B51: Net cost per meter of cable tray (Rs) | D51: =(1+D50)*D49 -> 1696.1836
B54: Engineering, Fabrication and Quality & Inspection cost of cable tray | M54: Cost of galvanization
B55: Engineering & Fabrication cost (Rs) | D55: =(D33+J32)*D9 -> 0 | M55: Galvanization cost (Rs) | N55: =O35*H14 -> 0
B56: Quality inspection and testing (Rs) | D56: =(D33+J32)*D10 -> 0
B61: Summary (Cost of cable tray per meter length)
B63: Cost of steel (Rs) | D63: =D51 -> 1696.1836
B64: Cost of raw material for galvanization (Rs) | D64: =O41 -> 717.08392
B65: Cost of fabrication (Rs) | D65: =D55 -> 0
B66: Cost of galvanization (Rs) | D66: =N55 -> 0
B67: Quality inspection and testing (Rs) | D67: =D56 -> 0
B68: Vendor Overheads (Rs) | D68: =SUM(D63:D67)*D14 -> 0
B69: Profit margin for vendor (Rs) | D69: =SUM(D63:D68)*D15 -> 6033.1688
B70: Contract Performance Bank Guarantee (Rs) | D70: =SUM(D63:D69)*D16 -> 0
B71: Transportation and handling to site (Rs) | D71: =(D32+J30*J23-D41-J43)*D13 -> 0
B72: Should be cost (Rs per meter) | D72: =SUM(D63:D71) -> 8446.4363
B73: Ex Works Should be cost (Rs per meter) | D73: =SUM(D63:D70) -> 8446.4363
B79: Comparison - Cost model viz-a-viz TPL estimations
C81: B4-i: Ladder Type Horizontal Tee, Bending Radius 1200 mm - 600mm(W) X 100mm(H) X 2mm(T), ~4.20 m
B83: Summary (Cost of cable tray - 2500 length)
B85: Cost of steel (Rs) | D85: =D71 -> 0
B86: Cost of raw material for galvanization (Rs) | D86: =O64 -> 0
B87: Cost of fabrication (Rs) | D87: =D75 -> 0
B88: Cost of galvanization (Rs) | D88: =O75 -> 0
B89: Quality inspection and testing (Rs) | D89: =D76 -> 0
B90: Vendor Overheads (Rs) | D90: =SUM(D85:D89)*D36 -> 0
B91: Profit margin for vendor | D91: =SUM(D85:D90)*D37 -> 0
B92: Contract Performance Bank Guarantee (Rs) | D92: =SUM(D85:D91)*D38 -> 0
B93: Transportation and handling to site (Rs) | D93: =(D54-D62-I63)*D35 -> 0
B95: Should be cost | D95: =SUM(D85:D93) -> 0
B96: Ex Works Should be cost | D96: =SUM(D85:D92) -> 0
D97: Suggested model | E97: TPL model
C98: Weight of runner (kg) | D98: =D32 -> 19.782 | E98: ='[1]Old Ladder type (2)'!K30 -> 19.782
C99: Savings due to holes/ slots in runner (kg) | D99: =D41 -> 0.049298 | E99: 0
C100: Weight of rung (kg) | D100: =J30*J23 -> 3.60315 | E100: ='[1]Old Ladder type (2)'!L30 -> 14.4126
C101: Savings due to slots in rung (kg) | D101: =J43 -> 0.25021875 | E101: 0
C102: ="Weight of Coupler plate ("&'[1]Coupler Plate'!N6&"X"&'[1]Coupler Plate'!N7&"X"&'[1]Coupler Plate'!N8&") (kg)" -> Weight of Coupler plate (70X210X2) (kg) | D102: ='[1]Coupler Plate'!D37*2 -> 0.414009 | E102: ='[1]Old Ladder type (2)'!M30 -> 0.46158
C103: Hardware weight (Nut,bolt and washer) (kg) | D103: 0.32 | E103: 0.32 | G103: fixed
C104: Total weight (kg) | D104: =D98-D99+D100-D101+D102+D103 -> 23.819642 | E104: =E98-E99+E100-E101+E102+E103 -> 34.97618 | F104: =(E104-D104)/D104 -> 0.46837554
C105: Cost of steel (INR) | D105: =(D98*D6-D11*D99*D6)+(D100*D6-D11*D101*D6)+('[1]Coupler Plate'!D24-D43*'[1]Coupler Plate'!D34)*D6*2+D103*D6 -> 1751.5026 | E105: =E104*D6 -> 2553.2611
C107: Weight of Zinc required for galvanization (kg) | D107: =5%*D104 -> 1.1909821 | E107: =5%*E104 -> 1.748809 | G107: TPL assumption: 5% of steel weight; zinc weight to be calculated basis coating thickness
C108: Cost of zinc (INR) | D108: =D107*$H$8 -> 506.88199 | E108: =E107*$H$8 -> 744.29311
C110: Labour,Fabrication,Overhead,Profit Margin (INR) | D110: =(D104+D107)*$D$17 -> 195.08287 | E110: =(E104+E107)*$D$17 -> 286.45491
C112: Total cost (INR) per tray | D112: =D110+D105+D108 -> 2453.4674 | E112: =E110+E105+E108 -> 3584.0092
C113: Cost per meter (INR) per tray | D113: =D112/(O12/1000) -> 584.15892 | E113: =E112/(O12/1000) -> 853.33552
C114: Savings | D114: =(E112-D112)/D112 -> 0.46079345
B118: Comparison table - Summary
D120: TPL | H120: Cost Model
C121: B4-i: Ladder Type Horizontal Tee, Bending Radius 1200 mm, 600mm(W) X 100mm(H), 2mm thk M.S. sheet, ~4.20 m, hot dip galvanised incl. coupler plate
D123: Weight of steel (kg) | E123: Weight of zinc (kg) | F123: Estimated price | H123: Weight of steel (kg) | I123: Weight of zinc (kg) | J123: Estimated price | K123: Price difference
C124: ='[1]Old Ladder type (2)'!B30 -> 600mm(W)X100mm(H) - B4-i horizontal tee | D124: ='[1]Old Ladder type (2)'!Q30 -> 34.97618 | E124: ='[1]Old Ladder type (2)'!U30 -> 1.748809 | F124: ='[1]Old Ladder type (2)'!Z30 -> 2950.7479 | H124: =D104 -> 23.819642 | I124: =D107 -> 1.1909821 | J124: =D112 -> 2453.4674 | K124: =(F124-J124)/J124 -> 0.20268477

Sheet Vertical bend down 600x100x2
A1: Cable Tray Costing : Ladder Type Vertical Bend 90 deg (DOWN), Bending Radius 1050 mm
B5: Input for raw material and conversion costs | M5: Cable Tray configuration
B6: Cost of 1 kg of MS (Rs) | D6: 73 | F6: Coating thickness of Zinc (micron) | H6: 86 | M6: Runners | Q6: Rungs
B7: Transportation and handling cost of raw material to vendor shop (% of raw material cost) | D7: 0 | F7: Specific weight of Zinc (kg/m3) | H7: 7135 | M7: Number of runners | O7: 2 | Q7: No of rungs per 2500 meter of runner | U7: 10
B8: Specific weight of MS (kg/m3) | D8: 7850 | F8: Cost of Zinc (Rs/kg) | H8: 425.6 | M8: Tray width (mm) | O8: 600 | Q8: Length of rung (mm) | U8: =O8 -> 600
B9: Cost of engg and fabrication (% of material cost) | D9: 0 | F9: Wastage during galvalization | H9: 0 | M9: Tray Depth (mm) | O9: 100 | Q9: Width of rung (mm) | U9: 50
B10: Quality test and inspection charges (%) | D10: 0 | F10: Recoverable scrap - Ash per meter of tray (%) | H10: 0.12 | M10: Tray thickness (mm) | O10: 2 | Q10: Collar / Height of rung (mm) | U10: 20
B11: Salvage value of scrap for MS plates(% of overall value) | D11: 0.5 | F11: Recoverable scrap - Dross per meter of tray (%) | H11: 0.08 | M11: Tray collar (mm) | O11: 25 | Q11: Thickness of rung (mm) | U11: 2
B12: Wastage allowance during fabrication | D12: 0 | F12: Recoverable scrap salvage value - Ash (%) | H12: 0.26 | M12: Tray length (mm) | O12: 1900 | Q12: No of slots per 40 mm of length | U12: 1
B13: Transportation and handling cost of finished goods to site (Rs/kg) | D13: 0 | F13: Recoverable scrap salvage value - Dross (%) | H13: 0.52 | M13: No of holes per 2500 mm length | O13: 20 | Q13: Length of 1 slot (mm) | U13: 25
B14: Overheads for vendor (%) | D14: 0 | F14: Cost of galvanization (% of material cost) | H14: 0 | M14: Dia of 1 hole (mm) | O14: 10 | Q14: Width of 1 slot (mm) | U14: 10
B15: Profit margin for vendor (%) | D15: 2.5
B16: Cost of contract Performance Bank Guarantee | D16: 0
B17: Labour,Fabrication,Overhead,Profit Margin (INR/ kg) | D17: =6.5*1.2 -> 7.8
B20: Detailed Costing
B21: Cable tray MS material cost | M21: Galvalization
B22: Runner | F22: Rung | M22: Zinc Requirement
B23: Number of runners per meter length | D23: =O7 -> 2 | F23: No of rungs in this fitting (U7 x length / 2500, rounded) | J23: =ROUND(U7*D28/2500,0) -> 8 | M23: Runner | Q23: Rung
B24: Tray width (mm) | D24: =O8 -> 600 | F24: Length of rung (mm) | J24: =U8 -> 600 | M24: Surface area for 1 m length (m2) | O24: =2*(2*(2*D27+D25)/1000*D28/1000) -> 1.14 | Q24: Surface area for 1 rung (m2) | T24: =2*J24/1000*(J25+2*J26)/1000 -> 0.108
B25: Tray Depth (mm) | D25: =O9 -> 100 | F25: Width of rung (mm) | J25: =U9 -> 50 | M25: Surface area holes along thickness for 1 m length (m2) | O25: =D37*3.14*D38/1000*D26/1000*D28/125 -> 0.0190912 | Q25: Surface area of slots along thickness for 1 rung (m2) | T25: =(2*(J38+J39)/1000*D26/1000)*D24/40 -> 0.0021
B26: Tray thickness (mm) | D26: =O10 -> 2 | F26: Collar / Height of rung (mm) | J26: =U10 -> 20 | M26: Top surface area of holes for 1 m length (m2) | O26: =D37*3.14*(D38/2/1000)^2*D28/125 -> 0.023864 | Q26: Top surface area of slots 1 rung (m2) | T26: =J38/1000*J39/1000*D24/40 -> 0.00375
B27: Tray collar (mm) | D27: =O11 -> 25 | F27: Thickness of rung (mm) | J27: =U11 -> 2
B28: Tray length (mm) | D28: =O12 -> 1900 | M28: Overall surface area for 1 meter of runner (m2) | O28: =O24+O25-O26 -> 1.1352272 | Q28: Overall rung surface area for 1 meter of runner (m2) | T28: =(T24+T25-T26)*J23 -> 0.8508
F29: Volume of 1 rung (m3) | J29: =(2*J26+J25)/1000*J24/1000*J27/1000 -> 0.000108
F30: Weight of 1 rung (kg) | J30: =J29*D8 -> 0.8478 | M30: Total surface area per meter of cable tray (m2) | O30: =O28+T28 -> 1.9860272
B31: Volume of runner (m3) | D31: =2*(D25+D27*2)/1000*D26/1000*D28/1000 -> 0.00114 | F31: Cost of 1 rung (Rs) | J31: =J30*(D6*(1+D7)) -> 61.8894
B32: Weight of runner per meter length (kg) | D32: =D31*D8 -> 8.949 | F32: Cost of rungs per meter of runner | J32: =J31*J23 -> 495.1152 | M32: Weight of Zinc required for galvanization (kg) | O32: =O30*H6*10^-6*H7 -> 1.2186462
B33: Cost of runner per meter length (Rs) | D33: =D32*(D6*(1+D7)) -> 653.277 | M33: Wastage during galvalization | O33: =H9 -> 0
M34: Total weight of Zinc required for galvanization (kg) | O34: =(1+O33)*O32 -> 1.2186462
B35: Scrap salvage due to holes / slots | M35: Cost of Zinc galvanization per meter of runner (Rs) | O35: =O34*H8 -> 518.6558
B36: Runner | F36: Rung
B37: No of holes per 2500 mm length | D37: =O13 -> 20 | F37: No of slots per 40 mm of length | J37: =U12 -> 1 | M37: Recoverable scrap - Ash per meter of tray (kg) | O37: =H10*O32 -> 0.14623754 | Q37: Recoverable scrap salvage - Ash (Rs/kg) | T37: =H12*$H$8 -> 110.656
B38: Dia of 1 hole (mm) | D38: =O14 -> 10 | F38: Length of 1 slot (mm) | J38: =U13 -> 25 | M38: Recoverable scrap - Dross per meter of tray (kg) | O38: =H11*O32 -> 0.097491692 | Q38: Recoverable scrap salvage - Dross (Rs/kg) | T38: =H13*$H$8 -> 221.312
B39: Volume of holes (m3) | D39: =2*D37*3.14*(D38/2/1000)^2*D26/1000 -> 6.28e-06 | F39: Width of 1 slot (mm) | J39: =U14 -> 10 | M39: Salvage value of scrap per meter of cable (Rs) | O39: =O37*T37+O38*T38 -> 37.758142
F40: Volume of 1 slot (m3) | J40: =J38/1000*J39/1000*J27/1000 -> 5e-07
B41: Weight of holes per 2500 mm of runner (kg) | D41: =D39*D8 -> 0.049298 | F41: Volume slots per rung (m3) | J41: =D24/40*J40 -> 7.5e-06 | M41: Net cost of Zinc galvanization per meter of runner (Rs) | O41: =O35-O39 -> 480.89766
B42: Value of scrap generated per meter of runner (Rs) | D42: =D41*D6 -> 3.598754 | F42: Weight of slots per rung (kg) | J42: =J41*D8 -> 0.058875
B43: Salvage value of scrap (% of overall value) | D43: =D11 -> 0.5 | F43: Weight of slots per 2500mm of runner (kg) | J43: =J42*J23 -> 0.471
B44: Salvage value of MS scrap per meter of runner (Rs) | D44: =D42*D43 -> 1.799377 | F44: Value of scrap generated per meter of runner (Rs) | J44: =J43*D6 -> 34.383
F45: Salvage value of MS scrap per meter of runner (Rs) | J45: =J44*D43 -> 17.1915
B47: Cost of material for 1 m of runner (Rs) | D47: =D33-D44 -> 651.47762 | F47: Cost of material for rungs per meter of runner (Rs) | J47: =J32-J45 -> 477.9237
B49: Total cost per meter of cable tray (Rs) | D49: =D47+J47 -> 1129.4013
B50: Wastage allowance during fabrication | D50: =D12 -> 0
B51: Net cost per meter of cable tray (Rs) | D51: =(1+D50)*D49 -> 1129.4013
B54: Engineering, Fabrication and Quality & Inspection cost of cable tray | M54: Cost of galvanization
B55: Engineering & Fabrication cost (Rs) | D55: =(D33+J32)*D9 -> 0 | M55: Galvanization cost (Rs) | N55: =O35*H14 -> 0
B56: Quality inspection and testing (Rs) | D56: =(D33+J32)*D10 -> 0
B61: Summary (Cost of cable tray per meter length)
B63: Cost of steel (Rs) | D63: =D51 -> 1129.4013
B64: Cost of raw material for galvanization (Rs) | D64: =O41 -> 480.89766
B65: Cost of fabrication (Rs) | D65: =D55 -> 0
B66: Cost of galvanization (Rs) | D66: =N55 -> 0
B67: Quality inspection and testing (Rs) | D67: =D56 -> 0
B68: Vendor Overheads (Rs) | D68: =SUM(D63:D67)*D14 -> 0
B69: Profit margin for vendor (Rs) | D69: =SUM(D63:D68)*D15 -> 4025.7475
B70: Contract Performance Bank Guarantee (Rs) | D70: =SUM(D63:D69)*D16 -> 0
B71: Transportation and handling to site (Rs) | D71: =(D32+J30*J23-D41-J43)*D13 -> 0
B72: Should be cost (Rs per meter) | D72: =SUM(D63:D71) -> 5636.0464
B73: Ex Works Should be cost (Rs per meter) | D73: =SUM(D63:D70) -> 5636.0464
B79: Comparison - Cost model viz-a-viz TPL estimations
C81: B3-i: Ladder Type Vertical Bend 90 deg (DOWN), Bending Radius 1050 mm - 600mm(W) X 100mm(H) X 2mm(T), ~1.90 m
B83: Summary (Cost of cable tray - 2500 length)
B85: Cost of steel (Rs) | D85: =D71 -> 0
B86: Cost of raw material for galvanization (Rs) | D86: =O64 -> 0
B87: Cost of fabrication (Rs) | D87: =D75 -> 0
B88: Cost of galvanization (Rs) | D88: =O75 -> 0
B89: Quality inspection and testing (Rs) | D89: =D76 -> 0
B90: Vendor Overheads (Rs) | D90: =SUM(D85:D89)*D36 -> 0
B91: Profit margin for vendor | D91: =SUM(D85:D90)*D37 -> 0
B92: Contract Performance Bank Guarantee (Rs) | D92: =SUM(D85:D91)*D38 -> 0
B93: Transportation and handling to site (Rs) | D93: =(D54-D62-I63)*D35 -> 0
B95: Should be cost | D95: =SUM(D85:D93) -> 0
B96: Ex Works Should be cost | D96: =SUM(D85:D92) -> 0
D97: Suggested model | E97: TPL model
C98: Weight of runner (kg) | D98: =D32 -> 8.949 | E98: ='[1]Old Ladder type (2)'!K27 -> 8.949
C99: Savings due to holes/ slots in runner (kg) | D99: =D41 -> 0.049298 | E99: 0
C100: Weight of rung (kg) | D100: =J30*J23 -> 6.7824 | E100: ='[1]Old Ladder type (2)'!L27 -> 6.7824
C101: Savings due to slots in rung (kg) | D101: =J43 -> 0.471 | E101: 0
C102: ="Weight of Coupler plate ("&'[1]Coupler Plate'!N6&"X"&'[1]Coupler Plate'!N7&"X"&'[1]Coupler Plate'!N8&") (kg)" -> Weight of Coupler plate (70X210X2) (kg) | D102: ='[1]Coupler Plate'!D37*2 -> 0.414009 | E102: ='[1]Old Ladder type (2)'!M27 -> 0.46158
C103: Hardware weight (Nut,bolt and washer) (kg) | D103: 0.32 | E103: 0.32 | G103: fixed
C104: Total weight (kg) | D104: =D98-D99+D100-D101+D102+D103 -> 15.945111 | E104: =E98-E99+E100-E101+E102+E103 -> 16.51298 | F104: =(E104-D104)/D104 -> 0.035613989
C105: Cost of steel (INR) | D105: =(D98*D6-D11*D99*D6)+(D100*D6-D11*D101*D6)+('[1]Coupler Plate'!D24-D43*'[1]Coupler Plate'!D34)*D6*2+D103*D6 -> 1184.7203 | E105: =E104*D6 -> 1205.4475
C107: Weight of Zinc required for galvanization (kg) | D107: =5%*D104 -> 0.79725555 | E107: =5%*E104 -> 0.825649 | G107: TPL assumption: 5% of steel weight; zinc weight to be calculated basis coating thickness
C108: Cost of zinc (INR) | D108: =D107*$H$8 -> 339.31196 | E108: =E107*$H$8 -> 351.39621
C110: Labour,Fabrication,Overhead,Profit Margin (INR) | D110: =(D104+D107)*$D$17 -> 130.59046 | E110: =(E104+E107)*$D$17 -> 135.24131
C112: Total cost (INR) per tray | D112: =D110+D105+D108 -> 1654.6227 | E112: =E110+E105+E108 -> 1692.0851
C113: Cost per meter (INR) per tray | D113: =D112/(O12/1000) -> 870.85408 | E113: =E112/(O12/1000) -> 890.57108
C114: Savings | D114: =(E112-D112)/D112 -> 0.022641003
B118: Comparison table - Summary
D120: TPL | H120: Cost Model
C121: B3-i: Ladder Type Vertical Bend 90 deg (DOWN), Bending Radius 1050 mm, 600mm(W) X 100mm(H), 2mm thk M.S. sheet, ~1.90 m, hot dip galvanised incl. coupler plate
D123: Weight of steel (kg) | E123: Weight of zinc (kg) | F123: Estimated price | H123: Weight of steel (kg) | I123: Weight of zinc (kg) | J123: Estimated price | K123: Price difference
C124: ='[1]Old Ladder type (2)'!B27 -> 600mm(W)X100mm(H) - B3-i vertical bend | D124: ='[1]Old Ladder type (2)'!Q27 -> 16.51298 | E124: ='[1]Old Ladder type (2)'!U27 -> 0.825649 | F124: ='[1]Old Ladder type (2)'!Z27 -> 1393.1093 | H124: =D104 -> 15.945111 | I124: =D107 -> 0.79725555 | J124: =D112 -> 1654.6227 | K124: =(F124-J124)/J124 -> -0.15805019

Sheet Vertical bend down 300x100x2
A1: Cable Tray Costing : Ladder Type Vertical Bend 90 deg (DOWN), Bending Radius 1050 mm
B5: Input for raw material and conversion costs | M5: Cable Tray configuration
B6: Cost of 1 kg of MS (Rs) | D6: 73 | F6: Coating thickness of Zinc (micron) | H6: 86 | M6: Runners | Q6: Rungs
B7: Transportation and handling cost of raw material to vendor shop (% of raw material cost) | D7: 0 | F7: Specific weight of Zinc (kg/m3) | H7: 7135 | M7: Number of runners | O7: 2 | Q7: No of rungs per 2500 meter of runner | U7: 10
B8: Specific weight of MS (kg/m3) | D8: 7850 | F8: Cost of Zinc (Rs/kg) | H8: 425.6 | M8: Tray width (mm) | O8: 300 | Q8: Length of rung (mm) | U8: =O8 -> 300
B9: Cost of engg and fabrication (% of material cost) | D9: 0 | F9: Wastage during galvalization | H9: 0 | M9: Tray Depth (mm) | O9: 100 | Q9: Width of rung (mm) | U9: 50
B10: Quality test and inspection charges (%) | D10: 0 | F10: Recoverable scrap - Ash per meter of tray (%) | H10: 0.12 | M10: Tray thickness (mm) | O10: 2 | Q10: Collar / Height of rung (mm) | U10: 20
B11: Salvage value of scrap for MS plates(% of overall value) | D11: 0.5 | F11: Recoverable scrap - Dross per meter of tray (%) | H11: 0.08 | M11: Tray collar (mm) | O11: 25 | Q11: Thickness of rung (mm) | U11: 2
B12: Wastage allowance during fabrication | D12: 0 | F12: Recoverable scrap salvage value - Ash (%) | H12: 0.26 | M12: Tray length (mm) | O12: 1900 | Q12: No of slots per 40 mm of length | U12: 1
B13: Transportation and handling cost of finished goods to site (Rs/kg) | D13: 0 | F13: Recoverable scrap salvage value - Dross (%) | H13: 0.52 | M13: No of holes per 2500 mm length | O13: 20 | Q13: Length of 1 slot (mm) | U13: 25
B14: Overheads for vendor (%) | D14: 0 | F14: Cost of galvanization (% of material cost) | H14: 0 | M14: Dia of 1 hole (mm) | O14: 10 | Q14: Width of 1 slot (mm) | U14: 10
B15: Profit margin for vendor (%) | D15: 2.5
B16: Cost of contract Performance Bank Guarantee | D16: 0
B17: Labour,Fabrication,Overhead,Profit Margin (INR/ kg) | D17: =6.5*1.2 -> 7.8
B20: Detailed Costing
B21: Cable tray MS material cost | M21: Galvalization
B22: Runner | F22: Rung | M22: Zinc Requirement
B23: Number of runners per meter length | D23: =O7 -> 2 | F23: No of rungs in this fitting (U7 x length / 2500, rounded) | J23: =ROUND(U7*D28/2500,0) -> 8 | M23: Runner | Q23: Rung
B24: Tray width (mm) | D24: =O8 -> 300 | F24: Length of rung (mm) | J24: =U8 -> 300 | M24: Surface area for 1 m length (m2) | O24: =2*(2*(2*D27+D25)/1000*D28/1000) -> 1.14 | Q24: Surface area for 1 rung (m2) | T24: =2*J24/1000*(J25+2*J26)/1000 -> 0.054
B25: Tray Depth (mm) | D25: =O9 -> 100 | F25: Width of rung (mm) | J25: =U9 -> 50 | M25: Surface area holes along thickness for 1 m length (m2) | O25: =D37*3.14*D38/1000*D26/1000*D28/125 -> 0.0190912 | Q25: Surface area of slots along thickness for 1 rung (m2) | T25: =(2*(J38+J39)/1000*D26/1000)*D24/40 -> 0.00105
B26: Tray thickness (mm) | D26: =O10 -> 2 | F26: Collar / Height of rung (mm) | J26: =U10 -> 20 | M26: Top surface area of holes for 1 m length (m2) | O26: =D37*3.14*(D38/2/1000)^2*D28/125 -> 0.023864 | Q26: Top surface area of slots 1 rung (m2) | T26: =J38/1000*J39/1000*D24/40 -> 0.001875
B27: Tray collar (mm) | D27: =O11 -> 25 | F27: Thickness of rung (mm) | J27: =U11 -> 2
B28: Tray length (mm) | D28: =O12 -> 1900 | M28: Overall surface area for 1 meter of runner (m2) | O28: =O24+O25-O26 -> 1.1352272 | Q28: Overall rung surface area for 1 meter of runner (m2) | T28: =(T24+T25-T26)*J23 -> 0.4254
F29: Volume of 1 rung (m3) | J29: =(2*J26+J25)/1000*J24/1000*J27/1000 -> 5.4e-05
F30: Weight of 1 rung (kg) | J30: =J29*D8 -> 0.4239 | M30: Total surface area per meter of cable tray (m2) | O30: =O28+T28 -> 1.5606272
B31: Volume of runner (m3) | D31: =2*(D25+D27*2)/1000*D26/1000*D28/1000 -> 0.00114 | F31: Cost of 1 rung (Rs) | J31: =J30*(D6*(1+D7)) -> 30.9447
B32: Weight of runner per meter length (kg) | D32: =D31*D8 -> 8.949 | F32: Cost of rungs per meter of runner | J32: =J31*J23 -> 247.5576 | M32: Weight of Zinc required for galvanization (kg) | O32: =O30*H6*10^-6*H7 -> 0.95761646
B33: Cost of runner per meter length (Rs) | D33: =D32*(D6*(1+D7)) -> 653.277 | M33: Wastage during galvalization | O33: =H9 -> 0
M34: Total weight of Zinc required for galvanization (kg) | O34: =(1+O33)*O32 -> 0.95761646
B35: Scrap salvage due to holes / slots | M35: Cost of Zinc galvanization per meter of runner (Rs) | O35: =O34*H8 -> 407.56156
B36: Runner | F36: Rung
B37: No of holes per 2500 mm length | D37: =O13 -> 20 | F37: No of slots per 40 mm of length | J37: =U12 -> 1 | M37: Recoverable scrap - Ash per meter of tray (kg) | O37: =H10*O32 -> 0.11491397 | Q37: Recoverable scrap salvage - Ash (Rs/kg) | T37: =H12*$H$8 -> 110.656
B38: Dia of 1 hole (mm) | D38: =O14 -> 10 | F38: Length of 1 slot (mm) | J38: =U13 -> 25 | M38: Recoverable scrap - Dross per meter of tray (kg) | O38: =H11*O32 -> 0.076609316 | Q38: Recoverable scrap salvage - Dross (Rs/kg) | T38: =H13*$H$8 -> 221.312
B39: Volume of holes (m3) | D39: =2*D37*3.14*(D38/2/1000)^2*D26/1000 -> 6.28e-06 | F39: Width of 1 slot (mm) | J39: =U14 -> 10 | M39: Salvage value of scrap per meter of cable (Rs) | O39: =O37*T37+O38*T38 -> 29.670482
F40: Volume of 1 slot (m3) | J40: =J38/1000*J39/1000*J27/1000 -> 5e-07
B41: Weight of holes per 2500 mm of runner (kg) | D41: =D39*D8 -> 0.049298 | F41: Volume slots per rung (m3) | J41: =D24/40*J40 -> 3.75e-06 | M41: Net cost of Zinc galvanization per meter of runner (Rs) | O41: =O35-O39 -> 377.89108
B42: Value of scrap generated per meter of runner (Rs) | D42: =D41*D6 -> 3.598754 | F42: Weight of slots per rung (kg) | J42: =J41*D8 -> 0.0294375
B43: Salvage value of scrap (% of overall value) | D43: =D11 -> 0.5 | F43: Weight of slots per 2500mm of runner (kg) | J43: =J42*J23 -> 0.2355
B44: Salvage value of MS scrap per meter of runner (Rs) | D44: =D42*D43 -> 1.799377 | F44: Value of scrap generated per meter of runner (Rs) | J44: =J43*D6 -> 17.1915
F45: Salvage value of MS scrap per meter of runner (Rs) | J45: =J44*D43 -> 8.59575
B47: Cost of material for 1 m of runner (Rs) | D47: =D33-D44 -> 651.47762 | F47: Cost of material for rungs per meter of runner (Rs) | J47: =J32-J45 -> 238.96185
B49: Total cost per meter of cable tray (Rs) | D49: =D47+J47 -> 890.43947
B50: Wastage allowance during fabrication | D50: =D12 -> 0
B51: Net cost per meter of cable tray (Rs) | D51: =(1+D50)*D49 -> 890.43947
B54: Engineering, Fabrication and Quality & Inspection cost of cable tray | M54: Cost of galvanization
B55: Engineering & Fabrication cost (Rs) | D55: =(D33+J32)*D9 -> 0 | M55: Galvanization cost (Rs) | N55: =O35*H14 -> 0
B56: Quality inspection and testing (Rs) | D56: =(D33+J32)*D10 -> 0
B61: Summary (Cost of cable tray per meter length)
B63: Cost of steel (Rs) | D63: =D51 -> 890.43947
B64: Cost of raw material for galvanization (Rs) | D64: =O41 -> 377.89108
B65: Cost of fabrication (Rs) | D65: =D55 -> 0
B66: Cost of galvanization (Rs) | D66: =N55 -> 0
B67: Quality inspection and testing (Rs) | D67: =D56 -> 0
B68: Vendor Overheads (Rs) | D68: =SUM(D63:D67)*D14 -> 0
B69: Profit margin for vendor (Rs) | D69: =SUM(D63:D68)*D15 -> 3170.8264
B70: Contract Performance Bank Guarantee (Rs) | D70: =SUM(D63:D69)*D16 -> 0
B71: Transportation and handling to site (Rs) | D71: =(D32+J30*J23-D41-J43)*D13 -> 0
B72: Should be cost (Rs per meter) | D72: =SUM(D63:D71) -> 4439.1569
B73: Ex Works Should be cost (Rs per meter) | D73: =SUM(D63:D70) -> 4439.1569
B79: Comparison - Cost model viz-a-viz TPL estimations
C81: B3-i: Ladder Type Vertical Bend 90 deg (DOWN), Bending Radius 1050 mm - 600mm(W) X 100mm(H) X 2mm(T), ~1.90 m
B83: Summary (Cost of cable tray - 2500 length)
B85: Cost of steel (Rs) | D85: =D71 -> 0
B86: Cost of raw material for galvanization (Rs) | D86: =O64 -> 0
B87: Cost of fabrication (Rs) | D87: =D75 -> 0
B88: Cost of galvanization (Rs) | D88: =O75 -> 0
B89: Quality inspection and testing (Rs) | D89: =D76 -> 0
B90: Vendor Overheads (Rs) | D90: =SUM(D85:D89)*D36 -> 0
B91: Profit margin for vendor | D91: =SUM(D85:D90)*D37 -> 0
B92: Contract Performance Bank Guarantee (Rs) | D92: =SUM(D85:D91)*D38 -> 0
B93: Transportation and handling to site (Rs) | D93: =(D54-D62-I63)*D35 -> 0
B95: Should be cost | D95: =SUM(D85:D93) -> 0
B96: Ex Works Should be cost | D96: =SUM(D85:D92) -> 0
D97: Suggested model | E97: TPL model
C98: Weight of runner (kg) | D98: =D32 -> 8.949 | E98: ='[1]Old Ladder type (2)'!K27 -> 8.949
C99: Savings due to holes/ slots in runner (kg) | D99: =D41 -> 0.049298 | E99: 0
C100: Weight of rung (kg) | D100: =J30*J23 -> 3.3912 | E100: ='[1]Old Ladder type (2)'!L27 -> 6.7824
C101: Savings due to slots in rung (kg) | D101: =J43 -> 0.2355 | E101: 0
C102: ="Weight of Coupler plate ("&'[1]Coupler Plate'!N6&"X"&'[1]Coupler Plate'!N7&"X"&'[1]Coupler Plate'!N8&") (kg)" -> Weight of Coupler plate (70X210X2) (kg) | D102: ='[1]Coupler Plate'!D37*2 -> 0.414009 | E102: ='[1]Old Ladder type (2)'!M27 -> 0.46158
C103: Hardware weight (Nut,bolt and washer) (kg) | D103: 0.32 | E103: 0.32 | G103: fixed
C104: Total weight (kg) | D104: =D98-D99+D100-D101+D102+D103 -> 12.789411 | E104: =E98-E99+E100-E101+E102+E103 -> 16.51298 | F104: =(E104-D104)/D104 -> 0.29114468
C105: Cost of steel (INR) | D105: =(D98*D6-D11*D99*D6)+(D100*D6-D11*D101*D6)+('[1]Coupler Plate'!D24-D43*'[1]Coupler Plate'!D34)*D6*2+D103*D6 -> 945.75847 | E105: =E104*D6 -> 1205.4475
C107: Weight of Zinc required for galvanization (kg) | D107: =5%*D104 -> 0.63947055 | E107: =5%*E104 -> 0.825649 | G107: TPL assumption: 5% of steel weight; zinc weight to be calculated basis coating thickness
C108: Cost of zinc (INR) | D108: =D107*$H$8 -> 272.15867 | E108: =E107*$H$8 -> 351.39621
C110: Labour,Fabrication,Overhead,Profit Margin (INR) | D110: =(D104+D107)*$D$17 -> 104.74528 | E110: =(E104+E107)*$D$17 -> 135.24131
C112: Total cost (INR) per tray | D112: =D110+D105+D108 -> 1322.6624 | E112: =E110+E105+E108 -> 1692.0851
C113: Cost per meter (INR) per tray | D113: =D112/(O12/1000) -> 696.13811 | E113: =E112/(O12/1000) -> 890.57108
C114: Savings | D114: =(E112-D112)/D112 -> 0.27930229
B118: Comparison table - Summary
D120: TPL | H120: Cost Model
C121: B3-i: Ladder Type Vertical Bend 90 deg (DOWN), Bending Radius 1050 mm, 600mm(W) X 100mm(H), 2mm thk M.S. sheet, ~1.90 m, hot dip galvanised incl. coupler plate
D123: Weight of steel (kg) | E123: Weight of zinc (kg) | F123: Estimated price | H123: Weight of steel (kg) | I123: Weight of zinc (kg) | J123: Estimated price | K123: Price difference
C124: ='[1]Old Ladder type (2)'!B27 -> 600mm(W)X100mm(H) - B3-i vertical bend | D124: ='[1]Old Ladder type (2)'!Q27 -> 16.51298 | E124: ='[1]Old Ladder type (2)'!U27 -> 0.825649 | F124: ='[1]Old Ladder type (2)'!Z27 -> 1393.1093 | H124: =D104 -> 12.789411 | I124: =D107 -> 0.63947055 | J124: =D112 -> 1322.6624 | K124: =(F124-J124)/J124 -> 0.053261427

Sheet Vertical bend down 150x100x2
A1: Cable Tray Costing : Ladder Type Vertical Bend 90 deg (DOWN), Bending Radius 1050 mm
B5: Input for raw material and conversion costs | M5: Cable Tray configuration
B6: Cost of 1 kg of MS (Rs) | D6: 73 | F6: Coating thickness of Zinc (micron) | H6: 86 | M6: Runners | Q6: Rungs
B7: Transportation and handling cost of raw material to vendor shop (% of raw material cost) | D7: 0 | F7: Specific weight of Zinc (kg/m3) | H7: 7135 | M7: Number of runners | O7: 2 | Q7: No of rungs per 2500 meter of runner | U7: 10
B8: Specific weight of MS (kg/m3) | D8: 7850 | F8: Cost of Zinc (Rs/kg) | H8: 425.6 | M8: Tray width (mm) | O8: 150 | Q8: Length of rung (mm) | U8: =O8 -> 150
B9: Cost of engg and fabrication (% of material cost) | D9: 0 | F9: Wastage during galvalization | H9: 0 | M9: Tray Depth (mm) | O9: 100 | Q9: Width of rung (mm) | U9: 50
B10: Quality test and inspection charges (%) | D10: 0 | F10: Recoverable scrap - Ash per meter of tray (%) | H10: 0.12 | M10: Tray thickness (mm) | O10: 2 | Q10: Collar / Height of rung (mm) | U10: 20
B11: Salvage value of scrap for MS plates(% of overall value) | D11: 0.5 | F11: Recoverable scrap - Dross per meter of tray (%) | H11: 0.08 | M11: Tray collar (mm) | O11: 25 | Q11: Thickness of rung (mm) | U11: 2
B12: Wastage allowance during fabrication | D12: 0 | F12: Recoverable scrap salvage value - Ash (%) | H12: 0.26 | M12: Tray length (mm) | O12: 1900 | Q12: No of slots per 40 mm of length | U12: 1
B13: Transportation and handling cost of finished goods to site (Rs/kg) | D13: 0 | F13: Recoverable scrap salvage value - Dross (%) | H13: 0.52 | M13: No of holes per 2500 mm length | O13: 20 | Q13: Length of 1 slot (mm) | U13: 25
B14: Overheads for vendor (%) | D14: 0 | F14: Cost of galvanization (% of material cost) | H14: 0 | M14: Dia of 1 hole (mm) | O14: 10 | Q14: Width of 1 slot (mm) | U14: 10
B15: Profit margin for vendor (%) | D15: 2.5
B16: Cost of contract Performance Bank Guarantee | D16: 0
B17: Labour,Fabrication,Overhead,Profit Margin (INR/ kg) | D17: =6.5*1.2 -> 7.8
B20: Detailed Costing
B21: Cable tray MS material cost | M21: Galvalization
B22: Runner | F22: Rung | M22: Zinc Requirement
B23: Number of runners per meter length | D23: =O7 -> 2 | F23: No of rungs in this fitting (U7 x length / 2500, rounded) | J23: =ROUND(U7*D28/2500,0) -> 8 | M23: Runner | Q23: Rung
B24: Tray width (mm) | D24: =O8 -> 150 | F24: Length of rung (mm) | J24: =U8 -> 150 | M24: Surface area for 1 m length (m2) | O24: =2*(2*(2*D27+D25)/1000*D28/1000) -> 1.14 | Q24: Surface area for 1 rung (m2) | T24: =2*J24/1000*(J25+2*J26)/1000 -> 0.027
B25: Tray Depth (mm) | D25: =O9 -> 100 | F25: Width of rung (mm) | J25: =U9 -> 50 | M25: Surface area holes along thickness for 1 m length (m2) | O25: =D37*3.14*D38/1000*D26/1000*D28/125 -> 0.0190912 | Q25: Surface area of slots along thickness for 1 rung (m2) | T25: =(2*(J38+J39)/1000*D26/1000)*D24/40 -> 0.000525
B26: Tray thickness (mm) | D26: =O10 -> 2 | F26: Collar / Height of rung (mm) | J26: =U10 -> 20 | M26: Top surface area of holes for 1 m length (m2) | O26: =D37*3.14*(D38/2/1000)^2*D28/125 -> 0.023864 | Q26: Top surface area of slots 1 rung (m2) | T26: =J38/1000*J39/1000*D24/40 -> 0.0009375
B27: Tray collar (mm) | D27: =O11 -> 25 | F27: Thickness of rung (mm) | J27: =U11 -> 2
B28: Tray length (mm) | D28: =O12 -> 1900 | M28: Overall surface area for 1 meter of runner (m2) | O28: =O24+O25-O26 -> 1.1352272 | Q28: Overall rung surface area for 1 meter of runner (m2) | T28: =(T24+T25-T26)*J23 -> 0.2127
F29: Volume of 1 rung (m3) | J29: =(2*J26+J25)/1000*J24/1000*J27/1000 -> 2.7e-05
F30: Weight of 1 rung (kg) | J30: =J29*D8 -> 0.21195 | M30: Total surface area per meter of cable tray (m2) | O30: =O28+T28 -> 1.3479272
B31: Volume of runner (m3) | D31: =2*(D25+D27*2)/1000*D26/1000*D28/1000 -> 0.00114 | F31: Cost of 1 rung (Rs) | J31: =J30*(D6*(1+D7)) -> 15.47235
B32: Weight of runner per meter length (kg) | D32: =D31*D8 -> 8.949 | F32: Cost of rungs per meter of runner | J32: =J31*J23 -> 123.7788 | M32: Weight of Zinc required for galvanization (kg) | O32: =O30*H6*10^-6*H7 -> 0.82710161
B33: Cost of runner per meter length (Rs) | D33: =D32*(D6*(1+D7)) -> 653.277 | M33: Wastage during galvalization | O33: =H9 -> 0
M34: Total weight of Zinc required for galvanization (kg) | O34: =(1+O33)*O32 -> 0.82710161
B35: Scrap salvage due to holes / slots | M35: Cost of Zinc galvanization per meter of runner (Rs) | O35: =O34*H8 -> 352.01444
B36: Runner | F36: Rung
B37: No of holes per 2500 mm length | D37: =O13 -> 20 | F37: No of slots per 40 mm of length | J37: =U12 -> 1 | M37: Recoverable scrap - Ash per meter of tray (kg) | O37: =H10*O32 -> 0.099252193 | Q37: Recoverable scrap salvage - Ash (Rs/kg) | T37: =H12*$H$8 -> 110.656
B38: Dia of 1 hole (mm) | D38: =O14 -> 10 | F38: Length of 1 slot (mm) | J38: =U13 -> 25 | M38: Recoverable scrap - Dross per meter of tray (kg) | O38: =H11*O32 -> 0.066168129 | Q38: Recoverable scrap salvage - Dross (Rs/kg) | T38: =H13*$H$8 -> 221.312
B39: Volume of holes (m3) | D39: =2*D37*3.14*(D38/2/1000)^2*D26/1000 -> 6.28e-06 | F39: Width of 1 slot (mm) | J39: =U14 -> 10 | M39: Salvage value of scrap per meter of cable (Rs) | O39: =O37*T37+O38*T38 -> 25.626652
F40: Volume of 1 slot (m3) | J40: =J38/1000*J39/1000*J27/1000 -> 5e-07
B41: Weight of holes per 2500 mm of runner (kg) | D41: =D39*D8 -> 0.049298 | F41: Volume slots per rung (m3) | J41: =D24/40*J40 -> 1.875e-06 | M41: Net cost of Zinc galvanization per meter of runner (Rs) | O41: =O35-O39 -> 326.38779
B42: Value of scrap generated per meter of runner (Rs) | D42: =D41*D6 -> 3.598754 | F42: Weight of slots per rung (kg) | J42: =J41*D8 -> 0.01471875
B43: Salvage value of scrap (% of overall value) | D43: =D11 -> 0.5 | F43: Weight of slots per 2500mm of runner (kg) | J43: =J42*J23 -> 0.11775
B44: Salvage value of MS scrap per meter of runner (Rs) | D44: =D42*D43 -> 1.799377 | F44: Value of scrap generated per meter of runner (Rs) | J44: =J43*D6 -> 8.59575
F45: Salvage value of MS scrap per meter of runner (Rs) | J45: =J44*D43 -> 4.297875
B47: Cost of material for 1 m of runner (Rs) | D47: =D33-D44 -> 651.47762 | F47: Cost of material for rungs per meter of runner (Rs) | J47: =J32-J45 -> 119.48092
B49: Total cost per meter of cable tray (Rs) | D49: =D47+J47 -> 770.95855
B50: Wastage allowance during fabrication | D50: =D12 -> 0
B51: Net cost per meter of cable tray (Rs) | D51: =(1+D50)*D49 -> 770.95855
B54: Engineering, Fabrication and Quality & Inspection cost of cable tray | M54: Cost of galvanization
B55: Engineering & Fabrication cost (Rs) | D55: =(D33+J32)*D9 -> 0 | M55: Galvanization cost (Rs) | N55: =O35*H14 -> 0
B56: Quality inspection and testing (Rs) | D56: =(D33+J32)*D10 -> 0
B61: Summary (Cost of cable tray per meter length)
B63: Cost of steel (Rs) | D63: =D51 -> 770.95855
B64: Cost of raw material for galvanization (Rs) | D64: =O41 -> 326.38779
B65: Cost of fabrication (Rs) | D65: =D55 -> 0
B66: Cost of galvanization (Rs) | D66: =N55 -> 0
B67: Quality inspection and testing (Rs) | D67: =D56 -> 0
B68: Vendor Overheads (Rs) | D68: =SUM(D63:D67)*D14 -> 0
B69: Profit margin for vendor (Rs) | D69: =SUM(D63:D68)*D15 -> 2743.3659
B70: Contract Performance Bank Guarantee (Rs) | D70: =SUM(D63:D69)*D16 -> 0
B71: Transportation and handling to site (Rs) | D71: =(D32+J30*J23-D41-J43)*D13 -> 0
B72: Should be cost (Rs per meter) | D72: =SUM(D63:D71) -> 3840.7122
B73: Ex Works Should be cost (Rs per meter) | D73: =SUM(D63:D70) -> 3840.7122
B79: Comparison - Cost model viz-a-viz TPL estimations
C81: B3-i: Ladder Type Vertical Bend 90 deg (DOWN), Bending Radius 1050 mm - 600mm(W) X 100mm(H) X 2mm(T), ~1.90 m
B83: Summary (Cost of cable tray - 2500 length)
B85: Cost of steel (Rs) | D85: =D71 -> 0
B86: Cost of raw material for galvanization (Rs) | D86: =O64 -> 0
B87: Cost of fabrication (Rs) | D87: =D75 -> 0
B88: Cost of galvanization (Rs) | D88: =O75 -> 0
B89: Quality inspection and testing (Rs) | D89: =D76 -> 0
B90: Vendor Overheads (Rs) | D90: =SUM(D85:D89)*D36 -> 0
B91: Profit margin for vendor | D91: =SUM(D85:D90)*D37 -> 0
B92: Contract Performance Bank Guarantee (Rs) | D92: =SUM(D85:D91)*D38 -> 0
B93: Transportation and handling to site (Rs) | D93: =(D54-D62-I63)*D35 -> 0
B95: Should be cost | D95: =SUM(D85:D93) -> 0
B96: Ex Works Should be cost | D96: =SUM(D85:D92) -> 0
D97: Suggested model | E97: TPL model
C98: Weight of runner (kg) | D98: =D32 -> 8.949 | E98: ='[1]Old Ladder type (2)'!K27 -> 8.949
C99: Savings due to holes/ slots in runner (kg) | D99: =D41 -> 0.049298 | E99: 0
C100: Weight of rung (kg) | D100: =J30*J23 -> 1.6956 | E100: ='[1]Old Ladder type (2)'!L27 -> 6.7824
C101: Savings due to slots in rung (kg) | D101: =J43 -> 0.11775 | E101: 0
C102: ="Weight of Coupler plate ("&'[1]Coupler Plate'!N6&"X"&'[1]Coupler Plate'!N7&"X"&'[1]Coupler Plate'!N8&") (kg)" -> Weight of Coupler plate (70X210X2) (kg) | D102: ='[1]Coupler Plate'!D37*2 -> 0.414009 | E102: ='[1]Old Ladder type (2)'!M27 -> 0.46158
C103: Hardware weight (Nut,bolt and washer) (kg) | D103: 0.32 | E103: 0.32 | G103: fixed
C104: Total weight (kg) | D104: =D98-D99+D100-D101+D102+D103 -> 11.211561 | E104: =E98-E99+E100-E101+E102+E103 -> 16.51298 | F104: =(E104-D104)/D104 -> 0.47285289
C105: Cost of steel (INR) | D105: =(D98*D6-D11*D99*D6)+(D100*D6-D11*D101*D6)+('[1]Coupler Plate'!D24-D43*'[1]Coupler Plate'!D34)*D6*2+D103*D6 -> 826.27755 | E105: =E104*D6 -> 1205.4475
C107: Weight of Zinc required for galvanization (kg) | D107: =5%*D104 -> 0.56057805 | E107: =5%*E104 -> 0.825649 | G107: TPL assumption: 5% of steel weight; zinc weight to be calculated basis coating thickness
C108: Cost of zinc (INR) | D108: =D107*$H$8 -> 238.58202 | E108: =E107*$H$8 -> 351.39621
C110: Labour,Fabrication,Overhead,Profit Margin (INR) | D110: =(D104+D107)*$D$17 -> 91.822685 | E110: =(E104+E107)*$D$17 -> 135.24131
C112: Total cost (INR) per tray | D112: =D110+D105+D108 -> 1156.6822 | E112: =E110+E105+E108 -> 1692.0851
C113: Cost per meter (INR) per tray | D113: =D112/(O12/1000) -> 608.78013 | E113: =E112/(O12/1000) -> 890.57108
C114: Savings | D114: =(E112-D112)/D112 -> 0.46287804
B118: Comparison table - Summary
D120: TPL | H120: Cost Model
C121: B3-i: Ladder Type Vertical Bend 90 deg (DOWN), Bending Radius 1050 mm, 600mm(W) X 100mm(H), 2mm thk M.S. sheet, ~1.90 m, hot dip galvanised incl. coupler plate
D123: Weight of steel (kg) | E123: Weight of zinc (kg) | F123: Estimated price | H123: Weight of steel (kg) | I123: Weight of zinc (kg) | J123: Estimated price | K123: Price difference
C124: ='[1]Old Ladder type (2)'!B27 -> 600mm(W)X100mm(H) - B3-i vertical bend | D124: ='[1]Old Ladder type (2)'!Q27 -> 16.51298 | E124: ='[1]Old Ladder type (2)'!U27 -> 0.825649 | F124: ='[1]Old Ladder type (2)'!Z27 -> 1393.1093 | H124: =D104 -> 11.211561 | I124: =D107 -> 0.56057805 | J124: =D112 -> 1156.6822 | K124: =(F124-J124)/J124 -> 0.20440104

Sheet Vertical bend up 600x100x2
A1: Cable Tray Costing: Ladder Type Vertical Bend 90 deg (UP), Bending Radius 1050 mm
B5: Input for raw material and conversion costs | M5: Cable Tray configuration
B6: Cost of 1 kg of MS (Rs) | D6: 73 | F6: Coating thickness of Zinc (micron) | H6: 86 | M6: Runners | Q6: Rungs
B7: Transportation and handling cost of raw material to vendor shop (% of raw material cost) | D7: 0 | F7: Specific weight of Zinc (kg/m3) | H7: 7135 | M7: Number of runners | O7: 2 | Q7: No of rungs per 2500 meter of runner | U7: 10
B8: Specific weight of MS (kg/m3) | D8: 7850 | F8: Cost of Zinc (Rs/kg) | H8: 425.6 | M8: Tray width (mm) | O8: 600 | Q8: Length of rung (mm) | U8: =O8 -> 600
B9: Cost of engg and fabrication (% of material cost) | D9: 0 | F9: Wastage during galvalization | H9: 0 | M9: Tray Depth (mm) | O9: 100 | Q9: Width of rung (mm) | U9: 50
B10: Quality test and inspection charges (%) | D10: 0 | F10: Recoverable scrap - Ash per meter of tray (%) | H10: 0.12 | M10: Tray thickness (mm) | O10: 2 | Q10: Collar / Height of rung (mm) | U10: 20
B11: Salvage value of scrap for MS plates(% of overall value) | D11: 0.5 | F11: Recoverable scrap - Dross per meter of tray (%) | H11: 0.08 | M11: Tray collar (mm) | O11: 25 | Q11: Thickness of rung (mm) | U11: 2
B12: Wastage allowance during fabrication | D12: 0 | F12: Recoverable scrap salvage value - Ash (%) | H12: 0.26 | M12: Tray length (mm) | O12: 1900 | Q12: No of slots per 40 mm of length | U12: 1
B13: Transportation and handling cost of finished goods to site (Rs/kg) | D13: 0 | F13: Recoverable scrap salvage value - Dross (%) | H13: 0.52 | M13: No of holes per 2500 mm length | O13: 20 | Q13: Length of 1 slot (mm) | U13: 25
B14: Overheads for vendor (%) | D14: 0 | F14: Cost of galvanization (% of material cost) | H14: 0 | M14: Dia of 1 hole (mm) | O14: 10 | Q14: Width of 1 slot (mm) | U14: 10
B15: Profit margin for vendor (%) | D15: 2.5
B16: Cost of contract Performance Bank Guarantee | D16: 0
B17: Labour,Fabrication,Overhead,Profit Margin (INR/ kg) | D17: =6.5*1.2 -> 7.8
B20: Detailed Costing
B21: Cable tray MS material cost | M21: Galvalization
B22: Runner | F22: Rung | M22: Zinc Requirement
B23: Number of runners per meter length | D23: =O7 -> 2 | F23: No of rungs in this fitting (U7 x length / 2500, rounded) | J23: =ROUND(U7*D28/2500,0) -> 8 | M23: Runner | Q23: Rung
B24: Tray width (mm) | D24: =O8 -> 600 | F24: Length of rung (mm) | J24: =U8 -> 600 | M24: Surface area for 1 m length (m2) | O24: =2*(2*(2*D27+D25)/1000*D28/1000) -> 1.14 | Q24: Surface area for 1 rung (m2) | T24: =2*J24/1000*(J25+2*J26)/1000 -> 0.108
B25: Tray Depth (mm) | D25: =O9 -> 100 | F25: Width of rung (mm) | J25: =U9 -> 50 | M25: Surface area holes along thickness for 1 m length (m2) | O25: =D37*3.14*D38/1000*D26/1000*D28/125 -> 0.0190912 | Q25: Surface area of slots along thickness for 1 rung (m2) | T25: =(2*(J38+J39)/1000*D26/1000)*D24/40 -> 0.0021
B26: Tray thickness (mm) | D26: =O10 -> 2 | F26: Collar / Height of rung (mm) | J26: =U10 -> 20 | M26: Top surface area of holes for 1 m length (m2) | O26: =D37*3.14*(D38/2/1000)^2*D28/125 -> 0.023864 | Q26: Top surface area of slots 1 rung (m2) | T26: =J38/1000*J39/1000*D24/40 -> 0.00375
B27: Tray collar (mm) | D27: =O11 -> 25 | F27: Thickness of rung (mm) | J27: =U11 -> 2
B28: Tray length (mm) | D28: =O12 -> 1900 | M28: Overall surface area for 1 meter of runner (m2) | O28: =O24+O25-O26 -> 1.1352272 | Q28: Overall rung surface area for 1 meter of runner (m2) | T28: =(T24+T25-T26)*J23 -> 0.8508
F29: Volume of 1 rung (m3) | J29: =(2*J26+J25)/1000*J24/1000*J27/1000 -> 0.000108
F30: Weight of 1 rung (kg) | J30: =J29*D8 -> 0.8478 | M30: Total surface area per meter of cable tray (m2) | O30: =O28+T28 -> 1.9860272
B31: Volume of runner (m3) | D31: =2*(D25+D27*2)/1000*D26/1000*D28/1000 -> 0.00114 | F31: Cost of 1 rung (Rs) | J31: =J30*(D6*(1+D7)) -> 61.8894
B32: Weight of runner per meter length (kg) | D32: =D31*D8 -> 8.949 | F32: Cost of rungs per meter of runner | J32: =J31*J23 -> 495.1152 | M32: Weight of Zinc required for galvanization (kg) | O32: =O30*H6*10^-6*H7 -> 1.2186462
B33: Cost of runner per meter length (Rs) | D33: =D32*(D6*(1+D7)) -> 653.277 | M33: Wastage during galvalization | O33: =H9 -> 0
M34: Total weight of Zinc required for galvanization (kg) | O34: =(1+O33)*O32 -> 1.2186462
B35: Scrap salvage due to holes / slots | M35: Cost of Zinc galvanization per meter of runner (Rs) | O35: =O34*H8 -> 518.6558
B36: Runner | F36: Rung
B37: No of holes per 2500 mm length | D37: =O13 -> 20 | F37: No of slots per 40 mm of length | J37: =U12 -> 1 | M37: Recoverable scrap - Ash per meter of tray (kg) | O37: =H10*O32 -> 0.14623754 | Q37: Recoverable scrap salvage - Ash (Rs/kg) | T37: =H12*$H$8 -> 110.656
B38: Dia of 1 hole (mm) | D38: =O14 -> 10 | F38: Length of 1 slot (mm) | J38: =U13 -> 25 | M38: Recoverable scrap - Dross per meter of tray (kg) | O38: =H11*O32 -> 0.097491692 | Q38: Recoverable scrap salvage - Dross (Rs/kg) | T38: =H13*$H$8 -> 221.312
B39: Volume of holes (m3) | D39: =2*D37*3.14*(D38/2/1000)^2*D26/1000 -> 6.28e-06 | F39: Width of 1 slot (mm) | J39: =U14 -> 10 | M39: Salvage value of scrap per meter of cable (Rs) | O39: =O37*T37+O38*T38 -> 37.758142
F40: Volume of 1 slot (m3) | J40: =J38/1000*J39/1000*J27/1000 -> 5e-07
B41: Weight of holes per 2500 mm of runner (kg) | D41: =D39*D8 -> 0.049298 | F41: Volume slots per rung (m3) | J41: =D24/40*J40 -> 7.5e-06 | M41: Net cost of Zinc galvanization per meter of runner (Rs) | O41: =O35-O39 -> 480.89766
B42: Value of scrap generated per meter of runner (Rs) | D42: =D41*D6 -> 3.598754 | F42: Weight of slots per rung (kg) | J42: =J41*D8 -> 0.058875
B43: Salvage value of scrap (% of overall value) | D43: =D11 -> 0.5 | F43: Weight of slots per 2500mm of runner (kg) | J43: =J42*J23 -> 0.471
B44: Salvage value of MS scrap per meter of runner (Rs) | D44: =D42*D43 -> 1.799377 | F44: Value of scrap generated per meter of runner (Rs) | J44: =J43*D6 -> 34.383
F45: Salvage value of MS scrap per meter of runner (Rs) | J45: =J44*D43 -> 17.1915
B47: Cost of material for 1 m of runner (Rs) | D47: =D33-D44 -> 651.47762 | F47: Cost of material for rungs per meter of runner (Rs) | J47: =J32-J45 -> 477.9237
B49: Total cost per meter of cable tray (Rs) | D49: =D47+J47 -> 1129.4013
B50: Wastage allowance during fabrication | D50: =D12 -> 0
B51: Net cost per meter of cable tray (Rs) | D51: =(1+D50)*D49 -> 1129.4013
B54: Engineering, Fabrication and Quality & Inspection cost of cable tray | M54: Cost of galvanization
B55: Engineering & Fabrication cost (Rs) | D55: =(D33+J32)*D9 -> 0 | M55: Galvanization cost (Rs) | N55: =O35*H14 -> 0
B56: Quality inspection and testing (Rs) | D56: =(D33+J32)*D10 -> 0
B61: Summary (Cost of cable tray per meter length)
B63: Cost of steel (Rs) | D63: =D51 -> 1129.4013
B64: Cost of raw material for galvanization (Rs) | D64: =O41 -> 480.89766
B65: Cost of fabrication (Rs) | D65: =D55 -> 0
B66: Cost of galvanization (Rs) | D66: =N55 -> 0
B67: Quality inspection and testing (Rs) | D67: =D56 -> 0
B68: Vendor Overheads (Rs) | D68: =SUM(D63:D67)*D14 -> 0
B69: Profit margin for vendor (Rs) | D69: =SUM(D63:D68)*D15 -> 4025.7475
B70: Contract Performance Bank Guarantee (Rs) | D70: =SUM(D63:D69)*D16 -> 0
B71: Transportation and handling to site (Rs) | D71: =(D32+J30*J23-D41-J43)*D13 -> 0
B72: Should be cost (Rs per meter) | D72: =SUM(D63:D71) -> 5636.0464
B73: Ex Works Should be cost (Rs per meter) | D73: =SUM(D63:D70) -> 5636.0464
B79: Comparison - Cost model viz-a-viz TPL estimations
C81: B2-i: Ladder Type Vertical Bend 90 deg (UP), Bending Radius 1050 mm - 600mm(W) X 100mm(H) X 2mm(T), ~1.90 m
B83: Summary (Cost of cable tray - 2500 length)
B85: Cost of steel (Rs) | D85: =D71 -> 0
B86: Cost of raw material for galvanization (Rs) | D86: =O64 -> 0
B87: Cost of fabrication (Rs) | D87: =D75 -> 0
B88: Cost of galvanization (Rs) | D88: =O75 -> 0
B89: Quality inspection and testing (Rs) | D89: =D76 -> 0
B90: Vendor Overheads (Rs) | D90: =SUM(D85:D89)*D36 -> 0
B91: Profit margin for vendor | D91: =SUM(D85:D90)*D37 -> 0
B92: Contract Performance Bank Guarantee (Rs) | D92: =SUM(D85:D91)*D38 -> 0
B93: Transportation and handling to site (Rs) | D93: =(D54-D62-I63)*D35 -> 0
B95: Should be cost | D95: =SUM(D85:D93) -> 0
B96: Ex Works Should be cost | D96: =SUM(D85:D92) -> 0
D97: Suggested model | E97: TPL model
C98: Weight of runner (kg) | D98: =D32 -> 8.949 | E98: ='[1]Old Ladder type (2)'!K24 -> 8.949
C99: Savings due to holes/ slots in runner (kg) | D99: =D41 -> 0.049298 | E99: 0
C100: Weight of rung (kg) | D100: =J30*J23 -> 6.7824 | E100: ='[1]Old Ladder type (2)'!L24 -> 6.7824
C101: Savings due to slots in rung (kg) | D101: =J43 -> 0.471 | E101: 0
C102: ="Weight of Coupler plate ("&'[1]Coupler Plate'!N6&"X"&'[1]Coupler Plate'!N7&"X"&'[1]Coupler Plate'!N8&") (kg)" -> Weight of Coupler plate (70X210X2) (kg) | D102: ='[1]Coupler Plate'!D37*2 -> 0.414009 | E102: ='[1]Old Ladder type (2)'!M24 -> 0.46158
C103: Hardware weight (Nut,bolt and washer) (kg) | D103: 0.32 | E103: 0.32 | G103: fixed
C104: Total weight (kg) | D104: =D98-D99+D100-D101+D102+D103 -> 15.945111 | E104: =E98-E99+E100-E101+E102+E103 -> 16.51298 | F104: =(E104-D104)/D104 -> 0.035613989
C105: Cost of steel (INR) | D105: =(D98*D6-D11*D99*D6)+(D100*D6-D11*D101*D6)+('[1]Coupler Plate'!D24-D43*'[1]Coupler Plate'!D34)*D6*2+D103*D6 -> 1184.7203 | E105: =E104*D6 -> 1205.4475
C107: Weight of Zinc required for galvanization (kg) | D107: =5%*D104 -> 0.79725555 | E107: =5%*E104 -> 0.825649 | G107: TPL assumption: 5% of steel weight; zinc weight to be calculated basis coating thickness
C108: Cost of zinc (INR) | D108: =D107*$H$8 -> 339.31196 | E108: =E107*$H$8 -> 351.39621
C110: Labour,Fabrication,Overhead,Profit Margin (INR) | D110: =(D104+D107)*$D$17 -> 130.59046 | E110: =(E104+E107)*$D$17 -> 135.24131
C112: Total cost (INR) per tray | D112: =D110+D105+D108 -> 1654.6227 | E112: =E110+E105+E108 -> 1692.0851
C113: Cost per meter (INR) per tray | D113: =D112/(O12/1000) -> 870.85408 | E113: =E112/(O12/1000) -> 890.57108
C114: Savings | D114: =(E112-D112)/D112 -> 0.022641003
B118: Comparison table - Summary
D120: TPL | H120: Cost Model
C121: B2-i: Ladder Type Vertical Bend 90 deg (UP), Bending Radius 1050 mm, 600mm(W) X 100mm(H), 2mm thk M.S. sheet, ~1.90 m, hot dip galvanised incl. coupler plate
D123: Weight of steel (kg) | E123: Weight of zinc (kg) | F123: Estimated price | H123: Weight of steel (kg) | I123: Weight of zinc (kg) | J123: Estimated price | K123: Price difference
C124: ='[1]Old Ladder type (2)'!B24 -> 600mm(W)X100mm(H) - B2-i vertical bend | D124: ='[1]Old Ladder type (2)'!Q24 -> 16.51298 | E124: ='[1]Old Ladder type (2)'!U24 -> 0.825649 | F124: ='[1]Old Ladder type (2)'!Z24 -> 1393.1093 | H124: =D104 -> 15.945111 | I124: =D107 -> 0.79725555 | J124: =D112 -> 1654.6227 | K124: =(F124-J124)/J124 -> -0.15805019

Sheet Vertical bend up 300x100x2
A1: Cable Tray Costing: Ladder Type Vertical Bend 90 deg (UP), Bending Radius 1050 mm
B5: Input for raw material and conversion costs | M5: Cable Tray configuration
B6: Cost of 1 kg of MS (Rs) | D6: 73 | F6: Coating thickness of Zinc (micron) | H6: 86 | M6: Runners | Q6: Rungs
B7: Transportation and handling cost of raw material to vendor shop (% of raw material cost) | D7: 0 | F7: Specific weight of Zinc (kg/m3) | H7: 7135 | M7: Number of runners | O7: 2 | Q7: No of rungs per 2500 meter of runner | U7: 10
B8: Specific weight of MS (kg/m3) | D8: 7850 | F8: Cost of Zinc (Rs/kg) | H8: 425.6 | M8: Tray width (mm) | O8: 300 | Q8: Length of rung (mm) | U8: =O8 -> 300
B9: Cost of engg and fabrication (% of material cost) | D9: 0 | F9: Wastage during galvalization | H9: 0 | M9: Tray Depth (mm) | O9: 100 | Q9: Width of rung (mm) | U9: 50
B10: Quality test and inspection charges (%) | D10: 0 | F10: Recoverable scrap - Ash per meter of tray (%) | H10: 0.12 | M10: Tray thickness (mm) | O10: 2 | Q10: Collar / Height of rung (mm) | U10: 20
B11: Salvage value of scrap for MS plates(% of overall value) | D11: 0.5 | F11: Recoverable scrap - Dross per meter of tray (%) | H11: 0.08 | M11: Tray collar (mm) | O11: 25 | Q11: Thickness of rung (mm) | U11: 2
B12: Wastage allowance during fabrication | D12: 0 | F12: Recoverable scrap salvage value - Ash (%) | H12: 0.26 | M12: Tray length (mm) | O12: 1900 | Q12: No of slots per 40 mm of length | U12: 1
B13: Transportation and handling cost of finished goods to site (Rs/kg) | D13: 0 | F13: Recoverable scrap salvage value - Dross (%) | H13: 0.52 | M13: No of holes per 2500 mm length | O13: 20 | Q13: Length of 1 slot (mm) | U13: 25
B14: Overheads for vendor (%) | D14: 0 | F14: Cost of galvanization (% of material cost) | H14: 0 | M14: Dia of 1 hole (mm) | O14: 10 | Q14: Width of 1 slot (mm) | U14: 10
B15: Profit margin for vendor (%) | D15: 2.5
B16: Cost of contract Performance Bank Guarantee | D16: 0
B17: Labour,Fabrication,Overhead,Profit Margin (INR/ kg) | D17: =6.5*1.2 -> 7.8
B20: Detailed Costing
B21: Cable tray MS material cost | M21: Galvalization
B22: Runner | F22: Rung | M22: Zinc Requirement
B23: Number of runners per meter length | D23: =O7 -> 2 | F23: No of rungs in this fitting (U7 x length / 2500, rounded) | J23: =ROUND(U7*D28/2500,0) -> 8 | M23: Runner | Q23: Rung
B24: Tray width (mm) | D24: =O8 -> 300 | F24: Length of rung (mm) | J24: =U8 -> 300 | M24: Surface area for 1 m length (m2) | O24: =2*(2*(2*D27+D25)/1000*D28/1000) -> 1.14 | Q24: Surface area for 1 rung (m2) | T24: =2*J24/1000*(J25+2*J26)/1000 -> 0.054
B25: Tray Depth (mm) | D25: =O9 -> 100 | F25: Width of rung (mm) | J25: =U9 -> 50 | M25: Surface area holes along thickness for 1 m length (m2) | O25: =D37*3.14*D38/1000*D26/1000*D28/125 -> 0.0190912 | Q25: Surface area of slots along thickness for 1 rung (m2) | T25: =(2*(J38+J39)/1000*D26/1000)*D24/40 -> 0.00105
B26: Tray thickness (mm) | D26: =O10 -> 2 | F26: Collar / Height of rung (mm) | J26: =U10 -> 20 | M26: Top surface area of holes for 1 m length (m2) | O26: =D37*3.14*(D38/2/1000)^2*D28/125 -> 0.023864 | Q26: Top surface area of slots 1 rung (m2) | T26: =J38/1000*J39/1000*D24/40 -> 0.001875
B27: Tray collar (mm) | D27: =O11 -> 25 | F27: Thickness of rung (mm) | J27: =U11 -> 2
B28: Tray length (mm) | D28: =O12 -> 1900 | M28: Overall surface area for 1 meter of runner (m2) | O28: =O24+O25-O26 -> 1.1352272 | Q28: Overall rung surface area for 1 meter of runner (m2) | T28: =(T24+T25-T26)*J23 -> 0.4254
F29: Volume of 1 rung (m3) | J29: =(2*J26+J25)/1000*J24/1000*J27/1000 -> 5.4e-05
F30: Weight of 1 rung (kg) | J30: =J29*D8 -> 0.4239 | M30: Total surface area per meter of cable tray (m2) | O30: =O28+T28 -> 1.5606272
B31: Volume of runner (m3) | D31: =2*(D25+D27*2)/1000*D26/1000*D28/1000 -> 0.00114 | F31: Cost of 1 rung (Rs) | J31: =J30*(D6*(1+D7)) -> 30.9447
B32: Weight of runner per meter length (kg) | D32: =D31*D8 -> 8.949 | F32: Cost of rungs per meter of runner | J32: =J31*J23 -> 247.5576 | M32: Weight of Zinc required for galvanization (kg) | O32: =O30*H6*10^-6*H7 -> 0.95761646
B33: Cost of runner per meter length (Rs) | D33: =D32*(D6*(1+D7)) -> 653.277 | M33: Wastage during galvalization | O33: =H9 -> 0
M34: Total weight of Zinc required for galvanization (kg) | O34: =(1+O33)*O32 -> 0.95761646
B35: Scrap salvage due to holes / slots | M35: Cost of Zinc galvanization per meter of runner (Rs) | O35: =O34*H8 -> 407.56156
B36: Runner | F36: Rung
B37: No of holes per 2500 mm length | D37: =O13 -> 20 | F37: No of slots per 40 mm of length | J37: =U12 -> 1 | M37: Recoverable scrap - Ash per meter of tray (kg) | O37: =H10*O32 -> 0.11491397 | Q37: Recoverable scrap salvage - Ash (Rs/kg) | T37: =H12*$H$8 -> 110.656
B38: Dia of 1 hole (mm) | D38: =O14 -> 10 | F38: Length of 1 slot (mm) | J38: =U13 -> 25 | M38: Recoverable scrap - Dross per meter of tray (kg) | O38: =H11*O32 -> 0.076609316 | Q38: Recoverable scrap salvage - Dross (Rs/kg) | T38: =H13*$H$8 -> 221.312
B39: Volume of holes (m3) | D39: =2*D37*3.14*(D38/2/1000)^2*D26/1000 -> 6.28e-06 | F39: Width of 1 slot (mm) | J39: =U14 -> 10 | M39: Salvage value of scrap per meter of cable (Rs) | O39: =O37*T37+O38*T38 -> 29.670482
F40: Volume of 1 slot (m3) | J40: =J38/1000*J39/1000*J27/1000 -> 5e-07
B41: Weight of holes per 2500 mm of runner (kg) | D41: =D39*D8 -> 0.049298 | F41: Volume slots per rung (m3) | J41: =D24/40*J40 -> 3.75e-06 | M41: Net cost of Zinc galvanization per meter of runner (Rs) | O41: =O35-O39 -> 377.89108
B42: Value of scrap generated per meter of runner (Rs) | D42: =D41*D6 -> 3.598754 | F42: Weight of slots per rung (kg) | J42: =J41*D8 -> 0.0294375
B43: Salvage value of scrap (% of overall value) | D43: =D11 -> 0.5 | F43: Weight of slots per 2500mm of runner (kg) | J43: =J42*J23 -> 0.2355
B44: Salvage value of MS scrap per meter of runner (Rs) | D44: =D42*D43 -> 1.799377 | F44: Value of scrap generated per meter of runner (Rs) | J44: =J43*D6 -> 17.1915
F45: Salvage value of MS scrap per meter of runner (Rs) | J45: =J44*D43 -> 8.59575
B47: Cost of material for 1 m of runner (Rs) | D47: =D33-D44 -> 651.47762 | F47: Cost of material for rungs per meter of runner (Rs) | J47: =J32-J45 -> 238.96185
B49: Total cost per meter of cable tray (Rs) | D49: =D47+J47 -> 890.43947
B50: Wastage allowance during fabrication | D50: =D12 -> 0
B51: Net cost per meter of cable tray (Rs) | D51: =(1+D50)*D49 -> 890.43947
B54: Engineering, Fabrication and Quality & Inspection cost of cable tray | M54: Cost of galvanization
B55: Engineering & Fabrication cost (Rs) | D55: =(D33+J32)*D9 -> 0 | M55: Galvanization cost (Rs) | N55: =O35*H14 -> 0
B56: Quality inspection and testing (Rs) | D56: =(D33+J32)*D10 -> 0
B61: Summary (Cost of cable tray per meter length)
B63: Cost of steel (Rs) | D63: =D51 -> 890.43947
B64: Cost of raw material for galvanization (Rs) | D64: =O41 -> 377.89108
B65: Cost of fabrication (Rs) | D65: =D55 -> 0
B66: Cost of galvanization (Rs) | D66: =N55 -> 0
B67: Quality inspection and testing (Rs) | D67: =D56 -> 0
B68: Vendor Overheads (Rs) | D68: =SUM(D63:D67)*D14 -> 0
B69: Profit margin for vendor (Rs) | D69: =SUM(D63:D68)*D15 -> 3170.8264
B70: Contract Performance Bank Guarantee (Rs) | D70: =SUM(D63:D69)*D16 -> 0
B71: Transportation and handling to site (Rs) | D71: =(D32+J30*J23-D41-J43)*D13 -> 0
B72: Should be cost (Rs per meter) | D72: =SUM(D63:D71) -> 4439.1569
B73: Ex Works Should be cost (Rs per meter) | D73: =SUM(D63:D70) -> 4439.1569
B79: Comparison - Cost model viz-a-viz TPL estimations
C81: B2-i: Ladder Type Vertical Bend 90 deg (UP), Bending Radius 1050 mm - 600mm(W) X 100mm(H) X 2mm(T), ~1.90 m
B83: Summary (Cost of cable tray - 2500 length)
B85: Cost of steel (Rs) | D85: =D71 -> 0
B86: Cost of raw material for galvanization (Rs) | D86: =O64 -> 0
B87: Cost of fabrication (Rs) | D87: =D75 -> 0
B88: Cost of galvanization (Rs) | D88: =O75 -> 0
B89: Quality inspection and testing (Rs) | D89: =D76 -> 0
B90: Vendor Overheads (Rs) | D90: =SUM(D85:D89)*D36 -> 0
B91: Profit margin for vendor | D91: =SUM(D85:D90)*D37 -> 0
B92: Contract Performance Bank Guarantee (Rs) | D92: =SUM(D85:D91)*D38 -> 0
B93: Transportation and handling to site (Rs) | D93: =(D54-D62-I63)*D35 -> 0
B95: Should be cost | D95: =SUM(D85:D93) -> 0
B96: Ex Works Should be cost | D96: =SUM(D85:D92) -> 0
D97: Suggested model | E97: TPL model
C98: Weight of runner (kg) | D98: =D32 -> 8.949 | E98: ='[1]Old Ladder type (2)'!K24 -> 8.949
C99: Savings due to holes/ slots in runner (kg) | D99: =D41 -> 0.049298 | E99: 0
C100: Weight of rung (kg) | D100: =J30*J23 -> 3.3912 | E100: ='[1]Old Ladder type (2)'!L24 -> 6.7824
C101: Savings due to slots in rung (kg) | D101: =J43 -> 0.2355 | E101: 0
C102: ="Weight of Coupler plate ("&'[1]Coupler Plate'!N6&"X"&'[1]Coupler Plate'!N7&"X"&'[1]Coupler Plate'!N8&") (kg)" -> Weight of Coupler plate (70X210X2) (kg) | D102: ='[1]Coupler Plate'!D37*2 -> 0.414009 | E102: ='[1]Old Ladder type (2)'!M24 -> 0.46158
C103: Hardware weight (Nut,bolt and washer) (kg) | D103: 0.32 | E103: 0.32 | G103: fixed
C104: Total weight (kg) | D104: =D98-D99+D100-D101+D102+D103 -> 12.789411 | E104: =E98-E99+E100-E101+E102+E103 -> 16.51298 | F104: =(E104-D104)/D104 -> 0.29114468
C105: Cost of steel (INR) | D105: =(D98*D6-D11*D99*D6)+(D100*D6-D11*D101*D6)+('[1]Coupler Plate'!D24-D43*'[1]Coupler Plate'!D34)*D6*2+D103*D6 -> 945.75847 | E105: =E104*D6 -> 1205.4475
C107: Weight of Zinc required for galvanization (kg) | D107: =5%*D104 -> 0.63947055 | E107: =5%*E104 -> 0.825649 | G107: TPL assumption: 5% of steel weight; zinc weight to be calculated basis coating thickness
C108: Cost of zinc (INR) | D108: =D107*$H$8 -> 272.15867 | E108: =E107*$H$8 -> 351.39621
C110: Labour,Fabrication,Overhead,Profit Margin (INR) | D110: =(D104+D107)*$D$17 -> 104.74528 | E110: =(E104+E107)*$D$17 -> 135.24131
C112: Total cost (INR) per tray | D112: =D110+D105+D108 -> 1322.6624 | E112: =E110+E105+E108 -> 1692.0851
C113: Cost per meter (INR) per tray | D113: =D112/(O12/1000) -> 696.13811 | E113: =E112/(O12/1000) -> 890.57108
C114: Savings | D114: =(E112-D112)/D112 -> 0.27930229
B118: Comparison table - Summary
D120: TPL | H120: Cost Model
C121: B2-i: Ladder Type Vertical Bend 90 deg (UP), Bending Radius 1050 mm, 600mm(W) X 100mm(H), 2mm thk M.S. sheet, ~1.90 m, hot dip galvanised incl. coupler plate
D123: Weight of steel (kg) | E123: Weight of zinc (kg) | F123: Estimated price | H123: Weight of steel (kg) | I123: Weight of zinc (kg) | J123: Estimated price | K123: Price difference
C124: ='[1]Old Ladder type (2)'!B24 -> 600mm(W)X100mm(H) - B2-i vertical bend | D124: ='[1]Old Ladder type (2)'!Q24 -> 16.51298 | E124: ='[1]Old Ladder type (2)'!U24 -> 0.825649 | F124: ='[1]Old Ladder type (2)'!Z24 -> 1393.1093 | H124: =D104 -> 12.789411 | I124: =D107 -> 0.63947055 | J124: =D112 -> 1322.6624 | K124: =(F124-J124)/J124 -> 0.053261427

Sheet Vertical bend up 150x100x2
A1: Cable Tray Costing: Ladder Type Vertical Bend 90 deg (UP), Bending Radius 1050 mm
B5: Input for raw material and conversion costs | M5: Cable Tray configuration
B6: Cost of 1 kg of MS (Rs) | D6: 73 | F6: Coating thickness of Zinc (micron) | H6: 86 | M6: Runners | Q6: Rungs
B7: Transportation and handling cost of raw material to vendor shop (% of raw material cost) | D7: 0 | F7: Specific weight of Zinc (kg/m3) | H7: 7135 | M7: Number of runners | O7: 2 | Q7: No of rungs per 2500 meter of runner | U7: 10
B8: Specific weight of MS (kg/m3) | D8: 7850 | F8: Cost of Zinc (Rs/kg) | H8: 425.6 | M8: Tray width (mm) | O8: 150 | Q8: Length of rung (mm) | U8: =O8 -> 150
B9: Cost of engg and fabrication (% of material cost) | D9: 0 | F9: Wastage during galvalization | H9: 0 | M9: Tray Depth (mm) | O9: 100 | Q9: Width of rung (mm) | U9: 50
B10: Quality test and inspection charges (%) | D10: 0 | F10: Recoverable scrap - Ash per meter of tray (%) | H10: 0.12 | M10: Tray thickness (mm) | O10: 2 | Q10: Collar / Height of rung (mm) | U10: 20
B11: Salvage value of scrap for MS plates(% of overall value) | D11: 0.5 | F11: Recoverable scrap - Dross per meter of tray (%) | H11: 0.08 | M11: Tray collar (mm) | O11: 25 | Q11: Thickness of rung (mm) | U11: 2
B12: Wastage allowance during fabrication | D12: 0 | F12: Recoverable scrap salvage value - Ash (%) | H12: 0.26 | M12: Tray length (mm) | O12: 1900 | Q12: No of slots per 40 mm of length | U12: 1
B13: Transportation and handling cost of finished goods to site (Rs/kg) | D13: 0 | F13: Recoverable scrap salvage value - Dross (%) | H13: 0.52 | M13: No of holes per 2500 mm length | O13: 20 | Q13: Length of 1 slot (mm) | U13: 25
B14: Overheads for vendor (%) | D14: 0 | F14: Cost of galvanization (% of material cost) | H14: 0 | M14: Dia of 1 hole (mm) | O14: 10 | Q14: Width of 1 slot (mm) | U14: 10
B15: Profit margin for vendor (%) | D15: 2.5
B16: Cost of contract Performance Bank Guarantee | D16: 0
B17: Labour,Fabrication,Overhead,Profit Margin (INR/ kg) | D17: =6.5*1.2 -> 7.8
B20: Detailed Costing
B21: Cable tray MS material cost | M21: Galvalization
B22: Runner | F22: Rung | M22: Zinc Requirement
B23: Number of runners per meter length | D23: =O7 -> 2 | F23: No of rungs in this fitting (U7 x length / 2500, rounded) | J23: =ROUND(U7*D28/2500,0) -> 8 | M23: Runner | Q23: Rung
B24: Tray width (mm) | D24: =O8 -> 150 | F24: Length of rung (mm) | J24: =U8 -> 150 | M24: Surface area for 1 m length (m2) | O24: =2*(2*(2*D27+D25)/1000*D28/1000) -> 1.14 | Q24: Surface area for 1 rung (m2) | T24: =2*J24/1000*(J25+2*J26)/1000 -> 0.027
B25: Tray Depth (mm) | D25: =O9 -> 100 | F25: Width of rung (mm) | J25: =U9 -> 50 | M25: Surface area holes along thickness for 1 m length (m2) | O25: =D37*3.14*D38/1000*D26/1000*D28/125 -> 0.0190912 | Q25: Surface area of slots along thickness for 1 rung (m2) | T25: =(2*(J38+J39)/1000*D26/1000)*D24/40 -> 0.000525
B26: Tray thickness (mm) | D26: =O10 -> 2 | F26: Collar / Height of rung (mm) | J26: =U10 -> 20 | M26: Top surface area of holes for 1 m length (m2) | O26: =D37*3.14*(D38/2/1000)^2*D28/125 -> 0.023864 | Q26: Top surface area of slots 1 rung (m2) | T26: =J38/1000*J39/1000*D24/40 -> 0.0009375
B27: Tray collar (mm) | D27: =O11 -> 25 | F27: Thickness of rung (mm) | J27: =U11 -> 2
B28: Tray length (mm) | D28: =O12 -> 1900 | M28: Overall surface area for 1 meter of runner (m2) | O28: =O24+O25-O26 -> 1.1352272 | Q28: Overall rung surface area for 1 meter of runner (m2) | T28: =(T24+T25-T26)*J23 -> 0.2127
F29: Volume of 1 rung (m3) | J29: =(2*J26+J25)/1000*J24/1000*J27/1000 -> 2.7e-05
F30: Weight of 1 rung (kg) | J30: =J29*D8 -> 0.21195 | M30: Total surface area per meter of cable tray (m2) | O30: =O28+T28 -> 1.3479272
B31: Volume of runner (m3) | D31: =2*(D25+D27*2)/1000*D26/1000*D28/1000 -> 0.00114 | F31: Cost of 1 rung (Rs) | J31: =J30*(D6*(1+D7)) -> 15.47235
B32: Weight of runner per meter length (kg) | D32: =D31*D8 -> 8.949 | F32: Cost of rungs per meter of runner | J32: =J31*J23 -> 123.7788 | M32: Weight of Zinc required for galvanization (kg) | O32: =O30*H6*10^-6*H7 -> 0.82710161
B33: Cost of runner per meter length (Rs) | D33: =D32*(D6*(1+D7)) -> 653.277 | M33: Wastage during galvalization | O33: =H9 -> 0
M34: Total weight of Zinc required for galvanization (kg) | O34: =(1+O33)*O32 -> 0.82710161
B35: Scrap salvage due to holes / slots | M35: Cost of Zinc galvanization per meter of runner (Rs) | O35: =O34*H8 -> 352.01444
B36: Runner | F36: Rung
B37: No of holes per 2500 mm length | D37: =O13 -> 20 | F37: No of slots per 40 mm of length | J37: =U12 -> 1 | M37: Recoverable scrap - Ash per meter of tray (kg) | O37: =H10*O32 -> 0.099252193 | Q37: Recoverable scrap salvage - Ash (Rs/kg) | T37: =H12*$H$8 -> 110.656
B38: Dia of 1 hole (mm) | D38: =O14 -> 10 | F38: Length of 1 slot (mm) | J38: =U13 -> 25 | M38: Recoverable scrap - Dross per meter of tray (kg) | O38: =H11*O32 -> 0.066168129 | Q38: Recoverable scrap salvage - Dross (Rs/kg) | T38: =H13*$H$8 -> 221.312
B39: Volume of holes (m3) | D39: =2*D37*3.14*(D38/2/1000)^2*D26/1000 -> 6.28e-06 | F39: Width of 1 slot (mm) | J39: =U14 -> 10 | M39: Salvage value of scrap per meter of cable (Rs) | O39: =O37*T37+O38*T38 -> 25.626652
F40: Volume of 1 slot (m3) | J40: =J38/1000*J39/1000*J27/1000 -> 5e-07
B41: Weight of holes per 2500 mm of runner (kg) | D41: =D39*D8 -> 0.049298 | F41: Volume slots per rung (m3) | J41: =D24/40*J40 -> 1.875e-06 | M41: Net cost of Zinc galvanization per meter of runner (Rs) | O41: =O35-O39 -> 326.38779
B42: Value of scrap generated per meter of runner (Rs) | D42: =D41*D6 -> 3.598754 | F42: Weight of slots per rung (kg) | J42: =J41*D8 -> 0.01471875
B43: Salvage value of scrap (% of overall value) | D43: =D11 -> 0.5 | F43: Weight of slots per 2500mm of runner (kg) | J43: =J42*J23 -> 0.11775
B44: Salvage value of MS scrap per meter of runner (Rs) | D44: =D42*D43 -> 1.799377 | F44: Value of scrap generated per meter of runner (Rs) | J44: =J43*D6 -> 8.59575
F45: Salvage value of MS scrap per meter of runner (Rs) | J45: =J44*D43 -> 4.297875
B47: Cost of material for 1 m of runner (Rs) | D47: =D33-D44 -> 651.47762 | F47: Cost of material for rungs per meter of runner (Rs) | J47: =J32-J45 -> 119.48092
B49: Total cost per meter of cable tray (Rs) | D49: =D47+J47 -> 770.95855
B50: Wastage allowance during fabrication | D50: =D12 -> 0
B51: Net cost per meter of cable tray (Rs) | D51: =(1+D50)*D49 -> 770.95855
B54: Engineering, Fabrication and Quality & Inspection cost of cable tray | M54: Cost of galvanization
B55: Engineering & Fabrication cost (Rs) | D55: =(D33+J32)*D9 -> 0 | M55: Galvanization cost (Rs) | N55: =O35*H14 -> 0
B56: Quality inspection and testing (Rs) | D56: =(D33+J32)*D10 -> 0
B61: Summary (Cost of cable tray per meter length)
B63: Cost of steel (Rs) | D63: =D51 -> 770.95855
B64: Cost of raw material for galvanization (Rs) | D64: =O41 -> 326.38779
B65: Cost of fabrication (Rs) | D65: =D55 -> 0
B66: Cost of galvanization (Rs) | D66: =N55 -> 0
B67: Quality inspection and testing (Rs) | D67: =D56 -> 0
B68: Vendor Overheads (Rs) | D68: =SUM(D63:D67)*D14 -> 0
B69: Profit margin for vendor (Rs) | D69: =SUM(D63:D68)*D15 -> 2743.3659
B70: Contract Performance Bank Guarantee (Rs) | D70: =SUM(D63:D69)*D16 -> 0
B71: Transportation and handling to site (Rs) | D71: =(D32+J30*J23-D41-J43)*D13 -> 0
B72: Should be cost (Rs per meter) | D72: =SUM(D63:D71) -> 3840.7122
B73: Ex Works Should be cost (Rs per meter) | D73: =SUM(D63:D70) -> 3840.7122
B79: Comparison - Cost model viz-a-viz TPL estimations
C81: B2-i: Ladder Type Vertical Bend 90 deg (UP), Bending Radius 1050 mm - 600mm(W) X 100mm(H) X 2mm(T), ~1.90 m
B83: Summary (Cost of cable tray - 2500 length)
B85: Cost of steel (Rs) | D85: =D71 -> 0
B86: Cost of raw material for galvanization (Rs) | D86: =O64 -> 0
B87: Cost of fabrication (Rs) | D87: =D75 -> 0
B88: Cost of galvanization (Rs) | D88: =O75 -> 0
B89: Quality inspection and testing (Rs) | D89: =D76 -> 0
B90: Vendor Overheads (Rs) | D90: =SUM(D85:D89)*D36 -> 0
B91: Profit margin for vendor | D91: =SUM(D85:D90)*D37 -> 0
B92: Contract Performance Bank Guarantee (Rs) | D92: =SUM(D85:D91)*D38 -> 0
B93: Transportation and handling to site (Rs) | D93: =(D54-D62-I63)*D35 -> 0
B95: Should be cost | D95: =SUM(D85:D93) -> 0
B96: Ex Works Should be cost | D96: =SUM(D85:D92) -> 0
D97: Suggested model | E97: TPL model
C98: Weight of runner (kg) | D98: =D32 -> 8.949 | E98: ='[1]Old Ladder type (2)'!K24 -> 8.949
C99: Savings due to holes/ slots in runner (kg) | D99: =D41 -> 0.049298 | E99: 0
C100: Weight of rung (kg) | D100: =J30*J23 -> 1.6956 | E100: ='[1]Old Ladder type (2)'!L24 -> 6.7824
C101: Savings due to slots in rung (kg) | D101: =J43 -> 0.11775 | E101: 0
C102: ="Weight of Coupler plate ("&'[1]Coupler Plate'!N6&"X"&'[1]Coupler Plate'!N7&"X"&'[1]Coupler Plate'!N8&") (kg)" -> Weight of Coupler plate (70X210X2) (kg) | D102: ='[1]Coupler Plate'!D37*2 -> 0.414009 | E102: ='[1]Old Ladder type (2)'!M24 -> 0.46158
C103: Hardware weight (Nut,bolt and washer) (kg) | D103: 0.32 | E103: 0.32 | G103: fixed
C104: Total weight (kg) | D104: =D98-D99+D100-D101+D102+D103 -> 11.211561 | E104: =E98-E99+E100-E101+E102+E103 -> 16.51298 | F104: =(E104-D104)/D104 -> 0.47285289
C105: Cost of steel (INR) | D105: =(D98*D6-D11*D99*D6)+(D100*D6-D11*D101*D6)+('[1]Coupler Plate'!D24-D43*'[1]Coupler Plate'!D34)*D6*2+D103*D6 -> 826.27755 | E105: =E104*D6 -> 1205.4475
C107: Weight of Zinc required for galvanization (kg) | D107: =5%*D104 -> 0.56057805 | E107: =5%*E104 -> 0.825649 | G107: TPL assumption: 5% of steel weight; zinc weight to be calculated basis coating thickness
C108: Cost of zinc (INR) | D108: =D107*$H$8 -> 238.58202 | E108: =E107*$H$8 -> 351.39621
C110: Labour,Fabrication,Overhead,Profit Margin (INR) | D110: =(D104+D107)*$D$17 -> 91.822685 | E110: =(E104+E107)*$D$17 -> 135.24131
C112: Total cost (INR) per tray | D112: =D110+D105+D108 -> 1156.6822 | E112: =E110+E105+E108 -> 1692.0851
C113: Cost per meter (INR) per tray | D113: =D112/(O12/1000) -> 608.78013 | E113: =E112/(O12/1000) -> 890.57108
C114: Savings | D114: =(E112-D112)/D112 -> 0.46287804
B118: Comparison table - Summary
D120: TPL | H120: Cost Model
C121: B2-i: Ladder Type Vertical Bend 90 deg (UP), Bending Radius 1050 mm, 600mm(W) X 100mm(H), 2mm thk M.S. sheet, ~1.90 m, hot dip galvanised incl. coupler plate
D123: Weight of steel (kg) | E123: Weight of zinc (kg) | F123: Estimated price | H123: Weight of steel (kg) | I123: Weight of zinc (kg) | J123: Estimated price | K123: Price difference
C124: ='[1]Old Ladder type (2)'!B24 -> 600mm(W)X100mm(H) - B2-i vertical bend | D124: ='[1]Old Ladder type (2)'!Q24 -> 16.51298 | E124: ='[1]Old Ladder type (2)'!U24 -> 0.825649 | F124: ='[1]Old Ladder type (2)'!Z24 -> 1393.1093 | H124: =D104 -> 11.211561 | I124: =D107 -> 0.56057805 | J124: =D112 -> 1156.6822 | K124: =(F124-J124)/J124 -> 0.20440104

Sheet U Trough 75x25x2
A1: Cable Tray Costing - Trough, U-Shaped
B5: Input for raw material and conversion costs | M5: Cable Tray configuration
B6: Cost of steel(Rs/kg) | D6: 73 | F6: Coating thickness of Zinc (micron) | H6: 86
B7: Transportation and handling cost of raw material to vendor shop (% of raw material cost) | D7: 0 | F7: Specific weight of Zinc (kg/m3) | H7: 7135 | M7: Tray width (mm) | O7: 75
B8: Specific weight of MS (kg/m3) | D8: 7850 | F8: Cost of Zinc (Rs/kg) | H8: 425.6 | M8: Tray Depth (mm) | O8: 25
B9: Cost of engg and fabrication (% of material cost) | D9: 0 | F9: Wastage during galvalization | H9: 0 | M9: Tray thickness (mm) | O9: 2
B10: Quality test and inspection charges (%) | D10: 0 | F10: Recoverable scrap - Ash per meter of tray (%) | H10: 0.12 | M10: Tray collar (mm) | O10: =IF(AND(O7>=300,O8>=100),15,0) -> 0
B11: Salvage value of scrap for MS plates(% of overall value) | D11: 0.3 | F11: Recoverable scrap - Dross per meter of tray (%) | H11: 0.08 | M11: Tray length (mm) | O11: 2500
B12: Wastage allowance during fabrication | D12: 0 | F12: Recoverable scrap salvage value - Ash (%) | H12: 0.26 | M12: Average no of perforations per row | O12: 2
B13: Transportation and handling cost of finished goods to site (Rs/kg) | D13: 0 | F13: Recoverable scrap salvage value - Dross (%) | H13: 0.52 | M13: Length of a perforation (mm) | O13: 10
B14: Overheads for vendor (%) | D14: 0 | F14: Cost of galvanization (% of material cost) | H14: 0 | M14: Width of a perforation (mm) | O14: 20
B15: Profit & overhead margin (INR/kg) | D15: 2.5 | M15: Average spacing between perforations along length of tray (mm) | O15: 40
B16: Cost of contract Performance Bank Guarantee | D16: 0 | M16: No of rows | O16: =ROUNDUP(O11/O15-1,0) -> 62
B17: Labour & Fabrication Charges (INR/ kg) | D17: =6.5*1.2 -> 7.8 | M17: No of coupler holes per 1000 mm length | O17: =4*2*2 -> 16
M18: Dia of 1 hole (mm) | O18: 10
M20: Coupler plate length (mm) | O20: =SUMPRODUCT('[1]Coupler plate dimensions (2)'!$F$2:$F$28,--('[1]Coupler plate dimensions (2)'!$D$2:$D$28=O7),--('[1]Coupler plate dimensions (2)'!$E$2:$E$28=O8)) -> 25
M21: Coupler plate height (mm) | O21: =SUMPRODUCT('[1]Coupler plate dimensions (2)'!$G$2:$G$28,--('[1]Coupler plate dimensions (2)'!$D$2:$D$28=O7),--('[1]Coupler plate dimensions (2)'!$E$2:$E$28=O8)) -> 210
M22: Coupler plate width (mm) | O22: 2
M23: No of coupler plates per runner | O23: =(2+2)/2 -> 2
B25: Detailed Costing
B26: Cable tray MS material cost | M26: Galvalization
M27: Zinc Requirement
B28: Tray width (mm) | D28: =O7 -> 75 | M28: Perforations | Q28: Coupler Holes
B29: Tray Depth (mm) | D29: =O8 -> 25 | M29: Total Surface area (m2) | O29: =2*(2*O10+2*O8+(O7+4))/1000*O11/1000 -> 0.645 | Q29: Surface area of 1 hole along thickness per meter (m2) | T29: =3.14*J42/1000*O9/1000*D32/2500*J41 -> 0
B30: Tray thickness (mm) | D30: =O9 -> 2 | M30: Surface area holes along thickness for 1000 mm length (m2) | O30: =(2*(O13+O14)/1000*O9/1000)*D42 -> 0.01488 | Q30: Top surface area of 1 hole (m2) | T30: =3.14*(J42/2/1000)^2*D32/2500*J41 -> 0
B31: Tray collar (mm) | D31: =O10 -> 0 | M31: Top surface area of holes for 1 m length (m2) | O31: =O13/1000*O14/1000*D42 -> 0.0248
B32: Tray length (mm) | D32: =O11 -> 2500
M33: Overall surface area for 1 meter of runner (m2) | O33: =O29+O30-O31 -> 0.63508
B35: Volume of tray (m3) | D35: =(2*D31+2*D29+(D28+4))/1000*D30/1000*D32/1000 -> 0.000645 | M35: Total surface area per meter of cable tray (m2) | O35: =O33+T29-T30 -> 0.63508
B36: Weight of tray per mm length (kg) | D36: =D35*D8 -> 5.06325
B37: Cost of tray per mm length (Rs) | D37: =D36*(D6*(1+D7)) -> 369.61725 | M37: Weight of Zinc required for galvanization (kg) | O37: =O35*H6*10^-6*H7 -> 0.38969144
M38: Wastage during galvalization | O38: =H9 -> 0
B39: Scrap salvage due to perforations | F39: Scrap salvage due to coupler holes | M39: Total weight of Zinc required for galvanization (kg) | O39: =(1+O38)*O37 -> 0.38969144
M40: Cost of Zinc galvanization per meter of runner (Rs) | O40: =O39*H8 -> 165.85268
B41: Average no of perforations per row | D41: =O12 -> 2 | F41: No of holes per mm of length | I41: =O17 -> 16
B42: No of perforations per mm length | D42: =D41*O16 -> 124 | F42: Dia of one hole (mm) | I42: =O18 -> 10 | M42: Recoverable scrap - Ash per meter of tray (kg) | O42: =H10*O37 -> 0.046762973 | Q42: Recoverable scrap salvage - Ash (Rs/kg) | T42: =H12*$H$8 -> 110.656
B43: Total volume of perforations (m3) | D43: =D42*O13/1000*O14/1000*O9/1000 -> 4.96e-05 | F43: Volume of holes (m3) | I43: =I41*3.14*(I42/2/1000)^2*O9/1000 -> 2.512e-06 | M43: Recoverable scrap - Dross per meter of tray (kg) | O43: =H11*O37 -> 0.031175315 | Q43: Recoverable scrap salvage - Dross (Rs/kg) | T43: =H13*$H$8 -> 221.312
B44: Weight of holes per 1000mm of runner (kg) | D44: =D43*D8 -> 0.38936 | F44: Volume of holes per 2500mm (m3) | I44: =I43*D32/2500 -> 2.512e-06 | M44: Salvage value of scrap per meter of cable (Rs) | O44: =O42*T42+O43*T43 -> 12.074075
B45: Value of scrap generated per meter of runner (Rs) | D45: =D44*D6 -> 28.42328 | F45: Weight of slots per 2500mm (kg) | I45: =I44*D8 -> 0.0197192
B46: Salvage value of scrap (% of overall value) | D46: =D11 -> 0.3 | F46: Value of scrap generated per meter of runner (Rs) | I46: =I45*D6 -> 1.4395016 | M46: Net cost of Zinc galvanization per meter of runner (Rs) | O46: =O40-O44 -> 153.7786
B47: Salvage value of MS scrap per 1000 mm of runner (Rs) | D47: =D45*D46 -> 8.526984 | F47: Salvage value of MS scrap per meter of runner (Rs) | I47: =I46*D46 -> 0.43185048
B49: Cost of material for 2500 mm of runner (Rs) | D49: =D37-D47-I47 -> 360.65842
B51: Total cost per meter of cable tray (Rs) | D51: =D49 -> 360.65842
B52: Wastage allowance during fabrication | D52: =D12 -> 0
B53: Net cost per meter of cable tray (Rs) | D53: =(1+D52)*D51 -> 360.65842
B56: Engineering, Fabrication and Quality & Inspection cost of cable tray
B57: Engineering & Fabrication cost (Rs) | D57: =D37*D9 -> 0
B58: Quality inspection and testing (Rs) | D58: =D37*D10 -> 0
B61: Comparison - Cost model viz-a-viz TPL estimations
B65: Summary (Cost of cable tray - 2500 length)
B67: Cost of steel (Rs) | D67: =D53 -> 360.65842
B68: Cost of raw material for galvanization (Rs) | D68: =O46 -> 153.7786
B69: Cost of fabrication (Rs) | D69: =D57 -> 0
B70: Cost of galvanization (Rs) | D70: =O57 -> 0
B71: Quality inspection and testing (Rs) | D71: =D58 -> 0
B72: Vendor Overheads (Rs) | D72: =SUM(D67:D71)*D14 -> 0
B73: Profit margin for vendor | D73: =SUM(D67:D72)*D15 -> 1286.0925
B74: Contract Performance Bank Guarantee (Rs) | D74: =SUM(D67:D73)*D16 -> 0
B75: Transportation and handling to site (Rs) | D75: =(D36-D44-I45)*D13 -> 0
B77: Should be cost | D77: =SUM(D67:D75) -> 1800.5296
B78: Ex Works Should be cost | D78: =SUM(D67:D74) -> 1800.5296
C79: Cable tray trough - 75 mm (W) x 25 mm (D) x 2 mm (T), 2500 mm length | E79: TPL model
C80: Weight of steel per 1000 mm length (kg) | D80: =D36 -> 5.06325 | E80: =D32/1000*(D28+2*D29+2*D31)/1000*D30/1000*D8 -> 4.90625
C81: Savings due to perforations (kg) | D81: =D44+I45 -> 0.4090792 | E81: 0 | F81: =D81/D80 -> 0.080793798
C82: Weight of Coupler plate (kg) | D82: =2*(O20*O21)/1000000*D8*O22/1000 -> 0.16485 | E82: =2*(O20*O21)/1000000*D8*O22/1000 -> 0.16485
C83: Hardware weight (Nut,bolt and washer) (kg) | D83: 0.32 | E83: 0.32 | G83: fixed
C84: Total weight (kg) | D84: =D80-D81+D82+D83 -> 5.1390208 | E84: =E80-E81+E82+E83 -> 5.3911 | F84: =(E84-D84)/D84 -> 0.049051991
C85: Cost of steel (INR) | D85: =((D80+D83)-D81*D46)*D6+2*('[1]Coupler Plate 75x25'!D24-'[1]Coupler Plate 75x25'!D34*'[1]Coupler Plate 75x25'!D11)*D6 -> 395.01066 | E85: =E84*D6 -> 393.5503 | F85: =(E85-D85)/D85 -> -0.0036970157
C87: Weight of Zinc required for galvanization (kg) | D87: =O39 -> 0.38969144 | E87: =5%*E84 -> 0.269555 | G87: TPL assumption: 5% of steel weight
C88: Cost of zinc (INR) | D88: =D87*H8-O44 -> 153.7786 | E88: =E87*H8 -> 114.72261
C90: Labour,Fabrication,Overhead,Profit Margin (INR) | D90: =(D84+D87)*($D$17+$D$15) -> 56.945736 | E90: =(E84+E87)*($D$17+$D$15) -> 58.304747
C92: Total cost (INR) | D92: =D90+D85+D88 -> 605.735 | E92: =E90+E85+E88 -> 566.57765
C93: Cost per meter (INR) per tray | D93: =D92/(O11/1000) -> 242.294 | E93: =E92/(O11/1000) -> 226.63106
C94: Savings | D94: =(E92-D92)/D92 -> -0.064644347

Sheet U Trough 50x25x2
A1: Cable Tray Costing - Trough, U-Shaped
B5: Input for raw material and conversion costs | M5: Cable Tray configuration
B6: Cost of steel(Rs/kg) | D6: 73 | F6: Coating thickness of Zinc (micron) | H6: 86
B7: Transportation and handling cost of raw material to vendor shop (% of raw material cost) | D7: 0 | F7: Specific weight of Zinc (kg/m3) | H7: 7135 | M7: Tray width (mm) | O7: 50
B8: Specific weight of MS (kg/m3) | D8: 7850 | F8: Cost of Zinc (Rs/kg) | H8: 425.6 | M8: Tray Depth (mm) | O8: 25
B9: Cost of engg and fabrication (% of material cost) | D9: 0 | F9: Wastage during galvalization | H9: 0 | M9: Tray thickness (mm) | O9: 2
B10: Quality test and inspection charges (%) | D10: 0 | F10: Recoverable scrap - Ash per meter of tray (%) | H10: 0.12 | M10: Tray collar (mm) | O10: =IF(AND(O7>=300,O8>=100),15,0) -> 0
B11: Salvage value of scrap for MS plates(% of overall value) | D11: 0.3 | F11: Recoverable scrap - Dross per meter of tray (%) | H11: 0.08 | M11: Tray length (mm) | O11: 2500
B12: Wastage allowance during fabrication | D12: 0 | F12: Recoverable scrap salvage value - Ash (%) | H12: 0.26 | M12: Average no of perforations per row | O12: 2
B13: Transportation and handling cost of finished goods to site (Rs/kg) | D13: 0 | F13: Recoverable scrap salvage value - Dross (%) | H13: 0.52 | M13: Length of a perforation (mm) | O13: 10
B14: Overheads for vendor (%) | D14: 0 | F14: Cost of galvanization (% of material cost) | H14: 0 | M14: Width of a perforation (mm) | O14: 20
B15: Profit & overhead margin (INR/kg) | D15: 2.5 | M15: Average spacing between perforations along length of tray (mm) | O15: 40
B16: Cost of contract Performance Bank Guarantee | D16: 0 | M16: No of rows | O16: =ROUNDUP(O11/O15-1,0) -> 62
B17: Labour & Fabrication Charges (INR/ kg) | D17: =6.5*1.2 -> 7.8 | M17: No of coupler holes per 1000 mm length | O17: =4*2*2 -> 16
M18: Dia of 1 hole (mm) | O18: 10
M20: Coupler plate length (mm) | O20: =SUMPRODUCT('[2]Coupler plate dimensions'!$F$2:$F$28,--('[2]Coupler plate dimensions'!$D$2:$D$28=O7),--('[2]Coupler plate dimensions'!$E$2:$E$28=O8)) -> 25
M21: Coupler plate height (mm) | O21: =SUMPRODUCT('[2]Coupler plate dimensions'!$G$2:$G$28,--('[2]Coupler plate dimensions'!$D$2:$D$28=O7),--('[2]Coupler plate dimensions'!$E$2:$E$28=O8)) -> 210
M22: Coupler plate width (mm) | O22: 2
M23: No of coupler plates per runner | O23: =(2+2)/2 -> 2
B25: Detailed Costing
B26: Cable tray MS material cost | M26: Galvalization
M27: Zinc Requirement
B28: Tray width (mm) | D28: =O7 -> 50 | M28: Perforations | Q28: Coupler Holes
B29: Tray Depth (mm) | D29: =O8 -> 25 | M29: Total Surface area (m2) | O29: =2*(2*O10+2*O8+(O7+4))/1000*O11/1000 -> 0.52 | Q29: Surface area of 1 hole along thickness per meter (m2) | T29: =3.14*J42/1000*O9/1000*D32/2500*J41 -> 0
B30: Tray thickness (mm) | D30: =O9 -> 2 | M30: Surface area holes along thickness for 1000 mm length (m2) | O30: =(2*(O13+O14)/1000*O9/1000)*D42 -> 0.01488 | Q30: Top surface area of 1 hole (m2) | T30: =3.14*(J42/2/1000)^2*D32/2500*J41 -> 0
B31: Tray collar (mm) | D31: =O10 -> 0 | M31: Top surface area of holes for 1 m length (m2) | O31: =O13/1000*O14/1000*D42 -> 0.0248
B32: Tray length (mm) | D32: =O11 -> 2500
M33: Overall surface area for 1 meter of runner (m2) | O33: =O29+O30-O31 -> 0.51008
B35: Volume of tray (m3) | D35: =(2*D31+2*D29+(D28+4))/1000*D30/1000*D32/1000 -> 0.00052 | M35: Total surface area per meter of cable tray (m2) | O35: =O33+T29-T30 -> 0.51008
B36: Weight of tray per mm length (kg) | D36: =D35*D8 -> 4.082
B37: Cost of tray per mm length (Rs) | D37: =D36*(D6*(1+D7)) -> 297.986 | M37: Weight of Zinc required for galvanization (kg) | O37: =O35*H6*10^-6*H7 -> 0.31299019
M38: Wastage during galvalization | O38: =H9 -> 0
B39: Scrap salvage due to perforations | F39: Scrap salvage due to coupler holes | M39: Total weight of Zinc required for galvanization (kg) | O39: =(1+O38)*O37 -> 0.31299019
M40: Cost of Zinc galvanization per meter of runner (Rs) | O40: =O39*H8 -> 133.20862
B41: Average no of perforations per row | D41: =O12 -> 2 | F41: No of holes per mm of length | I41: =O17 -> 16
B42: No of perforations per mm length | D42: =D41*O16 -> 124 | F42: Dia of one hole (mm) | I42: =O18 -> 10 | M42: Recoverable scrap - Ash per meter of tray (kg) | O42: =H10*O37 -> 0.037558823 | Q42: Recoverable scrap salvage - Ash (Rs/kg) | T42: =H12*$H$8 -> 110.656
B43: Total volume of perforations (m3) | D43: =D42*O13/1000*O14/1000*O9/1000 -> 4.96e-05 | F43: Volume of holes (m3) | I43: =I41*3.14*(I42/2/1000)^2*O9/1000 -> 2.512e-06 | M43: Recoverable scrap - Dross per meter of tray (kg) | O43: =H11*O37 -> 0.025039215 | Q43: Recoverable scrap salvage - Dross (Rs/kg) | T43: =H13*$H$8 -> 221.312
B44: Weight of holes per 1000mm of runner (kg) | D44: =D43*D8 -> 0.38936 | F44: Volume of holes per 2500mm (m3) | I44: =I43*D32/2500 -> 2.512e-06 | M44: Salvage value of scrap per meter of cable (Rs) | O44: =O42*T42+O43*T43 -> 9.6975879
B45: Value of scrap generated per meter of runner (Rs) | D45: =D44*D6 -> 28.42328 | F45: Weight of slots per 2500mm (kg) | I45: =I44*D8 -> 0.0197192
B46: Salvage value of scrap (% of overall value) | D46: =D11 -> 0.3 | F46: Value of scrap generated per meter of runner (Rs) | I46: =I45*D6 -> 1.4395016 | M46: Net cost of Zinc galvanization per meter of runner (Rs) | O46: =O40-O44 -> 123.51104
B47: Salvage value of MS scrap per 1000 mm of runner (Rs) | D47: =D45*D46 -> 8.526984 | F47: Salvage value of MS scrap per meter of runner (Rs) | I47: =I46*D46 -> 0.43185048
B49: Cost of material for 2500 mm of runner (Rs) | D49: =D37-D47-I47 -> 289.02717
B51: Total cost per meter of cable tray (Rs) | D51: =D49 -> 289.02717
B52: Wastage allowance during fabrication | D52: =D12 -> 0
B53: Net cost per meter of cable tray (Rs) | D53: =(1+D52)*D51 -> 289.02717
B56: Engineering, Fabrication and Quality & Inspection cost of cable tray
B57: Engineering & Fabrication cost (Rs) | D57: =D37*D9 -> 0
B58: Quality inspection and testing (Rs) | D58: =D37*D10 -> 0
B61: Comparison - Cost model viz-a-viz TPL estimations
B65: Summary (Cost of cable tray - 2500 length)
B67: Cost of steel (Rs) | D67: =D53 -> 289.02717
B68: Cost of raw material for galvanization (Rs) | D68: =O46 -> 123.51104
B69: Cost of fabrication (Rs) | D69: =D57 -> 0
B70: Cost of galvanization (Rs) | D70: =O57 -> 0
B71: Quality inspection and testing (Rs) | D71: =D58 -> 0
B72: Vendor Overheads (Rs) | D72: =SUM(D67:D71)*D14 -> 0
B73: Profit margin for vendor | D73: =SUM(D67:D72)*D15 -> 1031.3455
B74: Contract Performance Bank Guarantee (Rs) | D74: =SUM(D67:D73)*D16 -> 0
B75: Transportation and handling to site (Rs) | D75: =(D36-D44-I45)*D13 -> 0
B77: Should be cost | D77: =SUM(D67:D75) -> 1443.8837
B78: Ex Works Should be cost | D78: =SUM(D67:D74) -> 1443.8837
C79: Cable tray trough - 50 mm (W) x 25 mm (D) x 2 mm (T), 2500 mm length | E79: TPL model
C80: Weight of steel per 1000 mm length (kg) | D80: =D36 -> 4.082 | E80: =D32/1000*(D28+2*D29+2*D31)/1000*D30/1000*D8 -> 3.925
C81: Savings due to perforations (kg) | D81: =D44+I45 -> 0.4090792 | E81: 0 | F81: =D81/D80 -> 0.10021538
C82: Weight of Coupler plate (kg) | D82: =2*(O20*O21)/1000000*D8*O22/1000 -> 0.16485 | E82: =2*(O20*O21)/1000000*D8*O22/1000 -> 0.16485
C83: Hardware weight (Nut,bolt and washer) (kg) | D83: 0.32 | E83: 0.32 | G83: fixed
C84: Total weight (kg) | D84: =D80-D81+D82+D83 -> 4.1577708 | E84: =E80-E81+E82+E83 -> 4.40985 | F84: =(E84-D84)/D84 -> 0.06062845
C85: Cost of steel (INR) | D85: =((D80+D83)-D81*D46)*D6+2*('[2]Coupler Plate 50x25'!D24-'[2]Coupler Plate 50x25'!D34*'[2]Coupler Plate 50x25'!D11)*D6 -> 323.37941 | E85: =E84*D6 -> 321.91905 | F85: =(E85-D85)/D85 -> -0.0045159357
C87: Weight of Zinc required for galvanization (kg) | D87: =O39 -> 0.31299019 | E87: =5%*E84 -> 0.2204925 | G87: TPL assumption: 5% of steel weight
C88: Cost of zinc (INR) | D88: =D87*H8-O44 -> 123.51104 | E88: =E87*H8 -> 93.841608
C90: Labour,Fabrication,Overhead,Profit Margin (INR) | D90: =(D84+D87)*($D$17+$D$15) -> 46.048838 | E90: =(E84+E87)*($D$17+$D$15) -> 47.692528
C92: Total cost (INR) | D92: =D90+D85+D88 -> 492.93929 | E92: =E90+E85+E88 -> 463.45319
C93: Cost per meter (INR) per tray | D93: =D92/(O11/1000) -> 197.17571 | E93: =E92/(O11/1000) -> 185.38127
C94: Savings | D94: =(E92-D92)/D92 -> -0.059816899

Sheet H Bend 600x100x2
A1: Cable Tray Costing - Ladder Type Horizontal Bend 90 deg, Bending Radius 1200 mm
B5: Input for raw material and conversion costs | M5: Cable Tray configuration
B6: Cost of 1 kg of MS (Rs) | D6: 73 | F6: Coating thickness of Zinc (micron) | H6: 86 | M6: Runners | Q6: Rungs
B7: Transportation and handling cost of raw material to vendor shop (% of raw material cost) | D7: 0 | F7: Specific weight of Zinc (kg/m3) | H7: 7135 | M7: Number of runners | O7: 2 | Q7: No of rungs per 2500 meter of runner | U7: 10
B8: Specific weight of MS (kg/m3) | D8: 7850 | F8: Cost of Zinc (Rs/kg) | H8: 425.6 | M8: Tray width (mm) | O8: 600 | Q8: Length of rung (mm) | U8: =O8 -> 600
B9: Cost of engg and fabrication (% of material cost) | D9: 0 | F9: Wastage during galvalization | H9: 0 | M9: Tray Depth (mm) | O9: 100 | Q9: Width of rung (mm) | U9: 50
B10: Quality test and inspection charges (%) | D10: 0 | F10: Recoverable scrap - Ash per meter of tray (%) | H10: 0.12 | M10: Tray thickness (mm) | O10: 2 | Q10: Collar / Height of rung (mm) | U10: 20
B11: Salvage value of scrap for MS plates(% of overall value) | D11: 0.5 | F11: Recoverable scrap - Dross per meter of tray (%) | H11: 0.08 | M11: Tray collar (mm) | O11: 25 | Q11: Thickness of rung (mm) | U11: 2
B12: Wastage allowance during fabrication | D12: 0 | F12: Recoverable scrap salvage value - Ash (%) | H12: 0.26 | M12: Tray length (mm) | O12: 2360 | Q12: No of slots per 40 mm of length | U12: 1
B13: Transportation and handling cost of finished goods to site (Rs/kg) | D13: 0 | F13: Recoverable scrap salvage value - Dross (%) | H13: 0.52 | M13: No of holes per 2500 mm length | O13: 20 | Q13: Length of 1 slot (mm) | U13: 25
B14: Overheads for vendor (%) | D14: 0 | F14: Cost of galvanization (% of material cost) | H14: 0 | M14: Dia of 1 hole (mm) | O14: 10 | Q14: Width of 1 slot (mm) | U14: 10
B15: Profit margin for vendor (%) | D15: 2.5
B16: Cost of contract Performance Bank Guarantee | D16: 0
B17: Labour,Fabrication,Overhead,Profit Margin (INR/ kg) | D17: =6.5*1.2 -> 7.8
B20: Detailed Costing
B21: Cable tray MS material cost | M21: Galvalization
B22: Runner | F22: Rung | M22: Zinc Requirement
B23: Number of runners per meter length | D23: =O7 -> 2 | F23: No of rungs in this fitting (U7 x length / 2500, rounded) | J23: =ROUND(U7*D28/2500,0) -> 9 | M23: Runner | Q23: Rung
B24: Tray width (mm) | D24: =O8 -> 600 | F24: Length of rung (mm) | J24: =U8 -> 600 | M24: Surface area for 1 m length (m2) | O24: =2*(2*(2*D27+D25)/1000*D28/1000) -> 1.416 | Q24: Surface area for 1 rung (m2) | T24: =2*J24/1000*(J25+2*J26)/1000 -> 0.108
B25: Tray Depth (mm) | D25: =O9 -> 100 | F25: Width of rung (mm) | J25: =U9 -> 50 | M25: Surface area holes along thickness for 1 m length (m2) | O25: =D37*3.14*D38/1000*D26/1000*D28/125 -> 0.02371328 | Q25: Surface area of slots along thickness for 1 rung (m2) | T25: =(2*(J38+J39)/1000*D26/1000)*D24/40 -> 0.0021
B26: Tray thickness (mm) | D26: =O10 -> 2 | F26: Collar / Height of rung (mm) | J26: =U10 -> 20 | M26: Top surface area of holes for 1 m length (m2) | O26: =D37*3.14*(D38/2/1000)^2*D28/125 -> 0.0296416 | Q26: Top surface area of slots 1 rung (m2) | T26: =J38/1000*J39/1000*D24/40 -> 0.00375
B27: Tray collar (mm) | D27: =O11 -> 25 | F27: Thickness of rung (mm) | J27: =U11 -> 2
B28: Tray length (mm) | D28: =O12 -> 2360 | M28: Overall surface area for 1 meter of runner (m2) | O28: =O24+O25-O26 -> 1.4100717 | Q28: Overall rung surface area for 1 meter of runner (m2) | T28: =(T24+T25-T26)*J23 -> 0.95715
F29: Volume of 1 rung (m3) | J29: =(2*J26+J25)/1000*J24/1000*J27/1000 -> 0.000108
F30: Weight of 1 rung (kg) | J30: =J29*D8 -> 0.8478 | M30: Total surface area per meter of cable tray (m2) | O30: =O28+T28 -> 2.3672217
B31: Volume of runner (m3) | D31: =2*(D25+D27*2)/1000*D26/1000*D28/1000 -> 0.001416 | F31: Cost of 1 rung (Rs) | J31: =J30*(D6*(1+D7)) -> 61.8894
B32: Weight of runner per meter length (kg) | D32: =D31*D8 -> 11.1156 | F32: Cost of rungs per meter of runner | J32: =J31*J23 -> 557.0046 | M32: Weight of Zinc required for galvanization (kg) | O32: =O30*H6*10^-6*H7 -> 1.4525509
B33: Cost of runner per meter length (Rs) | D33: =D32*(D6*(1+D7)) -> 811.4388 | M33: Wastage during galvalization | O33: =H9 -> 0
M34: Total weight of Zinc required for galvanization (kg) | O34: =(1+O33)*O32 -> 1.4525509
B35: Scrap salvage due to holes / slots | M35: Cost of Zinc galvanization per meter of runner (Rs) | O35: =O34*H8 -> 618.20566
B36: Runner | F36: Rung
B37: No of holes per 2500 mm length | D37: =O13 -> 20 | F37: No of slots per 40 mm of length | J37: =U12 -> 1 | M37: Recoverable scrap - Ash per meter of tray (kg) | O37: =H10*O32 -> 0.17430611 | Q37: Recoverable scrap salvage - Ash (Rs/kg) | T37: =H12*$H$8 -> 110.656
B38: Dia of 1 hole (mm) | D38: =O14 -> 10 | F38: Length of 1 slot (mm) | J38: =U13 -> 25 | M38: Recoverable scrap - Dross per meter of tray (kg) | O38: =H11*O32 -> 0.11620407 | Q38: Recoverable scrap salvage - Dross (Rs/kg) | T38: =H13*$H$8 -> 221.312
B39: Volume of holes (m3) | D39: =2*D37*3.14*(D38/2/1000)^2*D26/1000 -> 6.28e-06 | F39: Width of 1 slot (mm) | J39: =U14 -> 10 | M39: Salvage value of scrap per meter of cable (Rs) | O39: =O37*T37+O38*T38 -> 45.005372
F40: Volume of 1 slot (m3) | J40: =J38/1000*J39/1000*J27/1000 -> 5e-07
B41: Weight of holes per 2500 mm of runner (kg) | D41: =D39*D8 -> 0.049298 | F41: Volume slots per rung (m3) | J41: =D24/40*J40 -> 7.5e-06 | M41: Net cost of Zinc galvanization per meter of runner (Rs) | O41: =O35-O39 -> 573.20029
B42: Value of scrap generated per meter of runner (Rs) | D42: =D41*D6 -> 3.598754 | F42: Weight of slots per rung (kg) | J42: =J41*D8 -> 0.058875
B43: Salvage value of scrap (% of overall value) | D43: =D11 -> 0.5 | F43: Weight of slots per 2500mm of runner (kg) | J43: =J42*J23 -> 0.529875
B44: Salvage value of MS scrap per meter of runner (Rs) | D44: =D42*D43 -> 1.799377 | F44: Value of scrap generated per meter of runner (Rs) | J44: =J43*D6 -> 38.680875
F45: Salvage value of MS scrap per meter of runner (Rs) | J45: =J44*D43 -> 19.340438
B47: Cost of material for 1 m of runner (Rs) | D47: =D33-D44 -> 809.63942 | F47: Cost of material for rungs per meter of runner (Rs) | J47: =J32-J45 -> 537.66416
B49: Total cost per meter of cable tray (Rs) | D49: =D47+J47 -> 1347.3036
B50: Wastage allowance during fabrication | D50: =D12 -> 0
B51: Net cost per meter of cable tray (Rs) | D51: =(1+D50)*D49 -> 1347.3036
B54: Engineering, Fabrication and Quality & Inspection cost of cable tray | M54: Cost of galvanization
B55: Engineering & Fabrication cost (Rs) | D55: =(D33+J32)*D9 -> 0 | M55: Galvanization cost (Rs) | N55: =O35*H14 -> 0
B56: Quality inspection and testing (Rs) | D56: =(D33+J32)*D10 -> 0
B61: Summary (Cost of cable tray per meter length)
B63: Cost of steel (Rs) | D63: =D51 -> 1347.3036
B64: Cost of raw material for galvanization (Rs) | D64: =O41 -> 573.20029
B65: Cost of fabrication (Rs) | D65: =D55 -> 0
B66: Cost of galvanization (Rs) | D66: =N55 -> 0
B67: Quality inspection and testing (Rs) | D67: =D56 -> 0
B68: Vendor Overheads (Rs) | D68: =SUM(D63:D67)*D14 -> 0
B69: Profit margin for vendor (Rs) | D69: =SUM(D63:D68)*D15 -> 4801.2597
B70: Contract Performance Bank Guarantee (Rs) | D70: =SUM(D63:D69)*D16 -> 0
B71: Transportation and handling to site (Rs) | D71: =(D32+J30*J23-D41-J43)*D13 -> 0
B72: Should be cost (Rs per meter) | D72: =SUM(D63:D71) -> 6721.7636
B73: Ex Works Should be cost (Rs per meter) | D73: =SUM(D63:D70) -> 6721.7636
B79: Comparison - Cost model viz-a-viz TPL estimations
C81: B1-i: Ladder Type Horizontal Bend 90 deg, Bending Radius 1200 mm - 600mm(W) X 100mm(H) X 2mm(T), ~2.36 m
B83: Summary (Cost of cable tray - 2500 length)
B85: Cost of steel (Rs) | D85: =D71 -> 0
B86: Cost of raw material for galvanization (Rs) | D86: =O64 -> 0
B87: Cost of fabrication (Rs) | D87: =D75 -> 0
B88: Cost of galvanization (Rs) | D88: =O75 -> 0
B89: Quality inspection and testing (Rs) | D89: =D76 -> 0
B90: Vendor Overheads (Rs) | D90: =SUM(D85:D89)*D36 -> 0
B91: Profit margin for vendor | D91: =SUM(D85:D90)*D37 -> 0
B92: Contract Performance Bank Guarantee (Rs) | D92: =SUM(D85:D91)*D38 -> 0
B93: Transportation and handling to site (Rs) | D93: =(D54-D62-I63)*D35 -> 0
B95: Should be cost | D95: =SUM(D85:D93) -> 0
B96: Ex Works Should be cost | D96: =SUM(D85:D92) -> 0
D97: Suggested model | E97: TPL model
C98: Weight of runner (kg) | D98: =D32 -> 11.1156 | E98: ='[3]Old Ladder type '!K21 -> 11.1156
C99: Savings due to holes/ slots in runner (kg) | D99: =D41 -> 0.049298 | E99: 0
C100: Weight of rung (kg) | D100: =J30*J23 -> 7.6302 | E100: ='[3]Old Ladder type '!L21 -> 7.6302
C101: Savings due to slots in rung (kg) | D101: =J43 -> 0.529875 | E101: 0
C102: ="Weight of Coupler plate ("&'[3]Coupler Plate'!N6&"X"&'[3]Coupler Plate'!N7&"X"&'[3]Coupler Plate'!N8&") (kg)" -> Weight of Coupler plate (70X210X2) (kg) | D102: ='[3]Coupler Plate'!D37*2 -> 0.414009 | E102: ='[3]Old Ladder type '!M21 -> 0.46158
C103: Hardware weight (Nut,bolt and washer) (kg) | D103: 0.32 | E103: 0.32 | G103: fixed
C104: Total weight (kg) | D104: =D98-D99+D100-D101+D102+D103 -> 18.900636 | E104: =E98-E99+E100-E101+E102+E103 -> 19.52738 | F104: =(E104-D104)/D104 -> 0.033159942
C105: Cost of steel (INR) | D105: =(D98*D6-D11*D99*D6)+(D100*D6-D11*D101*D6)+('[3]Coupler Plate'!D24-D43*'[3]Coupler Plate'!D34)*D6*2+D103*D6 -> 1402.6226 | E105: =E104*D6 -> 1425.4987
C107: Weight of Zinc required for galvanization (kg) | D107: =5%*D104 -> 0.9450318 | E107: =5%*E104 -> 0.976369 | G107: TPL assumption: 5% of steel weight; zinc weight to be calculated basis coating thickness
C108: Cost of zinc (INR) | D108: =D107*$H$8 -> 402.20553 | E108: =E107*$H$8 -> 415.54265
C110: Labour,Fabrication,Overhead,Profit Margin (INR) | D110: =(D104+D107)*$D$17 -> 154.79621 | E110: =(E104+E107)*$D$17 -> 159.92924
C112: Total cost (INR) per tray | D112: =D110+D105+D108 -> 1959.6243 | E112: =E110+E105+E108 -> 2000.9706
C113: Cost per meter (INR) per tray | D113: =D112/(O12/1000) -> 830.34929 | E113: =E112/(O12/1000) -> 847.86891
C114: Savings | D114: =(E112-D112)/D112 -> 0.021099096
B118: Comparison table - Summary
D120: TPL | H120: Cost Model
C121: B1-i: Ladder Type Horizontal Bend 90 deg, Bending Radius 1200 mm, 600mm(W) X 100mm(H), 2mm thk M.S. sheet, ~2.36 m, hot dip galvanised incl. coupler plate
D123: Weight of steel (kg) | E123: Weight of zinc (kg) | F123: Estimated price | H123: Weight of steel (kg) | I123: Weight of zinc (kg) | J123: Estimated price | K123: Price difference
C124: ='[3]Old Ladder type '!B21 -> 600mm(W)X100mm(H) - B1-i horizontal bend | D124: ='[3]Old Ladder type '!Q21 -> 19.52738 | E124: ='[3]Old Ladder type '!U21 -> 0.976369 | F124: ='[3]Old Ladder type '!Z21 -> 1647.4177 | H124: =D104 -> 18.900636 | I124: =D107 -> 0.9450318 | J124: =D112 -> 1959.6243 | K124: =(F124-J124)/J124 -> -0.15931966

Sheet H Bend 300x100x2
A1: Cable Tray Costing - Ladder Type Horizontal Bend 90 deg, Bending Radius 1200 mm
B5: Input for raw material and conversion costs | M5: Cable Tray configuration
B6: Cost of 1 kg of MS (Rs) | D6: 73 | F6: Coating thickness of Zinc (micron) | H6: 86 | M6: Runners | Q6: Rungs
B7: Transportation and handling cost of raw material to vendor shop (% of raw material cost) | D7: 0 | F7: Specific weight of Zinc (kg/m3) | H7: 7135 | M7: Number of runners | O7: 2 | Q7: No of rungs per 2500 meter of runner | U7: 10
B8: Specific weight of MS (kg/m3) | D8: 7850 | F8: Cost of Zinc (Rs/kg) | H8: 425.6 | M8: Tray width (mm) | O8: 300 | Q8: Length of rung (mm) | U8: =O8 -> 300
B9: Cost of engg and fabrication (% of material cost) | D9: 0 | F9: Wastage during galvalization | H9: 0 | M9: Tray Depth (mm) | O9: 100 | Q9: Width of rung (mm) | U9: 50
B10: Quality test and inspection charges (%) | D10: 0 | F10: Recoverable scrap - Ash per meter of tray (%) | H10: 0.12 | M10: Tray thickness (mm) | O10: 2 | Q10: Collar / Height of rung (mm) | U10: 20
B11: Salvage value of scrap for MS plates(% of overall value) | D11: 0.5 | F11: Recoverable scrap - Dross per meter of tray (%) | H11: 0.08 | M11: Tray collar (mm) | O11: 25 | Q11: Thickness of rung (mm) | U11: 2
B12: Wastage allowance during fabrication | D12: 0 | F12: Recoverable scrap salvage value - Ash (%) | H12: 0.26 | M12: Tray length (mm) | O12: 2360 | Q12: No of slots per 40 mm of length | U12: 1
B13: Transportation and handling cost of finished goods to site (Rs/kg) | D13: 0 | F13: Recoverable scrap salvage value - Dross (%) | H13: 0.52 | M13: No of holes per 2500 mm length | O13: 20 | Q13: Length of 1 slot (mm) | U13: 25
B14: Overheads for vendor (%) | D14: 0 | F14: Cost of galvanization (% of material cost) | H14: 0 | M14: Dia of 1 hole (mm) | O14: 10 | Q14: Width of 1 slot (mm) | U14: 10
B15: Profit margin for vendor (%) | D15: 2.5
B16: Cost of contract Performance Bank Guarantee | D16: 0
B17: Labour,Fabrication,Overhead,Profit Margin (INR/ kg) | D17: =6.5*1.2 -> 7.8
B20: Detailed Costing
B21: Cable tray MS material cost | M21: Galvalization
B22: Runner | F22: Rung | M22: Zinc Requirement
B23: Number of runners per meter length | D23: =O7 -> 2 | F23: No of rungs in this fitting (U7 x length / 2500, rounded) | J23: =ROUND(U7*D28/2500,0) -> 9 | M23: Runner | Q23: Rung
B24: Tray width (mm) | D24: =O8 -> 300 | F24: Length of rung (mm) | J24: =U8 -> 300 | M24: Surface area for 1 m length (m2) | O24: =2*(2*(2*D27+D25)/1000*D28/1000) -> 1.416 | Q24: Surface area for 1 rung (m2) | T24: =2*J24/1000*(J25+2*J26)/1000 -> 0.054
B25: Tray Depth (mm) | D25: =O9 -> 100 | F25: Width of rung (mm) | J25: =U9 -> 50 | M25: Surface area holes along thickness for 1 m length (m2) | O25: =D37*3.14*D38/1000*D26/1000*D28/125 -> 0.02371328 | Q25: Surface area of slots along thickness for 1 rung (m2) | T25: =(2*(J38+J39)/1000*D26/1000)*D24/40 -> 0.00105
B26: Tray thickness (mm) | D26: =O10 -> 2 | F26: Collar / Height of rung (mm) | J26: =U10 -> 20 | M26: Top surface area of holes for 1 m length (m2) | O26: =D37*3.14*(D38/2/1000)^2*D28/125 -> 0.0296416 | Q26: Top surface area of slots 1 rung (m2) | T26: =J38/1000*J39/1000*D24/40 -> 0.001875
B27: Tray collar (mm) | D27: =O11 -> 25 | F27: Thickness of rung (mm) | J27: =U11 -> 2
B28: Tray length (mm) | D28: =O12 -> 2360 | M28: Overall surface area for 1 meter of runner (m2) | O28: =O24+O25-O26 -> 1.4100717 | Q28: Overall rung surface area for 1 meter of runner (m2) | T28: =(T24+T25-T26)*J23 -> 0.478575
F29: Volume of 1 rung (m3) | J29: =(2*J26+J25)/1000*J24/1000*J27/1000 -> 5.4e-05
F30: Weight of 1 rung (kg) | J30: =J29*D8 -> 0.4239 | M30: Total surface area per meter of cable tray (m2) | O30: =O28+T28 -> 1.8886467
B31: Volume of runner (m3) | D31: =2*(D25+D27*2)/1000*D26/1000*D28/1000 -> 0.001416 | F31: Cost of 1 rung (Rs) | J31: =J30*(D6*(1+D7)) -> 30.9447
B32: Weight of runner per meter length (kg) | D32: =D31*D8 -> 11.1156 | F32: Cost of rungs per meter of runner | J32: =J31*J23 -> 278.5023 | M32: Weight of Zinc required for galvanization (kg) | O32: =O30*H6*10^-6*H7 -> 1.1588925
B33: Cost of runner per meter length (Rs) | D33: =D32*(D6*(1+D7)) -> 811.4388 | M33: Wastage during galvalization | O33: =H9 -> 0
M34: Total weight of Zinc required for galvanization (kg) | O34: =(1+O33)*O32 -> 1.1588925
B35: Scrap salvage due to holes / slots | M35: Cost of Zinc galvanization per meter of runner (Rs) | O35: =O34*H8 -> 493.22464
B36: Runner | F36: Rung
B37: No of holes per 2500 mm length | D37: =O13 -> 20 | F37: No of slots per 40 mm of length | J37: =U12 -> 1 | M37: Recoverable scrap - Ash per meter of tray (kg) | O37: =H10*O32 -> 0.1390671 | Q37: Recoverable scrap salvage - Ash (Rs/kg) | T37: =H12*$H$8 -> 110.656
B38: Dia of 1 hole (mm) | D38: =O14 -> 10 | F38: Length of 1 slot (mm) | J38: =U13 -> 25 | M38: Recoverable scrap - Dross per meter of tray (kg) | O38: =H11*O32 -> 0.092711399 | Q38: Recoverable scrap salvage - Dross (Rs/kg) | T38: =H13*$H$8 -> 221.312
B39: Volume of holes (m3) | D39: =2*D37*3.14*(D38/2/1000)^2*D26/1000 -> 6.28e-06 | F39: Width of 1 slot (mm) | J39: =U14 -> 10 | M39: Salvage value of scrap per meter of cable (Rs) | O39: =O37*T37+O38*T38 -> 35.906754
F40: Volume of 1 slot (m3) | J40: =J38/1000*J39/1000*J27/1000 -> 5e-07
B41: Weight of holes per 2500 mm of runner (kg) | D41: =D39*D8 -> 0.049298 | F41: Volume slots per rung (m3) | J41: =D24/40*J40 -> 3.75e-06 | M41: Net cost of Zinc galvanization per meter of runner (Rs) | O41: =O35-O39 -> 457.31789
B42: Value of scrap generated per meter of runner (Rs) | D42: =D41*D6 -> 3.598754 | F42: Weight of slots per rung (kg) | J42: =J41*D8 -> 0.0294375
B43: Salvage value of scrap (% of overall value) | D43: =D11 -> 0.5 | F43: Weight of slots per 2500mm of runner (kg) | J43: =J42*J23 -> 0.2649375
B44: Salvage value of MS scrap per meter of runner (Rs) | D44: =D42*D43 -> 1.799377 | F44: Value of scrap generated per meter of runner (Rs) | J44: =J43*D6 -> 19.340438
F45: Salvage value of MS scrap per meter of runner (Rs) | J45: =J44*D43 -> 9.6702188
B47: Cost of material for 1 m of runner (Rs) | D47: =D33-D44 -> 809.63942 | F47: Cost of material for rungs per meter of runner (Rs) | J47: =J32-J45 -> 268.83208
B49: Total cost per meter of cable tray (Rs) | D49: =D47+J47 -> 1078.4715
B50: Wastage allowance during fabrication | D50: =D12 -> 0
B51: Net cost per meter of cable tray (Rs) | D51: =(1+D50)*D49 -> 1078.4715
B54: Engineering, Fabrication and Quality & Inspection cost of cable tray | M54: Cost of galvanization
B55: Engineering & Fabrication cost (Rs) | D55: =(D33+J32)*D9 -> 0 | M55: Galvanization cost (Rs) | N55: =O35*H14 -> 0
B56: Quality inspection and testing (Rs) | D56: =(D33+J32)*D10 -> 0
B61: Summary (Cost of cable tray per meter length)
B63: Cost of steel (Rs) | D63: =D51 -> 1078.4715
B64: Cost of raw material for galvanization (Rs) | D64: =O41 -> 457.31789
B65: Cost of fabrication (Rs) | D65: =D55 -> 0
B66: Cost of galvanization (Rs) | D66: =N55 -> 0
B67: Quality inspection and testing (Rs) | D67: =D56 -> 0
B68: Vendor Overheads (Rs) | D68: =SUM(D63:D67)*D14 -> 0
B69: Profit margin for vendor (Rs) | D69: =SUM(D63:D68)*D15 -> 3839.4735
B70: Contract Performance Bank Guarantee (Rs) | D70: =SUM(D63:D69)*D16 -> 0
B71: Transportation and handling to site (Rs) | D71: =(D32+J30*J23-D41-J43)*D13 -> 0
B72: Should be cost (Rs per meter) | D72: =SUM(D63:D71) -> 5375.2629
B73: Ex Works Should be cost (Rs per meter) | D73: =SUM(D63:D70) -> 5375.2629
B79: Comparison - Cost model viz-a-viz TPL estimations
C81: B1-i: Ladder Type Horizontal Bend 90 deg, Bending Radius 1200 mm - 600mm(W) X 100mm(H) X 2mm(T), ~2.36 m
B83: Summary (Cost of cable tray - 2500 length)
B85: Cost of steel (Rs) | D85: =D71 -> 0
B86: Cost of raw material for galvanization (Rs) | D86: =O64 -> 0
B87: Cost of fabrication (Rs) | D87: =D75 -> 0
B88: Cost of galvanization (Rs) | D88: =O75 -> 0
B89: Quality inspection and testing (Rs) | D89: =D76 -> 0
B90: Vendor Overheads (Rs) | D90: =SUM(D85:D89)*D36 -> 0
B91: Profit margin for vendor | D91: =SUM(D85:D90)*D37 -> 0
B92: Contract Performance Bank Guarantee (Rs) | D92: =SUM(D85:D91)*D38 -> 0
B93: Transportation and handling to site (Rs) | D93: =(D54-D62-I63)*D35 -> 0
B95: Should be cost | D95: =SUM(D85:D93) -> 0
B96: Ex Works Should be cost | D96: =SUM(D85:D92) -> 0
D97: Suggested model | E97: TPL model
C98: Weight of runner (kg) | D98: =D32 -> 11.1156 | E98: ='[3]Old Ladder type '!K21 -> 11.1156
C99: Savings due to holes/ slots in runner (kg) | D99: =D41 -> 0.049298 | E99: 0
C100: Weight of rung (kg) | D100: =J30*J23 -> 3.8151 | E100: ='[3]Old Ladder type '!L21 -> 7.6302
C101: Savings due to slots in rung (kg) | D101: =J43 -> 0.2649375 | E101: 0
C102: ="Weight of Coupler plate ("&'[3]Coupler Plate'!N6&"X"&'[3]Coupler Plate'!N7&"X"&'[3]Coupler Plate'!N8&") (kg)" -> Weight of Coupler plate (70X210X2) (kg) | D102: ='[3]Coupler Plate'!D37*2 -> 0.414009 | E102: ='[3]Old Ladder type '!M21 -> 0.46158
C103: Hardware weight (Nut,bolt and washer) (kg) | D103: 0.32 | E103: 0.32 | G103: fixed
C104: Total weight (kg) | D104: =D98-D99+D100-D101+D102+D103 -> 15.350473 | E104: =E98-E99+E100-E101+E102+E103 -> 19.52738 | F104: =(E104-D104)/D104 -> 0.27210278
C105: Cost of steel (INR) | D105: =(D98*D6-D11*D99*D6)+(D100*D6-D11*D101*D6)+('[3]Coupler Plate'!D24-D43*'[3]Coupler Plate'!D34)*D6*2+D103*D6 -> 1133.7905 | E105: =E104*D6 -> 1425.4987
C107: Weight of Zinc required for galvanization (kg) | D107: =5%*D104 -> 0.76752367 | E107: =5%*E104 -> 0.976369 | G107: TPL assumption: 5% of steel weight; zinc weight to be calculated basis coating thickness
C108: Cost of zinc (INR) | D108: =D107*$H$8 -> 326.65808 | E108: =E107*$H$8 -> 415.54265
C110: Labour,Fabrication,Overhead,Profit Margin (INR) | D110: =(D104+D107)*$D$17 -> 125.72038 | E110: =(E104+E107)*$D$17 -> 159.92924
C112: Total cost (INR) per tray | D112: =D110+D105+D108 -> 1586.169 | E112: =E110+E105+E108 -> 2000.9706
C113: Cost per meter (INR) per tray | D113: =D112/(O12/1000) -> 672.10549 | E113: =E112/(O12/1000) -> 847.86891
C114: Savings | D114: =(E112-D112)/D112 -> 0.26151166
B118: Comparison table - Summary
D120: TPL | H120: Cost Model
C121: B1-i: Ladder Type Horizontal Bend 90 deg, Bending Radius 1200 mm, 600mm(W) X 100mm(H), 2mm thk M.S. sheet, ~2.36 m, hot dip galvanised incl. coupler plate
D123: Weight of steel (kg) | E123: Weight of zinc (kg) | F123: Estimated price | H123: Weight of steel (kg) | I123: Weight of zinc (kg) | J123: Estimated price | K123: Price difference
C124: ='[3]Old Ladder type '!B21 -> 600mm(W)X100mm(H) - B1-i horizontal bend | D124: ='[3]Old Ladder type '!Q21 -> 19.52738 | E124: ='[3]Old Ladder type '!U21 -> 0.976369 | F124: ='[3]Old Ladder type '!Z21 -> 1647.4177 | H124: =D104 -> 15.350473 | I124: =D107 -> 0.76752367 | J124: =D112 -> 1586.169 | K124: =(F124-J124)/J124 -> 0.03861423

Sheet H Bend 150x100x2
A1: Cable Tray Costing - Ladder Type Horizontal Bend 90 deg, Bending Radius 1200 mm
B5: Input for raw material and conversion costs | M5: Cable Tray configuration
B6: Cost of 1 kg of MS (Rs) | D6: 73 | F6: Coating thickness of Zinc (micron) | H6: 86 | M6: Runners | Q6: Rungs
B7: Transportation and handling cost of raw material to vendor shop (% of raw material cost) | D7: 0 | F7: Specific weight of Zinc (kg/m3) | H7: 7135 | M7: Number of runners | O7: 2 | Q7: No of rungs per 2500 meter of runner | U7: 10
B8: Specific weight of MS (kg/m3) | D8: 7850 | F8: Cost of Zinc (Rs/kg) | H8: 425.6 | M8: Tray width (mm) | O8: 150 | Q8: Length of rung (mm) | U8: =O8 -> 150
B9: Cost of engg and fabrication (% of material cost) | D9: 0 | F9: Wastage during galvalization | H9: 0 | M9: Tray Depth (mm) | O9: 100 | Q9: Width of rung (mm) | U9: 50
B10: Quality test and inspection charges (%) | D10: 0 | F10: Recoverable scrap - Ash per meter of tray (%) | H10: 0.12 | M10: Tray thickness (mm) | O10: 2 | Q10: Collar / Height of rung (mm) | U10: 20
B11: Salvage value of scrap for MS plates(% of overall value) | D11: 0.5 | F11: Recoverable scrap - Dross per meter of tray (%) | H11: 0.08 | M11: Tray collar (mm) | O11: 25 | Q11: Thickness of rung (mm) | U11: 2
B12: Wastage allowance during fabrication | D12: 0 | F12: Recoverable scrap salvage value - Ash (%) | H12: 0.26 | M12: Tray length (mm) | O12: 2360 | Q12: No of slots per 40 mm of length | U12: 1
B13: Transportation and handling cost of finished goods to site (Rs/kg) | D13: 0 | F13: Recoverable scrap salvage value - Dross (%) | H13: 0.52 | M13: No of holes per 2500 mm length | O13: 20 | Q13: Length of 1 slot (mm) | U13: 25
B14: Overheads for vendor (%) | D14: 0 | F14: Cost of galvanization (% of material cost) | H14: 0 | M14: Dia of 1 hole (mm) | O14: 10 | Q14: Width of 1 slot (mm) | U14: 10
B15: Profit margin for vendor (%) | D15: 2.5
B16: Cost of contract Performance Bank Guarantee | D16: 0
B17: Labour,Fabrication,Overhead,Profit Margin (INR/ kg) | D17: =6.5*1.2 -> 7.8
B20: Detailed Costing
B21: Cable tray MS material cost | M21: Galvalization
B22: Runner | F22: Rung | M22: Zinc Requirement
B23: Number of runners per meter length | D23: =O7 -> 2 | F23: No of rungs in this fitting (U7 x length / 2500, rounded) | J23: =ROUND(U7*D28/2500,0) -> 9 | M23: Runner | Q23: Rung
B24: Tray width (mm) | D24: =O8 -> 150 | F24: Length of rung (mm) | J24: =U8 -> 150 | M24: Surface area for 1 m length (m2) | O24: =2*(2*(2*D27+D25)/1000*D28/1000) -> 1.416 | Q24: Surface area for 1 rung (m2) | T24: =2*J24/1000*(J25+2*J26)/1000 -> 0.027
B25: Tray Depth (mm) | D25: =O9 -> 100 | F25: Width of rung (mm) | J25: =U9 -> 50 | M25: Surface area holes along thickness for 1 m length (m2) | O25: =D37*3.14*D38/1000*D26/1000*D28/125 -> 0.02371328 | Q25: Surface area of slots along thickness for 1 rung (m2) | T25: =(2*(J38+J39)/1000*D26/1000)*D24/40 -> 0.000525
B26: Tray thickness (mm) | D26: =O10 -> 2 | F26: Collar / Height of rung (mm) | J26: =U10 -> 20 | M26: Top surface area of holes for 1 m length (m2) | O26: =D37*3.14*(D38/2/1000)^2*D28/125 -> 0.0296416 | Q26: Top surface area of slots 1 rung (m2) | T26: =J38/1000*J39/1000*D24/40 -> 0.0009375
B27: Tray collar (mm) | D27: =O11 -> 25 | F27: Thickness of rung (mm) | J27: =U11 -> 2
B28: Tray length (mm) | D28: =O12 -> 2360 | M28: Overall surface area for 1 meter of runner (m2) | O28: =O24+O25-O26 -> 1.4100717 | Q28: Overall rung surface area for 1 meter of runner (m2) | T28: =(T24+T25-T26)*J23 -> 0.2392875
F29: Volume of 1 rung (m3) | J29: =(2*J26+J25)/1000*J24/1000*J27/1000 -> 2.7e-05
F30: Weight of 1 rung (kg) | J30: =J29*D8 -> 0.21195 | M30: Total surface area per meter of cable tray (m2) | O30: =O28+T28 -> 1.6493592
B31: Volume of runner (m3) | D31: =2*(D25+D27*2)/1000*D26/1000*D28/1000 -> 0.001416 | F31: Cost of 1 rung (Rs) | J31: =J30*(D6*(1+D7)) -> 15.47235
B32: Weight of runner per meter length (kg) | D32: =D31*D8 -> 11.1156 | F32: Cost of rungs per meter of runner | J32: =J31*J23 -> 139.25115 | M32: Weight of Zinc required for galvanization (kg) | O32: =O30*H6*10^-6*H7 -> 1.0120633
B33: Cost of runner per meter length (Rs) | D33: =D32*(D6*(1+D7)) -> 811.4388 | M33: Wastage during galvalization | O33: =H9 -> 0
M34: Total weight of Zinc required for galvanization (kg) | O34: =(1+O33)*O32 -> 1.0120633
B35: Scrap salvage due to holes / slots | M35: Cost of Zinc galvanization per meter of runner (Rs) | O35: =O34*H8 -> 430.73413
B36: Runner | F36: Rung
B37: No of holes per 2500 mm length | D37: =O13 -> 20 | F37: No of slots per 40 mm of length | J37: =U12 -> 1 | M37: Recoverable scrap - Ash per meter of tray (kg) | O37: =H10*O32 -> 0.12144759 | Q37: Recoverable scrap salvage - Ash (Rs/kg) | T37: =H12*$H$8 -> 110.656
