Workbook
Name \a: #N/A
Name \b: #N/A
Name _TB2: '[1]SPT vs PHI'!$B$2:$C$65
Name A: '[2]PRECAST lightconc-II'!$J$19
Name B: '[2]PRECAST lightconc-II'!$K$19
Name bol: #REF!
Name boml: #REF!
Name botl: #REF!
Name botn: #REF!
Name bp_capacity: '[3]Concreting Input'!$E$7
Name Breaks: #REF!
Name bua: #REF!
Name checked: #REF!
Name Columns: #REF!
Name D: '[2]PRECAST lightconc-II'!$J$20
Name dc: #REF!
Name designed: #REF!
Name df: #REF!
Name dg: #REF!
Name docu: #REF!
Name dq: #REF!
Name E: '[2]PRECAST lightconc-II'!$K$20
Name g: #REF!
Name gs: #REF!
Name hf: #REF!
Name JobID: #REF!
Name lef: #REF!
Name lel: #REF!
Name p: #REF!
Name project: #REF!
Name rel: #REF!
Name Rev: #REF!
Name rig: #REF!
Name robot: #REF!
Name rosid: #REF!
Name schools: #REF!
Name Sdate: #REF!
Name StrID: #REF!
Name structure: #REF!
Name Subject: #REF!
Name table1: '[1]SPT vs PHI'!$E$2:$F$47
Name TABLE2: #REF!
Name TableRange: #REF!
Name Title: '[4]Civil Boq'!$D$3
Name Title1: #REF!
Name Title2: #REF!
Name tol: #REF!
Name topl: #REF!
Name topn: #REF!
Name work: #REF!

Sheet Input
G1: Input
B2: Cost Model - Input Sheet - To be filled by buyer
B5: Current Requirement
B6: Payable quantity | C6: MT | D6: 37000
B7: Wastage | C7: % | D7: 0.03 | E7: >>Typically (2-5%) for rolled sections, (5-8%) for built up sections & (8-10%) for bridge & girder fabrication
B8: Total structural steel requirement | C8: MT | D8: =D6*(1+D7) -> 38110
B10: Wastage recoveries | C10: % | D10: 0.025
A12: 1 | B12: Raw Materials
D14: Requirement (MT) | E14: Cost (INR/MT)
B15: Grade 1 (E.g., E250) | C15: - | D15: =D8*20% -> 7622 | E15: =61700*(1.05) -> 64785
B16: Grade 2 (E.g., E350) | C16: - | D16: =D8*80% -> 30488 | E16: =61700*(1.05) -> 64785
B17: Grade 3 | C17: - | D17: 0 | E17: 0
D18: =SUM(D15:D17) -> 38110 | E18: =SUMPRODUCT(D15:D17,E15:E17)/SUM(D15:D17) -> 64785
A20: 2 | B20: Plant & Machinery
B23: Fabrication Type | C23: Yes/No | E23: Requirement (MT)
A24: i | B24: Built-Up fabrication & Bits Shop | C24: Yes | D24: q | E24: =D18*80% -> 30488
A25: ii | B25: Bridge & Girder fabrication | C25: No | D25: q | E25: =D18*0% -> 0
A26: iii | B26: Hot roll fabrication | C26: Yes | D26: q | E26: =D18*20% -> 7622 | G26: 0.14
A27: iv | B27: Blasting & Painting | C27: Yes | D27: q | E27: =D18 -> 38110
F28: Hollow section | G28: 0.06
A30: 3 | B30: Manpower
B32: No inputs required
B34: Fabrication Type | C34: Yes/No
A35: i | B35: Built-Up fabrication & Bits Shop | C35: =C24 -> Yes
A36: ii | B36: Bridge & Girder fabrication | C36: =C25 -> No
A37: iii | B37: Hot roll fabrication | C37: =C26 -> Yes
A38: iv | B38: Blasting & Painting | C38: =C27 -> Yes
F39: Hollow section | G39: Low productivity | H39: 1.5x of hot roll fabrication
A40: 4 | B40: Utility and consumables
A42: =MAX($A$1:A41)+0.1 -> 4.1 | B42: Power Cost | C42: Yes | D42: q
A45: =MAX($A$1:A42)+0.1 -> 4.2 | B45: Water Cost (e.g. Surface Cleaning & Preparation, Equipment Cooling) | C45: Yes | D45: q
A47: =MAX($A$1:A46)+0.1 -> 4.3 | B47: Spares & consumables
A48: a) | B48: Consumables - Welding
A50: > | B50: Welding material requirement
B51: Low complexity | C51: % of total requirement | D51: 0.6
B52: Moderate complexity | C52: % of total requirement | D52: 0.25
B53: Heavy complexity | C53: % of total requirement | D53: 0.15
D54: =SUM(D51:D53) -> 1
A56: b) | B56: Blasting & Painting
A58: > | B58: Blasting Requirement | C58: Yes | D58: q
A60: > | B60: Painting Requirement | C60: Yes | D60: q
A62: > | B62: Type of painting requirement
A63: i) | B63: Plate-heavy sections | C63: % of total requirement | D63: 0.8
A64: ii) | B64: Lighter, open profiles | C64: % of total requirement | D64: 0.2
B65: Overall | D65: =SUM(D63:D64) -> 1
A68: > | B68: Paint Requirement | D68: Requirement (Yes/No) | E68: No. of Coat | F68: Dry Film Thickness (μm)/coat | G68: Total Dry Film Thickness (μm)
B69: 1st coat - Primer | C69: - | D69: Yes | E69: 1 | F69: 30 | G69: =IFERROR(E69*F69,"") -> 30
B70: Intermediate Coat | C70: - | D70: Yes | E70: 1 | F70: 50 | G70: =IFERROR(E70*F70,"") -> 50
B71: Final Coat | C71: - | D71: Yes | E71: 1 | F71: 50 | G71: =IFERROR(E71*F71,"") -> 50
F72: =SUM(F69:F71) -> 130 | G72: =SUM(G69:G71) -> 130
A77: 5 | B77: Overhead
B79: Admin expense | C79: % | D79: 0.02
B80: Management expense including HO | C80: % | D80: 0.02 | F80: Add benchmarks
B81: HO overheads including admin expense | C81: % | D81: =D79+D80 -> 0.04
A84: 6 | B84: Transportation to Erection Site
B86: Payable quantity | C86: MT | D86: =D6 -> 37000
B87: - Light structure | C87: MT | D87: 5000
B88: - Medium/Heavy structure | C88: MT | D88: 0
B90: Distance from vendor to site | C90: Km | D90: 500
A92: 7 | B92: Vendor Profit Margin
B94: Maximum permissable vendor margin | C94: % of cost price | D94: 0.05
A97: 8 | B97: Boltings
B99: % of bolts required | C99: % | D99: 0.03
B100: Price of Bolts | C100: INR/Kg | D100: 180
A102: 9 | B102: Erection Charges
B104: Erection rate (flat) | C104: INR/MT | D104: 26000

Sheet Output
B2: Cost Model - Output Sheet
B5: Structural Steel Fabrication Requirement | C5: =Input!D6 -> 37000 | D5: MT
C7: INR | D7: INR/MT
A8: 1 | B8: Output: Total Costs (exlcuding profit) | C8: =SUM(C13,C28,C32,C33) -> 4.560231e+09 | D8: =SUM(D13,D28,D32,D33) -> 123200
A11: i) | B11: Stage 1: Fabrication at vendor unit
B13: Stage 1: Total Costs | C13: =SUM(C14,C15:C19,C23,C26) -> 3.394731e+09 | D13: =SUM(D14,D15:D19,D23,D26) -> 91700
A14: > | B14: Raw Material (incl. wastage) | C14: ='Calculation Sheet'!F20-'Calculation Sheet'!F23 -> 2.4380944e+09 | D14: =IFERROR(ROUND(C14/C5,-2),"") -> 65900
A15: > | B15: Machinery | C15: ='Calculation Sheet'!I34 -> 89664361 | D15: =ROUND(C15/$C$5,-2) -> 2400
A16: > | B16: Salaries | C16: ='Calculation Sheet'!J149 -> 2.7557504e+08 | D16: =ROUND(C16/$C$5,-2) -> 7400
A17: > | B17: Overheads | C17: =SUM(C14,C15:C16,C18:C19,C26)*'Calculation Sheet'!$D$291 -> 1.2888774e+08 | D17: =ROUND(C17/$C$5,-2) -> 3500
A18: > | B18: Utilities (Power, Water) | C18: =IFERROR(SUMPRODUCT('Calculation Sheet'!$E$29:$E$33,'Calculation Sheet'!$F$225:$F$229),0)+IFERROR(('Calculation Sheet'!E232*'Calculation Sheet'!E233)*C5,0) -> 48859721 | D18: =ROUND(C18/$C$5,-2) -> 1300
A19: > | B19: Consumables | C19: =SUM(C20:C22) -> 170200000 | D19: =ROUND(C19/$C$5,-2) -> 4600
B20: - Welding | C20: =D20*$C$5 -> 81400000 | D20: =ROUND('Calculation Sheet'!D251,-2) -> 2200
B21: - Blasting & Painting | C21: =D21*$C$5 -> 77700000 | D21: =ROUND('Calculation Sheet'!D282,-2) -> 2100
B22: - Others (e., tools, heating gases) | C22: =D22*$C$5 -> 11100000 | D22: =ROUND('Calculation Sheet'!D284,-2) -> 300
A23: > | B23: Civil, Infra & Mobilization Costs | C23: =SUM(C24:C25) -> 43649704 | D23: =ROUND(SUM(D24:D25),-2) -> 1200
B24: - Civil & PEB/electricity infra (amortized, facility-level) | C24: =SUMPRODUCT('Calculation Sheet'!$E$29:$E$32,'Calculation Sheet'!$D$325:$D$328) -> 3199358 | D24: =C24/$C$5 -> 86.469136
B25: - Site utility, mobilization & setup (fixed, recovered over this order) | C25: =SUMPRODUCT('Calculation Sheet'!$E29:$E32,'Calculation Sheet'!$D$355:$D$358)+SUM('Calculation Sheet'!F342:F349) -> 40450346 | D25: =C25/$C$5 -> 1093.2526
A26: > | B26: Bolting Charges (Nuts, Bolts, Washers) | C26: =D26*$C$5 -> 199800000 | D26: =ROUND('Calculation Sheet'!D381,-2) -> 5400
A28: ii) | B28: Stage 2: Transportation from Vendor to Erection Site | C28: =C29 -> 166500000 | D28: =D29 -> 4500
B29: Transportation costs | C29: =C5*'Calculation Sheet'!D310 -> 166500000 | D29: =ROUND('Calculation Sheet'!D310,-2) -> 4500
A31: ii) | B31: Stage 3: Erection charges | C31: =C32 -> 962000000 | D31: =D32 -> 26000
A32: iii) | B32: Erection Charges | C32: =D32*$C$5 -> 962000000 | D32: =Input!D104 -> 26000
A33: iv) | B33: Contingency | C33: =D33*$C$5 -> 37000000 | D33: 1000
B35: Total Cost | C35: =SUM(C13,C28,C32,C33) -> 4.560231e+09 | D35: =SUM(D13,D28,D32,D33) -> 123200
B36: Raw Material Cost | C36: =C14 -> 2.4380944e+09 | D36: =D14 -> 65900
B37: Fabrication Cost | C37: =C35-C36 -> 2.1221366e+09 | D37: =SUM(D15:D19,D23,D26,D29,D32,D33) -> 57300
B39: Profit Margin | C39: =Input!$D$94 -> 0.05 | E39: >> As per maximum allowable vendor margin provided in input sheet
B40: Selling Price | C40: =C36+C37*(1+$C$39) -> 4.6663378e+09 | D40: =D36+D37*(1+$C$39) -> 126065
B41: Fabrication Selling Price | C41: =C40-C36 -> 2.2282434e+09 | D41: =D40-D36 -> 60165
B43: Fabrication Profit | C43: =C40-SUM(C36:C37) -> 1.0610683e+08 | D43: =D40-SUM(D36:D37) -> 2865
B46: Cost categorisation
A47: > | B47: Blasting & Painting Cost | C47: =SUM(C48:C50) -> 1.256692e+08 | D47: =IFERROR(SUM(D48:D50),0) -> 3396.4648
B48: Consumables | C48: =C21 -> 77700000 | D48: =D21 -> 2100
B49: Manpower | C49: ='Calculation Sheet'!J146 -> 38618133 | D49: =C49/C5 -> 1043.7333
B50: Machinery | C50: ='Calculation Sheet'!I32 -> 9351064.8 | D50: =IFERROR(C50/C5,0) -> 252.73148

Sheet Calculation Sheet
G1: Input
B2: Cost Model - Calculation Sheet
B5: Current Requirement
B6: Payable quantity | C6: MT | D6: =Input!D6 -> 37000
B7: Wastage | C7: % | D7: =Input!D7 -> 0.03
B8: Total structural steel requirement | C8: MT | D8: =D6*(1+D7) -> 38110
B11: Work-days per month | C11: Days | D11: 25
B12: Work-hours per day | C12: Hours | D12: 20
A14: 1 | B14: Raw Materials
D16: Requirement (MT) | E16: Cost (INR/MT) | F16: Total Cost for Requirement
B17: Grade 1 (E.g., E250) | C17: - | D17: =Input!D15 -> 7622 | E17: =Input!E15 -> 64785 | F17: =D17*E17 -> 493791270
B18: Grade 2 (E.g., E350) | C18: - | D18: =Input!D16 -> 30488 | E18: =Input!E16 -> 64785 | F18: =D18*E18 -> 1975165080
B19: Grade 3 | C19: - | D19: =Input!D17 -> 0 | E19: =Input!E17 -> 0 | F19: =D19*E19 -> 0
D20: =SUM(D17:D19) -> 38110 | E20: =SUMPRODUCT(D17:D19,E17:E19)/SUM(D17:D19) -> 64785 | F20: =SUM(F17:F19) -> 2468956350
D22: Requirement (MT) | E22: Cost (INR/MT) | F22: Total Cost for Requirement
B23: Wastage Recoveries | C23: MT | D23: =Input!D10*D20 -> 952.75 | E23: =E20*50% -> 32392.5 | F23: =D23*E23 -> 30861954
A25: 2 | B25: Plant & Machinery
G26: Capacity Utilisation
G27: 0.75
B28: Fabrication Type | C28: Yes/No | E28: Requirement (MT) | F28: Capacity (MT)/month | G28: Actual Production (MT)/month | H28: Requirement (Months) | I28: Total Equipment Cost for current requirement (INR)
A29: i | B29: Built-Up fabrication & Bits Shop | C29: =Input!C24 -> Yes | D29: q | E29: =Input!E24 -> 30488 | F29: 1500 | G29: =F29*$G$27 -> 1125 | H29: =IFERROR(IF(C29="Yes",E29/G29,""),"") -> 27.100444 | I29: =IFERROR(H29*H69*D38,"") -> 49966444
A30: ii | B30: Bridge & Girder fabrication | C30: =Input!C25 -> No | D30: q | E30: =Input!E25 -> 0 | F30: 1000 | G30: =F30*$G$27 -> 750 | H30: =IFERROR(IF(C30="Yes",E30/G30,""),"") | I30: =IFERROR(H30*H90*D38,"")
A31: iii | B31: Hot roll fabrication | C31: =Input!C26 -> Yes | D31: q | E31: =Input!E26 -> 7622 | F31: 750 | G31: =F31*$G$27 -> 562.5 | H31: =IFERROR(IF(C31="Yes",E31/G31,""),"") -> 13.550222 | I31: =IFERROR(H31*H112*D38,"") -> 15526296 | K31: Vendor Capacity/Plant Capacity | L31: Machinery Cost
A32: iv | B32: Blasting & Painting | C32: =Input!C27 -> Yes | D32: q | E32: =IFERROR(Input!E27*SUM(Input!E69:E71)/3,"") -> 38110 | F32: 1500 | G32: =F32*$G$27 -> 1125 | H32: =IFERROR(IF(C32="Yes",E32/G32,""),"") -> 33.875556 | I32: =IFERROR(H32*H125*D38,"") -> 9351064.8 | K32: 0.25 | L32: 1.1
A33: v | B33: Other Equipment | C33: Yes | D33: q | E33: =D8 -> 38110 | F33: =SUM(F29:F31) -> 3250 | G33: =F33*$G$27 -> 2437.5 | H33: =IFERROR(IF(C33="Yes",E33/G33,""),"") -> 15.634872 | I33: =IFERROR(H33*H134*D38,"") -> 14820556 | K33: 0.5 | L33: 1.066
H34: Total | I34: =SUM(I29:I33) -> 89664361 | K34: 0.75 | L34: 1.033
B35: Model - Plant Capacity | C35: MT/month | D35: =SUM(F29:F31) -> 3250 | K35: 0.9 | L35: 1
B36: Vendor - Plant Capacity | C36: MT/month | D36: 3250 | K36: 1 | L36: 1
B37: Vendor Capacity/Model Capacity | C37: % | D37: =D36/D35 -> 1 | K37: 1.1 | L37: 1
B38: Machinery cost impact due to vendor capacity | C38: % | D38: =IF($D$37<=K32,L32,IF($D$37<=K33,L33,IF($D$37<=K34,L34,IF($D$37<=K35,L35,IF($D$37<=K36,L36,IF($D$37<=K37,L37,IF($D$37<=K38,L38,IF($D$37<=K39,L39,L40)))))))) -> 1 | K38: 1.25 | L38: 0.9666
K39: 1.5 | L39: 0.93333
B40: Monthly Depreciation | C40: INR | D40: =H136 -> 4213541.7 | G40: Monthly Depreciation | H40: =100%/8/12 -> 0.010416667 | I40: of Purchase cost (Assuming 100% depreciation over 8 years) | K40: 1.75 | L40: 0.9
A42: 2.1 | B42: Fabrication Requirement: Built-Up fabrication & Bits Shop | D42: =$C$29 -> Yes
A44: =MAX($A$1:A41)+0.1 -> 2.1 | B44: Built-Up fabrication & Bits Shop , Bay No-1 | D44: Original No.s | E44: Updated No.s | F44: Rate | G44: Puchase Cost | H44: Monthly Rental | I44: Equipment Description | K44: Power Consumption
A45: i | B45: Material Handling | K45: Power rating | L45: PF | M45: Demand load | N45: Working hours (monthly) | O45: Usage hours | P45: Electricity Cost/month | Q45: Electricity Cost/MT | S45: Electricity Tariff | T45: HSD
B46: EOT Crane 10T | D46: 1 | E46: =D46 -> 1 | F46: 4000000 | G46: =IF($C$29="Yes",E46*F46,"") -> 4000000 | H46: =IFERROR(G46*$H$40,"") -> 41666.667 | I46: Electric Overhead Traveling Crane with a lifting capacity of 10 tons | K46: 3.6 | L46: 0.8 | M46: =E46*K46*L46 -> 2.88 | N46: =$D$11*$D$12 -> 500 | O46: 0.6 | P46: =M46*N46*O46*$S$46 -> 12096 | Q46: =P46/$G$29 -> 10.752 | S46: 14 | T46: 90
B47: EOT Crane 5T | D47: 4 | E47: =D47 -> 4 | F47: 2000000 | G47: =IF($C$29="Yes",E47*F47,"") -> 8000000 | H47: =IFERROR(G47*$H$40,"") -> 83333.333 | I47: Electric Overhead Traveling Crane with a lifting capacity of 5 tons | K47: 2.4 | L47: 0.8 | M47: =E47*K47*L47 -> 7.68 | N47: =$D$11*$D$12 -> 500 | O47: 0.6 | P47: =M47*N47*O47*$S$46 -> 32256 | Q47: =P47/$G$29 -> 28.672
A48: ii | B48: Cutting Equipment
B49: CNC Plasma Cutting Machine (Multi-Torch) | D49: 2 | E49: =D49 -> 2 | F49: 4000000 | G49: =IF($C$29="Yes",E49*F49,"") -> 8000000 | H49: =IFERROR(G49*$H$40,"") -> 83333.333 | I49: A CNC (Computer Numerical Control) machine that automates the cutting process. Equipped with multiple torches (Plasma or Oxy-Fuel) to cut several steel plates or sections at the same time. | K49: 12 | L49: 0.8 | M49: =E49*K49*L49 -> 19.2 | N49: =$D$11*$D$12 -> 500 | O49: 0.6 | P49: =M49*N49*O49*$S$46 -> 80640 | Q49: =P49/$G$29 -> 71.68
B50: Shearing Machine 6000 X 20 | D50: 1 | E50: =D50 -> 1 | F50: 20000000 | G50: =IF($C$29="Yes",E50*F50,"") -> 20000000 | H50: =IFERROR(G50*$H$40,"") -> 208333.33 | I50: A Shearing Machine 6000 X 20 is a metal cutting machine used to cut steel plates up to 6 meters (6000 mm) in length and 20 mm in thickness. | K50: 12 | L50: 0.8 | M50: =E50*K50*L50 -> 9.6 | N50: =$D$11*$D$12 -> 500 | O50: 0.6 | P50: =M50*N50*O50*$S$46 -> 40320 | Q50: =P50/$G$29 -> 35.84
B51: Shearing Machine 2000 X 6 | D51: 1 | E51: =D51 -> 1 | F51: 7500000 | G51: =IF($C$29="Yes",E51*F51,"") -> 7500000 | H51: =IFERROR(G51*$H$40,"") -> 78125 | I51: Cut steel plates up to 2000 mm (2 meters) in length and 6 mm in thickness | K51: 8 | L51: 0.8 | M51: =E51*K51*L51 -> 6.4 | N51: =$D$11*$D$12 -> 500 | O51: 0.6 | P51: =M51*N51*O51*$S$46 -> 26880 | Q51: =P51/$G$29 -> 23.893333
B52: Light Shear 500X12 | D52: 1 | E52: =D52 -> 1 | F52: 1500000 | G52: =IF($C$29="Yes",E52*F52,"") -> 1500000 | H52: =IFERROR(G52*$H$40,"") -> 15625 | I52: Cut metal sheets up to 500 mm (0.5 meters) in length and 12 mm in thickness | K52: 6 | L52: 0.8 | M52: =E52*K52*L52 -> 4.8 | N52: =$D$11*$D$12 -> 500 | O52: 0.6 | P52: =M52*N52*O52*$S$46 -> 20160 | Q52: =P52/$G$29 -> 17.92
A53: iii | B53: Drilling and Punching Machines
B54: CNC Plate Driling -Base Plate | D54: 1 | E54: =D54 -> 1 | F54: 9000000 | G54: =IF($C$29="Yes",E54*F54,"") -> 9000000 | H54: =IFERROR(G54*$H$40,"") -> 93750 | I54: CNC (Computer Numerical Control) technology automates the drilling of bolt holes, slots, and countersinks in steel base plates. Base plates are thick steel plates used as foundation supports for columns, beams, and industrial equipment. | K54: 12 | L54: 0.8 | M54: =E54*K54*L54 -> 9.6 | N54: =$D$11*$D$12 -> 500 | O54: 0.6 | P54: =M54*N54*O54*$S$46 -> 40320 | Q54: =P54/$G$29 -> 35.84
B55: CNC Plate Drilling -Component | D55: 2 | E55: =D55 -> 2 | F55: 7500000 | G55: =IF($C$29="Yes",E55*F55,"") -> 15000000 | H55: =IFERROR(G55*$H$40,"") -> 156250 | K55: 12 | L55: 0.8 | M55: =E55*K55*L55 -> 19.2 | N55: =$D$11*$D$12 -> 500 | O55: 0.6 | P55: =M55*N55*O55*$S$46 -> 80640 | Q55: =P55/$G$29 -> 71.68
B56: Manual Punching Machine | D56: 1 | E56: =D56 -> 1 | F56: 2000000 | G56: =IF($C$29="Yes",E56*F56,"") -> 2000000 | H56: =IFERROR(G56*$H$40,"") -> 20833.333 | I56: A hand-operated or foot-operated machine that punches holes in steel plates, beams, and metal sheets using a die and punch mechanism. Works by applying mechanical or hydraulic force to shear out a hole in the material. | K56: 3.6 | L56: 0.8 | M56: =E56*K56*L56 -> 2.88 | N56: =$D$11*$D$12 -> 500 | O56: 0.6 | P56: =M56*N56*O56*$S$46 -> 12096 | Q56: =P56/$G$29 -> 10.752
B57: Radial Drilling Machine | D57: 1 | E57: =D57 -> 1 | F57: 5000000 | G57: =IF($C$29="Yes",E57*F57,"") -> 5000000 | H57: =IFERROR(G57*$H$40,"") -> 52083.333 | I57: A drilling machine with a movable radial arm that allows the drill head to be positioned over a large workpiece without moving the workpiece itself. | K57: 3.6 | L57: 0.8 | M57: =E57*K57*L57 -> 2.88 | N57: =$D$11*$D$12 -> 500 | O57: 0.6 | P57: =M57*N57*O57*$S$46 -> 12096 | Q57: =P57/$G$29 -> 10.752
B58: 4 Roll Flange Strt Machine | D58: 1 | E58: =D58 -> 1 | F58: 30000000 | G58: =IF($C$29="Yes",E58*F58,"") -> 30000000 | H58: =IFERROR(G58*$H$40,"") -> 312500 | I58: A heavy-duty machine designed to correct flange deformations in structural steel beams. Eliminates welding-induced warping, bending, and flange misalignment. | K58: 12 | L58: 0.8 | M58: =E58*K58*L58 -> 9.6 | N58: =$D$11*$D$12 -> 500 | O58: 0.6 | P58: =M58*N58*O58*$S$46 -> 40320 | Q58: =P58/$G$29 -> 35.84
A59: iv | B59: Bending and Forming Equipment
B60: Press brake Machine 3000X10 | D60: 1 | E60: =D60 -> 1 | F60: 5000000 | G60: =IF($C$29="Yes",E60*F60,"") -> 5000000 | H60: =IFERROR(G60*$H$40,"") -> 52083.333 | I60: A hydraulic or mechanical bending machine used to form metal sheets into angles, channels, and other shapes. | K60: 12 | L60: 0.8 | M60: =E60*K60*L60 -> 9.6 | N60: =$D$11*$D$12 -> 500 | O60: 0.6 | P60: =M60*N60*O60*$S$46 -> 40320 | Q60: =P60/$G$29 -> 35.84
A61: v | B61: Welding Equipment
B62: H Beam Welding | D62: 1 | E62: =D62 -> 1 | F62: 40000000 | G62: =IF($C$29="Yes",E62*F62,"") -> 40000000 | H62: =IFERROR(G62*$H$40,"") -> 416666.67 | I62: Specialized welding system used to fabricate H-beams or I-beams by welding steel plates together. | K62: 4 | L62: 0.8 | M62: =E62*K62*L62 -> 3.2 | N62: =$D$11*$D$12 -> 500 | O62: 0.6 | P62: =M62*N62*O62*$S$46 -> 13440 | Q62: =P62/$G$29 -> 11.946667
B63: Welding Machine | D63: 40 | E63: =D63 -> 40 | F63: 150000 | G63: =IF($C$29="Yes",E63*F63,"") -> 6000000 | H63: =IFERROR(G63*$H$40,"") -> 62500 | I63: Manual welding machine | K63: 2.4 | L63: 0.8 | M63: =E63*K63*L63 -> 76.8 | N63: =$D$11*$D$12 -> 500 | O63: 0.6 | P63: =M63*N63*O63*$S$46 -> 322560 | Q63: =P63/$G$29 -> 286.72
A64: vi | B64: Surface Preparation and Finishing
B65: Plate Blasting Machine | D65: 1 | E65: =D65 -> 1 | F65: 5000000 | G65: =IF($C$29="Yes",E65*F65,"") -> 5000000 | H65: =IFERROR(G65*$H$40,"") -> 52083.333 | I65: Descaling, and preparing metal plates (such as steel plates) before fabrication or coating. It uses abrasive blasting (typically steel shots or grit) to remove rust, scale, paint, and contaminants from the surface, improving adhesion for welding, painting, or coating. | K65: 4 | L65: 0.8 | M65: =E65*K65*L65 -> 3.2 | N65: =$D$11*$D$12 -> 500 | O65: 0.6 | P65: =M65*N65*O65*$S$46 -> 13440 | Q65: =P65/$G$29 -> 11.946667
A66: vii | B66: Other equipments
B67: Compressor 500CFM | D67: 1 | E67: =D67 -> 1 | F67: 4000000 | G67: =IF($C$29="Yes",E67*F67,"") -> 4000000 | H67: =IFERROR(G67*$H$40,"") -> 41666.667 | I67: Used for providing compressed air for blasting, cutting, welding support, bolting, and painting. It provides the necessary power and efficiency for various pneumatic tools and processes, ensuring faster and high-quality steel fabrication. | K67: 40 | L67: 0.8 | M67: =E67*K67*L67 -> 32 | N67: =$D$11*$D$12 -> 500 | O67: 0.6 | P67: =M67*N67*O67*$S$46 -> 134400 | Q67: =P67/$G$29 -> 119.46667
B68: Bogie | D68: 20 | E68: =D68 -> 20 | F68: 350000 | G68: =IF($C$29="Yes",E68*F68,"") -> 7000000 | H68: =IFERROR(G68*$H$40,"") -> 72916.667 | I68: Movable cart or trolley used to transport heavy steel components, such as beams, plates, or welded structures, within a fabrication shop or production line. It helps in moving materials efficiently between different workstations, such as cutting, welding, blasting, and painting stations. | K68: =T46 -> 90 | L68: 0.1 | M68: =E68*K68*L68 -> 180 | N68: =$D$11*$D$12 -> 500 | O68: 0.4 | P68: =M68*N68*O68 -> 36000 | Q68: =P68/$G$29 -> 32
B69: Total (Built-Up fabrication & Bits Shop) | D69: =SUM(D46:D68) -> 80 | E69: =D69 -> 80 | G69: =SUM(G46:G68) -> 177000000 | H69: =SUM(H46:H68) -> 1843750 | K69: Total (Built-Up fabrication & Bits Shop) | Q69: =SUM(Q46:Q68) -> 851.54133
A71: 2.2 | B71: Fabrication Requirement: Bridge & Girder fabrication | D71: =$C$30 -> No
A73: =MAX($A$1:A70)+0.1 -> 2.2 | B73: Bridge & Girder fabrication, Bay-2 | D73: Original No.s | E73: Updated No.s | F73: Rate | G73: Puchase Cost | H73: Monthly Rental | I73: Equipment Description
A74: i | B74: Material Handling
B75: EOT Crane 20T | D75: 2 | E75: =D75 -> 2 | F75: 6500000 | G75: =IF($C$30="Yes",E75*F75,"") | H75: =IFERROR(G75*$H$40,"") | I75: Electric Overhead Traveling Crane with a lifting capacity of 20 tons | K75: 4 | L75: 0.8 | M75: =E75*K75*L75 -> 6.4 | N75: =$D$11*$D$12 -> 500 | O75: 0.6 | P75: =M75*N75*O75*$S$46 -> 26880 | Q75: =P75/$G$29 -> 23.893333
A76: ii | B76: Cutting Equipment
B77: CNC Multi Torch | D77: 1 | E77: =D77 -> 1 | F77: 4000000 | G77: =IF($C$30="Yes",E77*F77,"") | H77: =IFERROR(G77*$H$40,"") | I77: A CNC (Computer Numerical Control) machine that automates the cutting process. Equipped with multiple torches (Plasma or Oxy-Fuel) to cut several steel plates or sections at the same time. | K77: =K49 -> 12 | L77: 0.8 | M77: =E77*K77*L77 -> 9.6 | N77: =$D$11*$D$12 -> 500 | O77: 0.6 | P77: =M77*N77*O77*$S$46 -> 40320 | Q77: =P77/$G$29 -> 35.84
A78: iii | B78: Drilling and Punching Machines
B79: CNC Plate Drilling - Thick Plate | D79: 1 | E79: =D79 -> 1 | F79: 9000000 | G79: =IF($C$30="Yes",E79*F79,"") | H79: =IFERROR(G79*$H$40,"") | I79: Computer-controlled drilling system used to drill precise holes in thick steel plates | K79: =K54 -> 12 | L79: 0.8 | M79: =E79*K79*L79 -> 9.6 | N79: =$D$11*$D$12 -> 500 | O79: 0.6 | P79: =M79*N79*O79*$S$46 -> 40320 | Q79: =P79/$G$29 -> 35.84
A80: iv | B80: Bending and Forming Equipment
B81: Plate Rolling Machine | D81: 1 | E81: =D81 -> 1 | F81: 10000000 | G81: =IF($C$30="Yes",E81*F81,"") | H81: =IFERROR(G81*$H$40,"") | I81: Used to bend and roll metal plates into cylindrical, conical, or curved shapes. | K81: 3.6 | L81: 0.8 | M81: =E81*K81*L81 -> 2.88 | N81: =$D$11*$D$12 -> 500 | O81: 0.6 | P81: =M81*N81*O81*$S$46 -> 12096 | Q81: =P81/$G$29 -> 10.752
A82: v | B82: Welding Equipment
B83: Welding Machine | D83: 20 | E83: =D83 -> 20 | F83: 150000 | G83: =IF($C$30="Yes",E83*F83,"") | H83: =IFERROR(G83*$H$40,"") | I83: Manual welding machine | K83: =K63 -> 2.4 | L83: 0.8 | M83: =E83*K83*L83 -> 38.4 | N83: =$D$11*$D$12 -> 500 | O83: 0.6 | P83: =M83*N83*O83*$S$46 -> 161280 | Q83: =P83/$G$29 -> 143.36
B84: Column and Boom Welding Machine | D84: 1 | E84: =D84 -> 1 | F84: 10000000 | G84: =IF($C$30="Yes",E84*F84,"") | H84: =IFERROR(G84*$H$40,"") | I84: Automated welding system used for welding large, heavy-duty steel components (H-beams, I-beams, and steel columns) | K84: 16 | L84: 0.8 | M84: =E84*K84*L84 -> 12.8 | N84: =$D$11*$D$12 -> 500 | O84: 0.6 | P84: =M84*N84*O84*$S$46 -> 53760 | Q84: =P84/$G$29 -> 47.786667
B85: Heavy Girder Built up I -Beam Machine | D85: 1 | E85: =D85 -> 1 | F85: 30000000 | G85: =IF($C$30="Yes",E85*F85,"") | H85: =IFERROR(G85*$H$40,"") | I85: Automated welding and assembly system used to manufacture large, heavy-duty I-beams and box girde | K85: 16 | L85: 0.8 | M85: =E85*K85*L85 -> 12.8 | N85: =$D$11*$D$12 -> 500 | O85: 0.6 | P85: =M85*N85*O85*$S$46 -> 53760 | Q85: =P85/$G$29 -> 47.786667
B86: Box Column Welding Machine | D86: 1 | E86: =D86 -> 1 | F86: 5000000 | G86: =IF($C$30="Yes",E86*F86,"") | H86: =IFERROR(G86*$H$40,"") | I86: Automated welding system used to fabricate heavy-duty box columns from steel plates | K86: 16 | L86: 0.8 | M86: =E86*K86*L86 -> 12.8 | N86: =$D$11*$D$12 -> 500 | O86: 0.6 | P86: =M86*N86*O86*$S$46 -> 53760 | Q86: =P86/$G$29 -> 47.786667
A87: vi | B87: Other equipments
B88: Compressor 250CFM | D88: 1 | E88: =D88 -> 1 | F88: 2000000 | G88: =IF($C$30="Yes",E88*F88,"") | H88: =IFERROR(G88*$H$40,"") | I88: Used for providing compressed air for blasting, cutting, welding support, bolting, and painting. It provides the necessary power and efficiency for various pneumatic tools and processes, ensuring faster and high-quality steel fabrication. | K88: 30 | L88: 0.8 | M88: =E88*K88*L88 -> 24 | N88: =$D$11*$D$12 -> 500 | O88: 0.6 | P88: =M88*N88*O88*$S$46 -> 100800 | Q88: =P88/$G$29 -> 89.6
B89: Test Rig | D89: 1 | E89: =D89 -> 1 | F89: 5000000 | G89: =IF($C$30="Yes",E89*F89,"") | H89: =IFERROR(G89*$H$40,"") | I89: Applies load, pressure, vibration, or other forces to a component or structure to assess its performance, strength, and failure limits | K89: 2 | L89: 0.8 | M89: =E89*K89*L89 -> 1.6 | N89: =$D$11*$D$12 -> 500 | O89: 0.6 | P89: =M89*N89*O89*$S$46 -> 6720 | Q89: =P89/$G$29 -> 5.9733333
B90: Total (Bridge & Girder fabrication) | D90: =SUM(D74:D89) -> 30 | E90: =SUM(E74:E89) -> 30 | G90: =SUM(G74:G89) -> 0 | H90: =SUM(H74:H89) -> 0 | K90: Total (Bridge & Girder fabrication) | Q90: =SUM(Q75:Q89) -> 488.61867
A92: 2.3 | B92: Fabrication Requirement: Hot roll fabrication | D92: =$C$31 -> Yes
A94: =MAX($A$1:A91)+0.1 -> 2.3 | B94: Hot roll fabrication, Bay-3 | D94: Original No.s | E94: Updated No.s | F94: Rate | G94: Puchase Cost | H94: Monthly Rental | I94: Equipment Description
A95: i | B95: Material Handling
B96: EOT Crane 10T | D96: 1 | E96: =D96 -> 1 | F96: 4000000 | G96: =IF($C$31="Yes",E96*F96,"") -> 4000000 | H96: =IFERROR(G96*$H$40,"") -> 41666.667 | I96: Electric Overhead Traveling Crane with a lifting capacity of 5 tons | K96: =K46 -> 3.6 | L96: 0.8 | M96: =E96*K96*L96 -> 2.88 | N96: =$D$11*$D$12 -> 500 | O96: 0.6 | P96: =M96*N96*O96*$S$46 -> 12096 | Q96: =P96/$G$29 -> 10.752
B97: EOT Crane 5T | D97: 4 | E97: =D97 -> 4 | F97: 2000000 | G97: =IF($C$31="Yes",E97*F97,"") -> 8000000 | H97: =IFERROR(G97*$H$40,"") -> 83333.333 | I97: Electric Overhead Traveling Crane with a lifting capacity of 10 tons | K97: =K47 -> 2.4 | L97: 0.8 | M97: =E97*K97*L97 -> 7.68 | N97: =$D$11*$D$12 -> 500 | O97: 0.6 | P97: =M97*N97*O97*$S$46 -> 32256 | Q97: =P97/$G$29 -> 28.672
A98: ii | B98: Cutting Equipment
B99: Manual Band Saw | D99: 1 | E99: =D99 -> 1 | F99: 5000000 | G99: =IF($C$31="Yes",E99*F99,"") -> 5000000 | H99: =IFERROR(G99*$H$40,"") -> 52083.333 | I99: Hand-operated cutting machine used for cutting steel beams, pipes, channels, and other metal profiles. | K99: 3 | L99: 0.8 | M99: =E99*K99*L99 -> 2.4 | N99: =$D$11*$D$12 -> 500 | O99: 0.6 | P99: =M99*N99*O99*$S$46 -> 10080 | Q99: =P99/$G$29 -> 8.96
A100: iii | B100: Drilling and Punching Machines
B101: CNC H Beam Drilling | D101: 2 | E101: =D101 -> 2 | F101: 25000000 | G101: =IF($C$31="Yes",E101*F101,"") -> 50000000 | H101: =IFERROR(G101*$H$40,"") -> 520833.33 | I101: Precision equipment used to drill holes automatically in H-beams (also called I-beams or universal beams) as per design requirements | K101: =K54 -> 12 | L101: 0.8 | M101: =E101*K101*L101 -> 19.2 | N101: =$D$11*$D$12 -> 500 | O101: 0.6 | P101: =M101*N101*O101*$S$46 -> 80640 | Q101: =P101/$G$29 -> 71.68
A102: iv | B102: Bending and Forming Equipment
B103: Cambering Machine | D103: 1 | E103: =D103 -> 1 | F103: 10000000 | G103: =IF($C$31="Yes",E103*F103,"") -> 10000000 | H103: =IFERROR(G103*$H$40,"") -> 104166.67 | I103: Cambering refers to the process of inducing a slight upward curve in a steel beam or girder to compensate for expected deflection under load. Widely used in bridges, long-span structures, and PEB construction to improve stability and performance. | K103: 3 | L103: 0.8 | M103: =E103*K103*L103 -> 2.4 | N103: =$D$11*$D$12 -> 500 | O103: 0.6 | P103: =M103*N103*O103*$S$46 -> 10080 | Q103: =P103/$G$29 -> 8.96
B104: Profile Rolling / Bending Machine | D104: 1 | E104: =D104 -> 1 | F104: 10000000 | G104: =IF($C$31="Yes",E104*F104,"") -> 10000000 | H104: =IFERROR(G104*$H$40,"") -> 104166.67 | I104: Profile Rolling refers to the cold or hot bending of metal sections (I-beams, angles, pipes, channels) into curved, spiral, or circular shapes without compromising structural integrity. Commonly used for arches, domes, circular staircases, curved beams, and piping systems. | K104: 3 | L104: 0.8 | M104: =E104*K104*L104 -> 2.4 | N104: =$D$11*$D$12 -> 500 | O104: 0.6 | P104: =M104*N104*O104*$S$46 -> 10080 | Q104: =P104/$G$29 -> 8.96
A105: v | B105: Welding Equipment
B106: Welding Machine | D106: 20 | E106: =D106 -> 20 | F106: 150000 | G106: =IF($C$31="Yes",E106*F106,"") -> 3000000 | H106: =IFERROR(G106*$H$40,"") -> 31250 | I106: MIG/Flux cored arc welding machine | K106: 3 | L106: 0.8 | M106: =E106*K106*L106 -> 48 | N106: =$D$11*$D$12 -> 500 | O106: 0.6 | P106: =M106*N106*O106*$S$46 -> 201600 | Q106: =P106/$G$29 -> 179.2
A107: vi | B107: Surface Preparation and Finishing
B108: H Beam Blasting Machine | D108: 1 | E108: =D108 -> 1 | F108: 9000000 | G108: =IF($C$31="Yes",E108*F108,"") -> 9000000 | H108: =IFERROR(G108*$H$40,"") -> 93750 | I108: Surface treatment machine used for cleaning, descaling, and preparing H-beams, I-beams, and other structural steel components before further processing like painting, coating, or welding. | K108: 3 | L108: 0.8 | M108: =E108*K108*L108 -> 2.4 | N108: =$D$11*$D$12 -> 500 | O108: 0.6 | P108: =M108*N108*O108*$S$46 -> 10080 | Q108: =P108/$G$29 -> 8.96
A109: vii | B109: Other equipments
B110: Compressor 500CFM | D110: 1 | E110: =D110 -> 1 | F110: 4000000 | G110: =IF($C$31="Yes",E110*F110,"") -> 4000000 | H110: =IFERROR(G110*$H$40,"") -> 41666.667 | I110: Used for providing compressed air for blasting, cutting, welding support, bolting, and painting. It provides the necessary power and efficiency for various pneumatic tools and processes, ensuring faster and high-quality steel fabrication. | K110: =K67 -> 40 | L110: 0.8 | M110: =E110*K110*L110 -> 32 | N110: =$D$11*$D$12 -> 500 | O110: 0.6 | P110: =M110*N110*O110*$S$46 -> 134400 | Q110: =P110/$G$29 -> 119.46667
B111: Bogie | D111: 20 | E111: =D111 -> 20 | F111: 350000 | G111: =IF($C$31="Yes",E111*F111,"") -> 7000000 | H111: =IFERROR(G111*$H$40,"") -> 72916.667 | I111: Movable cart or trolley used to transport heavy steel components, such as beams, plates, or welded structures, within a fabrication shop or production line. It helps in moving materials efficiently between different workstations, such as cutting, welding, blasting, and painting stations. | K111: =$T$46 -> 90 | L111: =L68 -> 0.1 | M111: =E111*K111*L111 -> 180 | N111: =$D$11*$D$12 -> 500 | O111: =O68 -> 0.4 | P111: =M111*N111*O111 -> 36000 | Q111: =P111/$G$29 -> 32
B112: Total (Hot Roll Fabrication) | D112: =SUM(D96:D111) -> 52 | E112: =SUM(E96:E111) -> 52 | G112: =SUM(G96:G111) -> 110000000 | H112: =SUM(H96:H111) -> 1145833.3 | K112: Total (Hot Roll Fabrication) | Q112: =SUM(Q96:Q111) -> 477.61067
A114: 2.4 | B114: Fabrication Requirement: Blasting & Painting | D114: =$C$32 -> Yes
A116: =MAX($A$1:A113)+0.1 -> 2.4 | B116: Blasting & Painting, Bay-4 | D116: Original No.s | E116: Updated No.s | F116: Rate | G116: Puchase Cost | H116: Monthly Rental | I116: Equipment Description
...

Sheet >> Backups

Sheet Painting Inputs
C5: 24 Rs conversion - including wastage
C6: painting - 7.8 rs
C7: Transportation ODC 50% - | D7: 5.5
C13: Coating Name | D13: Layer | E13: Price per Litre (INR) | F13: Source URL
C14: Red Oxide Metal Primer | D14: 1 — Primer | E14: 135 | F14: https://m.indiamart.com/plasmacoating-products/metal-primer.html
C15: Red Oxide Zinc Chromate Primer | D15: 1 — Primer | E15: 175 | F15: https://m.indiamart.com/plasmacoating-products/metal-primer.html
C16: Epoxy Zinc Phosphate Primer (Jagdamba) | D16: 1 — Primer | E16: 180 | F16: https://m.indiamart.com/impcat/epoxy-primer-paint.html
C17: Apcodur HB ZP Primer (Asian Paints) | D17: 1 — Primer | E17: 220 | F17: https://m.indiamart.com/impcat/phosphate-primer.html
C18: Epoxy ZP Grey Primer (Plasma Paints) | D18: 1 — Primer | E18: 265 | F18: https://m.indiamart.com/plasmacoating-products/metal-primer.html
C19: Neropoxy HB MIO Primer Grey (Berger) | D19: 2 — Intermediate | E19: 215 | F19: https://m.indiamart.com/aimpolymers/epoxy-primer.html
C20: Epoxy Grey Primer HB (Plasma Paints) | D20: 2 — Intermediate | E20: 295 | F20: https://m.indiamart.com/plasmacoating-products/metal-primer.html
C21: PU Finish Paint (Alfa Paints) | D21: 3 — Final Coat | E21: 279 | F21: https://m.indiamart.com/impcat/phosphate-primer.html
C22: Nerothane PU Enamel (Berger) | D22: 3 — Final Coat | E22: 330 | F22: https://m.indiamart.com/aimpolymers/epoxy-primer.html
