Workbook
Name Armor: '[1]Ref - Data, Assumptions'!#REF!
Name Armor: 'Data Input'!#REF!
Name Armordensity: 'Data Input'!$J$2:$K$7
Name Armour: '[1]Ref - Data, Assumptions'!$H$12:$H$16
Name Armour: 'Data Input'!$J$3:$J$7
Name Conductor: 'Data Input'!$D$3:$D$4
Name Density: '[1]Ref - Data, Assumptions'!$H$3:$I$5
Name Density: 'Data Input'!$G$2:$H$4
Name Density1: '[1]Ref - Data, Assumptions'!$H$7:$I$9
Name Density1: 'Data Input'!$D$2:$E$4
Name Insulation: '[1]Ref - Data, Assumptions'!$H$4:$H$5
Name Insulation: 'Data Input'!$G$3:$G$4
Name Shape: '[1]Ref - Data, Assumptions'!$H$19:$H$20
Name Shape: 'Data Input'!$B$3:$B$4

Sheet Summary
J1: * Incl. wastage
A2: # | B2: Cable Type | C2: Wire Size | D2: Shape of the core | E2: Insulation Details | F2: Armoured / Unarmoured | G2: Conductor | H2: Spl. Construction | I2: Approx Net wt. (as per ppt) | J2: Approx Net wt. (as per cost sheet) | K2: Price as per cost sheet | L2: Baseline Price in INR/ KM | M2: Qty Required | N2: Total Spend in INR | O2: Cost Optimization Potential in INR | P2: % Benefit
A3: 1 | B3: LT Cable | C3: 1 x 300 mm2 | D3: Circular | E3: XLPE insl. | F3: Unarmoured | G3: Aluminium | H3: FRLS - inner, outer | I3: 1180 | J3: 1184.8826 | K3: ='Al LT Cables (1 x 300)'!M78 -> 165988.52 | L3: 242630 | M3: 4.32 | N3: =M3*L3 -> 1048161.6 | O3: =IF((L3-K3)*M3<0,0,(L3-K3)*M3) -> 331091.2 | P3: =(L3-K3)/L3 -> 0.31587801
A4: =A3+1 -> 2 | B4: LT Cable | C4: 1 x 630 mm2 | D4: Circular | E4: XLPE insl. | F4: Unarmoured | G4: Aluminium | H4: FRLS - inner, outer | I4: 2305 | J4: 2343.0609 | K4: ='Al LT Cables (1 x 630)'!M78 -> 334919.08 | L4: 434000 | M4: 79.906 | N4: =M4*L4 -> 34679204 | O4: =IF((L4-K4)*M4<0,0,(L4-K4)*M4) -> 7917160.3 | P4: =(L4-K4)/L4 -> 0.22829706
A5: =A4+1 -> 3 | B5: LT Cable | C5: 1 x 630 mm2 | D5: Circular | E5: XLPE insl. | F5: Unarmoured | G5: Copper | H5: FRLS - inner, outer | I5: 6195 | J5: 6392.1969 | K5: ='Cu LT Cables (1 x 630)'!M78 -> 2804390.3 | L5: 2521000 | M5: 2.56 | N5: =M5*L5 -> 6453760 | O5: =IF((L5-K5)*M5<0,0,(L5-K5)*M5) -> 0 | P5: =(L5-K5)/L5 -> -0.11241188
A6: =A5+1 -> 4 | B6: LT Cable | C6: 2 x 2.5 mm2 | D6: Sectoral - 180 Deg. | E6: XLPE insl. | F6: Unarmoured | G6: Copper | H6: FRLS - inner, outer | I6: 155 | J6: 154.46617 | K6: ='Cu LT Cables (2 x 2.5)'!M78 -> 32011.19 | L6: 35800 | M6: 189.315 | N6: =M6*L6 -> 6777477 | O6: =IF((L6-K6)*M6<0,0,(L6-K6)*M6) -> 717278.64 | P6: =(L6-K6)/L6 -> 0.10583269
A7: =A6+1 -> 5 | B7: LT Cable | C7: 2 x 6 mm2 | D7: Sectoral - 180 Deg. | E7: XLPE insl. | F7: Unarmoured | G7: Aluminium | H7: FRLS - inner, outer | I7: 175 | J7: 166.23762 | K7: ='Al LT Cables (2 x 6)'!M78 -> 17829.455 | L7: 28000 | M7: 102.994 | N7: =M7*L7 -> 2883832 | O7: =IF((L7-K7)*M7<0,0,(L7-K7)*M7) -> 1047505.1 | P7: =(L7-K7)/L7 -> 0.36323376
A8: =A7+1 -> 6 | B8: LT Cable | C8: 2 x 10mm2 | D8: Sectoral - 180 Deg. | E8: XLPE insl. | F8: Unarmoured | G8: Aluminium | H8: FRLS - inner, outer | I8: 215 | J8: 211.87899 | K8: ='Al LT Cables (2 x 10)'!M78 -> 23571.058 | L8: 34400 | M8: 13.164 | N8: =M8*L8 -> 452841.6 | O8: =IF((L8-K8)*M8<0,0,(L8-K8)*M8) -> 142552.19 | P8: =(L8-K8)/L8 -> 0.31479483
A9: =A8+1 -> 7 | B9: LT Cable | C9: 2 x 16 mm2 | D9: Sectoral - 180 Deg. | E9: XLPE insl. | F9: Unarmoured | G9: Aluminium | H9: FRLS - inner, outer | I9: 250 | J9: 241.62505 | K9: ='Al LT Cables (2 x 16)'!M78 -> 28616.015 | L9: 33400 | M9: 22.169 | N9: =M9*L9 -> 740444.6 | O9: =IF((L9-K9)*M9<0,0,(L9-K9)*M9) -> 106056.16 | P9: =(L9-K9)/L9 -> 0.14323309
A10: =A9+1 -> 8 | B10: LT Cable | C10: 2 x 25mm2 | D10: Sectoral - 180 Deg. | E10: XLPE insl. | F10: Unarmoured | G10: Aluminium | H10: FRLS - inner, outer | I10: 355 | J10: 351.8583 | K10: ='Al LT Cables (2 x 25)'!M78 -> 42397.259 | L10: 48800 | M10: 14.298 | N10: =M10*L10 -> 697742.4 | O10: =IF((L10-K10)*M10<0,0,(L10-K10)*M10) -> 91546.39 | P10: =(L10-K10)/L10 -> 0.13120371
A11: =A10+1 -> 9 | B11: LT Cable | C11: 2 x 35mm2 | D11: Sectoral - 180 Deg. | E11: XLPE insl. | F11: Unarmoured | G11: Aluminium | H11: FRLS - inner, outer | I11: 440 | J11: 430.6981 | K11: ='Al LT Cables (2 x 35)'!M78 -> 53453.124 | L11: 59800 | M11: 7.53 | N11: =M11*L11 -> 450294 | O11: =IF((L11-K11)*M11<0,0,(L11-K11)*M11) -> 47791.975 | P11: =(L11-K11)/L11 -> 0.10613505
A12: =A11+1 -> 10 | B12: LT Cable | C12: 2 x 50mm2 | D12: Sectoral - 180 Deg. | E12: XLPE insl. | F12: Unarmoured | G12: Aluminium | H12: FRLS - inner, outer | I12: 545 | J12: 553.665 | K12: ='Al LT Cables (2 x 50)'!M78 -> 70599.775 | L12: 74500 | M12: 11.288 | N12: =M12*L12 -> 840956 | O12: =IF((L12-K12)*M12<0,0,(L12-K12)*M12) -> 44025.737 | P12: =(L12-K12)/L12 -> 0.05235201
A13: =A12+1 -> 11 | B13: LT Cable | C13: 2 x 70mm2 | D13: Sectoral - 180 Deg. | E13: XLPE insl. | F13: Unarmoured | G13: Aluminium | H13: FRLS - inner, outer | I13: 710 | J13: 718.60097 | K13: ='Al LT Cables (2 x 70)'!M78 -> 93507.08 | L13: 97800 | M13: 7.623 | N13: =M13*L13 -> 745529.4 | O13: =IF((L13-K13)*M13<0,0,(L13-K13)*M13) -> 32724.928 | P13: =(L13-K13)/L13 -> 0.043894886
A14: =A13+1 -> 12 | B14: LT Cable | C14: 2 x 95mm2 | D14: Sectoral - 180 Deg. | E14: XLPE insl. | F14: Unarmoured | G14: Aluminium | H14: FRLS - inner, outer | I14: 930 | J14: 932.73387 | K14: ='Al LT Cables (2 x 95)'!M78 -> 122607.37 | L14: 130000 | M14: 23.557 | N14: =M14*L14 -> 3062410 | O14: =IF((L14-K14)*M14<0,0,(L14-K14)*M14) -> 174148.08 | P14: =(L14-K14)/L14 -> 0.056866349
A15: =A14+1 -> 13 | B15: LT Cable | C15: 2 x 120mm2 | D15: Sectoral - 180 Deg. | E15: XLPE insl. | F15: Unarmoured | G15: Aluminium | H15: FRLS - inner, outer | I15: 1110 | J15: 1126.7768 | K15: ='Al LT Cables (2 x 120)'!M78 -> 150083.06 | L15: 156600 | M15: 9.153 | N15: =M15*L15 -> 1433359.8 | O15: =IF((L15-K15)*M15<0,0,(L15-K15)*M15) -> 59649.59 | P15: =(L15-K15)/L15 -> 0.041615225
A16: =A15+1 -> 14 | B16: LT Cable | C16: 2 x 150mm2 | D16: Sectoral - 180 Deg. | E16: XLPE insl. | F16: Unarmoured | G16: Aluminium | H16: FRLS - inner, outer | I16: 1320 | J16: 1361.6583 | K16: ='Al LT Cables (2 x 150)'!M78 -> 183487.3 | L16: 186200 | M16: 10.702 | N16: =M16*L16 -> 1992712.4 | O16: =IF((L16-K16)*M16<0,0,(L16-K16)*M16) -> 29031.332 | P16: =(L16-K16)/L16 -> 0.014568752
A17: =A16+1 -> 15 | B17: LT Cable | C17: 2 x 240mm2 | D17: Sectoral - 180 Deg. | E17: XLPE insl. | F17: Unarmoured | G17: Aluminium | H17: FRLS - inner, outer | I17: 2085 | J17: 2130.1206 | K17: ='Al LT Cables (2 x 240)'!M78 -> 288894.39 | L17: 299200 | M17: 108 | N17: =M17*L17 -> 32313600 | O17: =IF((L17-K17)*M17<0,0,(L17-K17)*M17) -> 1113006.2 | P17: =(L17-K17)/L17 -> 0.034443892
A18: =A17+1 -> 16 | B18: LT Cable | C18: 3 x 6 mm2 | D18: Sectoral - 120 Deg. | E18: XLPE insl. | F18: Unarmoured | G18: Aluminium | H18: FRLS - inner, outer | I18: 210 | J18: 191.28924 | K18: ='Al LT Cables (3 x 6)'!M78 -> 21298.615 | L18: 32400 | M18: 256.995 | N18: =M18*L18 -> 8326638 | O18: =IF((L18-K18)*M18<0,0,(L18-K18)*M18) -> 2853000.4 | P18: =(L18-K18)/L18 -> 0.34263533
A19: =A18+1 -> 17 | B19: LT Cable | C19: 3 x 10mm2 | D19: Sectoral - 120 Deg. | E19: XLPE insl. | F19: Unarmoured | G19: Aluminium | H19: FRLS - inner, outer | I19: 260 | J19: 249.13709 | K19: ='Al LT Cables (3 x 10)'!M78 -> 28916.511 | L19: 40300 | M19: 65.575 | N19: =M19*L19 -> 2642672.5 | O19: =IF((L19-K19)*M19<0,0,(L19-K19)*M19) -> 746472.26 | P19: =(L19-K19)/L19 -> 0.2824687
A20: =A19+1 -> 18 | B20: LT Cable | C20: 3 x 16 mm2 | D20: Sectoral - 120 Deg. | E20: XLPE insl. | F20: Unarmoured | G20: Aluminium | H20: FRLS - inner, outer | I20: 335 | J20: 310.76971 | K20: ='Al LT Cables (3 x 16)'!M78 -> 38010.405 | L20: 45500 | M20: 131.51 | N20: =M20*L20 -> 5983705 | O20: =IF((L20-K20)*M20<0,0,(L20-K20)*M20) -> 984956.65 | P20: =(L20-K20)/L20 -> 0.16460649
A21: =A20+1 -> 19 | B21: LT Cable | C21: 3 x 25mm2 | D21: Sectoral - 120 Deg. | E21: XLPE insl. | F21: Unarmoured | G21: Aluminium | H21: FRLS - inner, outer | I21: 480 | J21: 451.49487 | K21: ='Al LT Cables (3 x 25)'!M78 -> 56313.017 | L21: 64800 | M21: 68.205 | N21: =M21*L21 -> 4419684 | O21: =IF((L21-K21)*M21<0,0,(L21-K21)*M21) -> 578854.66 | P21: =(L21-K21)/L21 -> 0.13097196
A22: =A21+1 -> 20 | B22: LT Cable | C22: 3 x 35mm2 | D22: Sectoral - 120 Deg. | E22: XLPE insl. | F22: Unarmoured | G22: Aluminium | H22: FRLS - inner, outer | I22: 600 | J22: 565.0229 | K22: ='Al LT Cables (3 x 35)'!M78 -> 72424.098 | L22: 80300 | M22: 68.78 | N22: =M22*L22 -> 5523034 | O22: =IF((L22-K22)*M22<0,0,(L22-K22)*M22) -> 541704.51 | P22: =(L22-K22)/L22 -> 0.098080965
A23: =A22+1 -> 21 | B23: LT Cable | C23: 3 x 50mm2 | D23: Sectoral - 120 Deg. | E23: XLPE insl. | F23: Unarmoured | G23: Aluminium | H23: FRLS - inner, outer | I23: 750 | J23: 738.59002 | K23: ='Al LT Cables (3 x 50)'!M78 -> 97042.99 | L23: 101400 | M23: 22.275 | N23: =M23*L23 -> 2258685 | O23: =IF((L23-K23)*M23<0,0,(L23-K23)*M23) -> 97052.389 | P23: =(L23-K23)/L23 -> 0.042968537
A24: =A23+1 -> 22 | B24: LT Cable | C24: 3 x 70mm2 | D24: Sectoral - 120 Deg. | E24: XLPE insl. | F24: Unarmoured | G24: Aluminium | H24: FRLS - inner, outer | I24: 1030 | J24: 1005.1718 | K24: ='Al LT Cables (3 x 70)'!M78 -> 133029.47 | L24: 141400 | M24: 62.73 | N24: =M24*L24 -> 8870022 | O24: =IF((L24-K24)*M24<0,0,(L24-K24)*M24) -> 525083.65 | P24: =(L24-K24)/L24 -> 0.059197559
A25: =A24+1 -> 23 | B25: LT Cable | C25: 3 x 95mm2 | D25: Sectoral - 120 Deg. | E25: XLPE insl. | F25: Unarmoured | G25: Aluminium | H25: FRLS - inner, outer | I25: 1290 | J25: 1260.4529 | K25: ='Al LT Cables (3 x 95)'!M78 -> 170580.76 | L25: 179000 | M25: 28.65 | N25: =M25*L25 -> 5128350 | O25: =IF((L25-K25)*M25<0,0,(L25-K25)*M25) -> 241211.34 | P25: =(L25-K25)/L25 -> 0.047034883
A26: =A25+1 -> 24 | B26: LT Cable | C26: 3 x 120mm2 | D26: Sectoral - 120 Deg. | E26: XLPE insl. | F26: Unarmoured | G26: Aluminium | H26: FRLS - inner, outer | I26: 1560 | J26: 1535.0456 | K26: ='Al LT Cables (3 x 120)'!M78 -> 210144.91 | L26: 218700 | M26: 37.8 | N26: =M26*L26 -> 8266860 | O26: =IF((L26-K26)*M26<0,0,(L26-K26)*M26) -> 323382.34 | P26: =(L26-K26)/L26 -> 0.039117916
A27: =A26+1 -> 25 | B27: LT Cable | C27: 3 x 150mm2 | D27: Sectoral - 120 Deg. | E27: XLPE insl. | F27: Unarmoured | G27: Aluminium | H27: FRLS - inner, outer | I27: 1920 | J27: 1928.079 | K27: ='Al LT Cables (3 x 150)'!M78 -> 263719.35 | L27: 271300 | M27: 35.86 | N27: =M27*L27 -> 9728818 | O27: =IF((L27-K27)*M27<0,0,(L27-K27)*M27) -> 271842.02 | P27: =(L27-K27)/L27 -> 0.027941937
A28: =A27+1 -> 26 | B28: LT Cable | C28: 3 x 240mm2 | D28: Sectoral - 120 Deg. | E28: XLPE insl. | F28: Unarmoured | G28: Aluminium | H28: FRLS - inner, outer | I28: 3025 | J28: 3011.9108 | K28: ='Al LT Cables (3 x 240)'!M78 -> 414984.13 | L28: 437000 | M28: 223.285 | N28: =M28*L28 -> 97575545 | O28: =IF((L28-K28)*M28<0,0,(L28-K28)*M28) -> 4915813 | P28: =(L28-K28)/L28 -> 0.05037956
A29: =A28+1 -> 27 | B29: LT Cable | C29: 4 x 6 mm2 | D29: Sectoral - 90 Deg. | E29: XLPE insl. | F29: Unarmoured | G29: Aluminium | H29: FRLS - inner, outer | I29: 250 | J29: 225.04329 | K29: ='Al LT Cables (4 x 6)'!M78 -> 25552.473 | L29: 37600 | M29: 171.55 | N29: =M29*L29 -> 6450280 | O29: =IF((L29-K29)*M29<0,0,(L29-K29)*M29) -> 2066753.2 | P29: =(L29-K29)/L29 -> 0.32041295
A30: =A29+1 -> 28 | B30: LT Cable | C30: 4 x 10mm2 | D30: Sectoral - 90 Deg. | E30: XLPE insl. | F30: Unarmoured | G30: Aluminium | H30: FRLS - inner, outer | I30: 315 | J30: 294.93159 | K30: ='Al LT Cables (4 x 10)'!M78 -> 35028.366 | L30: 48600 | M30: 1.87 | N30: =M30*L30 -> 90882 | O30: =IF((L30-K30)*M30<0,0,(L30-K30)*M30) -> 25378.955 | P30: =(L30-K30)/L30 -> 0.27925172
A31: =A30+1 -> 29 | B31: LT Cable | C31: 4 x 16 mm2 | D31: Sectoral - 90 Deg. | E31: XLPE insl. | F31: Unarmoured | G31: Aluminium | H31: FRLS - inner, outer | I31: 410 | J31: 378.96671 | K31: ='Al LT Cables (4 x 16)'!M78 -> 47300.667 | L31: 55700 | M31: 9.525 | N31: =M31*L31 -> 530542.5 | O31: =IF((L31-K31)*M31<0,0,(L31-K31)*M31) -> 80003.648 | P31: =(L31-K31)/L31 -> 0.15079593
N32: =SUM(N3:N31) -> 2.6036804e+08 | O32: =SUM(O3:O31) -> 26105077 | P32: =O32/N32 -> 0.10026222

Sheet Data Input
B2: Shape | D2: Conductor | E2: Density | G2: Insulation | H2: Density | J2: Armour | K2: Density | M2: Commodity | N2: Landed | O2: UoM | P2: Price as on | Q2: Remarks / Source
B3: Sector shaped | D3: Copper | E3: 8.94 | G3: XLPE | H3: 0.93 | J3: Galvanised steel round wire | K3: 7.86 | M3: Aluminium | N3: =123*1.05 -> 129.15 | O3: Rs/Kg. | P3: Jun'17 | Q3: MCX
B4: Circular | D4: Aluminium | E4: 2.7 | G4: PVC | H4: 1.35 | J4: Galvanised steel flat strip | K4: 7.86 | M4: Copper | N4: =368.558*1.05 -> 386.9859 | O4: Rs/Kg. | P4: Jun'17 | Q4: MCX
J5: Aluminium Flat Strip | K5: 2.7 | M5: PVC | N5: =71.5*1.05 -> 75.075 | O5: Rs/Kg. | P5: Jun'17 | Q5: Plasetmart
J6: Unarmored | K6: 0 | M6: Steel Wire | N6: =40*1.05 -> 42 | O6: Rs/Kg. | P6: Jun'17 | Q6: meps / other
J7: Aluminium Round Wired | K7: 2.7

Sheet Commodities
C3: Aluminum | D3: https://www.indexmundi.com/commodities/?commodity=aluminum&months=60&currency=inr
C44: Copper | D44: https://www.indexmundi.com/commodities/?commodity=copper&months=120&currency=inr

Sheet Al LT Cables (1 x 300)
B2: ="Cost Sheet for"&" "&C6&" Core"&" "&C9&" sq.mm"&" "&C10&" Cable" -> Cost Sheet for 1 Core 300 sq.mm Aluminium Cable
B4: Data Inputs
B6: No. of cores | C6: 1
B7: Shape of the core | C7: Circular
B8: Conductor
B9: Conductor Size (in sq. mm) | C9: 300 | D9: sq. mm
B10: Conductor Material | C10: Aluminium | L10: =2*L9 -> 0
B11: Angle - Main | C11: =IF(C7="Sector shaped", (360/C6),360) -> 360
B12: Angle - Main | C12: =IF(C7="Sector shaped",360-C11*3,0) -> 0
B13: Conductor Radius | C13: =SQRT((C9*(360/C11))/PI()) -> 9.7720502 | D13: mm
B14: Density of Conductor | C14: =VLOOKUP(C10,Density1,2,0) -> 2.7 | D14: g/cm3
B16: Insulation
B17: Material | C17: XLPE
B18: Nominal thickness of insulation | C18: 1.8
B19: Calculated radius over insulation | C19: =IF(C7="Circular", C13+C18,C13+2*C18) -> 11.57205 | D19: mm
B20: Density of Conductor | C20: =VLOOKUP(C17,Density,2,0) -> 0.93 | D20: g/cm3
B22: PVC Filler
B23: Filler Type | C23: PVC
B24: Area below inner sheath | C24: =PI()*((C31/2)^2) -> 471.43525 | D24: mm2
B25: Area till insulation | C25: =IF(C6=3.5,((C11/360)*PI()*(C19^2)*3)+((C12/360)*PI()*(C19^2)),(C11/360)*PI()*(C19^2)*C6) -> 420.69804 | D25: mm2
B26: Density | C26: =VLOOKUP(C23,Density,2,0) -> 1.35 | D26: g/cm3
B28: Inner Sheath
B29: Material | C29: PVC
B30: Minimum Thickness | C30: 0 | D30: mm
B31: Calculated diameter below innersheath | C31: =C37-2*C30 -> 24.5 | D31: mm
B32: Density of Conductor | C32: =VLOOKUP(C29,Density,2,0) -> 1.35 | D32: g/cm3
B34: Armour
B35: Material | C35: Unarmored
B36: Thickness of armour | C36: 0 | D36: mm
B37: Calculated diameter below armor | C37: =C43-2*C36 -> 24.5 | D37: mm
B38: Density of Conductor | C38: =VLOOKUP(C35,Armordensity,2,0) -> 0 | D38: g/cm3
B40: Outer Sheath
B41: Material | C41: PVC
B42: Minimum Thickness | C42: 2 | D42: mm
B43: Calculated diameter below outersheath | C43: =C46-(2*C42) -> 24.5 | D43: mm
B44: Density of Conductor | C44: =VLOOKUP(C41,Density,2,0) -> 1.35 | D44: g/cm3
B46: Overall OD of Cable | C46: 28.5
A48: ="COST SHEET FOR "&C6 & " CORE "&C9&" SQMM "&C10&" CABLE" -> COST SHEET FOR 1 CORE 300 SQMM Aluminium CABLE
A50: ASSUMPTIONS | G50: CALCULATION - SCENARIO 1
B52: Wastage Assumptions | H52: Material Cost Estimation | J52: Loading | K52: %
B53: =C10 -> Aluminium | C53: 0.02 | H53: ="Cost of"&" "&C10 -> Cost of Aluminium | L53: Rs | M53: =D67*C60 -> 106703.73
B54: Steel | C54: 0.02 | H54: Cost of PVC | L54: Rs | M54: =IF(C17="PVC",(D68+D69+D70+D72)*C61,(D69+D70+D72)*C61) -> 17302.587
B55: PVC | C55: 0.025 | H55: Cost of Steel | L55: Rs | M55: =D71*C62 -> 0
B56: XLPE | C56: 0.025 | H56: Cost of XLPE | L56: Rs | M56: =IF(C17="XLPE",D68*C63,0) -> 10365.342
H57: Material Cost per Km | L57: Rs | M57: =M53+M54+M55+M56 -> 134371.66
B58: Price Assumptions
B59: Material | C59: Rs/Kg | H59: Other Costs as a % of Total Cost
B60: =C10 -> Aluminium | C60: =VLOOKUP(B60,'Data Input'!$M$3:$N$6,2,0) -> 129.15 | H60: Other Manufacturing Costs | L60: Rs | M60: =C78/$C$77*$M$57 -> 7904.2152
B61: PVC | C61: =VLOOKUP(B61,'Data Input'!$M$3:$N$6,2,0) -> 75.075 | H61: Energy Cost | L61: Rs | M61: =M57/C77*C79 -> 4742.5291
B62: Steel Wire | C62: =VLOOKUP(B62,'Data Input'!$M$3:$N$6,2,0) -> 42 | H62: Labour Cost | L62: Rs | M62: =$M$57/$C$77*C80 -> 3161.6861
B63: XLPE | C63: =(1+E63)*C61 -> 90.09 | D63: 20% over PVC | E63: 0.2 | H63: Administrative and Other Expenses | L63: Rs | M63: =$M$57/$C$77*C81 -> 4742.5291
H64: Overheads and Finance Costs | L64: Rs | M64: =$M$57/$C$77*C82 -> 3161.6861
B65: Material Composition Estimates per Km of Cable | H65: Total Costs | L65: Rs | M65: =SUM(M60:M64)+M57 -> 158084.3
B66: =C6&" core"&" "&C9&" sq.mm"&" "&C10&" cable" -> 1 core 300 sq.mm Aluminium cable | C66: Used in Cable (Kg) | D66: Including Wastage (Kg)
B67: ="Weight of"&" "&C10 -> Weight of Aluminium | C67: =(C9*10^-3*C14*10^3*IF(C6=3.5,3,C6))+(C9*10^-3*C14*10^3*IF(C6=3.5,1,0)) -> 810 | D67: =C67*(1+C53) -> 826.2 | H67: Special Construction costs
B68: Weight of Insulation | C68: =IF(C6=3.5,((C11/360)*PI()*(C19^2-C13^2)*C20*3)+((C12/360)*PI()*(C19^2-C13^2)*C20),(C11/360)*PI()*(C19^2-C13^2)*C20*C6) -> 112.24918 | D68: =C68*(1+C55) -> 115.05541 | H68: FRLS PVC inner sheath construction cost | J68: Y | K68: 0.025 | L68: Rs | M68: =IF(J68="Y",K68*$M$65,0) -> 3952.1076
B69: Weight of Inner Sheath | C69: =PI()*($C$37^2-$C$31^2)/4*$C$32 -> 0 | D69: =C69*(1+C55) -> 0 | H69: FRLS PVC outer sheath construction cost | J69: Y | K69: 0.025 | L69: Rs | M69: =IF(J69="Y",K69*$M$65,0) -> 3952.1076
B70: Weight of Outer Sheath | C70: =PI()*($C$46^2-$C$43^2)/4*$C$44 -> 224.78095 | D70: =C70*(1+C55) -> 230.40048 | H70: LSZH Inner sheath construction cost | J70: N | K70: 0.1 | L70: Rs | M70: =IF(J70="Y",K70*$M$65,0) -> 0
B71: Weight of Armour | C71: =PI()*($C$43^2-$C$37^2)/4*$C$38 -> 0 | D71: =C71*(1+C54) -> 0 | H71: LSZH outersheath construction cost | J71: N | K71: 0.1 | L71: Rs | M71: =IF(J71="Y",K71*$M$65,0) -> 0
B72: Weight of PVC Filler | C72: =(C24-C25)*C26/1000 -> 0.068495224 | D72: =C72*(1+C55) -> 0.070207605 | H72: Oxygen Index(Outer sheath) | J72: N | K72: 0.025 | L72: Rs | M72: =IF(J72="Y",K72*$M$65,0) -> 0
H73: HRPVC Inner Sheath | J73: N | K73: 0.02 | L73: Rs | M73: =IF(J73="Y",K73*$M$65,0) -> 0
H74: HRPVC Outer Sheath | J74: N | K74: 0.02 | L74: Rs | M74: =IF(J74="Y",K74*$M$65,0) -> 0
H75: Extruded PVC Inner sheath- Upto 50 sq.mm | J75: N | K75: 0.03 | L75: Rs | M75: =IF(J75="Y",K75*$M$65,0) -> 0
B76: Costs as a % of Material Cost | C76: % | H76: Extruded PVC Inner sheath-70 sq.mm | J76: N | K76: 0.025 | L76: Rs | M76: =IF(J76="Y",K76*$M$65,0) -> 0
B77: Material Costs | C77: 0.85 | H77: Stranding of Conductor | J77: N | K77: 0.015 | L77: Rs | M77: =IF(J77="Y",K77*$M$65,0) -> 0
B78: Other Manufacturing expenses | C78: 0.05 | H78: Total Cable Costs | L78: Rs | M78: =M65+SUM(M68:M77) -> 165988.52
B79: Energy Costs | C79: 0.03
B80: Labour Costs | C80: 0.02 | H80: Selling Price | M80: =M78*(1+C84) -> 178437.66
B81: Administrative and Other expenses | C81: 0.03
B82: Overheads and Finance Costs | C82: 0.02
B84: Margins | C84: 0.075

Sheet Al LT Cables (1 x 630)
B2: ="Cost Sheet for"&" "&C6&" Core"&" "&C9&" sq.mm"&" "&C10&" Cable" -> Cost Sheet for 1 Core 630 sq.mm Aluminium Cable
B4: Data Inputs
B6: No. of cores | C6: 1
B7: Shape of the core | C7: Circular
B8: Conductor
B9: Conductor Size (in sq. mm) | C9: 630 | D9: sq. mm
B10: Conductor Material | C10: Aluminium | L10: =2*L9 -> 0
B11: Angle - Main | C11: =IF(C7="Sector shaped", (360/C6),360) -> 360
B12: Angle - Main | C12: =IF(C7="Sector shaped",360-C11*3,0) -> 0
B13: Conductor Radius | C13: =SQRT((C9*(360/C11))/PI()) -> 14.161046 | D13: mm
B14: Density of Conductor | C14: =VLOOKUP(C10,Density1,2,0) -> 2.7 | D14: g/cm3
B16: Insulation
B17: Material | C17: XLPE
B18: Nominal thickness of insulation | C18: 2.4
B19: Calculated radius over insulation | C19: =IF(C7="Circular", C13+C18,C13+2*C18) -> 16.561046 | D19: mm
B20: Density of Conductor | C20: =VLOOKUP(C17,Density,2,0) -> 0.93 | D20: g/cm3
B22: PVC Filler
B23: Filler Type | C23: PVC
B24: Area below inner sheath | C24: =PI()*((C31/2)^2) -> 995.38222 | D24: mm2
B25: Area till insulation | C25: =IF(C6=3.5,((C11/360)*PI()*(C19^2)*3)+((C12/360)*PI()*(C19^2)),(C11/360)*PI()*(C19^2)*C6) -> 861.63912 | D25: mm2
B26: Density | C26: =VLOOKUP(C23,Density,2,0) -> 1.35 | D26: g/cm3
B28: Inner Sheath
B29: Material | C29: PVC
B30: Minimum Thickness | C30: 0 | D30: mm
B31: Calculated diameter below innersheath | C31: =C37-2*C30 -> 35.6 | D31: mm
B32: Density of Conductor | C32: =VLOOKUP(C29,Density,2,0) -> 1.35 | D32: g/cm3
B34: Armour
B35: Material | C35: Unarmored
B36: Thickness of armour | C36: 0 | D36: mm
B37: Calculated diameter below armor | C37: =C43-2*C36 -> 35.6 | D37: mm
B38: Density of Conductor | C38: =VLOOKUP(C35,Armordensity,2,0) -> 0 | D38: g/cm3
B40: Outer Sheath
B41: Material | C41: PVC
B42: Minimum Thickness | C42: 2.2 | D42: mm
B43: Calculated diameter below outersheath | C43: =C46-(2*C42) -> 35.6 | D43: mm
B44: Density of Conductor | C44: =VLOOKUP(C41,Density,2,0) -> 1.35 | D44: g/cm3
B46: Overall OD of Cable | C46: 40
A48: ="COST SHEET FOR "&C6 & " CORE "&C9&" SQMM "&C10&" CABLE" -> COST SHEET FOR 1 CORE 630 SQMM Aluminium CABLE
A50: ASSUMPTIONS | G50: CALCULATION - SCENARIO 1
B52: Wastage Assumptions | H52: Material Cost Estimation | J52: Loading | K52: %
B53: =C10 -> Aluminium | C53: 0.02 | H53: ="Cost of"&" "&C10 -> Cost of Aluminium | L53: Rs | M53: =D67*C60 -> 224077.83
B54: Steel | C54: 0.02 | H54: Cost of PVC | L54: Rs | M54: =IF(C17="PVC",(D68+D69+D70+D72)*C61,(D69+D70+D72)*C61) -> 27154.362
B55: PVC | C55: 0.025 | H55: Cost of Steel | L55: Rs | M55: =D71*C62 -> 0
B56: XLPE | C56: 0.025 | H56: Cost of XLPE | L56: Rs | M56: =IF(C17="XLPE",D68*C63,0) -> 19892.772
H57: Material Cost per Km | L57: Rs | M57: =M53+M54+M55+M56 -> 271124.97
B58: Price Assumptions
B59: Material | C59: Rs/Kg | H59: Other Costs as a % of Total Cost
B60: =C10 -> Aluminium | C60: =VLOOKUP(B60,'Data Input'!$M$3:$N$6,2,0) -> 129.15 | H60: Other Manufacturing Costs | L60: Rs | M60: =C78/$C$77*$M$57 -> 15948.527
B61: PVC | C61: =VLOOKUP(B61,'Data Input'!$M$3:$N$6,2,0) -> 75.075 | H61: Energy Cost | L61: Rs | M61: =M57/C77*C79 -> 9569.1165
B62: Steel Wire | C62: =VLOOKUP(B62,'Data Input'!$M$3:$N$6,2,0) -> 42 | H62: Labour Cost | L62: Rs | M62: =$M$57/$C$77*C80 -> 6379.411
B63: XLPE | C63: =(1+E63)*C61 -> 90.09 | D63: 20% over PVC | E63: 0.2 | H63: Administrative and Other Expenses | L63: Rs | M63: =$M$57/$C$77*C81 -> 9569.1165
H64: Overheads and Finance Costs | L64: Rs | M64: =$M$57/$C$77*C82 -> 6379.411
B65: Material Composition Estimates per Km of Cable | H65: Total Costs | L65: Rs | M65: =SUM(M60:M64)+M57 -> 318970.55
B66: =C6&" core"&" "&C9&" sq.mm"&" "&C10&" cable" -> 1 core 630 sq.mm Aluminium cable | C66: Used in Cable (Kg) | D66: Including Wastage (Kg)
B67: ="Weight of"&" "&C10 -> Weight of Aluminium | C67: =(C9*10^-3*C14*10^3*IF(C6=3.5,3,C6))+(C9*10^-3*C14*10^3*IF(C6=3.5,1,0)) -> 1701 | D67: =C67*(1+C53) -> 1735.02 | H67: Special Construction costs
B68: Weight of Insulation | C68: =IF(C6=3.5,((C11/360)*PI()*(C19^2-C13^2)*C20*3)+((C12/360)*PI()*(C19^2-C13^2)*C20),(C11/360)*PI()*(C19^2-C13^2)*C20*C6) -> 215.42438 | D68: =C68*(1+C55) -> 220.80999 | H68: FRLS PVC inner sheath construction cost | J68: Y | K68: 0.025 | L68: Rs | M68: =IF(J68="Y",K68*$M$65,0) -> 7974.2637
B69: Weight of Inner Sheath | C69: =PI()*($C$37^2-$C$31^2)/4*$C$32 -> 0 | D69: =C69*(1+C55) -> 0 | H69: FRLS PVC outer sheath construction cost | J69: Y | K69: 0.025 | L69: Rs | M69: =IF(J69="Y",K69*$M$65,0) -> 7974.2637
B70: Weight of Outer Sheath | C70: =PI()*($C$46^2-$C$43^2)/4*$C$44 -> 352.69404 | D70: =C70*(1+C55) -> 361.51139 | H70: LSZH Inner sheath construction cost | J70: N | K70: 0.1 | L70: Rs | M70: =IF(J70="Y",K70*$M$65,0) -> 0
B71: Weight of Armour | C71: =PI()*($C$43^2-$C$37^2)/4*$C$38 -> 0 | D71: =C71*(1+C54) -> 0 | H71: LSZH outersheath construction cost | J71: N | K71: 0.1 | L71: Rs | M71: =IF(J71="Y",K71*$M$65,0) -> 0
B72: Weight of PVC Filler | C72: =(C24-C25)*C26/1000 -> 0.18055318 | D72: =C72*(1+C55) -> 0.18506701 | H72: Oxygen Index(Outer sheath) | J72: N | K72: 0.025 | L72: Rs | M72: =IF(J72="Y",K72*$M$65,0) -> 0
H73: HRPVC Inner Sheath | J73: N | K73: 0.02 | L73: Rs | M73: =IF(J73="Y",K73*$M$65,0) -> 0
H74: HRPVC Outer Sheath | J74: N | K74: 0.02 | L74: Rs | M74: =IF(J74="Y",K74*$M$65,0) -> 0
H75: Extruded PVC Inner sheath- Upto 50 sq.mm | J75: N | K75: 0.03 | L75: Rs | M75: =IF(J75="Y",K75*$M$65,0) -> 0
B76: Costs as a % of Material Cost | C76: % | H76: Extruded PVC Inner sheath-70 sq.mm | J76: N | K76: 0.025 | L76: Rs | M76: =IF(J76="Y",K76*$M$65,0) -> 0
B77: Material Costs | C77: 0.85 | H77: Stranding of Conductor | J77: N | K77: 0.015 | L77: Rs | M77: =IF(J77="Y",K77*$M$65,0) -> 0
B78: Other Manufacturing expenses | C78: 0.05 | H78: Total Cable Costs | L78: Rs | M78: =M65+SUM(M68:M77) -> 334919.08
B79: Energy Costs | C79: 0.03
B80: Labour Costs | C80: 0.02 | H80: Selling Price | M80: =M78*(1+C84) -> 360038.01
B81: Administrative and Other expenses | C81: 0.03
B82: Overheads and Finance Costs | C82: 0.02
B84: Margins | C84: 0.075

Sheet Cu LT Cables (1 x 630)
B1: =#REF! -> #REF! | C1: =SUM(D67:D72) -> 6327.3504
B2: ="Cost Sheet for"&" "&C6&" Core"&" "&C9&" sq.mm"&" "&C10&" Cable" -> Cost Sheet for 1 Core 630 sq.mm Copper Cable
B4: Data Inputs
B6: No. of cores | C6: 1
B7: Shape of the core | C7: Circular
B8: Conductor
B9: Conductor Size (in sq. mm) | C9: 630 | D9: sq. mm
B10: Conductor Material | C10: Copper
B11: Angle - Main | C11: =IF(C7="Sector shaped", (360/C6),360) -> 360
B12: Angle - Main | C12: =IF(C7="Sector shaped",360-C11*3,0) -> 0
B13: Conductor Radius | C13: =SQRT((C9*(360/C11))/PI()) -> 14.161046 | D13: mm
B14: Density of Conductor | C14: =VLOOKUP(C10,Density1,2,0) -> 8.94 | D14: g/cm3
B16: Insulation
B17: Material | C17: XLPE
B18: Nominal thickness of insulation | C18: 2.4
B19: Calculated radius over insulation | C19: =IF(C7="Circular", C13+C18,C13+2*C18) -> 16.561046 | D19: mm
B20: Density of Conductor | C20: =VLOOKUP(C17,Density,2,0) -> 0.93 | D20: g/cm3
B22: PVC Filler
B23: Filler Type | C23: PVC
B24: Area below inner sheath | C24: =PI()*((C31/2)^2) -> 995.38222 | D24: mm2
B25: Area till insulation | C25: =IF(C6=3.5,((C11/360)*PI()*(C19^2)*3)+((C12/360)*PI()*(C19^2)),(C11/360)*PI()*(C19^2)*C6) -> 861.63912 | D25: mm2
B26: Density | C26: =VLOOKUP(C23,Density,2,0) -> 1.35 | D26: g/cm3
B28: Inner Sheath
B29: Material | C29: PVC
B30: Minimum Thickness | C30: 0 | D30: mm
B31: Calculated diameter below innersheath | C31: =C37-2*C30 -> 35.6 | D31: mm
B32: Density of Conductor | C32: =VLOOKUP(C29,Density,2,0) -> 1.35 | D32: g/cm3
B34: Armour
B35: Material | C35: Unarmored
B36: Thickness of armour | C36: 0 | D36: mm
B37: Calculated diameter below armor | C37: =C43-2*C36 -> 35.6 | D37: mm
B38: Density of Conductor | C38: =VLOOKUP(C35,Armordensity,2,0) -> 0 | D38: g/cm3
B40: Outer Sheath
B41: Material | C41: PVC
B42: Minimum Thickness | C42: 2.2 | D42: mm
B43: Calculated diameter below outersheath | C43: =C46-(2*C42) -> 35.6 | D43: mm
B44: Density of Conductor | C44: =VLOOKUP(C41,Density,2,0) -> 1.35 | D44: g/cm3
B46: Overall OD of Cable | C46: 40
A48: ="COST SHEET FOR "&C6 & " CORE "&C9&" SQMM "&C10&" CABLE" -> COST SHEET FOR 1 CORE 630 SQMM Copper CABLE
A50: ASSUMPTIONS | G50: CALCULATION - SCENARIO 1
B52: Wastage Assumptions | H52: Material Cost Estimation | J52: Loading | K52: %
B53: =C10 -> Copper | C53: 0.02 | H53: ="Cost of"&" "&C10 -> Cost of Copper | L53: Rs | M53: =D67*C60 -> 2223173.6
B54: Steel | C54: 0.02 | H54: Cost of PVC | L54: Rs | M54: =IF(C17="PVC",(D68+D69+D70+D72)*C61,(D69+D70+D72)*C61) -> 27154.362
B55: PVC | C55: 0.025 | H55: Cost of Steel | L55: Rs | M55: =D71*C62 -> 0
B56: XLPE | C56: 0.025 | H56: Cost of XLPE | L56: Rs | M56: =IF(C17="XLPE",D68*C63,0) -> 19892.772
H57: Material Cost per Km | L57: Rs | M57: =M53+M54+M55+M56 -> 2270220.8
B58: Price Assumptions
B59: Material | C59: Rs/Kg | H59: Other Costs as a % of Total Cost
B60: =C10 -> Copper | C60: =VLOOKUP(B60,'Data Input'!$M$3:$N$6,2,0) -> 386.9859 | H60: Other Manufacturing Costs | L60: Rs | M60: =C78/$C$77*$M$57 -> 133542.4
B61: PVC | C61: =VLOOKUP(B61,'Data Input'!$M$3:$N$6,2,0) -> 75.075 | H61: Energy Cost | L61: Rs | M61: =M57/C77*C79 -> 80125.439
B62: Steel Wire | C62: =VLOOKUP(B62,'Data Input'!$M$3:$N$6,2,0) -> 42 | H62: Labour Cost | L62: Rs | M62: =$M$57/$C$77*C80 -> 53416.959
B63: XLPE | C63: =(1+E63)*C61 -> 90.09 | D63: 20% over PVC | E63: 0.2 | H63: Administrative and Other Expenses | L63: Rs | M63: =$M$57/$C$77*C81 -> 80125.439
H64: Overheads and Finance Costs | L64: Rs | M64: =$M$57/$C$77*C82 -> 53416.959
B65: Material Composition Estimates per Km of Cable | H65: Total Costs | L65: Rs | M65: =SUM(M60:M64)+M57 -> 2670848
B66: =C6&" core"&" "&C9&" sq.mm"&" "&C10&" cable" -> 1 core 630 sq.mm Copper cable | C66: Used in Cable (Kg) | D66: Including Wastage (Kg)
B67: ="Weight of"&" "&C10 -> Weight of Copper | C67: =(C9*10^-3*C14*10^3*IF(C6=3.5,3,C6))+(C9*10^-3*C14*10^3*IF(C6=3.5,1,0)) -> 5632.2 | D67: =C67*(1+C53) -> 5744.844 | H67: Special Construction costs
B68: Weight of Insulation | C68: =IF(C6=3.5,((C11/360)*PI()*(C19^2-C13^2)*C20*3)+((C12/360)*PI()*(C19^2-C13^2)*C20),(C11/360)*PI()*(C19^2-C13^2)*C20*C6) -> 215.42438 | D68: =C68*(1+C55) -> 220.80999 | H68: FRLS PVC inner sheath construction cost | J68: Y | K68: 0.025 | L68: Rs | M68: =IF(J68="Y",K68*$M$65,0) -> 66771.199
B69: Weight of Inner Sheath | C69: =PI()*($C$37^2-$C$31^2)/4*$C$32 -> 0 | D69: =C69*(1+C55) -> 0 | H69: FRLS PVC outer sheath construction cost | J69: Y | K69: 0.025 | L69: Rs | M69: =IF(J69="Y",K69*$M$65,0) -> 66771.199
B70: Weight of Outer Sheath | C70: =PI()*($C$46^2-$C$43^2)/4*$C$44 -> 352.69404 | D70: =C70*(1+C55) -> 361.51139 | H70: LSZH Inner sheath construction cost | J70: N | K70: 0.1 | L70: Rs | M70: =IF(J70="Y",K70*$M$65,0) -> 0
B71: Weight of Armour | C71: =PI()*($C$43^2-$C$37^2)/4*$C$38 -> 0 | D71: =C71*(1+C54) -> 0 | H71: LSZH outersheath construction cost | J71: N | K71: 0.1 | L71: Rs | M71: =IF(J71="Y",K71*$M$65,0) -> 0
B72: Weight of PVC Filler | C72: =(C24-C25)*C26/1000 -> 0.18055318 | D72: =C72*(1+C55) -> 0.18506701 | H72: Oxygen Index(Outer sheath) | J72: N | K72: 0.025 | L72: Rs | M72: =IF(J72="Y",K72*$M$65,0) -> 0
H73: HRPVC Insulation | J73: N | K73: 0.02 | L73: Rs | M73: =IF(J73="Y",K73*$M$65,0) -> 0
H74: HRPVC Inner Sheath | J74: N | K74: 0.02 | L74: Rs | M74: =IF(J74="Y",K74*$M$65,0) -> 0
H75: HRPVC Outer Sheath | J75: N | K75: 0.02 | L75: Rs | M75: =IF(J75="Y",K75*$M$65,0) -> 0
B76: Costs as a % of Material Cost | C76: % | H76: Extruded PVC Inner sheath | J76: N | K76: 0.03 | L76: Rs | M76: =IF(J76="Y",K76*$M$65,0) -> 0
B77: Material Costs | C77: 0.85 | H77: Stranding of Conductor | J77: N | K77: 0.015 | L77: Rs | M77: =IF(J77="Y",K77*$M$65,0) -> 0
B78: Other Manufacturing expenses | C78: 0.05 | H78: Total Cable Costs | L78: Rs | M78: =M65+SUM(M68:M77) -> 2804390.3
B79: Energy Costs | C79: 0.03
B80: Labour Costs | C80: 0.02 | H80: Selling Price | M80: =M78*(1+C84) -> 3014719.6
B81: Administrative and Other expenses | C81: 0.03
B82: Overheads and Finance Costs | C82: 0.02
B84: Margins | C84: 0.075

Sheet Cu LT Cables (2 x 2.5)
B1: =#REF! -> #REF! | C1: =SUM(D67:D72) -> 152.45535
B2: ="Cost Sheet for"&" "&C6&" Core"&" "&C9&" sq.mm"&" "&C10&" Cable" -> Cost Sheet for 2 Core 2.5 sq.mm Copper Cable
B4: Data Inputs
B6: No. of cores | C6: 2
B7: Shape of the core | C7: Sector shaped
B8: Conductor
B9: Conductor Size (in sq. mm) | C9: 2.5 | D9: sq. mm
B10: Conductor Material | C10: Copper
B11: Angle - Main | C11: =IF(C7="Sector shaped", (360/C6),360) -> 180
B12: Angle - Main | C12: =IF(C7="Sector shaped",360-C11*3,0) -> -180
B13: Conductor Radius | C13: =SQRT((C9*(360/C11))/PI()) -> 1.2615663 | D13: mm
B14: Density of Conductor | C14: =VLOOKUP(C10,Density1,2,0) -> 8.94 | D14: g/cm3
B16: Insulation
B17: Material | C17: XLPE
B18: Nominal thickness of insulation | C18: 0.7
B19: Calculated radius over insulation | C19: =IF(C7="Circular", C13+C18,C13+2*C18) -> 2.6615663 | D19: mm
B20: Density of Conductor | C20: =VLOOKUP(C17,Density,2,0) -> 0.93 | D20: g/cm3
B22: PVC Filler
B23: Filler Type | C23: PVC
B24: Area below inner sheath | C24: =PI()*((C31/2)^2) -> 47.783624 | D24: mm2
B25: Area till insulation | C25: =IF(C6=3.5,((C11/360)*PI()*(C19^2)*3)+((C12/360)*PI()*(C19^2)),(C11/360)*PI()*(C19^2)*C6) -> 22.254838 | D25: mm2
B26: Density | C26: =VLOOKUP(C23,Density,2,0) -> 1.35 | D26: g/cm3
B28: Inner Sheath
B29: Material | C29: PVC
B30: Minimum Thickness | C30: 0.3 | D30: mm
B31: Calculated diameter below innersheath | C31: =C37-2*C30 -> 7.8 | D31: mm
B32: Density of Conductor | C32: =VLOOKUP(C29,Density,2,0) -> 1.35 | D32: g/cm3
B34: Armour
B35: Material | C35: Unarmored
B36: Thickness of armour | C36: 0 | D36: mm
B37: Calculated diameter below armor | C37: =C43-2*C36 -> 8.4 | D37: mm
B38: Density of Conductor | C38: =VLOOKUP(C35,Armordensity,2,0) -> 0 | D38: g/cm3
B40: Outer Sheath
B41: Material | C41: PVC
B42: Minimum Thickness | C42: 1.8 | D42: mm
B43: Calculated diameter below outersheath | C43: =C46-(2*C42) -> 8.4 | D43: mm
B44: Density of Conductor | C44: =VLOOKUP(C41,Density,2,0) -> 1.35 | D44: g/cm3
B46: Overall OD of Cable | C46: 12
A48: ="COST SHEET FOR "&C6 & " CORE "&C9&" SQMM "&C10&" CABLE" -> COST SHEET FOR 2 CORE 2.5 SQMM Copper CABLE
A50: ASSUMPTIONS | G50: CALCULATION - SCENARIO 1
B52: Wastage Assumptions | H52: Material Cost Estimation | J52: Loading | K52: %
B53: =C10 -> Copper | C53: 0.02 | H53: ="Cost of"&" "&C10 -> Cost of Copper | L53: Rs | M53: =D67*C60 -> 17644.235
B54: Steel | C54: 0.02 | H54: Cost of PVC | L54: Rs | M54: =IF(C17="PVC",(D68+D69+D70+D72)*C61,(D69+D70+D72)*C61) -> 6787.769
B55: PVC | C55: 0.025 | H55: Cost of Steel | L55: Rs | M55: =D71*C62 -> 0
B56: XLPE | C56: 0.025 | H56: Cost of XLPE | L56: Rs | M56: =IF(C17="XLPE",D68*C63,0) -> 1481.816
H57: Material Cost per Km | L57: Rs | M57: =M53+M54+M55+M56 -> 25913.82
B58: Price Assumptions
B59: Material | C59: Rs/Kg | H59: Other Costs as a % of Total Cost
B60: =C10 -> Copper | C60: =VLOOKUP(B60,'Data Input'!$M$3:$N$6,2,0) -> 386.9859 | H60: Other Manufacturing Costs | L60: Rs | M60: =C78/$C$77*$M$57 -> 1524.3424
B61: PVC | C61: =VLOOKUP(B61,'Data Input'!$M$3:$N$6,2,0) -> 75.075 | H61: Energy Cost | L61: Rs | M61: =M57/C77*C79 -> 914.60542
B62: Steel Wire | C62: =VLOOKUP(B62,'Data Input'!$M$3:$N$6,2,0) -> 42 | H62: Labour Cost | L62: Rs | M62: =$M$57/$C$77*C80 -> 609.73694
B63: XLPE | C63: =(1+E63)*C61 -> 90.09 | D63: 20% over PVC | E63: 0.2 | H63: Administrative and Other Expenses | L63: Rs | M63: =$M$57/$C$77*C81 -> 914.60542
H64: Overheads and Finance Costs | L64: Rs | M64: =$M$57/$C$77*C82 -> 609.73694
B65: Material Composition Estimates per Km of Cable | H65: Total Costs | L65: Rs | M65: =SUM(M60:M64)+M57 -> 30486.847
B66: =C6&" core"&" "&C9&" sq.mm"&" "&C10&" cable" -> 2 core 2.5 sq.mm Copper cable | C66: Used in Cable (Kg) | D66: Including Wastage (Kg)
B67: ="Weight of"&" "&C10 -> Weight of Copper | C67: =(C9*10^-3*C14*10^3*IF(C6=3.5,3,C6))+(C9*10^-3*C14*10^3*IF(C6=3.5,1,0)) -> 44.7 | D67: =C67*(1+C53) -> 45.594 | H67: Special Construction costs
B68: Weight of Insulation | C68: =IF(C6=3.5,((C11/360)*PI()*(C19^2-C13^2)*C20*3)+((C12/360)*PI()*(C19^2-C13^2)*C20),(C11/360)*PI()*(C19^2-C13^2)*C20*C6) -> 16.046999 | D68: =C68*(1+C55) -> 16.448174 | H68: FRLS PVC inner sheath construction cost | J68: Y | K68: 0.025 | L68: Rs | M68: =IF(J68="Y",K68*$M$65,0) -> 762.17118
B69: Weight of Inner Sheath | C69: =PI()*($C$37^2-$C$31^2)/4*$C$32 -> 10.305995 | D69: =C69*(1+C55) -> 10.563645 | H69: FRLS PVC outer sheath construction cost | J69: Y | K69: 0.025 | L69: Rs | M69: =IF(J69="Y",K69*$M$65,0) -> 762.17118
B70: Weight of Outer Sheath | C70: =PI()*($C$46^2-$C$43^2)/4*$C$44 -> 77.867516 | D70: =C70*(1+C55) -> 79.814203 | H70: LSZH Inner sheath construction cost | J70: N | K70: 0.1 | L70: Rs | M70: =IF(J70="Y",K70*$M$65,0) -> 0
B71: Weight of Armour | C71: =PI()*($C$43^2-$C$37^2)/4*$C$38 -> 0 | D71: =C71*(1+C54) -> 0 | H71: LSZH outersheath construction cost | J71: N | K71: 0.1 | L71: Rs | M71: =IF(J71="Y",K71*$M$65,0) -> 0
B72: Weight of PVC Filler | C72: =(C24-C25)*C26/1000 -> 0.034463861 | D72: =C72*(1+C55) -> 0.035325458 | H72: Oxygen Index(Outer sheath) | J72: N | K72: 0.025 | L72: Rs | M72: =IF(J72="Y",K72*$M$65,0) -> 0
H73: HRPVC Insulation | J73: N | K73: 0.02 | L73: Rs | M73: =IF(J73="Y",K73*$M$65,0) -> 0
H74: HRPVC Inner Sheath | J74: N | K74: 0.02 | L74: Rs | M74: =IF(J74="Y",K74*$M$65,0) -> 0
H75: HRPVC Outer Sheath | J75: N | K75: 0.02 | L75: Rs | M75: =IF(J75="Y",K75*$M$65,0) -> 0
B76: Costs as a % of Material Cost | C76: % | H76: Extruded PVC Inner sheath | J76: N | K76: 0.03 | L76: Rs | M76: =IF(J76="Y",K76*$M$65,0) -> 0
B77: Material Costs | C77: 0.85 | H77: Stranding of Conductor | J77: N | K77: 0.015 | L77: Rs | M77: =IF(J77="Y",K77*$M$65,0) -> 0
B78: Other Manufacturing expenses | C78: 0.05 | H78: Total Cable Costs | L78: Rs | M78: =M65+SUM(M68:M77) -> 32011.19
B79: Energy Costs | C79: 0.03
B80: Labour Costs | C80: 0.02 | H80: Selling Price | M80: =M78*(1+C84) -> 34412.029
B81: Administrative and Other expenses | C81: 0.03
B82: Overheads and Finance Costs | C82: 0.02
B84: Margins | C84: 0.075

Sheet Al LT Cables (2 x 6)
B1: =#REF! -> #REF! | C1: =SUM(D67:D72) -> 163.99729
B2: ="Cost Sheet for"&" "&C6&" Core"&" "&C9&" sq.mm"&" "&C10&" Cable" -> Cost Sheet for 2 Core 6 sq.mm Aluminium Cable
B4: Data Inputs
B6: No. of cores | C6: 2
B7: Shape of the core | C7: Sector shaped
B8: Conductor
B9: Conductor Size (in sq. mm) | C9: 6 | D9: sq. mm
B10: Conductor Material | C10: Aluminium | L10: =2*L9 -> 0
B11: Angle - Main | C11: =IF(C7="Sector shaped", (360/C6),360) -> 180
B12: Angle - Main | C12: =IF(C7="Sector shaped",360-C11*3,0) -> -180
B13: Conductor Radius | C13: =SQRT((C9*(360/C11))/PI()) -> 1.95441 | D13: mm
B14: Density of Conductor | C14: =VLOOKUP(C10,Density1,2,0) -> 2.7 | D14: g/cm3
B16: Insulation
B17: Material | C17: XLPE
B18: Nominal thickness of insulation | C18: 0.7
B19: Calculated radius over insulation | C19: =IF(C7="Circular", C13+C18,C13+2*C18) -> 3.35441 | D19: mm
B20: Density of Conductor | C20: =VLOOKUP(C17,Density,2,0) -> 0.93 | D20: g/cm3
B22: PVC Filler
B23: Filler Type | C23: PVC
B24: Area below inner sheath | C24: =PI()*((C31/2)^2) -> 75.42964 | D24: mm2
B25: Area till insulation | C25: =IF(C6=3.5,((C11/360)*PI()*(C19^2)*3)+((C12/360)*PI()*(C19^2)),(C11/360)*PI()*(C19^2)*C6) -> 35.34941 | D25: mm2
B26: Density | C26: =VLOOKUP(C23,Density,2,0) -> 1.35 | D26: g/cm3
B28: Inner Sheath
B29: Material | C29: PVC
B30: Minimum Thickness | C30: 0.3 | D30: mm
B31: Calculated diameter below innersheath | C31: =C37-2*C30 -> 9.8 | D31: mm
B32: Density of Conductor | C32: =VLOOKUP(C29,Density,2,0) -> 1.35 | D32: g/cm3
B34: Armour
B35: Material | C35: Unarmored
B36: Thickness of armour | C36: 0 | D36: mm
B37: Calculated diameter below armor | C37: =C43-2*C36 -> 10.4 | D37: mm
B38: Density of Conductor | C38: =VLOOKUP(C35,Armordensity,2,0) -> 0 | D38: g/cm3
B40: Outer Sheath
B41: Material | C41: PVC
B42: Minimum Thickness | C42: 1.8 | D42: mm
B43: Calculated diameter below outersheath | C43: =C46-(2*C42) -> 10.4 | D43: mm
B44: Density of Conductor | C44: =VLOOKUP(C41,Density,2,0) -> 1.35 | D44: g/cm3
B46: Overall OD of Cable | C46: 14
A48: ="COST SHEET FOR "&C6 & " CORE "&C9&" SQMM "&C10&" CABLE" -> COST SHEET FOR 2 CORE 6 SQMM Aluminium CABLE
A50: ASSUMPTIONS | G50: CALCULATION - SCENARIO 1
B52: Wastage Assumptions | H52: Material Cost Estimation | J52: Loading | K52: %
B53: =C10 -> Aluminium | C53: 0.02 | H53: ="Cost of"&" "&C10 -> Cost of Aluminium | L53: Rs | M53: =D67*C60 -> 4268.1492
B54: Steel | C54: 0.02 | H54: Cost of PVC | L54: Rs | M54: =IF(C17="PVC",(D68+D69+D70+D72)*C61,(D69+D70+D72)*C61) -> 8160.0114
B55: PVC | C55: 0.025 | H55: Cost of Steel | L55: Rs | M55: =D71*C62 -> 0
B56: XLPE | C56: 0.025 | H56: Cost of XLPE | L56: Rs | M56: =IF(C17="XLPE",D68*C63,0) -> 2005.2075
H57: Material Cost per Km | L57: Rs | M57: =M53+M54+M55+M56 -> 14433.368
B58: Price Assumptions
B59: Material | C59: Rs/Kg | H59: Other Costs as a % of Total Cost
B60: =C10 -> Aluminium | C60: =VLOOKUP(B60,'Data Input'!$M$3:$N$6,2,0) -> 129.15 | H60: Other Manufacturing Costs | L60: Rs | M60: =C78/$C$77*$M$57 -> 849.02165
B61: PVC | C61: =VLOOKUP(B61,'Data Input'!$M$3:$N$6,2,0) -> 75.075 | H61: Energy Cost | L61: Rs | M61: =M57/C77*C79 -> 509.41299
B62: Steel Wire | C62: =VLOOKUP(B62,'Data Input'!$M$3:$N$6,2,0) -> 42 | H62: Labour Cost | L62: Rs | M62: =$M$57/$C$77*C80 -> 339.60866
B63: XLPE | C63: =(1+E63)*C61 -> 90.09 | D63: 20% over PVC | E63: 0.2 | H63: Administrative and Other Expenses | L63: Rs | M63: =$M$57/$C$77*C81 -> 509.41299
H64: Overheads and Finance Costs | L64: Rs | M64: =$M$57/$C$77*C82 -> 339.60866
B65: Material Composition Estimates per Km of Cable | H65: Total Costs | L65: Rs | M65: =SUM(M60:M64)+M57 -> 16980.433
B66: =C6&" core"&" "&C9&" sq.mm"&" "&C10&" cable" -> 2 core 6 sq.mm Aluminium cable | C66: Used in Cable (Kg) | D66: Including Wastage (Kg)
B67: ="Weight of"&" "&C10 -> Weight of Aluminium | C67: =(C9*10^-3*C14*10^3*IF(C6=3.5,3,C6))+(C9*10^-3*C14*10^3*IF(C6=3.5,1,0)) -> 32.4 | D67: =C67*(1+C53) -> 33.048 | H67: Special Construction costs
B68: Weight of Insulation | C68: =IF(C6=3.5,((C11/360)*PI()*(C19^2-C13^2)*C20*3)+((C12/360)*PI()*(C19^2-C13^2)*C20),(C11/360)*PI()*(C19^2-C13^2)*C20*C6) -> 21.714952 | D68: =C68*(1+C55) -> 22.257825 | H68: FRLS PVC inner sheath construction cost | J68: Y | K68: 0.025 | L68: Rs | M68: =IF(J68="Y",K68*$M$65,0) -> 424.51083
B69: Weight of Inner Sheath | C69: =PI()*($C$37^2-$C$31^2)/4*$C$32 -> 12.850685 | D69: =C69*(1+C55) -> 13.171952 | H69: FRLS PVC outer sheath construction cost | J69: Y | K69: 0.025 | L69: Rs | M69: =IF(J69="Y",K69*$M$65,0) -> 424.51083
B70: Weight of Outer Sheath | C70: =PI()*($C$46^2-$C$43^2)/4*$C$44 -> 93.135656 | D70: =C70*(1+C55) -> 95.464047 | H70: LSZH Inner sheath construction cost | J70: N | K70: 0.1 | L70: Rs | M70: =IF(J70="Y",K70*$M$65,0) -> 0
B71: Weight of Armour | C71: =PI()*($C$43^2-$C$37^2)/4*$C$38 -> 0 | D71: =C71*(1+C54) -> 0 | H71: LSZH outersheath construction cost | J71: N | K71: 0.1 | L71: Rs | M71: =IF(J71="Y",K71*$M$65,0) -> 0
B72: Weight of PVC Filler | C72: =(C24-C25)*C26/1000 -> 0.05410831 | D72: =C72*(1+C55) -> 0.055461017 | H72: Oxygen Index(Outer sheath) | J72: N | K72: 0.025 | L72: Rs | M72: =IF(J72="Y",K72*$M$65,0) -> 0
H73: HRPVC Inner Sheath | J73: N | K73: 0.02 | L73: Rs | M73: =IF(J73="Y",K73*$M$65,0) -> 0
H74: HRPVC Outer Sheath | J74: N | K74: 0.02 | L74: Rs | M74: =IF(J74="Y",K74*$M$65,0) -> 0
H75: Extruded PVC Inner sheath- Upto 50 sq.mm | J75: N | K75: 0.03 | L75: Rs | M75: =IF(J75="Y",K75*$M$65,0) -> 0
B76: Costs as a % of Material Cost | C76: % | H76: Extruded PVC Inner sheath-70 sq.mm | J76: N | K76: 0.025 | L76: Rs | M76: =IF(J76="Y",K76*$M$65,0) -> 0
B77: Material Costs | C77: 0.85 | H77: Stranding of Conductor | J77: N | K77: 0.015 | L77: Rs | M77: =IF(J77="Y",K77*$M$65,0) -> 0
B78: Other Manufacturing expenses | C78: 0.05 | H78: Total Cable Costs | L78: Rs | M78: =M65+SUM(M68:M77) -> 17829.455
B79: Energy Costs | C79: 0.03
B80: Labour Costs | C80: 0.02 | H80: Selling Price | M80: =M78*(1+C84) -> 19166.664
B81: Administrative and Other expenses | C81: 0.03
B82: Overheads and Finance Costs | C82: 0.02
B84: Margins | C84: 0.075

Sheet Al LT Cables (2 x 10)
B1: =#REF! -> #REF! | C1: =SUM(D67:D72) -> 209.08526
B2: ="Cost Sheet for"&" "&C6&" Core"&" "&C9&" sq.mm"&" "&C10&" Cable" -> Cost Sheet for 2 Core 10 sq.mm Aluminium Cable
B4: Data Inputs
B6: No. of cores | C6: 2
B7: Shape of the core | C7: Sector shaped
B8: Conductor
B9: Conductor Size (in sq. mm) | C9: 10 | D9: sq. mm
B10: Conductor Material | C10: Aluminium | L10: =2*L9 -> 0
B11: Angle - Main | C11: =IF(C7="Sector shaped", (360/C6),360) -> 180
B12: Angle - Main | C12: =IF(C7="Sector shaped",360-C11*3,0) -> -180
B13: Conductor Radius | C13: =SQRT((C9*(360/C11))/PI()) -> 2.5231325 | D13: mm
B14: Density of Conductor | C14: =VLOOKUP(C10,Density1,2,0) -> 2.7 | D14: g/cm3
B16: Insulation
B17: Material | C17: XLPE
B18: Nominal thickness of insulation | C18: 0.7
B19: Calculated radius over insulation | C19: =IF(C7="Circular", C13+C18,C13+2*C18) -> 3.9231325 | D19: mm
B20: Density of Conductor | C20: =VLOOKUP(C17,Density,2,0) -> 0.93 | D20: g/cm3
B22: PVC Filler
B23: Filler Type | C23: PVC
B24: Area below inner sheath | C24: =PI()*((C31/2)^2) -> 109.35884 | D24: mm2
B25: Area till insulation | C25: =IF(C6=3.5,((C11/360)*PI()*(C19^2)*3)+((C12/360)*PI()*(C19^2)),(C11/360)*PI()*(C19^2)*C6) -> 48.352154 | D25: mm2
B26: Density | C26: =VLOOKUP(C23,Density,2,0) -> 1.35 | D26: g/cm3
B28: Inner Sheath
B29: Material | C29: PVC
B30: Minimum Thickness | C30: 0.3 | D30: mm
B31: Calculated diameter below innersheath | C31: =C37-2*C30 -> 11.8 | D31: mm
B32: Density of Conductor | C32: =VLOOKUP(C29,Density,2,0) -> 1.35 | D32: g/cm3
B34: Armour
B35: Material | C35: Unarmored
B36: Thickness of armour | C36: 0 | D36: mm
B37: Calculated diameter below armor | C37: =C43-2*C36 -> 12.4 | D37: mm
B38: Density of Conductor | C38: =VLOOKUP(C35,Armordensity,2,0) -> 0 | D38: g/cm3
B40: Outer Sheath
B41: Material | C41: PVC
B42: Minimum Thickness | C42: 1.8 | D42: mm
B43: Calculated diameter below outersheath | C43: =C46-(2*C42) -> 12.4 | D43: mm
B44: Density of Conductor | C44: =VLOOKUP(C41,Density,2,0) -> 1.35 | D44: g/cm3
B46: Overall OD of Cable | C46: 16
A48: ="COST SHEET FOR "&C6 & " CORE "&C9&" SQMM "&C10&" CABLE" -> COST SHEET FOR 2 CORE 10 SQMM Aluminium CABLE
A50: ASSUMPTIONS | G50: CALCULATION - SCENARIO 1
B52: Wastage Assumptions | H52: Material Cost Estimation | J52: Loading | K52: %
B53: =C10 -> Aluminium | C53: 0.02 | H53: ="Cost of"&" "&C10 -> Cost of Aluminium | L53: Rs | M53: =D67*C60 -> 7113.582
B54: Steel | C54: 0.02 | H54: Cost of PVC | L54: Rs | M54: =IF(C17="PVC",(D68+D69+D70+D72)*C61,(D69+D70+D72)*C61) -> 9532.916
B55: PVC | C55: 0.025 | H55: Cost of Steel | L55: Rs | M55: =D71*C62 -> 0
B56: XLPE | C56: 0.025 | H56: Cost of XLPE | L56: Rs | M56: =IF(C17="XLPE",D68*C63,0) -> 2434.8346
H57: Material Cost per Km | L57: Rs | M57: =M53+M54+M55+M56 -> 19081.333
B58: Price Assumptions
B59: Material | C59: Rs/Kg | H59: Other Costs as a % of Total Cost
B60: =C10 -> Aluminium | C60: =VLOOKUP(B60,'Data Input'!$M$3:$N$6,2,0) -> 129.15 | H60: Other Manufacturing Costs | L60: Rs | M60: =C78/$C$77*$M$57 -> 1122.4313
B61: PVC | C61: =VLOOKUP(B61,'Data Input'!$M$3:$N$6,2,0) -> 75.075 | H61: Energy Cost | L61: Rs | M61: =M57/C77*C79 -> 673.4588
B62: Steel Wire | C62: =VLOOKUP(B62,'Data Input'!$M$3:$N$6,2,0) -> 42 | H62: Labour Cost | L62: Rs | M62: =$M$57/$C$77*C80 -> 448.97253
B63: XLPE | C63: =(1+E63)*C61 -> 90.09 | D63: 20% over PVC | E63: 0.2 | H63: Administrative and Other Expenses | L63: Rs | M63: =$M$57/$C$77*C81 -> 673.4588
H64: Overheads and Finance Costs | L64: Rs | M64: =$M$57/$C$77*C82 -> 448.97253
B65: Material Composition Estimates per Km of Cable | H65: Total Costs | L65: Rs | M65: =SUM(M60:M64)+M57 -> 22448.627
B66: =C6&" core"&" "&C9&" sq.mm"&" "&C10&" cable" -> 2 core 10 sq.mm Aluminium cable | C66: Used in Cable (Kg) | D66: Including Wastage (Kg)
B67: ="Weight of"&" "&C10 -> Weight of Aluminium | C67: =(C9*10^-3*C14*10^3*IF(C6=3.5,3,C6))+(C9*10^-3*C14*10^3*IF(C6=3.5,1,0)) -> 54 | D67: =C67*(1+C53) -> 55.08 | H67: Special Construction costs
B68: Weight of Insulation | C68: =IF(C6=3.5,((C11/360)*PI()*(C19^2-C13^2)*C20*3)+((C12/360)*PI()*(C19^2-C13^2)*C20),(C11/360)*PI()*(C19^2-C13^2)*C20*C6) -> 26.367504 | D68: =C68*(1+C55) -> 27.026691 | H68: FRLS PVC inner sheath construction cost | J68: Y | K68: 0.025 | L68: Rs | M68: =IF(J68="Y",K68*$M$65,0) -> 561.21567
B69: Weight of Inner Sheath | C69: =PI()*($C$37^2-$C$31^2)/4*$C$32 -> 15.395375 | D69: =C69*(1+C55) -> 15.780259 | H69: FRLS PVC outer sheath construction cost | J69: Y | K69: 0.025 | L69: Rs | M69: =IF(J69="Y",K69*$M$65,0) -> 561.21567
B70: Weight of Outer Sheath | C70: =PI()*($C$46^2-$C$43^2)/4*$C$44 -> 108.4038 | D70: =C70*(1+C55) -> 111.11389 | H70: LSZH Inner sheath construction cost | J70: N | K70: 0.1 | L70: Rs | M70: =IF(J70="Y",K70*$M$65,0) -> 0
B71: Weight of Armour | C71: =PI()*($C$43^2-$C$37^2)/4*$C$38 -> 0 | D71: =C71*(1+C54) -> 0 | H71: LSZH outersheath construction cost | J71: N | K71: 0.1 | L71: Rs | M71: =IF(J71="Y",K71*$M$65,0) -> 0
B72: Weight of PVC Filler | C72: =(C24-C25)*C26/1000 -> 0.082359026 | D72: =C72*(1+C55) -> 0.084418001 | H72: Oxygen Index(Outer sheath) | J72: N | K72: 0.025 | L72: Rs | M72: =IF(J72="Y",K72*$M$65,0) -> 0
H73: HRPVC Inner Sheath | J73: N | K73: 0.02 | L73: Rs | M73: =IF(J73="Y",K73*$M$65,0) -> 0
H74: HRPVC Outer Sheath | J74: N | K74: 0.02 | L74: Rs | M74: =IF(J74="Y",K74*$M$65,0) -> 0
H75: Extruded PVC Inner sheath- Upto 50 sq.mm | J75: N | K75: 0.03 | L75: Rs | M75: =IF(J75="Y",K75*$M$65,0) -> 0
B76: Costs as a % of Material Cost | C76: % | H76: Extruded PVC Inner sheath-70 sq.mm | J76: N | K76: 0.025 | L76: Rs | M76: =IF(J76="Y",K76*$M$65,0) -> 0
B77: Material Costs | C77: 0.85 | H77: Stranding of Conductor | J77: N | K77: 0.015 | L77: Rs | M77: =IF(J77="Y",K77*$M$65,0) -> 0
B78: Other Manufacturing expenses | C78: 0.05 | H78: Total Cable Costs | L78: Rs | M78: =M65+SUM(M68:M77) -> 23571.058
B79: Energy Costs | C79: 0.03
B80: Labour Costs | C80: 0.02 | H80: Selling Price | M80: =M78*(1+C84) -> 25338.887
B81: Administrative and Other expenses | C81: 0.03
B82: Overheads and Finance Costs | C82: 0.02
B84: Margins | C84: 0.075

Sheet Al LT Cables (2 x 16)
B1: =#REF! -> #REF! | C1: =SUM(D67:D72) -> 238.55961
B2: ="Cost Sheet for"&" "&C6&" Core"&" "&C9&" sq.mm"&" "&C10&" Cable" -> Cost Sheet for 2 Core 16 sq.mm Aluminium Cable
B4: Data Inputs
B6: No. of cores | C6: 2
B7: Shape of the core | C7: Sector shaped
B8: Conductor
B9: Conductor Size (in sq. mm) | C9: 16 | D9: sq. mm
B10: Conductor Material | C10: Aluminium | L10: =2*L9 -> 0
B11: Angle - Main | C11: =IF(C7="Sector shaped", (360/C6),360) -> 180
B12: Angle - Main | C12: =IF(C7="Sector shaped",360-C11*3,0) -> -180
B13: Conductor Radius | C13: =SQRT((C9*(360/C11))/PI()) -> 3.1915382 | D13: mm
B14: Density of Conductor | C14: =VLOOKUP(C10,Density1,2,0) -> 2.7 | D14: g/cm3
B16: Insulation
B17: Material | C17: XLPE
B18: Nominal thickness of insulation | C18: 0.7
B19: Calculated radius over insulation | C19: =IF(C7="Circular", C13+C18,C13+2*C18) -> 4.5915382 | D19: mm
B20: Density of Conductor | C20: =VLOOKUP(C17,Density,2,0) -> 0.93 | D20: g/cm3
B22: PVC Filler
B23: Filler Type | C23: PVC
B24: Area below inner sheath | C24: =PI()*((C31/2)^2) -> 91.608842 | D24: mm2
B25: Area till insulation | C25: =IF(C6=3.5,((C11/360)*PI()*(C19^2)*3)+((C12/360)*PI()*(C19^2)),(C11/360)*PI()*(C19^2)*C6) -> 66.231758 | D25: mm2
B26: Density | C26: =VLOOKUP(C23,Density,2,0) -> 1.35 | D26: g/cm3
B28: Inner Sheath
B29: Material | C29: PVC
B30: Minimum Thickness | C30: 0.3 | D30: mm
B31: Calculated diameter below innersheath | C31: =C37-2*C30 -> 10.8 | D31: mm
B32: Density of Conductor | C32: =VLOOKUP(C29,Density,2,0) -> 1.35 | D32: g/cm3
B34: Armour
B35: Material | C35: Unarmored
B36: Thickness of armour | C36: 0 | D36: mm
B37: Calculated diameter below armor | C37: =C43-2*C36 -> 11.4 | D37: mm
B38: Density of Conductor | C38: =VLOOKUP(C35,Armordensity,2,0) -> 0 | D38: g/cm3
B40: Outer Sheath
B41: Material | C41: PVC
B42: Minimum Thickness | C42: 1.8 | D42: mm
B43: Calculated diameter below outersheath | C43: =C46-(2*C42) -> 11.4 | D43: mm
B44: Density of Conductor | C44: =VLOOKUP(C41,Density,2,0) -> 1.35 | D44: g/cm3
B46: Overall OD of Cable | C46: 15
A48: ="COST SHEET FOR "&C6 & " CORE "&C9&" SQMM "&C10&" CABLE" -> COST SHEET FOR 2 CORE 16 SQMM Aluminium CABLE
A50: ASSUMPTIONS | G50: CALCULATION - SCENARIO 1
B52: Wastage Assumptions | H52: Material Cost Estimation | J52: Loading | K52: %
B53: =C10 -> Aluminium | C53: 0.02 | H53: ="Cost of"&" "&C10 -> Cost of Aluminium | L53: Rs | M53: =D67*C60 -> 11381.731
B54: Steel | C54: 0.02 | H54: Cost of PVC | L54: Rs | M54: =IF(C17="PVC",(D68+D69+D70+D72)*C61,(D69+D70+D72)*C61) -> 8843.8493
B55: PVC | C55: 0.025 | H55: Cost of Steel | L55: Rs | M55: =D71*C62 -> 0
B56: XLPE | C56: 0.025 | H56: Cost of XLPE | L56: Rs | M56: =IF(C17="XLPE",D68*C63,0) -> 2939.765
H57: Material Cost per Km | L57: Rs | M57: =M53+M54+M55+M56 -> 23165.345
B58: Price Assumptions
B59: Material | C59: Rs/Kg | H59: Other Costs as a % of Total Cost
B60: =C10 -> Aluminium | C60: =VLOOKUP(B60,'Data Input'!$M$3:$N$6,2,0) -> 129.15 | H60: Other Manufacturing Costs | L60: Rs | M60: =C78/$C$77*$M$57 -> 1362.6674
B61: PVC | C61: =VLOOKUP(B61,'Data Input'!$M$3:$N$6,2,0) -> 75.075 | H61: Energy Cost | L61: Rs | M61: =M57/C77*C79 -> 817.60043
B62: Steel Wire | C62: =VLOOKUP(B62,'Data Input'!$M$3:$N$6,2,0) -> 42 | H62: Labour Cost | L62: Rs | M62: =$M$57/$C$77*C80 -> 545.06695
B63: XLPE | C63: =(1+E63)*C61 -> 90.09 | D63: 20% over PVC | E63: 0.2 | H63: Administrative and Other Expenses | L63: Rs | M63: =$M$57/$C$77*C81 -> 817.60043
H64: Overheads and Finance Costs | L64: Rs | M64: =$M$57/$C$77*C82 -> 545.06695
B65: Material Composition Estimates per Km of Cable | H65: Total Costs | L65: Rs | M65: =SUM(M60:M64)+M57 -> 27253.348
B66: =C6&" core"&" "&C9&" sq.mm"&" "&C10&" cable" -> 2 core 16 sq.mm Aluminium cable | C66: Used in Cable (Kg) | D66: Including Wastage (Kg)
B67: ="Weight of"&" "&C10 -> Weight of Aluminium | C67: =(C9*10^-3*C14*10^3*IF(C6=3.5,3,C6))+(C9*10^-3*C14*10^3*IF(C6=3.5,1,0)) -> 86.4 | D67: =C67*(1+C53) -> 88.128 | H67: Special Construction costs
B68: Weight of Insulation | C68: =IF(C6=3.5,((C11/360)*PI()*(C19^2-C13^2)*C20*3)+((C12/360)*PI()*(C19^2-C13^2)*C20),(C11/360)*PI()*(C19^2-C13^2)*C20*C6) -> 31.835535 | D68: =C68*(1+C55) -> 32.631424 | H68: FRLS PVC inner sheath construction cost | J68: Y | K68: 0.025 | L68: Rs | M68: =IF(J68="Y",K68*$M$65,0) -> 681.33369
B69: Weight of Inner Sheath | C69: =PI()*($C$37^2-$C$31^2)/4*$C$32 -> 14.12303 | D69: =C69*(1+C55) -> 14.476106 | H69: FRLS PVC outer sheath construction cost | J69: Y | K69: 0.025 | L69: Rs | M69: =IF(J69="Y",K69*$M$65,0) -> 681.33369
B70: Weight of Outer Sheath | C70: =PI()*($C$46^2-$C$43^2)/4*$C$44 -> 100.76973 | D70: =C70*(1+C55) -> 103.28897 | H70: LSZH Inner sheath construction cost | J70: N | K70: 0.1 | L70: Rs | M70: =IF(J70="Y",K70*$M$65,0) -> 0
B71: Weight of Armour | C71: =PI()*($C$43^2-$C$37^2)/4*$C$38 -> 0 | D71: =C71*(1+C54) -> 0 | H71: LSZH outersheath construction cost | J71: N | K71: 0.1 | L71: Rs | M71: =IF(J71="Y",K71*$M$65,0) -> 0
B72: Weight of PVC Filler | C72: =(C24-C25)*C26/1000 -> 0.034259063 | D72: =C72*(1+C55) -> 0.035115539 | H72: Oxygen Index(Outer sheath) | J72: N | K72: 0.025 | L72: Rs | M72: =IF(J72="Y",K72*$M$65,0) -> 0
H73: HRPVC Inner Sheath | J73: N | K73: 0.02 | L73: Rs | M73: =IF(J73="Y",K73*$M$65,0) -> 0
H74: HRPVC Outer Sheath | J74: N | K74: 0.02 | L74: Rs | M74: =IF(J74="Y",K74*$M$65,0) -> 0
H75: Extruded PVC Inner sheath- Upto 50 sq.mm | J75: N | K75: 0.03 | L75: Rs | M75: =IF(J75="Y",K75*$M$65,0) -> 0
B76: Costs as a % of Material Cost | C76: % | H76: Extruded PVC Inner sheath-70 sq.mm | J76: N | K76: 0.025 | L76: Rs | M76: =IF(J76="Y",K76*$M$65,0) -> 0
B77: Material Costs | C77: 0.85 | H77: Stranding of Conductor | J77: N | K77: 0.015 | L77: Rs | M77: =IF(J77="Y",K77*$M$65,0) -> 0
B78: Other Manufacturing expenses | C78: 0.05 | H78: Total Cable Costs | L78: Rs | M78: =M65+SUM(M68:M77) -> 28616.015
B79: Energy Costs | C79: 0.03
B80: Labour Costs | C80: 0.02 | H80: Selling Price | M80: =M78*(1+C84) -> 30762.216
B81: Administrative and Other expenses | C81: 0.03
B82: Overheads and Finance Costs | C82: 0.02
B84: Margins | C84: 0.075

Sheet Al LT Cables (2 x 25)
B1: =#REF! -> #REF! | C1: =SUM(D67:D72) -> 347.43895
B2: ="Cost Sheet for"&" "&C6&" Core"&" "&C9&" sq.mm"&" "&C10&" Cable" -> Cost Sheet for 2 Core 25 sq.mm Aluminium Cable
B4: Data Inputs
B6: No. of cores | C6: 2
B7: Shape of the core | C7: Sector shaped
B8: Conductor
B9: Conductor Size (in sq. mm) | C9: 25 | D9: sq. mm
B10: Conductor Material | C10: Aluminium | L10: =2*L9 -> 0
B11: Angle - Main | C11: =IF(C7="Sector shaped", (360/C6),360) -> 180
B12: Angle - Main | C12: =IF(C7="Sector shaped",360-C11*3,0) -> -180
B13: Conductor Radius | C13: =SQRT((C9*(360/C11))/PI()) -> 3.9894228 | D13: mm
B14: Density of Conductor | C14: =VLOOKUP(C10,Density1,2,0) -> 2.7 | D14: g/cm3
B16: Insulation
B17: Material | C17: XLPE
B18: Nominal thickness of insulation | C18: 0.9
B19: Calculated radius over insulation | C19: =IF(C7="Circular", C13+C18,C13+2*C18) -> 5.7894228 | D19: mm
B20: Density of Conductor | C20: =VLOOKUP(C17,Density,2,0) -> 0.93 | D20: g/cm3
B22: PVC Filler
B23: Filler Type | C23: PVC
B24: Area below inner sheath | C24: =PI()*((C31/2)^2) -> 141.02609 | D24: mm2
B25: Area till insulation | C25: =IF(C6=3.5,((C11/360)*PI()*(C19^2)*3)+((C12/360)*PI()*(C19^2)),(C11/360)*PI()*(C19^2)*C6) -> 105.29807 | D25: mm2
B26: Density | C26: =VLOOKUP(C23,Density,2,0) -> 1.35 | D26: g/cm3
B28: Inner Sheath
B29: Material | C29: PVC
B30: Minimum Thickness | C30: 0.3 | D30: mm
B31: Calculated diameter below innersheath | C31: =C37-2*C30 -> 13.4 | D31: mm
B32: Density of Conductor | C32: =VLOOKUP(C29,Density,2,0) -> 1.35 | D32: g/cm3
B34: Armour
B35: Material | C35: Unarmored
B36: Thickness of armour | C36: 0 | D36: mm
B37: Calculated diameter below armor | C37: =C43-2*C36 -> 14 | D37: mm
B38: Density of Conductor | C38: =VLOOKUP(C35,Armordensity,2,0) -> 0 | D38: g/cm3
B40: Outer Sheath
B41: Material | C41: PVC
B42: Minimum Thickness | C42: 2 | D42: mm
B43: Calculated diameter below outersheath | C43: =C46-(2*C42) -> 14 | D43: mm
B44: Density of Conductor | C44: =VLOOKUP(C41,Density,2,0) -> 1.35 | D44: g/cm3
B46: Overall OD of Cable | C46: 18
A48: ="COST SHEET FOR "&C6 & " CORE "&C9&" SQMM "&C10&" CABLE" -> COST SHEET FOR 2 CORE 25 SQMM Aluminium CABLE
A50: ASSUMPTIONS | G50: CALCULATION - SCENARIO 1
B52: Wastage Assumptions | H52: Material Cost Estimation | J52: Loading | K52: %
B53: =C10 -> Aluminium | C53: 0.02 | H53: ="Cost of"&" "&C10 -> Cost of Aluminium | L53: Rs | M53: =D67*C60 -> 17783.955
B54: Steel | C54: 0.02 | H54: Cost of PVC | L54: Rs | M54: =IF(C17="PVC",(D68+D69+D70+D72)*C61,(D69+D70+D72)*C61) -> 11788.732
B55: PVC | C55: 0.025 | H55: Cost of Steel | L55: Rs | M55: =D71*C62 -> 0
B56: XLPE | C56: 0.025 | H56: Cost of XLPE | L56: Rs | M56: =IF(C17="XLPE",D68*C63,0) -> 4748.9038
H57: Material Cost per Km | L57: Rs | M57: =M53+M54+M55+M56 -> 34321.591
B58: Price Assumptions
B59: Material | C59: Rs/Kg | H59: Other Costs as a % of Total Cost
B60: =C10 -> Aluminium | C60: =VLOOKUP(B60,'Data Input'!$M$3:$N$6,2,0) -> 129.15 | H60: Other Manufacturing Costs | L60: Rs | M60: =C78/$C$77*$M$57 -> 2018.9171
B61: PVC | C61: =VLOOKUP(B61,'Data Input'!$M$3:$N$6,2,0) -> 75.075 | H61: Energy Cost | L61: Rs | M61: =M57/C77*C79 -> 1211.3503
B62: Steel Wire | C62: =VLOOKUP(B62,'Data Input'!$M$3:$N$6,2,0) -> 42 | H62: Labour Cost | L62: Rs | M62: =$M$57/$C$77*C80 -> 807.56684
B63: XLPE | C63: =(1+E63)*C61 -> 90.09 | D63: 20% over PVC | E63: 0.2 | H63: Administrative and Other Expenses | L63: Rs | M63: =$M$57/$C$77*C81 -> 1211.3503
H64: Overheads and Finance Costs | L64: Rs | M64: =$M$57/$C$77*C82 -> 807.56684
B65: Material Composition Estimates per Km of Cable | H65: Total Costs | L65: Rs | M65: =SUM(M60:M64)+M57 -> 40378.342
B66: =C6&" core"&" "&C9&" sq.mm"&" "&C10&" cable" -> 2 core 25 sq.mm Aluminium cable | C66: Used in Cable (Kg) | D66: Including Wastage (Kg)
B67: ="Weight of"&" "&C10 -> Weight of Aluminium | C67: =(C9*10^-3*C14*10^3*IF(C6=3.5,3,C6))+(C9*10^-3*C14*10^3*IF(C6=3.5,1,0)) -> 135 | D67: =C67*(1+C53) -> 137.7 | H67: Special Construction costs
B68: Weight of Insulation | C68: =IF(C6=3.5,((C11/360)*PI()*(C19^2-C13^2)*C20*3)+((C12/360)*PI()*(C19^2-C13^2)*C20),(C11/360)*PI()*(C19^2-C13^2)*C20*C6) -> 51.427204 | D68: =C68*(1+C55) -> 52.712884 | H68: FRLS PVC inner sheath construction cost | J68: Y | K68: 0.025 | L68: Rs | M68: =IF(J68="Y",K68*$M$65,0) -> 1009.4585
B69: Weight of Inner Sheath | C69: =PI()*($C$37^2-$C$31^2)/4*$C$32 -> 17.431127 | D69: =C69*(1+C55) -> 17.866905 | H69: FRLS PVC outer sheath construction cost | J69: Y | K69: 0.025 | L69: Rs | M69: =IF(J69="Y",K69*$M$65,0) -> 1009.4585
B70: Weight of Outer Sheath | C70: =PI()*($C$46^2-$C$43^2)/4*$C$44 -> 135.7168 | D70: =C70*(1+C55) -> 139.10972 | H70: LSZH Inner sheath construction cost | J70: N | K70: 0.1 | L70: Rs | M70: =IF(J70="Y",K70*$M$65,0) -> 0
B71: Weight of Armour | C71: =PI()*($C$43^2-$C$37^2)/4*$C$38 -> 0 | D71: =C71*(1+C54) -> 0 | H71: LSZH outersheath construction cost | J71: N | K71: 0.1 | L71: Rs | M71: =IF(J71="Y",K71*$M$65,0) -> 0
B72: Weight of PVC Filler | C72: =(C24-C25)*C26/1000 -> 0.048232834 | D72: =C72*(1+C55) -> 0.049438655 | H72: Oxygen Index(Outer sheath) | J72: N | K72: 0.025 | L72: Rs | M72: =IF(J72="Y",K72*$M$65,0) -> 0
H73: HRPVC Inner Sheath | J73: N | K73: 0.02 | L73: Rs | M73: =IF(J73="Y",K73*$M$65,0) -> 0
H74: HRPVC Outer Sheath | J74: N | K74: 0.02 | L74: Rs | M74: =IF(J74="Y",K74*$M$65,0) -> 0
H75: Extruded PVC Inner sheath- Upto 50 sq.mm | J75: N | K75: 0.03 | L75: Rs | M75: =IF(J75="Y",K75*$M$65,0) -> 0
B76: Costs as a % of Material Cost | C76: % | H76: Extruded PVC Inner sheath-70 sq.mm | J76: N | K76: 0.025 | L76: Rs | M76: =IF(J76="Y",K76*$M$65,0) -> 0
B77: Material Costs | C77: 0.85 | H77: Stranding of Conductor | J77: N | K77: 0.015 | L77: Rs | M77: =IF(J77="Y",K77*$M$65,0) -> 0
B78: Other Manufacturing expenses | C78: 0.05 | H78: Total Cable Costs | L78: Rs | M78: =M65+SUM(M68:M77) -> 42397.259
B79: Energy Costs | C79: 0.03
B80: Labour Costs | C80: 0.02 | H80: Selling Price | M80: =M78*(1+C84) -> 45577.054
B81: Administrative and Other expenses | C81: 0.03
B82: Overheads and Finance Costs | C82: 0.02
B84: Margins | C84: 0.075

Sheet Al LT Cables (2 x 35)
B1: =#REF! -> #REF! | C1: =SUM(D67:D72) -> 425.40385
B2: ="Cost Sheet for"&" "&C6&" Core"&" "&C9&" sq.mm"&" "&C10&" Cable" -> Cost Sheet for 2 Core 35 sq.mm Aluminium Cable
B4: Data Inputs
B6: No. of cores | C6: 2
B7: Shape of the core | C7: Sector shaped
B8: Conductor
B9: Conductor Size (in sq. mm) | C9: 35 | D9: sq. mm
B10: Conductor Material | C10: Aluminium | L10: =2*L9 -> 0
B11: Angle - Main | C11: =IF(C7="Sector shaped", (360/C6),360) -> 180
B12: Angle - Main | C12: =IF(C7="Sector shaped",360-C11*3,0) -> -180
B13: Conductor Radius | C13: =SQRT((C9*(360/C11))/PI()) -> 4.7203487 | D13: mm
B14: Density of Conductor | C14: =VLOOKUP(C10,Density1,2,0) -> 2.7 | D14: g/cm3
B16: Insulation
B17: Material | C17: XLPE
B18: Nominal thickness of insulation | C18: 0.9
B19: Calculated radius over insulation | C19: =IF(C7="Circular", C13+C18,C13+2*C18) -> 6.5203487 | D19: mm
B20: Density of Conductor | C20: =VLOOKUP(C17,Density,2,0) -> 0.93 | D20: g/cm3
B22: PVC Filler
B23: Filler Type | C23: PVC
B24: Area below inner sheath | C24: =PI()*((C31/2)^2) -> 174.36625 | D24: mm2
B25: Area till insulation | C25: =IF(C6=3.5,((C11/360)*PI()*(C19^2)*3)+((C12/360)*PI()*(C19^2)),(C11/360)*PI()*(C19^2)*C6) -> 133.56465 | D25: mm2
B26: Density | C26: =VLOOKUP(C23,Density,2,0) -> 1.35 | D26: g/cm3
B28: Inner Sheath
B29: Material | C29: PVC
B30: Minimum Thickness | C30: 0.3 | D30: mm
B31: Calculated diameter below innersheath | C31: =C37-2*C30 -> 14.9 | D31: mm
B32: Density of Conductor | C32: =VLOOKUP(C29,Density,2,0) -> 1.35 | D32: g/cm3
B34: Armour
B35: Material | C35: Unarmored
B36: Thickness of armour | C36: 0 | D36: mm
B37: Calculated diameter below armor | C37: =C43-2*C36 -> 15.5 | D37: mm
B38: Density of Conductor | C38: =VLOOKUP(C35,Armordensity,2,0) -> 0 | D38: g/cm3
B40: Outer Sheath
B41: Material | C41: PVC
B42: Minimum Thickness | C42: 2 | D42: mm
B43: Calculated diameter below outersheath | C43: =C46-(2*C42) -> 15.5 | D43: mm
B44: Density of Conductor | C44: =VLOOKUP(C41,Density,2,0) -> 1.35 | D44: g/cm3
B46: Overall OD of Cable | C46: 19.5
A48: ="COST SHEET FOR "&C6 & " CORE "&C9&" SQMM "&C10&" CABLE" -> COST SHEET FOR 2 CORE 35 SQMM Aluminium CABLE
A50: ASSUMPTIONS | G50: CALCULATION - SCENARIO 1
B52: Wastage Assumptions | H52: Material Cost Estimation | J52: Loading | K52: %
B53: =C10 -> Aluminium | C53: 0.02 | H53: ="Cost of"&" "&C10 -> Cost of Aluminium | L53: Rs | M53: =D67*C60 -> 24897.537
B54: Steel | C54: 0.02 | H54: Cost of PVC | L54: Rs | M54: =IF(C17="PVC",(D68+D69+D70+D72)*C61,(D69+D70+D72)*C61) -> 12915.216
B55: PVC | C55: 0.025 | H55: Cost of Steel | L55: Rs | M55: =D71*C62 -> 0
B56: XLPE | C56: 0.025 | H56: Cost of XLPE | L56: Rs | M56: =IF(C17="XLPE",D68*C63,0) -> 5458.8233
H57: Material Cost per Km | L57: Rs | M57: =M53+M54+M55+M56 -> 43271.577
B58: Price Assumptions
B59: Material | C59: Rs/Kg | H59: Other Costs as a % of Total Cost
B60: =C10 -> Aluminium | C60: =VLOOKUP(B60,'Data Input'!$M$3:$N$6,2,0) -> 129.15 | H60: Other Manufacturing Costs | L60: Rs | M60: =C78/$C$77*$M$57 -> 2545.3869
B61: PVC | C61: =VLOOKUP(B61,'Data Input'!$M$3:$N$6,2,0) -> 75.075 | H61: Energy Cost | L61: Rs | M61: =M57/C77*C79 -> 1527.2321
B62: Steel Wire | C62: =VLOOKUP(B62,'Data Input'!$M$3:$N$6,2,0) -> 42 | H62: Labour Cost | L62: Rs | M62: =$M$57/$C$77*C80 -> 1018.1547
B63: XLPE | C63: =(1+E63)*C61 -> 90.09 | D63: 20% over PVC | E63: 0.2 | H63: Administrative and Other Expenses | L63: Rs | M63: =$M$57/$C$77*C81 -> 1527.2321
H64: Overheads and Finance Costs | L64: Rs | M64: =$M$57/$C$77*C82 -> 1018.1547
B65: Material Composition Estimates per Km of Cable | H65: Total Costs | L65: Rs | M65: =SUM(M60:M64)+M57 -> 50907.737
B66: =C6&" core"&" "&C9&" sq.mm"&" "&C10&" cable" -> 2 core 35 sq.mm Aluminium cable | C66: Used in Cable (Kg) | D66: Including Wastage (Kg)
B67: ="Weight of"&" "&C10 -> Weight of Aluminium | C67: =(C9*10^-3*C14*10^3*IF(C6=3.5,3,C6))+(C9*10^-3*C14*10^3*IF(C6=3.5,1,0)) -> 189 | D67: =C67*(1+C53) -> 192.78 | H67: Special Construction costs
B68: Weight of Insulation | C68: =IF(C6=3.5,((C11/360)*PI()*(C19^2-C13^2)*C20*3)+((C12/360)*PI()*(C19^2-C13^2)*C20),(C11/360)*PI()*(C19^2-C13^2)*C20*C6) -> 59.115121 | D68: =C68*(1+C55) -> 60.592999 | H68: FRLS PVC inner sheath construction cost | J68: Y | K68: 0.025 | L68: Rs | M68: =IF(J68="Y",K68*$M$65,0) -> 1272.6934
B69: Weight of Inner Sheath | C69: =PI()*($C$37^2-$C$31^2)/4*$C$32 -> 19.339644 | D69: =C69*(1+C55) -> 19.823135 | H69: FRLS PVC outer sheath construction cost | J69: Y | K69: 0.025 | L69: Rs | M69: =IF(J69="Y",K69*$M$65,0) -> 1272.6934
B70: Weight of Outer Sheath | C70: =PI()*($C$46^2-$C$43^2)/4*$C$44 -> 148.44025 | D70: =C70*(1+C55) -> 152.15126 | H70: LSZH Inner sheath construction cost | J70: N | K70: 0.1 | L70: Rs | M70: =IF(J70="Y",K70*$M$65,0) -> 0
B71: Weight of Armour | C71: =PI()*($C$43^2-$C$37^2)/4*$C$38 -> 0 | D71: =C71*(1+C54) -> 0 | H71: LSZH outersheath construction cost | J71: N | K71: 0.1 | L71: Rs | M71: =IF(J71="Y",K71*$M$65,0) -> 0
B72: Weight of PVC Filler | C72: =(C24-C25)*C26/1000 -> 0.05508216 | D72: =C72*(1+C55) -> 0.056459214 | H72: Oxygen Index(Outer sheath) | J72: N | K72: 0.025 | L72: Rs | M72: =IF(J72="Y",K72*$M$65,0) -> 0
H73: HRPVC Inner Sheath | J73: N | K73: 0.02 | L73: Rs | M73: =IF(J73="Y",K73*$M$65,0) -> 0
H74: HRPVC Outer Sheath | J74: N | K74: 0.02 | L74: Rs | M74: =IF(J74="Y",K74*$M$65,0) -> 0
H75: Extruded PVC Inner sheath- Upto 50 sq.mm | J75: N | K75: 0.03 | L75: Rs | M75: =IF(J75="Y",K75*$M$65,0) -> 0
B76: Costs as a % of Material Cost | C76: % | H76: Extruded PVC Inner sheath-70 sq.mm | J76: N | K76: 0.025 | L76: Rs | M76: =IF(J76="Y",K76*$M$65,0) -> 0
B77: Material Costs | C77: 0.85 | H77: Stranding of Conductor | J77: N | K77: 0.015 | L77: Rs | M77: =IF(J77="Y",K77*$M$65,0) -> 0
B78: Other Manufacturing expenses | C78: 0.05 | H78: Total Cable Costs | L78: Rs | M78: =M65+SUM(M68:M77) -> 53453.124
B79: Energy Costs | C79: 0.03
B80: Labour Costs | C80: 0.02 | H80: Selling Price | M80: =M78*(1+C84) -> 57462.108
B81: Administrative and Other expenses | C81: 0.03
B82: Overheads and Finance Costs | C82: 0.02
B84: Margins | C84: 0.075

Sheet Al LT Cables (2 x 50)
B1: =#REF! -> #REF! | C1: =SUM(D67:D72) -> 546.99051
B2: ="Cost Sheet for"&" "&C6&" Core"&" "&C9&" sq.mm"&" "&C10&" Cable" -> Cost Sheet for 2 Core 50 sq.mm Aluminium Cable
B4: Data Inputs
B6: No. of cores | C6: 2
B7: Shape of the core | C7: Sector shaped
B8: Conductor
B9: Conductor Size (in sq. mm) | C9: 50 | D9: sq. mm
B10: Conductor Material | C10: Aluminium | L10: =2*L9 -> 0
B11: Angle - Main | C11: =IF(C7="Sector shaped", (360/C6),360) -> 180
B12: Angle - Main | C12: =IF(C7="Sector shaped",360-C11*3,0) -> -180
B13: Conductor Radius | C13: =SQRT((C9*(360/C11))/PI()) -> 5.6418958 | D13: mm
B14: Density of Conductor | C14: =VLOOKUP(C10,Density1,2,0) -> 2.7 | D14: g/cm3
B16: Insulation
B17: Material | C17: XLPE
B18: Nominal thickness of insulation | C18: 1
B19: Calculated radius over insulation | C19: =IF(C7="Circular", C13+C18,C13+2*C18) -> 7.6418958 | D19: mm
B20: Density of Conductor | C20: =VLOOKUP(C17,Density,2,0) -> 0.93 | D20: g/cm3
B22: PVC Filler
B23: Filler Type | C23: PVC
B24: Area below inner sheath | C24: =PI()*((C31/2)^2) -> 224.31757 | D24: mm2
B25: Area till insulation | C25: =IF(C6=3.5,((C11/360)*PI()*(C19^2)*3)+((C12/360)*PI()*(C19^2)),(C11/360)*PI()*(C19^2)*C6) -> 183.46452 | D25: mm2
B26: Density | C26: =VLOOKUP(C23,Density,2,0) -> 1.35 | D26: g/cm3
B28: Inner Sheath
B29: Material | C29: PVC
B30: Minimum Thickness | C30: 0.3 | D30: mm
B31: Calculated diameter below innersheath | C31: =C37-2*C30 -> 16.9 | D31: mm
B32: Density of Conductor | C32: =VLOOKUP(C29,Density,2,0) -> 1.35 | D32: g/cm3
B34: Armour
B35: Material | C35: Unarmored
B36: Thickness of armour | C36: 0 | D36: mm
B37: Calculated diameter below armor | C37: =C43-2*C36 -> 17.5 | D37: mm
B38: Density of Conductor | C38: =VLOOKUP(C35,Armordensity,2,0) -> 0 | D38: g/cm3
B40: Outer Sheath
B41: Material | C41: PVC
B42: Minimum Thickness | C42: 2 | D42: mm
B43: Calculated diameter below outersheath | C43: =C46-(2*C42) -> 17.5 | D43: mm
B44: Density of Conductor | C44: =VLOOKUP(C41,Density,2,0) -> 1.35 | D44: g/cm3
B46: Overall OD of Cable | C46: 21.5
A48: ="COST SHEET FOR "&C6 & " CORE "&C9&" SQMM "&C10&" CABLE" -> COST SHEET FOR 2 CORE 50 SQMM Aluminium CABLE
A50: ASSUMPTIONS | G50: CALCULATION - SCENARIO 1
B52: Wastage Assumptions | H52: Material Cost Estimation | J52: Loading | K52: %
B53: =C10 -> Aluminium | C53: 0.02 | H53: ="Cost of"&" "&C10 -> Cost of Aluminium | L53: Rs | M53: =D67*C60 -> 35567.91
B54: Steel | C54: 0.02 | H54: Cost of PVC | L54: Rs | M54: =IF(C17="PVC",(D68+D69+D70+D72)*C61,(D69+D70+D72)*C61) -> 14416.498
B55: PVC | C55: 0.025 | H55: Cost of Steel | L55: Rs | M55: =D71*C62 -> 0
B56: XLPE | C56: 0.025 | H56: Cost of XLPE | L56: Rs | M56: =IF(C17="XLPE",D68*C63,0) -> 7167.7909
H57: Material Cost per Km | L57: Rs | M57: =M53+M54+M55+M56 -> 57152.199
B58: Price Assumptions
B59: Material | C59: Rs/Kg | H59: Other Costs as a % of Total Cost
B60: =C10 -> Aluminium | C60: =VLOOKUP(B60,'Data Input'!$M$3:$N$6,2,0) -> 129.15 | H60: Other Manufacturing Costs | L60: Rs | M60: =C78/$C$77*$M$57 -> 3361.8941
B61: PVC | C61: =VLOOKUP(B61,'Data Input'!$M$3:$N$6,2,0) -> 75.075 | H61: Energy Cost | L61: Rs | M61: =M57/C77*C79 -> 2017.1364
B62: Steel Wire | C62: =VLOOKUP(B62,'Data Input'!$M$3:$N$6,2,0) -> 42 | H62: Labour Cost | L62: Rs | M62: =$M$57/$C$77*C80 -> 1344.7576
B63: XLPE | C63: =(1+E63)*C61 -> 90.09 | D63: 20% over PVC | E63: 0.2 | H63: Administrative and Other Expenses | L63: Rs | M63: =$M$57/$C$77*C81 -> 2017.1364
H64: Overheads and Finance Costs | L64: Rs | M64: =$M$57/$C$77*C82 -> 1344.7576
B65: Material Composition Estimates per Km of Cable | H65: Total Costs | L65: Rs | M65: =SUM(M60:M64)+M57 -> 67237.881
B66: =C6&" core"&" "&C9&" sq.mm"&" "&C10&" cable" -> 2 core 50 sq.mm Aluminium cable | C66: Used in Cable (Kg) | D66: Including Wastage (Kg)
B67: ="Weight of"&" "&C10 -> Weight of Aluminium | C67: =(C9*10^-3*C14*10^3*IF(C6=3.5,3,C6))+(C9*10^-3*C14*10^3*IF(C6=3.5,1,0)) -> 270 | D67: =C67*(1+C53) -> 275.4 | H67: Special Construction costs
B68: Weight of Insulation | C68: =IF(C6=3.5,((C11/360)*PI()*(C19^2-C13^2)*C20*3)+((C12/360)*PI()*(C19^2-C13^2)*C20),(C11/360)*PI()*(C19^2-C13^2)*C20*C6) -> 77.622008 | D68: =C68*(1+C55) -> 79.562558 | H68: FRLS PVC inner sheath construction cost | J68: Y | K68: 0.025 | L68: Rs | M68: =IF(J68="Y",K68*$M$65,0) -> 1680.947
B69: Weight of Inner Sheath | C69: =PI()*($C$37^2-$C$31^2)/4*$C$32 -> 21.884334 | D69: =C69*(1+C55) -> 22.431443 | H69: FRLS PVC outer sheath construction cost | J69: Y | K69: 0.025 | L69: Rs | M69: =IF(J69="Y",K69*$M$65,0) -> 1680.947
B70: Weight of Outer Sheath | C70: =PI()*($C$46^2-$C$43^2)/4*$C$44 -> 165.40485 | D70: =C70*(1+C55) -> 169.53997 | H70: LSZH Inner sheath construction cost | J70: N | K70: 0.1 | L70: Rs | M70: =IF(J70="Y",K70*$M$65,0) -> 0
B71: Weight of Armour | C71: =PI()*($C$43^2-$C$37^2)/4*$C$38 -> 0 | D71: =C71*(1+C54) -> 0 | H71: LSZH outersheath construction cost | J71: N | K71: 0.1 | L71: Rs | M71: =IF(J71="Y",K71*$M$65,0) -> 0
B72: Weight of PVC Filler | C72: =(C24-C25)*C26/1000 -> 0.05515161 | D72: =C72*(1+C55) -> 0.056530401 | H72: Oxygen Index(Outer sheath) | J72: N | K72: 0.025 | L72: Rs | M72: =IF(J72="Y",K72*$M$65,0) -> 0
H73: HRPVC Inner Sheath | J73: N | K73: 0.02 | L73: Rs | M73: =IF(J73="Y",K73*$M$65,0) -> 0
H74: HRPVC Outer Sheath | J74: N | K74: 0.02 | L74: Rs | M74: =IF(J74="Y",K74*$M$65,0) -> 0
H75: Extruded PVC Inner sheath- Upto 50 sq.mm | J75: N | K75: 0.03 | L75: Rs | M75: =IF(J75="Y",K75*$M$65,0) -> 0
B76: Costs as a % of Material Cost | C76: % | H76: Extruded PVC Inner sheath-70 sq.mm | J76: N | K76: 0.025 | L76: Rs | M76: =IF(J76="Y",K76*$M$65,0) -> 0
B77: Material Costs | C77: 0.85 | H77: Stranding of Conductor | J77: N | K77: 0.015 | L77: Rs | M77: =IF(J77="Y",K77*$M$65,0) -> 0
B78: Other Manufacturing expenses | C78: 0.05 | H78: Total Cable Costs | L78: Rs | M78: =M65+SUM(M68:M77) -> 70599.775
B79: Energy Costs | C79: 0.03
B80: Labour Costs | C80: 0.02 | H80: Selling Price | M80: =M78*(1+C84) -> 75894.758
B81: Administrative and Other expenses | C81: 0.03
B82: Overheads and Finance Costs | C82: 0.02
B84: Margins | C84: 0.075

Sheet Al LT Cables (2 x 70)
B1: =#REF! -> #REF! | C1: =SUM(D67:D72) -> 710.07202
B2: ="Cost Sheet for"&" "&C6&" Core"&" "&C9&" sq.mm"&" "&C10&" Cable" -> Cost Sheet for 2 Core 70 sq.mm Aluminium Cable
B4: Data Inputs
B6: No. of cores | C6: 2
B7: Shape of the core | C7: Sector shaped
B8: Conductor
B9: Conductor Size (in sq. mm) | C9: 70 | D9: sq. mm
B10: Conductor Material | C10: Aluminium | L10: =2*L9 -> 0
B11: Angle - Main | C11: =IF(C7="Sector shaped", (360/C6),360) -> 180
B12: Angle - Main | C12: =IF(C7="Sector shaped",360-C11*3,0) -> -180
B13: Conductor Radius | C13: =SQRT((C9*(360/C11))/PI()) -> 6.6755812 | D13: mm
B14: Density of Conductor | C14: =VLOOKUP(C10,Density1,2,0) -> 2.7 | D14: g/cm3
B16: Insulation
B17: Material | C17: XLPE
B18: Nominal thickness of insulation | C18: 1.1
B19: Calculated radius over insulation | C19: =IF(C7="Circular", C13+C18,C13+2*C18) -> 8.8755812 | D19: mm
B20: Density of Conductor | C20: =VLOOKUP(C17,Density,2,0) -> 0.93 | D20: g/cm3
B22: PVC Filler
B23: Filler Type | C23: PVC
B24: Area below inner sheath | C24: =PI()*((C31/2)^2) -> 311.02553 | D24: mm2
B25: Area till insulation | C25: =IF(C6=3.5,((C11/360)*PI()*(C19^2)*3)+((C12/360)*PI()*(C19^2)),(C11/360)*PI()*(C19^2)*C6) -> 247.48192 | D25: mm2
B26: Density | C26: =VLOOKUP(C23,Density,2,0) -> 1.35 | D26: g/cm3
B28: Inner Sheath
B29: Material | C29: PVC
B30: Minimum Thickness | C30: 0.3 | D30: mm
B31: Calculated diameter below innersheath | C31: =C37-2*C30 -> 19.9 | D31: mm
B32: Density of Conductor | C32: =VLOOKUP(C29,Density,2,0) -> 1.35 | D32: g/cm3
B34: Armour
B35: Material | C35: Unarmored
B36: Thickness of armour | C36: 0 | D36: mm
B37: Calculated diameter below armor | C37: =C43-2*C36 -> 20.5 | D37: mm
B38: Density of Conductor | C38: =VLOOKUP(C35,Armordensity,2,0) -> 0 | D38: g/cm3
B40: Outer Sheath
B41: Material | C41: PVC
B42: Minimum Thickness | C42: 2 | D42: mm
B43: Calculated diameter below outersheath | C43: =C46-(2*C42) -> 20.5 | D43: mm
B44: Density of Conductor | C44: =VLOOKUP(C41,Density,2,0) -> 1.35 | D44: g/cm3
B46: Overall OD of Cable | C46: 24.5
A48: ="COST SHEET FOR "&C6 & " CORE "&C9&" SQMM "&C10&" CABLE" -> COST SHEET FOR 2 CORE 70 SQMM Aluminium CABLE
A50: ASSUMPTIONS | G50: CALCULATION - SCENARIO 1
B52: Wastage Assumptions | H52: Material Cost Estimation | J52: Loading | K52: %
B53: =C10 -> Aluminium | C53: 0.02 | H53: ="Cost of"&" "&C10 -> Cost of Aluminium | L53: Rs | M53: =D67*C60 -> 49795.074
B54: Steel | C54: 0.02 | H54: Cost of PVC | L54: Rs | M54: =IF(C17="PVC",(D68+D69+D70+D72)*C61,(D69+D70+D72)*C61) -> 16670.77
B55: PVC | C55: 0.025 | H55: Cost of Steel | L55: Rs | M55: =D71*C62 -> 0
B56: XLPE | C56: 0.025 | H56: Cost of XLPE | L56: Rs | M56: =IF(C17="XLPE",D68*C63,0) -> 9230.3636
H57: Material Cost per Km | L57: Rs | M57: =M53+M54+M55+M56 -> 75696.208
B58: Price Assumptions
B59: Material | C59: Rs/Kg | H59: Other Costs as a % of Total Cost
B60: =C10 -> Aluminium | C60: =VLOOKUP(B60,'Data Input'!$M$3:$N$6,2,0) -> 129.15 | H60: Other Manufacturing Costs | L60: Rs | M60: =C78/$C$77*$M$57 -> 4452.7181
B61: PVC | C61: =VLOOKUP(B61,'Data Input'!$M$3:$N$6,2,0) -> 75.075 | H61: Energy Cost | L61: Rs | M61: =M57/C77*C79 -> 2671.6309
B62: Steel Wire | C62: =VLOOKUP(B62,'Data Input'!$M$3:$N$6,2,0) -> 42 | H62: Labour Cost | L62: Rs | M62: =$M$57/$C$77*C80 -> 1781.0872
B63: XLPE | C63: =(1+E63)*C61 -> 90.09 | D63: 20% over PVC | E63: 0.2 | H63: Administrative and Other Expenses | L63: Rs | M63: =$M$57/$C$77*C81 -> 2671.6309
H64: Overheads and Finance Costs | L64: Rs | M64: =$M$57/$C$77*C82 -> 1781.0872
B65: Material Composition Estimates per Km of Cable | H65: Total Costs | L65: Rs | M65: =SUM(M60:M64)+M57 -> 89054.362
B66: =C6&" core"&" "&C9&" sq.mm"&" "&C10&" cable" -> 2 core 70 sq.mm Aluminium cable | C66: Used in Cable (Kg) | D66: Including Wastage (Kg)
B67: ="Weight of"&" "&C10 -> Weight of Aluminium | C67: =(C9*10^-3*C14*10^3*IF(C6=3.5,3,C6))+(C9*10^-3*C14*10^3*IF(C6=3.5,1,0)) -> 378 | D67: =C67*(1+C53) -> 385.56 | H67: Special Construction costs
B68: Weight of Insulation | C68: =IF(C6=3.5,((C11/360)*PI()*(C19^2-C13^2)*C20*3)+((C12/360)*PI()*(C19^2-C13^2)*C20),(C11/360)*PI()*(C19^2-C13^2)*C20*C6) -> 99.958184 | D68: =C68*(1+C55) -> 102.45714 | H68: FRLS PVC inner sheath construction cost | J68: Y | K68: 0.025 | L68: Rs | M68: =IF(J68="Y",K68*$M$65,0) -> 2226.3591
B69: Weight of Inner Sheath | C69: =PI()*($C$37^2-$C$31^2)/4*$C$32 -> 25.701369 | D69: =C69*(1+C55) -> 26.343904 | H69: FRLS PVC outer sheath construction cost | J69: Y | K69: 0.025 | L69: Rs | M69: =IF(J69="Y",K69*$M$65,0) -> 2226.3591
B70: Weight of Outer Sheath | C70: =PI()*($C$46^2-$C$43^2)/4*$C$44 -> 190.85175 | D70: =C70*(1+C55) -> 195.62305 | H70: LSZH Inner sheath construction cost | J70: N | K70: 0.1 | L70: Rs | M70: =IF(J70="Y",K70*$M$65,0) -> 0
B71: Weight of Armour | C71: =PI()*($C$43^2-$C$37^2)/4*$C$38 -> 0 | D71: =C71*(1+C54) -> 0 | H71: LSZH outersheath construction cost | J71: N | K71: 0.1 | L71: Rs | M71: =IF(J71="Y",K71*$M$65,0) -> 0
B72: Weight of PVC Filler | C72: =(C24-C25)*C26/1000 -> 0.085783871 | D72: =C72*(1+C55) -> 0.087928468 | H72: Oxygen Index(Outer sheath) | J72: N | K72: 0.025 | L72: Rs | M72: =IF(J72="Y",K72*$M$65,0) -> 0
H73: HRPVC Inner Sheath | J73: N | K73: 0.02 | L73: Rs | M73: =IF(J73="Y",K73*$M$65,0) -> 0
H74: HRPVC Outer Sheath | J74: N | K74: 0.02 | L74: Rs | M74: =IF(J74="Y",K74*$M$65,0) -> 0
H75: Extruded PVC Inner sheath- Upto 50 sq.mm | J75: N | K75: 0.03 | L75: Rs | M75: =IF(J75="Y",K75*$M$65,0) -> 0
B76: Costs as a % of Material Cost | C76: % | H76: Extruded PVC Inner sheath-70 sq.mm | J76: N | K76: 0.025 | L76: Rs | M76: =IF(J76="Y",K76*$M$65,0) -> 0
B77: Material Costs | C77: 0.85 | H77: Stranding of Conductor | J77: N | K77: 0.015 | L77: Rs | M77: =IF(J77="Y",K77*$M$65,0) -> 0
B78: Other Manufacturing expenses | C78: 0.05 | H78: Total Cable Costs | L78: Rs | M78: =M65+SUM(M68:M77) -> 93507.08
B79: Energy Costs | C79: 0.03
B80: Labour Costs | C80: 0.02 | H80: Selling Price | M80: =M78*(1+C84) -> 100520.11
B81: Administrative and Other expenses | C81: 0.03
B82: Overheads and Finance Costs | C82: 0.02
B84: Margins | C84: 0.075

Sheet Al LT Cables (2 x 95)
B1: =#REF! -> #REF! | C1: =SUM(D67:D72) -> 921.77198
B2: ="Cost Sheet for"&" "&C6&" Core"&" "&C9&" sq.mm"&" "&C10&" Cable" -> Cost Sheet for 2 Core 95 sq.mm Aluminium Cable
B4: Data Inputs
B6: No. of cores | C6: 2
B7: Shape of the core | C7: Sector shaped
B8: Conductor
B9: Conductor Size (in sq. mm) | C9: 95 | D9: sq. mm
B10: Conductor Material | C10: Aluminium | L10: =2*L9 -> 0
B11: Angle - Main | C11: =IF(C7="Sector shaped", (360/C6),360) -> 180
B12: Angle - Main | C12: =IF(C7="Sector shaped",360-C11*3,0) -> -180
B13: Conductor Radius | C13: =SQRT((C9*(360/C11))/PI()) -> 7.7768167 | D13: mm
B14: Density of Conductor | C14: =VLOOKUP(C10,Density1,2,0) -> 2.7 | D14: g/cm3
B16: Insulation
B17: Material | C17: XLPE
B18: Nominal thickness of insulation | C18: 1.1
B19: Calculated radius over insulation | C19: =IF(C7="Circular", C13+C18,C13+2*C18) -> 9.9768167 | D19: mm
B20: Density of Conductor | C20: =VLOOKUP(C17,Density,2,0) -> 0.93 | D20: g/cm3
B22: PVC Filler
B23: Filler Type | C23: PVC
B24: Area below inner sheath | C24: =PI()*((C31/2)^2) -> 390.57065 | D24: mm2
B25: Area till insulation | C25: =IF(C6=3.5,((C11/360)*PI()*(C19^2)*3)+((C12/360)*PI()*(C19^2)),(C11/360)*PI()*(C19^2)*C6) -> 312.70431 | D25: mm2
B26: Density | C26: =VLOOKUP(C23,Density,2,0) -> 1.35 | D26: g/cm3
B28: Inner Sheath
B29: Material | C29: PVC
B30: Minimum Thickness | C30: 0.4 | D30: mm
B31: Calculated diameter below innersheath | C31: =C37-2*C30 -> 22.3 | D31: mm
B32: Density of Conductor | C32: =VLOOKUP(C29,Density,2,0) -> 1.35 | D32: g/cm3
B34: Armour
B35: Material | C35: Unarmored
B36: Thickness of armour | C36: 0 | D36: mm
B37: Calculated diameter below armor | C37: =C43-2*C36 -> 23.1 | D37: mm
B38: Density of Conductor | C38: =VLOOKUP(C35,Armordensity,2,0) -> 0 | D38: g/cm3
B40: Outer Sheath
B41: Material | C41: PVC
B42: Minimum Thickness | C42: 2.2 | D42: mm
B43: Calculated diameter below outersheath | C43: =C46-(2*C42) -> 23.1 | D43: mm
B44: Density of Conductor | C44: =VLOOKUP(C41,Density,2,0) -> 1.35 | D44: g/cm3
B46: Overall OD of Cable | C46: 27.5
A48: ="COST SHEET FOR "&C6 & " CORE "&C9&" SQMM "&C10&" CABLE" -> COST SHEET FOR 2 CORE 95 SQMM Aluminium CABLE
A50: ASSUMPTIONS | G50: CALCULATION - SCENARIO 1
B52: Wastage Assumptions | H52: Material Cost Estimation | J52: Loading | K52: %
B53: =C10 -> Aluminium | C53: 0.02 | H53: ="Cost of"&" "&C10 -> Cost of Aluminium | L53: Rs | M53: =D67*C60 -> 67579.029
B54: Steel | C54: 0.02 | H54: Cost of PVC | L54: Rs | M54: =IF(C17="PVC",(D68+D69+D70+D72)*C61,(D69+D70+D72)*C61) -> 21136.924
B55: PVC | C55: 0.025 | H55: Cost of Steel | L55: Rs | M55: =D71*C62 -> 0
B56: XLPE | C56: 0.025 | H56: Cost of XLPE | L56: Rs | M56: =IF(C17="XLPE",D68*C63,0) -> 10537.636
H57: Material Cost per Km | L57: Rs | M57: =M53+M54+M55+M56 -> 99253.589
B58: Price Assumptions
B59: Material | C59: Rs/Kg | H59: Other Costs as a % of Total Cost
B60: =C10 -> Aluminium | C60: =VLOOKUP(B60,'Data Input'!$M$3:$N$6,2,0) -> 129.15 | H60: Other Manufacturing Costs | L60: Rs | M60: =C78/$C$77*$M$57 -> 5838.4464
B61: PVC | C61: =VLOOKUP(B61,'Data Input'!$M$3:$N$6,2,0) -> 75.075 | H61: Energy Cost | L61: Rs | M61: =M57/C77*C79 -> 3503.0678
B62: Steel Wire | C62: =VLOOKUP(B62,'Data Input'!$M$3:$N$6,2,0) -> 42 | H62: Labour Cost | L62: Rs | M62: =$M$57/$C$77*C80 -> 2335.3786
B63: XLPE | C63: =(1+E63)*C61 -> 90.09 | D63: 20% over PVC | E63: 0.2 | H63: Administrative and Other Expenses | L63: Rs | M63: =$M$57/$C$77*C81 -> 3503.0678
H64: Overheads and Finance Costs | L64: Rs | M64: =$M$57/$C$77*C82 -> 2335.3786
B65: Material Composition Estimates per Km of Cable | H65: Total Costs | L65: Rs | M65: =SUM(M60:M64)+M57 -> 116768.93
B66: =C6&" core"&" "&C9&" sq.mm"&" "&C10&" cable" -> 2 core 95 sq.mm Aluminium cable | C66: Used in Cable (Kg) | D66: Including Wastage (Kg)
B67: ="Weight of"&" "&C10 -> Weight of Aluminium | C67: =(C9*10^-3*C14*10^3*IF(C6=3.5,3,C6))+(C9*10^-3*C14*10^3*IF(C6=3.5,1,0)) -> 513 | D67: =C67*(1+C53) -> 523.26 | H67: Special Construction costs
B68: Weight of Insulation | C68: =IF(C6=3.5,((C11/360)*PI()*(C19^2-C13^2)*C20*3)+((C12/360)*PI()*(C19^2-C13^2)*C20),(C11/360)*PI()*(C19^2-C13^2)*C20*C6) -> 114.115 | D68: =C68*(1+C55) -> 116.96788 | H68: FRLS PVC inner sheath construction cost | J68: Y | K68: 0.025 | L68: Rs | M68: =IF(J68="Y",K68*$M$65,0) -> 2919.2232
B69: Weight of Inner Sheath | C69: =PI()*($C$37^2-$C$31^2)/4*$C$32 -> 38.509643 | D69: =C69*(1+C55) -> 39.472384 | H69: FRLS PVC outer sheath construction cost | J69: Y | K69: 0.025 | L69: Rs | M69: =IF(J69="Y",K69*$M$65,0) -> 2919.2232
B70: Weight of Outer Sheath | C70: =PI()*($C$46^2-$C$43^2)/4*$C$44 -> 236.06241 | D70: =C70*(1+C55) -> 241.96397 | H70: LSZH Inner sheath construction cost | J70: N | K70: 0.1 | L70: Rs | M70: =IF(J70="Y",K70*$M$65,0) -> 0
B71: Weight of Armour | C71: =PI()*($C$43^2-$C$37^2)/4*$C$38 -> 0 | D71: =C71*(1+C54) -> 0 | H71: LSZH outersheath construction cost | J71: N | K71: 0.1 | L71: Rs | M71: =IF(J71="Y",K71*$M$65,0) -> 0
B72: Weight of PVC Filler | C72: =(C24-C25)*C26/1000 -> 0.10511957 | D72: =C72*(1+C55) -> 0.10774756 | H72: Oxygen Index(Outer sheath) | J72: N | K72: 0.025 | L72: Rs | M72: =IF(J72="Y",K72*$M$65,0) -> 0
H73: HRPVC Inner Sheath | J73: N | K73: 0.02 | L73: Rs | M73: =IF(J73="Y",K73*$M$65,0) -> 0
H74: HRPVC Outer Sheath | J74: N | K74: 0.02 | L74: Rs | M74: =IF(J74="Y",K74*$M$65,0) -> 0
H75: Extruded PVC Inner sheath- Upto 50 sq.mm | J75: N | K75: 0.03 | L75: Rs | M75: =IF(J75="Y",K75*$M$65,0) -> 0
B76: Costs as a % of Material Cost | C76: % | H76: Extruded PVC Inner sheath-70 sq.mm | J76: N | K76: 0.025 | L76: Rs | M76: =IF(J76="Y",K76*$M$65,0) -> 0
B77: Material Costs | C77: 0.85 | H77: Stranding of Conductor | J77: N | K77: 0.015 | L77: Rs | M77: =IF(J77="Y",K77*$M$65,0) -> 0
B78: Other Manufacturing expenses | C78: 0.05 | H78: Total Cable Costs | L78: Rs | M78: =M65+SUM(M68:M77) -> 122607.37
B79: Energy Costs | C79: 0.03
B80: Labour Costs | C80: 0.02 | H80: Selling Price | M80: =M78*(1+C84) -> 131802.93
B81: Administrative and Other expenses | C81: 0.03
B82: Overheads and Finance Costs | C82: 0.02
B84: Margins | C84: 0.075

Sheet Al LT Cables (2 x 120)
B1: =#REF! -> #REF! | C1: =SUM(D67:D72) -> 1113.6717
B2: ="Cost Sheet for"&" "&C6&" Core"&" "&C9&" sq.mm"&" "&C10&" Cable" -> Cost Sheet for 2 Core 120 sq.mm Aluminium Cable
B4: Data Inputs
B6: No. of cores | C6: 2
B7: Shape of the core | C7: Sector shaped
B8: Conductor
B9: Conductor Size (in sq. mm) | C9: 120 | D9: sq. mm
B10: Conductor Material | C10: Aluminium | L10: =2*L9 -> 0
B11: Angle - Main | C11: =IF(C7="Sector shaped", (360/C6),360) -> 180
B12: Angle - Main | C12: =IF(C7="Sector shaped",360-C11*3,0) -> -180
B13: Conductor Radius | C13: =SQRT((C9*(360/C11))/PI()) -> 8.7403874 | D13: mm
B14: Density of Conductor | C14: =VLOOKUP(C10,Density1,2,0) -> 2.7 | D14: g/cm3
B16: Insulation
B17: Material | C17: XLPE
B18: Nominal thickness of insulation | C18: 1.2
B19: Calculated radius over insulation | C19: =IF(C7="Circular", C13+C18,C13+2*C18) -> 11.140387 | D19: mm
B20: Density of Conductor | C20: =VLOOKUP(C17,Density,2,0) -> 0.93 | D20: g/cm3
B22: PVC Filler
B23: Filler Type | C23: PVC
B24: Area below inner sheath | C24: =PI()*((C31/2)^2) -> 483.05129 | D24: mm2
B25: Area till insulation | C25: =IF(C6=3.5,((C11/360)*PI()*(C19^2)*3)+((C12/360)*PI()*(C19^2)),(C11/360)*PI()*(C19^2)*C6) -> 389.89751 | D25: mm2
B26: Density | C26: =VLOOKUP(C23,Density,2,0) -> 1.35 | D26: g/cm3
B28: Inner Sheath
B29: Material | C29: PVC
B30: Minimum Thickness | C30: 0.4 | D30: mm
B31: Calculated diameter below innersheath | C31: =C37-2*C30 -> 24.8 | D31: mm
B32: Density of Conductor | C32: =VLOOKUP(C29,Density,2,0) -> 1.35 | D32: g/cm3
B34: Armour
B35: Material | C35: Unarmored
B36: Thickness of armour | C36: 0 | D36: mm
B37: Calculated diameter below armor | C37: =C43-2*C36 -> 25.6 | D37: mm
B38: Density of Conductor | C38: =VLOOKUP(C35,Armordensity,2,0) -> 0 | D38: g/cm3
B40: Outer Sheath
B41: Material | C41: PVC
B42: Minimum Thickness | C42: 2.2 | D42: mm
B43: Calculated diameter below outersheath | C43: =C46-(2*C42) -> 25.6 | D43: mm
B44: Density of Conductor | C44: =VLOOKUP(C41,Density,2,0) -> 1.35 | D44: g/cm3
B46: Overall OD of Cable | C46: 30
A48: ="COST SHEET FOR "&C6 & " CORE "&C9&" SQMM "&C10&" CABLE" -> COST SHEET FOR 2 CORE 120 SQMM Aluminium CABLE
A50: ASSUMPTIONS | G50: CALCULATION - SCENARIO 1
B52: Wastage Assumptions | H52: Material Cost Estimation | J52: Loading | K52: %
B53: =C10 -> Aluminium | C53: 0.02 | H53: ="Cost of"&" "&C10 -> Cost of Aluminium | L53: Rs | M53: =D67*C60 -> 85362.984
B54: Steel | C54: 0.02 | H54: Cost of PVC | L54: Rs | M54: =IF(C17="PVC",(D68+D69+D70+D72)*C61,(D69+D70+D72)*C61) -> 23259.881
B55: PVC | C55: 0.025 | H55: Cost of Steel | L55: Rs | M55: =D71*C62 -> 0
B56: XLPE | C56: 0.025 | H56: Cost of XLPE | L56: Rs | M56: =IF(C17="XLPE",D68*C63,0) -> 12872.942
H57: Material Cost per Km | L57: Rs | M57: =M53+M54+M55+M56 -> 121495.81
B58: Price Assumptions
B59: Material | C59: Rs/Kg | H59: Other Costs as a % of Total Cost
B60: =C10 -> Aluminium | C60: =VLOOKUP(B60,'Data Input'!$M$3:$N$6,2,0) -> 129.15 | H60: Other Manufacturing Costs | L60: Rs | M60: =C78/$C$77*$M$57 -> 7146.8122
B61: PVC | C61: =VLOOKUP(B61,'Data Input'!$M$3:$N$6,2,0) -> 75.075 | H61: Energy Cost | L61: Rs | M61: =M57/C77*C79 -> 4288.0873
B62: Steel Wire | C62: =VLOOKUP(B62,'Data Input'!$M$3:$N$6,2,0) -> 42 | H62: Labour Cost | L62: Rs | M62: =$M$57/$C$77*C80 -> 2858.7249
B63: XLPE | C63: =(1+E63)*C61 -> 90.09 | D63: 20% over PVC | E63: 0.2 | H63: Administrative and Other Expenses | L63: Rs | M63: =$M$57/$C$77*C81 -> 4288.0873
H64: Overheads and Finance Costs | L64: Rs | M64: =$M$57/$C$77*C82 -> 2858.7249
B65: Material Composition Estimates per Km of Cable | H65: Total Costs | L65: Rs | M65: =SUM(M60:M64)+M57 -> 142936.24
B66: =C6&" core"&" "&C9&" sq.mm"&" "&C10&" cable" -> 2 core 120 sq.mm Aluminium cable | C66: Used in Cable (Kg) | D66: Including Wastage (Kg)
B67: ="Weight of"&" "&C10 -> Weight of Aluminium | C67: =(C9*10^-3*C14*10^3*IF(C6=3.5,3,C6))+(C9*10^-3*C14*10^3*IF(C6=3.5,1,0)) -> 648 | D67: =C67*(1+C53) -> 660.96 | H67: Special Construction costs
B68: Weight of Insulation | C68: =IF(C6=3.5,((C11/360)*PI()*(C19^2-C13^2)*C20*3)+((C12/360)*PI()*(C19^2-C13^2)*C20),(C11/360)*PI()*(C19^2-C13^2)*C20*C6) -> 139.40469 | D68: =C68*(1+C55) -> 142.8898 | H68: FRLS PVC inner sheath construction cost | J68: Y | K68: 0.025 | L68: Rs | M68: =IF(J68="Y",K68*$M$65,0) -> 3573.4061
B69: Weight of Inner Sheath | C69: =PI()*($C$37^2-$C$31^2)/4*$C$32 -> 42.750793 | D69: =C69*(1+C55) -> 43.819563 | H69: FRLS PVC outer sheath construction cost | J69: Y | K69: 0.025 | L69: Rs | M69: =IF(J69="Y",K69*$M$65,0) -> 3573.4061
B70: Weight of Outer Sheath | C70: =PI()*($C$46^2-$C$43^2)/4*$C$44 -> 259.38874 | D70: =C70*(1+C55) -> 265.87346 | H70: LSZH Inner sheath construction cost | J70: N | K70: 0.1 | L70: Rs | M70: =IF(J70="Y",K70*$M$65,0) -> 0
B71: Weight of Armour | C71: =PI()*($C$43^2-$C$37^2)/4*$C$38 -> 0 | D71: =C71*(1+C54) -> 0 | H71: LSZH outersheath construction cost | J71: N | K71: 0.1 | L71: Rs | M71: =IF(J71="Y",K71*$M$65,0) -> 0
B72: Weight of PVC Filler | C72: =(C24-C25)*C26/1000 -> 0.1257576 | D72: =C72*(1+C55) -> 0.12890154 | H72: Oxygen Index(Outer sheath) | J72: N | K72: 0.025 | L72: Rs | M72: =IF(J72="Y",K72*$M$65,0) -> 0
H73: HRPVC Inner Sheath | J73: N | K73: 0.02 | L73: Rs | M73: =IF(J73="Y",K73*$M$65,0) -> 0
H74: HRPVC Outer Sheath | J74: N | K74: 0.02 | L74: Rs | M74: =IF(J74="Y",K74*$M$65,0) -> 0
H75: Extruded PVC Inner sheath- Upto 50 sq.mm | J75: N | K75: 0.03 | L75: Rs | M75: =IF(J75="Y",K75*$M$65,0) -> 0
B76: Costs as a % of Material Cost | C76: % | H76: Extruded PVC Inner sheath-70 sq.mm | J76: N | K76: 0.025 | L76: Rs | M76: =IF(J76="Y",K76*$M$65,0) -> 0
B77: Material Costs | C77: 0.85 | H77: Stranding of Conductor | J77: N | K77: 0.015 | L77: Rs | M77: =IF(J77="Y",K77*$M$65,0) -> 0
B78: Other Manufacturing expenses | C78: 0.05 | H78: Total Cable Costs | L78: Rs | M78: =M65+SUM(M68:M77) -> 150083.06
B79: Energy Costs | C79: 0.03
B80: Labour Costs | C80: 0.02 | H80: Selling Price | M80: =M78*(1+C84) -> 161339.28
B81: Administrative and Other expenses | C81: 0.03
B82: Overheads and Finance Costs | C82: 0.02
B84: Margins | C84: 0.075

Sheet Al LT Cables (2 x 150)
B1: =#REF! -> #REF! | C1: =SUM(D67:D72) -> 1345.9521
B2: ="Cost Sheet for"&" "&C6&" Core"&" "&C9&" sq.mm"&" "&C10&" Cable" -> Cost Sheet for 2 Core 150 sq.mm Aluminium Cable
B4: Data Inputs
B6: No. of cores | C6: 2
B7: Shape of the core | C7: Sector shaped
B8: Conductor
B9: Conductor Size (in sq. mm) | C9: 150 | D9: sq. mm
B10: Conductor Material | C10: Aluminium | L10: =2*L9 -> 0
B11: Angle - Main | C11: =IF(C7="Sector shaped", (360/C6),360) -> 180
B12: Angle - Main | C12: =IF(C7="Sector shaped",360-C11*3,0) -> -180
B13: Conductor Radius | C13: =SQRT((C9*(360/C11))/PI()) -> 9.7720502 | D13: mm
B14: Density of Conductor | C14: =VLOOKUP(C10,Density1,2,0) -> 2.7 | D14: g/cm3
B16: Insulation
B17: Material | C17: XLPE
B18: Nominal thickness of insulation | C18: 1.4
B19: Calculated radius over insulation | C19: =IF(C7="Circular", C13+C18,C13+2*C18) -> 12.57205 | D19: mm
B20: Density of Conductor | C20: =VLOOKUP(C17,Density,2,0) -> 0.93 | D20: g/cm3
B22: PVC Filler
B23: Filler Type | C23: PVC
B24: Area below inner sheath | C24: =PI()*((C31/2)^2) -> 564.10438 | D24: mm2
B25: Area till insulation | C25: =IF(C6=3.5,((C11/360)*PI()*(C19^2)*3)+((C12/360)*PI()*(C19^2)),(C11/360)*PI()*(C19^2)*C6) -> 496.54897 | D25: mm2
B26: Density | C26: =VLOOKUP(C23,Density,2,0) -> 1.35 | D26: g/cm3
B28: Inner Sheath
B29: Material | C29: PVC
B30: Minimum Thickness | C30: 0.4 | D30: mm
B31: Calculated diameter below innersheath | C31: =C37-2*C30 -> 26.8 | D31: mm
B32: Density of Conductor | C32: =VLOOKUP(C29,Density,2,0) -> 1.35 | D32: g/cm3
B34: Armour
B35: Material | C35: Unarmored
B36: Thickness of armour | C36: 0 | D36: mm
B37: Calculated diameter below armor | C37: =C43-2*C36 -> 27.6 | D37: mm
B38: Density of Conductor | C38: =VLOOKUP(C35,Armordensity,2,0) -> 0 | D38: g/cm3
B40: Outer Sheath
B41: Material | C41: PVC
B42: Minimum Thickness | C42: 2.2 | D42: mm
B43: Calculated diameter below outersheath | C43: =C46-(2*C42) -> 27.6 | D43: mm
B44: Density of Conductor | C44: =VLOOKUP(C41,Density,2,0) -> 1.35 | D44: g/cm3
B46: Overall OD of Cable | C46: 32
A48: ="COST SHEET FOR "&C6 & " CORE "&C9&" SQMM "&C10&" CABLE" -> COST SHEET FOR 2 CORE 150 SQMM Aluminium CABLE
A50: ASSUMPTIONS | G50: CALCULATION - SCENARIO 1
B52: Wastage Assumptions | H52: Material Cost Estimation | J52: Loading | K52: %
B53: =C10 -> Aluminium | C53: 0.02 | H53: ="Cost of"&" "&C10 -> Cost of Aluminium | L53: Rs | M53: =D67*C60 -> 106703.73
B54: Steel | C54: 0.02 | H54: Cost of PVC | L54: Rs | M54: =IF(C17="PVC",(D68+D69+D70+D72)*C61,(D69+D70+D72)*C61) -> 24954.317
B55: PVC | C55: 0.025 | H55: Cost of Steel | L55: Rs | M55: =D71*C62 -> 0
B56: XLPE | C56: 0.025 | H56: Cost of XLPE | L56: Rs | M56: =IF(C17="XLPE",D68*C63,0) -> 16879.29
H57: Material Cost per Km | L57: Rs | M57: =M53+M54+M55+M56 -> 148537.34
B58: Price Assumptions
B59: Material | C59: Rs/Kg | H59: Other Costs as a % of Total Cost
B60: =C10 -> Aluminium | C60: =VLOOKUP(B60,'Data Input'!$M$3:$N$6,2,0) -> 129.15 | H60: Other Manufacturing Costs | L60: Rs | M60: =C78/$C$77*$M$57 -> 8737.4904
B61: PVC | C61: =VLOOKUP(B61,'Data Input'!$M$3:$N$6,2,0) -> 75.075 | H61: Energy Cost | L61: Rs | M61: =M57/C77*C79 -> 5242.4942
B62: Steel Wire | C62: =VLOOKUP(B62,'Data Input'!$M$3:$N$6,2,0) -> 42 | H62: Labour Cost | L62: Rs | M62: =$M$57/$C$77*C80 -> 3494.9962
B63: XLPE | C63: =(1+E63)*C61 -> 90.09 | D63: 20% over PVC | E63: 0.2 | H63: Administrative and Other Expenses | L63: Rs | M63: =$M$57/$C$77*C81 -> 5242.4942
H64: Overheads and Finance Costs | L64: Rs | M64: =$M$57/$C$77*C82 -> 3494.9962
B65: Material Composition Estimates per Km of Cable | H65: Total Costs | L65: Rs | M65: =SUM(M60:M64)+M57 -> 174749.81
B66: =C6&" core"&" "&C9&" sq.mm"&" "&C10&" cable" -> 2 core 150 sq.mm Aluminium cable | C66: Used in Cable (Kg) | D66: Including Wastage (Kg)
B67: ="Weight of"&" "&C10 -> Weight of Aluminium | C67: =(C9*10^-3*C14*10^3*IF(C6=3.5,3,C6))+(C9*10^-3*C14*10^3*IF(C6=3.5,1,0)) -> 810 | D67: =C67*(1+C53) -> 826.2 | H67: Special Construction costs
B68: Weight of Insulation | C68: =IF(C6=3.5,((C11/360)*PI()*(C19^2-C13^2)*C20*3)+((C12/360)*PI()*(C19^2-C13^2)*C20),(C11/360)*PI()*(C19^2-C13^2)*C20*C6) -> 182.79055 | D68: =C68*(1+C55) -> 187.36031 | H68: FRLS PVC inner sheath construction cost | J68: Y | K68: 0.025 | L68: Rs | M68: =IF(J68="Y",K68*$M$65,0) -> 4368.7452
B69: Weight of Inner Sheath | C69: =PI()*($C$37^2-$C$31^2)/4*$C$32 -> 46.143713 | D69: =C69*(1+C55) -> 47.297306 | H69: FRLS PVC outer sheath construction cost | J69: Y | K69: 0.025 | L69: Rs | M69: =IF(J69="Y",K69*$M$65,0) -> 4368.7452
B70: Weight of Outer Sheath | C70: =PI()*($C$46^2-$C$43^2)/4*$C$44 -> 278.0498 | D70: =C70*(1+C55) -> 285.00104 | H70: LSZH Inner sheath construction cost | J70: N | K70: 0.1 | L70: Rs | M70: =IF(J70="Y",K70*$M$65,0) -> 0
B71: Weight of Armour | C71: =PI()*($C$43^2-$C$37^2)/4*$C$38 -> 0 | D71: =C71*(1+C54) -> 0 | H71: LSZH outersheath construction cost | J71: N | K71: 0.1 | L71: Rs | M71: =IF(J71="Y",K71*$M$65,0) -> 0
B72: Weight of PVC Filler | C72: =(C24-C25)*C26/1000 -> 0.091199795 | D72: =C72*(1+C55) -> 0.09347979 | H72: Oxygen Index(Outer sheath) | J72: N | K72: 0.025 | L72: Rs | M72: =IF(J72="Y",K72*$M$65,0) -> 0
H73: HRPVC Inner Sheath | J73: N | K73: 0.02 | L73: Rs | M73: =IF(J73="Y",K73*$M$65,0) -> 0
H74: HRPVC Outer Sheath | J74: N | K74: 0.02 | L74: Rs | M74: =IF(J74="Y",K74*$M$65,0) -> 0
H75: Extruded PVC Inner sheath- Upto 50 sq.mm | J75: N | K75: 0.03 | L75: Rs | M75: =IF(J75="Y",K75*$M$65,0) -> 0
B76: Costs as a % of Material Cost | C76: % | H76: Extruded PVC Inner sheath-70 sq.mm | J76: N | K76: 0.025 | L76: Rs | M76: =IF(J76="Y",K76*$M$65,0) -> 0
B77: Material Costs | C77: 0.85 | H77: Stranding of Conductor | J77: N | K77: 0.015 | L77: Rs | M77: =IF(J77="Y",K77*$M$65,0) -> 0
B78: Other Manufacturing expenses | C78: 0.05 | H78: Total Cable Costs | L78: Rs | M78: =M65+SUM(M68:M77) -> 183487.3
B79: Energy Costs | C79: 0.03
B80: Labour Costs | C80: 0.02 | H80: Selling Price | M80: =M78*(1+C84) -> 197248.85
B81: Administrative and Other expenses | C81: 0.03
B82: Overheads and Finance Costs | C82: 0.02
B84: Margins | C84: 0.075

Sheet Al LT Cables (2 x 185)
B1: =#REF! -> #REF! | C1: =SUM(D67:D72) -> 1668.7281
B2: ="Cost Sheet for"&" "&C6&" Core"&" "&C9&" sq.mm"&" "&C10&" Cable" -> Cost Sheet for 2 Core 185 sq.mm Aluminium Cable
B4: Data Inputs
B6: No. of cores | C6: 2
B7: Shape of the core | C7: Sector shaped
B8: Conductor
B9: Conductor Size (in sq. mm) | C9: 185 | D9: sq. mm
B10: Conductor Material | C10: Aluminium | L10: =2*L9 -> 0
B11: Angle - Main | C11: =IF(C7="Sector shaped", (360/C6),360) -> 180
B12: Angle - Main | C12: =IF(C7="Sector shaped",360-C11*3,0) -> -180
B13: Conductor Radius | C13: =SQRT((C9*(360/C11))/PI()) -> 10.852403 | D13: mm
B14: Density of Conductor | C14: =VLOOKUP(C10,Density1,2,0) -> 2.7 | D14: g/cm3
B16: Insulation
B17: Material | C17: XLPE
B18: Nominal thickness of insulation | C18: 1.6
B19: Calculated radius over insulation | C19: =IF(C7="Circular", C13+C18,C13+2*C18) -> 14.052403 | D19: mm
B20: Density of Conductor | C20: =VLOOKUP(C17,Density,2,0) -> 0.93 | D20: g/cm3
B22: PVC Filler
B23: Filler Type | C23: PVC
B24: Area below inner sheath | C24: =PI()*((C31/2)^2) -> 692.79187 | D24: mm2
B25: Area till insulation | C25: =IF(C6=3.5,((C11/360)*PI()*(C19^2)*3)+((C12/360)*PI()*(C19^2)),(C11/360)*PI()*(C19^2)*C6) -> 620.37042 | D25: mm2
B26: Density | C26: =VLOOKUP(C23,Density,2,0) -> 1.35 | D26: g/cm3
B28: Inner Sheath
B29: Material | C29: PVC
B30: Minimum Thickness | C30: 0.5 | D30: mm
B31: Calculated diameter below innersheath | C31: =C37-2*C30 -> 29.7 | D31: mm
B32: Density of Conductor | C32: =VLOOKUP(C29,Density,2,0) -> 1.35 | D32: g/cm3
B34: Armour
B35: Material | C35: Unarmored
B36: Thickness of armour | C36: 0 | D36: mm
B37: Calculated diameter below armor | C37: =C43-2*C36 -> 30.7 | D37: mm
B38: Density of Conductor | C38: =VLOOKUP(C35,Armordensity,2,0) -> 0 | D38: g/cm3
B40: Outer Sheath
B41: Material | C41: PVC
B42: Minimum Thickness | C42: 2.4 | D42: mm
B43: Calculated diameter below outersheath | C43: =C46-(2*C42) -> 30.7 | D43: mm
B44: Density of Conductor | C44: =VLOOKUP(C41,Density,2,0) -> 1.35 | D44: g/cm3
B46: Overall OD of Cable | C46: 35.5
A48: ="COST SHEET FOR "&C6 & " CORE "&C9&" SQMM "&C10&" CABLE" -> COST SHEET FOR 2 CORE 185 SQMM Aluminium CABLE
A50: ASSUMPTIONS | G50: CALCULATION - SCENARIO 1
B52: Wastage Assumptions | H52: Material Cost Estimation | J52: Loading | K52: %
B53: =C10 -> Aluminium | C53: 0.02 | H53: ="Cost of"&" "&C10 -> Cost of Aluminium | L53: Rs | M53: =D67*C60 -> 131601.27
B54: Steel | C54: 0.02 | H54: Cost of PVC | L54: Rs | M54: =IF(C17="PVC",(D68+D69+D70+D72)*C61,(D69+D70+D72)*C61) -> 30862.019
B55: PVC | C55: 0.025 | H55: Cost of Steel | L55: Rs | M55: =D71*C62 -> 0
B56: XLPE | C56: 0.025 | H56: Cost of XLPE | L56: Rs | M56: =IF(C17="XLPE",D68*C63,0) -> 21501.385
H57: Material Cost per Km | L57: Rs | M57: =M53+M54+M55+M56 -> 183964.67
B58: Price Assumptions
B59: Material | C59: Rs/Kg | H59: Other Costs as a % of Total Cost
B60: =C10 -> Aluminium | C60: =VLOOKUP(B60,'Data Input'!$M$3:$N$6,2,0) -> 129.15 | H60: Other Manufacturing Costs | L60: Rs | M60: =C78/$C$77*$M$57 -> 10821.451
B61: PVC | C61: =VLOOKUP(B61,'Data Input'!$M$3:$N$6,2,0) -> 75.075 | H61: Energy Cost | L61: Rs | M61: =M57/C77*C79 -> 6492.8707
B62: Steel Wire | C62: =VLOOKUP(B62,'Data Input'!$M$3:$N$6,2,0) -> 42 | H62: Labour Cost | L62: Rs | M62: =$M$57/$C$77*C80 -> 4328.5805
B63: XLPE | C63: =(1+E63)*C61 -> 90.09 | D63: 20% over PVC | E63: 0.2 | H63: Administrative and Other Expenses | L63: Rs | M63: =$M$57/$C$77*C81 -> 6492.8707
H64: Overheads and Finance Costs | L64: Rs | M64: =$M$57/$C$77*C82 -> 4328.5805
B65: Material Composition Estimates per Km of Cable | H65: Total Costs | L65: Rs | M65: =SUM(M60:M64)+M57 -> 216429.02
B66: =C6&" core"&" "&C9&" sq.mm"&" "&C10&" cable" -> 2 core 185 sq.mm Aluminium cable | C66: Used in Cable (Kg) | D66: Including Wastage (Kg)
B67: ="Weight of"&" "&C10 -> Weight of Aluminium | C67: =(C9*10^-3*C14*10^3*IF(C6=3.5,3,C6))+(C9*10^-3*C14*10^3*IF(C6=3.5,1,0)) -> 999 | D67: =C67*(1+C53) -> 1018.98 | H67: Special Construction costs
B68: Weight of Insulation | C68: =IF(C6=3.5,((C11/360)*PI()*(C19^2-C13^2)*C20*3)+((C12/360)*PI()*(C19^2-C13^2)*C20),(C11/360)*PI()*(C19^2-C13^2)*C20*C6) -> 232.84449 | D68: =C68*(1+C55) -> 238.66561 | H68: FRLS PVC inner sheath construction cost | J68: Y | K68: 0.025 | L68: Rs | M68: =IF(J68="Y",K68*$M$65,0) -> 5410.7256
B69: Weight of Inner Sheath | C69: =PI()*($C$37^2-$C$31^2)/4*$C$32 -> 64.041366 | D69: =C69*(1+C55) -> 65.6424 | H69: FRLS PVC outer sheath construction cost | J69: Y | K69: 0.025 | L69: Rs | M69: =IF(J69="Y",K69*$M$65,0) -> 5410.7256
B70: Weight of Outer Sheath | C70: =PI()*($C$46^2-$C$43^2)/4*$C$44 -> 336.91696 | D70: =C70*(1+C55) -> 345.33989 | H70: LSZH Inner sheath construction cost | J70: N | K70: 0.1 | L70: Rs | M70: =IF(J70="Y",K70*$M$65,0) -> 0
B71: Weight of Armour | C71: =PI()*($C$43^2-$C$37^2)/4*$C$38 -> 0 | D71: =C71*(1+C54) -> 0 | H71: LSZH outersheath construction cost | J71: N | K71: 0.1 | L71: Rs | M71: =IF(J71="Y",K71*$M$65,0) -> 0
B72: Weight of PVC Filler | C72: =(C24-C25)*C26/1000 -> 0.097768946 | D72: =C72*(1+C55) -> 0.10021317 | H72: Oxygen Index(Outer sheath) | J72: N | K72: 0.025 | L72: Rs | M72: =IF(J72="Y",K72*$M$65,0) -> 0
H73: HRPVC Inner Sheath | J73: N | K73: 0.02 | L73: Rs | M73: =IF(J73="Y",K73*$M$65,0) -> 0
H74: HRPVC Outer Sheath | J74: N | K74: 0.02 | L74: Rs | M74: =IF(J74="Y",K74*$M$65,0) -> 0
H75: Extruded PVC Inner sheath- Upto 50 sq.mm | J75: N | K75: 0.03 | L75: Rs | M75: =IF(J75="Y",K75*$M$65,0) -> 0
B76: Costs as a % of Material Cost | C76: % | H76: Extruded PVC Inner sheath-70 sq.mm | J76: N | K76: 0.025 | L76: Rs | M76: =IF(J76="Y",K76*$M$65,0) -> 0
B77: Material Costs | C77: 0.85 | H77: Stranding of Conductor | J77: N | K77: 0.015 | L77: Rs | M77: =IF(J77="Y",K77*$M$65,0) -> 0
B78: Other Manufacturing expenses | C78: 0.05 | H78: Total Cable Costs | L78: Rs | M78: =M65+SUM(M68:M77) -> 227250.47
B79: Energy Costs | C79: 0.03
B80: Labour Costs | C80: 0.02 | H80: Selling Price | M80: =M78*(1+C84) -> 244294.26
B81: Administrative and Other expenses | C81: 0.03
B82: Overheads and Finance Costs | C82: 0.02
B84: Margins | C84: 0.075

Sheet Al LT Cables (2 x 240)
B1: =#REF! -> #REF! | C1: =SUM(D67:D72) -> 2105.6908
B2: ="Cost Sheet for"&" "&C6&" Core"&" "&C9&" sq.mm"&" "&C10&" Cable" -> Cost Sheet for 2 Core 240 sq.mm Aluminium Cable
B4: Data Inputs
B6: No. of cores | C6: 2
B7: Shape of the core | C7: Sector shaped
B8: Conductor
B9: Conductor Size (in sq. mm) | C9: 240 | D9: sq. mm
B10: Conductor Material | C10: Aluminium | L10: =2*L9 -> 0
B11: Angle - Main | C11: =IF(C7="Sector shaped", (360/C6),360) -> 180
B12: Angle - Main | C12: =IF(C7="Sector shaped",360-C11*3,0) -> -180
B13: Conductor Radius | C13: =SQRT((C9*(360/C11))/PI()) -> 12.360774 | D13: mm
B14: Density of Conductor | C14: =VLOOKUP(C10,Density1,2,0) -> 2.7 | D14: g/cm3
B16: Insulation
B17: Material | C17: XLPE
B18: Nominal thickness of insulation | C18: 1.7
B19: Calculated radius over insulation | C19: =IF(C7="Circular", C13+C18,C13+2*C18) -> 15.760774 | D19: mm
B20: Density of Conductor | C20: =VLOOKUP(C17,Density,2,0) -> 0.93 | D20: g/cm3
B22: PVC Filler
B23: Filler Type | C23: PVC
B24: Area below inner sheath | C24: =PI()*((C31/2)^2) -> 897.27028 | D24: mm2
B25: Area till insulation | C25: =IF(C6=3.5,((C11/360)*PI()*(C19^2)*3)+((C12/360)*PI()*(C19^2)),(C11/360)*PI()*(C19^2)*C6) -> 780.37794 | D25: mm2
B26: Density | C26: =VLOOKUP(C23,Density,2,0) -> 1.35 | D26: g/cm3
B28: Inner Sheath
B29: Material | C29: PVC
B30: Minimum Thickness | C30: 0.5 | D30: mm
B31: Calculated diameter below innersheath | C31: =C37-2*C30 -> 33.8 | D31: mm
B32: Density of Conductor | C32: =VLOOKUP(C29,Density,2,0) -> 1.35 | D32: g/cm3
B34: Armour
B35: Material | C35: Unarmored
B36: Thickness of armour | C36: 0 | D36: mm
B37: Calculated diameter below armor | C37: =C43-2*C36 -> 34.8 | D37: mm
B38: Density of Conductor | C38: =VLOOKUP(C35,Armordensity,2,0) -> 0 | D38: g/cm3
B40: Outer Sheath
B41: Material | C41: PVC
B42: Minimum Thickness | C42: 2.6 | D42: mm
B43: Calculated diameter below outersheath | C43: =C46-(2*C42) -> 34.8 | D43: mm
B44: Density of Conductor | C44: =VLOOKUP(C41,Density,2,0) -> 1.35 | D44: g/cm3
B46: Overall OD of Cable | C46: 40
A48: ="COST SHEET FOR "&C6 & " CORE "&C9&" SQMM "&C10&" CABLE" -> COST SHEET FOR 2 CORE 240 SQMM Aluminium CABLE
A50: ASSUMPTIONS | G50: CALCULATION - SCENARIO 1
B52: Wastage Assumptions | H52: Material Cost Estimation | J52: Loading | K52: %
B53: =C10 -> Aluminium | C53: 0.02 | H53: ="Cost of"&" "&C10 -> Cost of Aluminium | L53: Rs | M53: =D67*C60 -> 170725.97
B54: Steel | C54: 0.02 | H54: Cost of PVC | L54: Rs | M54: =IF(C17="PVC",(D68+D69+D70+D72)*C61,(D69+D70+D72)*C61) -> 37344.973
B55: PVC | C55: 0.025 | H55: Cost of Steel | L55: Rs | M55: =D71*C62 -> 0
B56: XLPE | C56: 0.025 | H56: Cost of XLPE | L56: Rs | M56: =IF(C17="XLPE",D68*C63,0) -> 25795.944
H57: Material Cost per Km | L57: Rs | M57: =M53+M54+M55+M56 -> 233866.89
B58: Price Assumptions
B59: Material | C59: Rs/Kg | H59: Other Costs as a % of Total Cost
B60: =C10 -> Aluminium | C60: =VLOOKUP(B60,'Data Input'!$M$3:$N$6,2,0) -> 129.15 | H60: Other Manufacturing Costs | L60: Rs | M60: =C78/$C$77*$M$57 -> 13756.876
B61: PVC | C61: =VLOOKUP(B61,'Data Input'!$M$3:$N$6,2,0) -> 75.075 | H61: Energy Cost | L61: Rs | M61: =M57/C77*C79 -> 8254.1254
B62: Steel Wire | C62: =VLOOKUP(B62,'Data Input'!$M$3:$N$6,2,0) -> 42 | H62: Labour Cost | L62: Rs | M62: =$M$57/$C$77*C80 -> 5502.7502
B63: XLPE | C63: =(1+E63)*C61 -> 90.09 | D63: 20% over PVC | E63: 0.2 | H63: Administrative and Other Expenses | L63: Rs | M63: =$M$57/$C$77*C81 -> 8254.1254
H64: Overheads and Finance Costs | L64: Rs | M64: =$M$57/$C$77*C82 -> 5502.7502
B65: Material Composition Estimates per Km of Cable | H65: Total Costs | L65: Rs | M65: =SUM(M60:M64)+M57 -> 275137.51
B66: =C6&" core"&" "&C9&" sq.mm"&" "&C10&" cable" -> 2 core 240 sq.mm Aluminium cable | C66: Used in Cable (Kg) | D66: Including Wastage (Kg)
B67: ="Weight of"&" "&C10 -> Weight of Aluminium | C67: =(C9*10^-3*C14*10^3*IF(C6=3.5,3,C6))+(C9*10^-3*C14*10^3*IF(C6=3.5,1,0)) -> 1296 | D67: =C67*(1+C53) -> 1321.92 | H67: Special Construction costs
B68: Weight of Insulation | C68: =IF(C6=3.5,((C11/360)*PI()*(C19^2-C13^2)*C20*3)+((C12/360)*PI()*(C19^2-C13^2)*C20),(C11/360)*PI()*(C19^2-C13^2)*C20*C6) -> 279.35148 | D68: =C68*(1+C55) -> 286.33527 | H68: FRLS PVC inner sheath construction cost | J68: Y | K68: 0.025 | L68: Rs | M68: =IF(J68="Y",K68*$M$65,0) -> 6878.4378
B69: Weight of Inner Sheath | C69: =PI()*($C$37^2-$C$31^2)/4*$C$32 -> 72.735724 | D69: =C69*(1+C55) -> 74.554117 | H69: FRLS PVC outer sheath construction cost | J69: Y | K69: 0.025 | L69: Rs | M69: =IF(J69="Y",K69*$M$65,0) -> 6878.4378
B70: Weight of Outer Sheath | C70: =PI()*($C$46^2-$C$43^2)/4*$C$44 -> 412.40943 | D70: =C70*(1+C55) -> 422.71967 | H70: LSZH Inner sheath construction cost | J70: N | K70: 0.1 | L70: Rs | M70: =IF(J70="Y",K70*$M$65,0) -> 0
B71: Weight of Armour | C71: =PI()*($C$43^2-$C$37^2)/4*$C$38 -> 0 | D71: =C71*(1+C54) -> 0 | H71: LSZH outersheath construction cost | J71: N | K71: 0.1 | L71: Rs | M71: =IF(J71="Y",K71*$M$65,0) -> 0
B72: Weight of PVC Filler | C72: =(C24-C25)*C26/1000 -> 0.15780466 | D72: =C72*(1+C55) -> 0.16174978 | H72: Oxygen Index(Outer sheath) | J72: N | K72: 0.025 | L72: Rs | M72: =IF(J72="Y",K72*$M$65,0) -> 0
H73: HRPVC Inner Sheath | J73: N | K73: 0.02 | L73: Rs | M73: =IF(J73="Y",K73*$M$65,0) -> 0
H74: HRPVC Outer Sheath | J74: N | K74: 0.02 | L74: Rs | M74: =IF(J74="Y",K74*$M$65,0) -> 0
H75: Extruded PVC Inner sheath- Upto 50 sq.mm | J75: N | K75: 0.03 | L75: Rs | M75: =IF(J75="Y",K75*$M$65,0) -> 0
B76: Costs as a % of Material Cost | C76: % | H76: Extruded PVC Inner sheath-70 sq.mm | J76: N | K76: 0.025 | L76: Rs | M76: =IF(J76="Y",K76*$M$65,0) -> 0
B77: Material Costs | C77: 0.85 | H77: Stranding of Conductor | J77: N | K77: 0.015 | L77: Rs | M77: =IF(J77="Y",K77*$M$65,0) -> 0
B78: Other Manufacturing expenses | C78: 0.05 | H78: Total Cable Costs | L78: Rs | M78: =M65+SUM(M68:M77) -> 288894.39
B79: Energy Costs | C79: 0.03
B80: Labour Costs | C80: 0.02 | H80: Selling Price | M80: =M78*(1+C84) -> 310561.47
B81: Administrative and Other expenses | C81: 0.03
B82: Overheads and Finance Costs | C82: 0.02
B84: Margins | C84: 0.075

Sheet Al LT Cables (3 x 6)
B1: =#REF! -> #REF! | C1: =SUM(D67:D72) -> 188.76625
B2: ="Cost Sheet for"&" "&C6&" Core"&" "&C9&" sq.mm"&" "&C10&" Cable" -> Cost Sheet for 3 Core 6 sq.mm Aluminium Cable
B4: Data Inputs
B6: No. of cores | C6: 3
B7: Shape of the core | C7: Sector shaped
B8: Conductor
B9: Conductor Size (in sq. mm) | C9: 6 | D9: sq. mm
B10: Conductor Material | C10: Aluminium | L10: =2*L9 -> 0
B11: Angle - Main | C11: =IF(C7="Sector shaped", (360/C6),360) -> 120
B12: Angle - Main | C12: =IF(C7="Sector shaped",360-C11*3,0) -> 0
B13: Conductor Radius | C13: =SQRT((C9*(360/C11))/PI()) -> 2.3936537 | D13: mm
B14: Density of Conductor | C14: =VLOOKUP(C10,Density1,2,0) -> 2.7 | D14: g/cm3
B16: Insulation
B17: Material | C17: XLPE
B18: Nominal thickness of insulation | C18: 0.7
B19: Calculated radius over insulation | C19: =IF(C7="Circular", C13+C18,C13+2*C18) -> 3.7936537 | D19: mm
B20: Density of Conductor | C20: =VLOOKUP(C17,Density,2,0) -> 0.93 | D20: g/cm3
B22: PVC Filler
B23: Filler Type | C23: PVC
B24: Area below inner sheath | C24: =PI()*((C31/2)^2) -> 83.322891 | D24: mm2
B25: Area till insulation | C25: =IF(C6=3.5,((C11/360)*PI()*(C19^2)*3)+((C12/360)*PI()*(C19^2)),(C11/360)*PI()*(C19^2)*C6) -> 45.213199 | D25: mm2
B26: Density | C26: =VLOOKUP(C23,Density,2,0) -> 1.35 | D26: g/cm3
B28: Inner Sheath
B29: Material | C29: PVC
B30: Minimum Thickness | C30: 0.3 | D30: mm
B31: Calculated diameter below innersheath | C31: =C37-2*C30 -> 10.3 | D31: mm
B32: Density of Conductor | C32: =VLOOKUP(C29,Density,2,0) -> 1.35 | D32: g/cm3
B34: Armour
B35: Material | C35: Unarmored
B36: Thickness of armour | C36: 0 | D36: mm
B37: Calculated diameter below armor | C37: =C43-2*C36 -> 10.9 | D37: mm
B38: Density of Conductor | C38: =VLOOKUP(C35,Armordensity,2,0) -> 0 | D38: g/cm3
B40: Outer Sheath
B41: Material | C41: PVC
B42: Minimum Thickness | C42: 1.8 | D42: mm
B43: Calculated diameter below outersheath | C43: =C46-(2*C42) -> 10.9 | D43: mm
B44: Density of Conductor | C44: =VLOOKUP(C41,Density,2,0) -> 1.35 | D44: g/cm3
B46: Overall OD of Cable | C46: 14.5
A48: ="COST SHEET FOR "&C6 & " CORE "&C9&" SQMM "&C10&" CABLE" -> COST SHEET FOR 3 CORE 6 SQMM Aluminium CABLE
A50: ASSUMPTIONS | G50: CALCULATION - SCENARIO 1
B52: Wastage Assumptions | H52: Material Cost Estimation | J52: Loading | K52: %
B53: =C10 -> Aluminium | C53: 0.02 | H53: ="Cost of"&" "&C10 -> Cost of Aluminium | L53: Rs | M53: =D67*C60 -> 6402.2238
B54: Steel | C54: 0.02 | H54: Cost of PVC | L54: Rs | M54: =IF(C17="PVC",(D68+D69+D70+D72)*C61,(D69+D70+D72)*C61) -> 8502.4893
B55: PVC | C55: 0.025 | H55: Cost of Steel | L55: Rs | M55: =D71*C62 -> 0
B56: XLPE | C56: 0.025 | H56: Cost of XLPE | L56: Rs | M56: =IF(C17="XLPE",D68*C63,0) -> 2337.0231
H57: Material Cost per Km | L57: Rs | M57: =M53+M54+M55+M56 -> 17241.736
B58: Price Assumptions
B59: Material | C59: Rs/Kg | H59: Other Costs as a % of Total Cost
B60: =C10 -> Aluminium | C60: =VLOOKUP(B60,'Data Input'!$M$3:$N$6,2,0) -> 129.15 | H60: Other Manufacturing Costs | L60: Rs | M60: =C78/$C$77*$M$57 -> 1014.2198
B61: PVC | C61: =VLOOKUP(B61,'Data Input'!$M$3:$N$6,2,0) -> 75.075 | H61: Energy Cost | L61: Rs | M61: =M57/C77*C79 -> 608.53187
B62: Steel Wire | C62: =VLOOKUP(B62,'Data Input'!$M$3:$N$6,2,0) -> 42 | H62: Labour Cost | L62: Rs | M62: =$M$57/$C$77*C80 -> 405.68791
B63: XLPE | C63: =(1+E63)*C61 -> 90.09 | D63: 20% over PVC | E63: 0.2 | H63: Administrative and Other Expenses | L63: Rs | M63: =$M$57/$C$77*C81 -> 608.53187
H64: Overheads and Finance Costs | L64: Rs | M64: =$M$57/$C$77*C82 -> 405.68791
B65: Material Composition Estimates per Km of Cable | L65: Rs | M65: =SUM(M60:M64)+M57 -> 20284.396
B66: =C6&" core"&" "&C9&" sq.mm"&" "&C10&" cable" -> 3 core 6 sq.mm Aluminium cable | C66: Used in Cable (Kg) | D66: Including Wastage (Kg)
B67: ="Weight of"&" "&C10 -> Weight of Aluminium | C67: =(C9*10^-3*C14*10^3*IF(C6=3.5,3,C6))+(C9*10^-3*C14*10^3*IF(C6=3.5,1,0)) -> 48.6 | D67: =C67*(1+C53) -> 49.572 | H67: Special Construction costs
B68: Weight of Insulation | C68: =IF(C6=3.5,((C11/360)*PI()*(C19^2-C13^2)*C20*3)+((C12/360)*PI()*(C19^2-C13^2)*C20),(C11/360)*PI()*(C19^2-C13^2)*C20*C6) -> 25.308275 | D68: =C68*(1+C55) -> 25.940982 | H68: FRLS PVC inner sheath construction cost | J68: Y | K68: 0.025 | L68: Rs | M68: =IF(J68="Y",K68*$M$65,0) -> 507.10989
B69: Weight of Inner Sheath | C69: =PI()*($C$37^2-$C$31^2)/4*$C$32 -> 13.486857 | D69: =C69*(1+C55) -> 13.824029 | H69: FRLS PVC outer sheath construction cost | J69: Y | K69: 0.025 | L69: Rs | M69: =IF(J69="Y",K69*$M$65,0) -> 507.10989
B70: Weight of Outer Sheath | C70: =PI()*($C$46^2-$C$43^2)/4*$C$44 -> 96.952691 | D70: =C70*(1+C55) -> 99.376508 | H70: LSZH Inner sheath construction cost | J70: N | K70: 0.1 | L70: Rs | M70: =IF(J70="Y",K70*$M$65,0) -> 0
B71: Weight of Armour | C71: =PI()*($C$43^2-$C$37^2)/4*$C$38 -> 0 | D71: =C71*(1+C54) -> 0 | H71: LSZH outersheath construction cost | J71: N | K71: 0.1 | L71: Rs | M71: =IF(J71="Y",K71*$M$65,0) -> 0
B72: Weight of PVC Filler | C72: =(C24-C25)*C26/1000 -> 0.051448084 | D72: =C72*(1+C55) -> 0.052734286 | H72: Oxygen Index(Outer sheath) | J72: N | K72: 0.025 | L72: Rs | M72: =IF(J72="Y",K72*$M$65,0) -> 0
H73: HRPVC Inner Sheath | J73: N | K73: 0.02 | L73: Rs | M73: =IF(J73="Y",K73*$M$65,0) -> 0
H74: HRPVC Outer Sheath | J74: N | K74: 0.02 | L74: Rs | M74: =IF(J74="Y",K74*$M$65,0) -> 0
H75: Extruded PVC Inner sheath- Upto 50 sq.mm | J75: N | K75: 0.03 | L75: Rs | M75: =IF(J75="Y",K75*$M$65,0) -> 0
B76: Costs as a % of Material Cost | C76: % | H76: Extruded PVC Inner sheath-70 sq.mm | J76: N | K76: 0.025 | L76: Rs | M76: =IF(J76="Y",K76*$M$65,0) -> 0
B77: Material Costs | C77: 0.85 | H77: Stranding of Conductor | J77: N | K77: 0.015 | L77: Rs | M77: =IF(J77="Y",K77*$M$65,0) -> 0
B78: Other Manufacturing expenses | C78: 0.05 | H78: Total Cable Costs | L78: Rs | M78: =M65+SUM(M68:M77) -> 21298.615
B79: Energy Costs | C79: 0.03
B80: Labour Costs | C80: 0.02 | H80: Selling Price | M80: =M78*(1+C84) -> 22896.011
B81: Administrative and Other expenses | C81: 0.03
B82: Overheads and Finance Costs | C82: 0.02
B84: Margins | C84: 0.075

Sheet Al LT Cables (3 x 10)
B1: =#REF! -> #REF! | C1: =SUM(D67:D72) -> 245.93709
B2: ="Cost Sheet for"&" "&C6&" Core"&" "&C9&" sq.mm"&" "&C10&" Cable" -> Cost Sheet for 3 Core 10 sq.mm Aluminium Cable
B4: Data Inputs
B6: No. of cores | C6: 3
B7: Shape of the core | C7: Sector shaped
B8: Conductor
B9: Conductor Size (in sq. mm) | C9: 10 | D9: sq. mm
B10: Conductor Material | C10: Aluminium | L10: =2*L9 -> 0
B11: Angle - Main | C11: =IF(C7="Sector shaped", (360/C6),360) -> 120
B12: Angle - Main | C12: =IF(C7="Sector shaped",360-C11*3,0) -> 0
B13: Conductor Radius | C13: =SQRT((C9*(360/C11))/PI()) -> 3.0901936 | D13: mm
B14: Density of Conductor | C14: =VLOOKUP(C10,Density1,2,0) -> 2.7 | D14: g/cm3
B16: Insulation
B17: Material | C17: XLPE
B18: Nominal thickness of insulation | C18: 0.7
B19: Calculated radius over insulation | C19: =IF(C7="Circular", C13+C18,C13+2*C18) -> 4.4901936 | D19: mm
B20: Density of Conductor | C20: =VLOOKUP(C17,Density,2,0) -> 0.93 | D20: g/cm3
B22: PVC Filler
B23: Filler Type | C23: PVC
B24: Area below inner sheath | C24: =PI()*((C31/2)^2) -> 118.82289 | D24: mm2
B25: Area till insulation | C25: =IF(C6=3.5,((C11/360)*PI()*(C19^2)*3)+((C12/360)*PI()*(C19^2)),(C11/360)*PI()*(C19^2)*C6) -> 63.340284 | D25: mm2
B26: Density | C26: =VLOOKUP(C23,Density,2,0) -> 1.35 | D26: g/cm3
B28: Inner Sheath
B29: Material | C29: PVC
B30: Minimum Thickness | C30: 0.3 | D30: mm
B31: Calculated diameter below innersheath | C31: =C37-2*C30 -> 12.3 | D31: mm
B32: Density of Conductor | C32: =VLOOKUP(C29,Density,2,0) -> 1.35 | D32: g/cm3
B34: Armour
B35: Material | C35: Unarmored
B36: Thickness of armour | C36: 0 | D36: mm
B37: Calculated diameter below armor | C37: =C43-2*C36 -> 12.9 | D37: mm
B38: Density of Conductor | C38: =VLOOKUP(C35,Armordensity,2,0) -> 0 | D38: g/cm3
B40: Outer Sheath
B41: Material | C41: PVC
B42: Minimum Thickness | C42: 1.8 | D42: mm
B43: Calculated diameter below outersheath | C43: =C46-(2*C42) -> 12.9 | D43: mm
B44: Density of Conductor | C44: =VLOOKUP(C41,Density,2,0) -> 1.35 | D44: g/cm3
B46: Overall OD of Cable | C46: 16.5
A48: ="COST SHEET FOR "&C6 & " CORE "&C9&" SQMM "&C10&" CABLE" -> COST SHEET FOR 3 CORE 10 SQMM Aluminium CABLE
A50: ASSUMPTIONS | G50: CALCULATION - SCENARIO 1
B52: Wastage Assumptions | H52: Material Cost Estimation | J52: Loading | K52: %
B53: =C10 -> Aluminium | C53: 0.02 | H53: ="Cost of"&" "&C10 -> Cost of Aluminium | L53: Rs | M53: =D67*C60 -> 10670.373
B54: Steel | C54: 0.02 | H54: Cost of PVC | L54: Rs | M54: =IF(C17="PVC",(D68+D69+D70+D72)*C61,(D69+D70+D72)*C61) -> 9875.0248
B55: PVC | C55: 0.025 | H55: Cost of Steel | L55: Rs | M55: =D71*C62 -> 0
B56: XLPE | C56: 0.025 | H56: Cost of XLPE | L56: Rs | M56: =IF(C17="XLPE",D68*C63,0) -> 2863.2067
H57: Material Cost per Km | L57: Rs | M57: =M53+M54+M55+M56 -> 23408.605
B58: Price Assumptions
B59: Material | C59: Rs/Kg | H59: Other Costs as a % of Total Cost
B60: =C10 -> Aluminium | C60: =VLOOKUP(B60,'Data Input'!$M$3:$N$6,2,0) -> 129.15 | H60: Other Manufacturing Costs | L60: Rs | M60: =C78/$C$77*$M$57 -> 1376.9767
B61: PVC | C61: =VLOOKUP(B61,'Data Input'!$M$3:$N$6,2,0) -> 75.075 | H61: Energy Cost | L61: Rs | M61: =M57/C77*C79 -> 826.18604
B62: Steel Wire | C62: =VLOOKUP(B62,'Data Input'!$M$3:$N$6,2,0) -> 42 | H62: Labour Cost | L62: Rs | M62: =$M$57/$C$77*C80 -> 550.79069
B63: XLPE | C63: =(1+E63)*C61 -> 90.09 | D63: 20% over PVC | E63: 0.2 | H63: Administrative and Other Expenses | L63: Rs | M63: =$M$57/$C$77*C81 -> 826.18604
H64: Overheads and Finance Costs | L64: Rs | M64: =$M$57/$C$77*C82 -> 550.79069
B65: Material Composition Estimates per Km of Cable | H65: Total Costs | L65: Rs | M65: =SUM(M60:M64)+M57 -> 27539.535
B66: =C6&" core"&" "&C9&" sq.mm"&" "&C10&" cable" -> 3 core 10 sq.mm Aluminium cable | C66: Used in Cable (Kg) | D66: Including Wastage (Kg)
B67: ="Weight of"&" "&C10 -> Weight of Aluminium | C67: =(C9*10^-3*C14*10^3*IF(C6=3.5,3,C6))+(C9*10^-3*C14*10^3*IF(C6=3.5,1,0)) -> 81 | D67: =C67*(1+C53) -> 82.62 | H67: Special Construction costs
B68: Weight of Insulation | C68: =IF(C6=3.5,((C11/360)*PI()*(C19^2-C13^2)*C20*3)+((C12/360)*PI()*(C19^2-C13^2)*C20),(C11/360)*PI()*(C19^2-C13^2)*C20*C6) -> 31.006464 | D68: =C68*(1+C55) -> 31.781626 | H68: FRLS PVC inner sheath construction cost | J68: Y | K68: 0.025 | L68: Rs | M68: =IF(J68="Y",K68*$M$65,0) -> 688.48837
B69: Weight of Inner Sheath | C69: =PI()*($C$37^2-$C$31^2)/4*$C$32 -> 16.031547 | D69: =C69*(1+C55) -> 16.432336 | H69: FRLS PVC outer sheath construction cost | J69: Y | K69: 0.025 | L69: Rs | M69: =IF(J69="Y",K69*$M$65,0) -> 688.48837
B70: Weight of Outer Sheath | C70: =PI()*($C$46^2-$C$43^2)/4*$C$44 -> 112.22083 | D70: =C70*(1+C55) -> 115.02635 | H70: LSZH Inner sheath construction cost | J70: N | K70: 0.1 | L70: Rs | M70: =IF(J70="Y",K70*$M$65,0) -> 0
B71: Weight of Armour | C71: =PI()*($C$43^2-$C$37^2)/4*$C$38 -> 0 | D71: =C71*(1+C54) -> 0 | H71: LSZH outersheath construction cost | J71: N | K71: 0.1 | L71: Rs | M71: =IF(J71="Y",K71*$M$65,0) -> 0
B72: Weight of PVC Filler | C72: =(C24-C25)*C26/1000 -> 0.074901515 | D72: =C72*(1+C55) -> 0.076774053 | H72: Oxygen Index(Outer sheath) | J72: N | K72: 0.025 | L72: Rs | M72: =IF(J72="Y",K72*$M$65,0) -> 0
H73: HRPVC Inner Sheath | J73: N | K73: 0.02 | L73: Rs | M73: =IF(J73="Y",K73*$M$65,0) -> 0
H74: HRPVC Outer Sheath | J74: N | K74: 0.02 | L74: Rs | M74: =IF(J74="Y",K74*$M$65,0) -> 0
H75: Extruded PVC Inner sheath- Upto 50 sq.mm | J75: N | K75: 0.03 | L75: Rs | M75: =IF(J75="Y",K75*$M$65,0) -> 0
B76: Costs as a % of Material Cost | C76: % | H76: Extruded PVC Inner sheath-70 sq.mm | J76: N | K76: 0.025 | L76: Rs | M76: =IF(J76="Y",K76*$M$65,0) -> 0
B77: Material Costs | C77: 0.85 | H77: Stranding of Conductor | J77: N | K77: 0.015 | L77: Rs | M77: =IF(J77="Y",K77*$M$65,0) -> 0
B78: Other Manufacturing expenses | C78: 0.05 | H78: Total Cable Costs | L78: Rs | M78: =M65+SUM(M68:M77) -> 28916.511
B79: Energy Costs | C79: 0.03
B80: Labour Costs | C80: 0.02 | H80: Selling Price | M80: =M78*(1+C84) -> 31085.25
B81: Administrative and Other expenses | C81: 0.03
B82: Overheads and Finance Costs | C82: 0.02
B84: Margins | C84: 0.075

Sheet Al LT Cables (3 x 16)
B1: =#REF! -> #REF! | C1: =SUM(D67:D72) -> 306.91676
B2: ="Cost Sheet for"&" "&C6&" Core"&" "&C9&" sq.mm"&" "&C10&" Cable" -> Cost Sheet for 3 Core 16 sq.mm Aluminium Cable
B4: Data Inputs
B6: No. of cores | C6: 3
B7: Shape of the core | C7: Sector shaped
B8: Conductor
B9: Conductor Size (in sq. mm) | C9: 16 | D9: sq. mm
B10: Conductor Material | C10: Aluminium | L10: =2*L9 -> 0
B11: Angle - Main | C11: =IF(C7="Sector shaped", (360/C6),360) -> 120
B12: Angle - Main | C12: =IF(C7="Sector shaped",360-C11*3,0) -> 0
B13: Conductor Radius | C13: =SQRT((C9*(360/C11))/PI()) -> 3.9088201 | D13: mm
B14: Density of Conductor | C14: =VLOOKUP(C10,Density1,2,0) -> 2.7 | D14: g/cm3
B16: Insulation
B17: Material | C17: XLPE
B18: Nominal thickness of insulation | C18: 0.7
B19: Calculated radius over insulation | C19: =IF(C7="Circular", C13+C18,C13+2*C18) -> 5.3088201 | D19: mm
B20: Density of Conductor | C20: =VLOOKUP(C17,Density,2,0) -> 0.93 | D20: g/cm3
B22: PVC Filler
B23: Filler Type | C23: PVC
B24: Area below inner sheath | C24: =PI()*((C31/2)^2) -> 128.67964 | D24: mm2
B25: Area till insulation | C25: =IF(C6=3.5,((C11/360)*PI()*(C19^2)*3)+((C12/360)*PI()*(C19^2)),(C11/360)*PI()*(C19^2)*C6) -> 88.541299 | D25: mm2
B26: Density | C26: =VLOOKUP(C23,Density,2,0) -> 1.35 | D26: g/cm3
B28: Inner Sheath
B29: Material | C29: PVC
B30: Minimum Thickness | C30: 0.3 | D30: mm
B31: Calculated diameter below innersheath | C31: =C37-2*C30 -> 12.8 | D31: mm
B32: Density of Conductor | C32: =VLOOKUP(C29,Density,2,0) -> 1.35 | D32: g/cm3
B34: Armour
B35: Material | C35: Unarmored
B36: Thickness of armour | C36: 0 | D36: mm
B37: Calculated diameter below armor | C37: =C43-2*C36 -> 13.4 | D37: mm
B38: Density of Conductor | C38: =VLOOKUP(C35,Armordensity,2,0) -> 0 | D38: g/cm3
B40: Outer Sheath
B41: Material | C41: PVC
B42: Minimum Thickness | C42: 1.8 | D42: mm
B43: Calculated diameter below outersheath | C43: =C46-(2*C42) -> 13.4 | D43: mm
B44: Density of Conductor | C44: =VLOOKUP(C41,Density,2,0) -> 1.35 | D44: g/cm3
B46: Overall OD of Cable | C46: 17
A48: ="COST SHEET FOR "&C6 & " CORE "&C9&" SQMM "&C10&" CABLE" -> COST SHEET FOR 3 CORE 16 SQMM Aluminium CABLE
A50: ASSUMPTIONS | G50: CALCULATION - SCENARIO 1
B52: Wastage Assumptions | H52: Material Cost Estimation | J52: Loading | K52: %
B53: =C10 -> Aluminium | C53: 0.02 | H53: ="Cost of"&" "&C10 -> Cost of Aluminium | L53: Rs | M53: =D67*C60 -> 17072.597
B54: Steel | C54: 0.02 | H54: Cost of PVC | L54: Rs | M54: =IF(C17="PVC",(D68+D69+D70+D72)*C61,(D69+D70+D72)*C61) -> 10216.113
B55: PVC | C55: 0.025 | H55: Cost of Steel | L55: Rs | M55: =D71*C62 -> 0
B56: XLPE | C56: 0.025 | H56: Cost of XLPE | L56: Rs | M56: =IF(C17="XLPE",D68*C63,0) -> 3481.6175
H57: Material Cost per Km | L57: Rs | M57: =M53+M54+M55+M56 -> 30770.328
B58: Price Assumptions
B59: Material | C59: Rs/Kg | H59: Other Costs as a % of Total Cost
B60: =C10 -> Aluminium | C60: =VLOOKUP(B60,'Data Input'!$M$3:$N$6,2,0) -> 129.15 | H60: Other Manufacturing Costs | L60: Rs | M60: =C78/$C$77*$M$57 -> 1810.0193
B61: PVC | C61: =VLOOKUP(B61,'Data Input'!$M$3:$N$6,2,0) -> 75.075 | H61: Energy Cost | L61: Rs | M61: =M57/C77*C79 -> 1086.0116
B62: Steel Wire | C62: =VLOOKUP(B62,'Data Input'!$M$3:$N$6,2,0) -> 42 | H62: Labour Cost | L62: Rs | M62: =$M$57/$C$77*C80 -> 724.00771
B63: XLPE | C63: =(1+E63)*C61 -> 90.09 | D63: 20% over PVC | E63: 0.2 | H63: Administrative and Other Expenses | L63: Rs | M63: =$M$57/$C$77*C81 -> 1086.0116
H64: Overheads and Finance Costs | L64: Rs | M64: =$M$57/$C$77*C82 -> 724.00771
B65: Material Composition Estimates per Km of Cable | H65: Total Costs | L65: Rs | M65: =SUM(M60:M64)+M57 -> 36200.386
B66: =C6&" core"&" "&C9&" sq.mm"&" "&C10&" cable" -> 3 core 16 sq.mm Aluminium cable | C66: Used in Cable (Kg) | D66: Including Wastage (Kg)
B67: ="Weight of"&" "&C10 -> Weight of Aluminium | C67: =(C9*10^-3*C14*10^3*IF(C6=3.5,3,C6))+(C9*10^-3*C14*10^3*IF(C6=3.5,1,0)) -> 129.6 | D67: =C67*(1+C53) -> 132.192 | H67: Special Construction costs
B68: Weight of Insulation | C68: =IF(C6=3.5,((C11/360)*PI()*(C19^2-C13^2)*C20*3)+((C12/360)*PI()*(C19^2-C13^2)*C20),(C11/360)*PI()*(C19^2-C13^2)*C20*C6) -> 37.703408 | D68: =C68*(1+C55) -> 38.645993 | H68: FRLS PVC inner sheath construction cost | J68: Y | K68: 0.025 | L68: Rs | M68: =IF(J68="Y",K68*$M$65,0) -> 905.00964
B69: Weight of Inner Sheath | C69: =PI()*($C$37^2-$C$31^2)/4*$C$32 -> 16.66772 | D69: =C69*(1+C55) -> 17.084413 | H69: FRLS PVC outer sheath construction cost | J69: Y | K69: 0.025 | L69: Rs | M69: =IF(J69="Y",K69*$M$65,0) -> 905.00964
B70: Weight of Outer Sheath | C70: =PI()*($C$46^2-$C$43^2)/4*$C$44 -> 116.03787 | D70: =C70*(1+C55) -> 118.93881 | H70: LSZH Inner sheath construction cost | J70: N | K70: 0.1 | L70: Rs | M70: =IF(J70="Y",K70*$M$65,0) -> 0
B71: Weight of Armour | C71: =PI()*($C$43^2-$C$37^2)/4*$C$38 -> 0 | D71: =C71*(1+C54) -> 0 | H71: LSZH outersheath construction cost | J71: N | K71: 0.1 | L71: Rs | M71: =IF(J71="Y",K71*$M$65,0) -> 0
B72: Weight of PVC Filler | C72: =(C24-C25)*C26/1000 -> 0.054186754 | D72: =C72*(1+C55) -> 0.055541423 | H72: Oxygen Index(Outer sheath) | J72: N | K72: 0.025 | L72: Rs | M72: =IF(J72="Y",K72*$M$65,0) -> 0
H73: HRPVC Inner Sheath | J73: N | K73: 0.02 | L73: Rs | M73: =IF(J73="Y",K73*$M$65,0) -> 0
H74: HRPVC Outer Sheath | J74: N | K74: 0.02 | L74: Rs | M74: =IF(J74="Y",K74*$M$65,0) -> 0
H75: Extruded PVC Inner sheath- Upto 50 sq.mm | J75: N | K75: 0.03 | L75: Rs | M75: =IF(J75="Y",K75*$M$65,0) -> 0
B76: Costs as a % of Material Cost | C76: % | H76: Extruded PVC Inner sheath-70 sq.mm | J76: N | K76: 0.025 | L76: Rs | M76: =IF(J76="Y",K76*$M$65,0) -> 0
B77: Material Costs | C77: 0.85 | H77: Stranding of Conductor | J77: N | K77: 0.015 | L77: Rs | M77: =IF(J77="Y",K77*$M$65,0) -> 0
B78: Other Manufacturing expenses | C78: 0.05 | H78: Total Cable Costs | L78: Rs | M78: =M65+SUM(M68:M77) -> 38010.405
B79: Energy Costs | C79: 0.03
B80: Labour Costs | C80: 0.02 | H80: Selling Price | M80: =M78*(1+C84) -> 40861.185
B81: Administrative and Other expenses | C81: 0.03
B82: Overheads and Finance Costs | C82: 0.02
B84: Margins | C84: 0.075

Sheet Al LT Cables (3 x 25)
B1: =#REF! -> #REF! | C1: =SUM(D67:D72) -> 445.96622
B2: ="Cost Sheet for"&" "&C6&" Core"&" "&C9&" sq.mm"&" "&C10&" Cable" -> Cost Sheet for 3 Core 25 sq.mm Aluminium Cable
B4: Data Inputs
B6: No. of cores | C6: 3
B7: Shape of the core | C7: Sector shaped
B8: Conductor
B9: Conductor Size (in sq. mm) | C9: 25 | D9: sq. mm
B10: Conductor Material | C10: Aluminium | L10: =2*L9 -> 0
B11: Angle - Main | C11: =IF(C7="Sector shaped", (360/C6),360) -> 120
B12: Angle - Main | C12: =IF(C7="Sector shaped",360-C11*3,0) -> 0
B13: Conductor Radius | C13: =SQRT((C9*(360/C11))/PI()) -> 4.8860251 | D13: mm
B14: Density of Conductor | C14: =VLOOKUP(C10,Density1,2,0) -> 2.7 | D14: g/cm3
B16: Insulation
B17: Material | C17: XLPE
B18: Nominal thickness of insulation | C18: 0.9
B19: Calculated radius over insulation | C19: =IF(C7="Circular", C13+C18,C13+2*C18) -> 6.6860251 | D19: mm
B20: Density of Conductor | C20: =VLOOKUP(C17,Density,2,0) -> 0.93 | D20: g/cm3
B22: PVC Filler
B23: Filler Type | C23: PVC
B24: Area below inner sheath | C24: =PI()*((C31/2)^2) -> 186.26503 | D24: mm2
B25: Area till insulation | C25: =IF(C6=3.5,((C11/360)*PI()*(C19^2)*3)+((C12/360)*PI()*(C19^2)),(C11/360)*PI()*(C19^2)*C6) -> 140.4384 | D25: mm2
B26: Density | C26: =VLOOKUP(C23,Density,2,0) -> 1.35 | D26: g/cm3
B28: Inner Sheath
B29: Material | C29: PVC
B30: Minimum Thickness | C30: 0.3 | D30: mm
B31: Calculated diameter below innersheath | C31: =C37-2*C30 -> 15.4 | D31: mm
B32: Density of Conductor | C32: =VLOOKUP(C29,Density,2,0) -> 1.35 | D32: g/cm3
B34: Armour
B35: Material | C35: Unarmored
B36: Thickness of armour | C36: 0 | D36: mm
B37: Calculated diameter below armor | C37: =C43-2*C36 -> 16 | D37: mm
B38: Density of Conductor | C38: =VLOOKUP(C35,Armordensity,2,0) -> 0 | D38: g/cm3
B40: Outer Sheath
B41: Material | C41: PVC
B42: Minimum Thickness | C42: 2 | D42: mm
B43: Calculated diameter below outersheath | C43: =C46-(2*C42) -> 16 | D43: mm
B44: Density of Conductor | C44: =VLOOKUP(C41,Density,2,0) -> 1.35 | D44: g/cm3
B46: Overall OD of Cable | C46: 20
A48: ="COST SHEET FOR "&C6 & " CORE "&C9&" SQMM "&C10&" CABLE" -> COST SHEET FOR 3 CORE 25 SQMM Aluminium CABLE
A50: ASSUMPTIONS | G50: CALCULATION - SCENARIO 1
B52: Wastage Assumptions | H52: Material Cost Estimation | J52: Loading | K52: %
B53: =C10 -> Aluminium | C53: 0.02 | H53: ="Cost of"&" "&C10 -> Cost of Aluminium | L53: Rs | M53: =D67*C60 -> 26675.933
B54: Steel | C54: 0.02 | H54: Cost of PVC | L54: Rs | M54: =IF(C17="PVC",(D68+D69+D70+D72)*C61,(D69+D70+D72)*C61) -> 13291.058
B55: PVC | C55: 0.025 | H55: Cost of Steel | L55: Rs | M55: =D71*C62 -> 0
B56: XLPE | C56: 0.025 | H56: Cost of XLPE | L56: Rs | M56: =IF(C17="XLPE",D68*C63,0) -> 5619.7383
H57: Material Cost per Km | L57: Rs | M57: =M53+M54+M55+M56 -> 45586.728
B58: Price Assumptions
B59: Material | C59: Rs/Kg | H59: Other Costs as a % of Total Cost
B60: =C10 -> Aluminium | C60: =VLOOKUP(B60,'Data Input'!$M$3:$N$6,2,0) -> 129.15 | H60: Other Manufacturing Costs | L60: Rs | M60: =C78/$C$77*$M$57 -> 2681.5723
B61: PVC | C61: =VLOOKUP(B61,'Data Input'!$M$3:$N$6,2,0) -> 75.075 | H61: Energy Cost | L61: Rs | M61: =M57/C77*C79 -> 1608.9434
B62: Steel Wire | C62: =VLOOKUP(B62,'Data Input'!$M$3:$N$6,2,0) -> 42 | H62: Labour Cost | L62: Rs | M62: =$M$57/$C$77*C80 -> 1072.6289
B63: XLPE | C63: =(1+E63)*C61 -> 90.09 | D63: 20% over PVC | E63: 0.2 | H63: Administrative and Other Expenses | L63: Rs | M63: =$M$57/$C$77*C81 -> 1608.9434
H64: Overheads and Finance Costs | L64: Rs | M64: =$M$57/$C$77*C82 -> 1072.6289
B65: Material Composition Estimates per Km of Cable | H65: Total Costs | L65: Rs | M65: =SUM(M60:M64)+M57 -> 53631.445
B66: =C6&" core"&" "&C9&" sq.mm"&" "&C10&" cable" -> 3 core 25 sq.mm Aluminium cable | C66: Used in Cable (Kg) | D66: Including Wastage (Kg)
B67: ="Weight of"&" "&C10 -> Weight of Aluminium | C67: =(C9*10^-3*C14*10^3*IF(C6=3.5,3,C6))+(C9*10^-3*C14*10^3*IF(C6=3.5,1,0)) -> 202.5 | D67: =C67*(1+C53) -> 206.55 | H67: Special Construction costs
B68: Weight of Insulation | C68: =IF(C6=3.5,((C11/360)*PI()*(C19^2-C13^2)*C20*3)+((C12/360)*PI()*(C19^2-C13^2)*C20),(C11/360)*PI()*(C19^2-C13^2)*C20*C6) -> 60.857714 | D68: =C68*(1+C55) -> 62.379157 | H68: FRLS PVC inner sheath construction cost | J68: Y | K68: 0.025 | L68: Rs | M68: =IF(J68="Y",K68*$M$65,0) -> 1340.7861
B69: Weight of Inner Sheath | C69: =PI()*($C$37^2-$C$31^2)/4*$C$32 -> 19.975817 | D69: =C69*(1+C55) -> 20.475212 | H69: FRLS PVC outer sheath construction cost | J69: Y | K69: 0.025 | L69: Rs | M69: =IF(J69="Y",K69*$M$65,0) -> 1340.7861
B70: Weight of Outer Sheath | C70: =PI()*($C$46^2-$C$43^2)/4*$C$44 -> 152.6814 | D70: =C70*(1+C55) -> 156.49844 | H70: LSZH Inner sheath construction cost | J70: N | K70: 0.1 | L70: Rs | M70: =IF(J70="Y",K70*$M$65,0) -> 0
B71: Weight of Armour | C71: =PI()*($C$43^2-$C$37^2)/4*$C$38 -> 0 | D71: =C71*(1+C54) -> 0 | H71: LSZH outersheath construction cost | J71: N | K71: 0.1 | L71: Rs | M71: =IF(J71="Y",K71*$M$65,0) -> 0
B72: Weight of PVC Filler | C72: =(C24-C25)*C26/1000 -> 0.061865945 | D72: =C72*(1+C55) -> 0.063412594 | H72: Oxygen Index(Outer sheath) | J72: N | K72: 0.025 | L72: Rs | M72: =IF(J72="Y",K72*$M$65,0) -> 0
H73: HRPVC Inner Sheath | J73: N | K73: 0.02 | L73: Rs | M73: =IF(J73="Y",K73*$M$65,0) -> 0
H74: HRPVC Outer Sheath | J74: N | K74: 0.02 | L74: Rs | M74: =IF(J74="Y",K74*$M$65,0) -> 0
H75: Extruded PVC Inner sheath- Upto 50 sq.mm | J75: N | K75: 0.03 | L75: Rs | M75: =IF(J75="Y",K75*$M$65,0) -> 0
B76: Costs as a % of Material Cost | C76: % | H76: Extruded PVC Inner sheath-70 sq.mm | J76: N | K76: 0.025 | L76: Rs | M76: =IF(J76="Y",K76*$M$65,0) -> 0
B77: Material Costs | C77: 0.85 | H77: Stranding of Conductor | J77: N | K77: 0.015 | L77: Rs | M77: =IF(J77="Y",K77*$M$65,0) -> 0
B78: Other Manufacturing expenses | C78: 0.05 | H78: Total Cable Costs | L78: Rs | M78: =M65+SUM(M68:M77) -> 56313.017
B79: Energy Costs | C79: 0.03
B80: Labour Costs | C80: 0.02 | H80: Selling Price | M80: =M78*(1+C84) -> 60536.494
B81: Administrative and Other expenses | C81: 0.03
B82: Overheads and Finance Costs | C82: 0.02
B84: Margins | C84: 0.075

Sheet Al LT Cables (3 x 35)
B1: =#REF! -> #REF! | C1: =SUM(D67:D72) -> 558.25014
B2: ="Cost Sheet for"&" "&C6&" Core"&" "&C9&" sq.mm"&" "&C10&" Cable" -> Cost Sheet for 3 Core 35 sq.mm Aluminium Cable
B4: Data Inputs
B6: No. of cores | C6: 3
B7: Shape of the core | C7: Sector shaped
B8: Conductor
B9: Conductor Size (in sq. mm) | C9: 35 | D9: sq. mm
B10: Conductor Material | C10: Aluminium | L10: =2*L9 -> 0
B11: Angle - Main | C11: =IF(C7="Sector shaped", (360/C6),360) -> 120
B12: Angle - Main | C12: =IF(C7="Sector shaped",360-C11*3,0) -> 0
B13: Conductor Radius | C13: =SQRT((C9*(360/C11))/PI()) -> 5.7812229 | D13: mm
B14: Density of Conductor | C14: =VLOOKUP(C10,Density1,2,0) -> 2.7 | D14: g/cm3
B16: Insulation
B17: Material | C17: XLPE
B18: Nominal thickness of insulation | C18: 0.9
B19: Calculated radius over insulation | C19: =IF(C7="Circular", C13+C18,C13+2*C18) -> 7.5812229 | D19: mm
B20: Density of Conductor | C20: =VLOOKUP(C17,Density,2,0) -> 0.93 | D20: g/cm3
B22: PVC Filler
B23: Filler Type | C23: PVC
B24: Area below inner sheath | C24: =PI()*((C31/2)^2) -> 237.78715 | D24: mm2
B25: Area till insulation | C25: =IF(C6=3.5,((C11/360)*PI()*(C19^2)*3)+((C12/360)*PI()*(C19^2)),(C11/360)*PI()*(C19^2)*C6) -> 180.56285 | D25: mm2
B26: Density | C26: =VLOOKUP(C23,Density,2,0) -> 1.35 | D26: g/cm3
B28: Inner Sheath
B29: Material | C29: PVC
B30: Minimum Thickness | C30: 0.3 | D30: mm
B31: Calculated diameter below innersheath | C31: =C37-2*C30 -> 17.4 | D31: mm
B32: Density of Conductor | C32: =VLOOKUP(C29,Density,2,0) -> 1.35 | D32: g/cm3
B34: Armour
B35: Material | C35: Unarmored
B36: Thickness of armour | C36: 0 | D36: mm
B37: Calculated diameter below armor | C37: =C43-2*C36 -> 18 | D37: mm
B38: Density of Conductor | C38: =VLOOKUP(C35,Armordensity,2,0) -> 0 | D38: g/cm3
B40: Outer Sheath
B41: Material | C41: PVC
B42: Minimum Thickness | C42: 2 | D42: mm
B43: Calculated diameter below outersheath | C43: =C46-(2*C42) -> 18 | D43: mm
B44: Density of Conductor | C44: =VLOOKUP(C41,Density,2,0) -> 1.35 | D44: g/cm3
B46: Overall OD of Cable | C46: 22
A48: ="COST SHEET FOR "&C6 & " CORE "&C9&" SQMM "&C10&" CABLE" -> COST SHEET FOR 3 CORE 35 SQMM Aluminium CABLE
A50: ASSUMPTIONS | G50: CALCULATION - SCENARIO 1
B52: Wastage Assumptions | H52: Material Cost Estimation | J52: Loading | K52: %
B53: =C10 -> Aluminium | C53: 0.02 | H53: ="Cost of"&" "&C10 -> Cost of Aluminium | L53: Rs | M53: =D67*C60 -> 37346.306
B54: Steel | C54: 0.02 | H54: Cost of PVC | L54: Rs | M54: =IF(C17="PVC",(D68+D69+D70+D72)*C61,(D69+D70+D72)*C61) -> 14793.518
B55: PVC | C55: 0.025 | H55: Cost of Steel | L55: Rs | M55: =D71*C62 -> 0
B56: XLPE | C56: 0.025 | H56: Cost of XLPE | L56: Rs | M56: =IF(C17="XLPE",D68*C63,0) -> 6489.2086
H57: Material Cost per Km | L57: Rs | M57: =M53+M54+M55+M56 -> 58629.032
B58: Price Assumptions
B59: Material | C59: Rs/Kg | H59: Other Costs as a % of Total Cost
B60: =C10 -> Aluminium | C60: =VLOOKUP(B60,'Data Input'!$M$3:$N$6,2,0) -> 129.15 | H60: Other Manufacturing Costs | L60: Rs | M60: =C78/$C$77*$M$57 -> 3448.7666
B61: PVC | C61: =VLOOKUP(B61,'Data Input'!$M$3:$N$6,2,0) -> 75.075 | H61: Energy Cost | L61: Rs | M61: =M57/C77*C79 -> 2069.26
B62: Steel Wire | C62: =VLOOKUP(B62,'Data Input'!$M$3:$N$6,2,0) -> 42 | H62: Labour Cost | L62: Rs | M62: =$M$57/$C$77*C80 -> 1379.5066
B63: XLPE | C63: =(1+E63)*C61 -> 90.09 | D63: 20% over PVC | E63: 0.2 | H63: Administrative and Other Expenses | L63: Rs | M63: =$M$57/$C$77*C81 -> 2069.26
H64: Overheads and Finance Costs | L64: Rs | M64: =$M$57/$C$77*C82 -> 1379.5066
B65: Material Composition Estimates per Km of Cable | H65: Total Costs | L65: Rs | M65: =SUM(M60:M64)+M57 -> 68975.332
B66: =C6&" core"&" "&C9&" sq.mm"&" "&C10&" cable" -> 3 core 35 sq.mm Aluminium cable | C66: Used in Cable (Kg) | D66: Including Wastage (Kg)
B67: ="Weight of"&" "&C10 -> Weight of Aluminium | C67: =(C9*10^-3*C14*10^3*IF(C6=3.5,3,C6))+(C9*10^-3*C14*10^3*IF(C6=3.5,1,0)) -> 283.5 | D67: =C67*(1+C53) -> 289.17 | H67: Special Construction costs
B68: Weight of Insulation | C68: =IF(C6=3.5,((C11/360)*PI()*(C19^2-C13^2)*C20*3)+((C12/360)*PI()*(C19^2-C13^2)*C20),(C11/360)*PI()*(C19^2-C13^2)*C20*C6) -> 70.273451 | D68: =C68*(1+C55) -> 72.030287 | H68: FRLS PVC inner sheath construction cost | J68: Y | K68: 0.025 | L68: Rs | M68: =IF(J68="Y",K68*$M$65,0) -> 1724.3833
B69: Weight of Inner Sheath | C69: =PI()*($C$37^2-$C$31^2)/4*$C$32 -> 22.520507 | D69: =C69*(1+C55) -> 23.08352 | H69: FRLS PVC outer sheath construction cost | J69: Y | K69: 0.025 | L69: Rs | M69: =IF(J69="Y",K69*$M$65,0) -> 1724.3833
B70: Weight of Outer Sheath | C70: =PI()*($C$46^2-$C$43^2)/4*$C$44 -> 169.646 | D70: =C70*(1+C55) -> 173.88715 | H70: LSZH Inner sheath construction cost | J70: N | K70: 0.1 | L70: Rs | M70: =IF(J70="Y",K70*$M$65,0) -> 0
B71: Weight of Armour | C71: =PI()*($C$43^2-$C$37^2)/4*$C$38 -> 0 | D71: =C71*(1+C54) -> 0 | H71: LSZH outersheath construction cost | J71: N | K71: 0.1 | L71: Rs | M71: =IF(J71="Y",K71*$M$65,0) -> 0
B72: Weight of PVC Filler | C72: =(C24-C25)*C26/1000 -> 0.077252801 | D72: =C72*(1+C55) -> 0.079184121 | H72: Oxygen Index(Outer sheath) | J72: N | K72: 0.025 | L72: Rs | M72: =IF(J72="Y",K72*$M$65,0) -> 0
H73: HRPVC Inner Sheath | J73: N | K73: 0.02 | L73: Rs | M73: =IF(J73="Y",K73*$M$65,0) -> 0
H74: HRPVC Outer Sheath | J74: N | K74: 0.02 | L74: Rs | M74: =IF(J74="Y",K74*$M$65,0) -> 0
H75: Extruded PVC Inner sheath- Upto 50 sq.mm | J75: N | K75: 0.03 | L75: Rs | M75: =IF(J75="Y",K75*$M$65,0) -> 0
B76: Costs as a % of Material Cost | C76: % | H76: Extruded PVC Inner sheath-70 sq.mm | J76: N | K76: 0.025 | L76: Rs | M76: =IF(J76="Y",K76*$M$65,0) -> 0
B77: Material Costs | C77: 0.85 | H77: Stranding of Conductor | J77: N | K77: 0.015 | L77: Rs | M77: =IF(J77="Y",K77*$M$65,0) -> 0
B78: Other Manufacturing expenses | C78: 0.05 | H78: Total Cable Costs | L78: Rs | M78: =M65+SUM(M68:M77) -> 72424.098
B79: Energy Costs | C79: 0.03
B80: Labour Costs | C80: 0.02 | H80: Selling Price | M80: =M78*(1+C84) -> 77855.906
B81: Administrative and Other expenses | C81: 0.03
B82: Overheads and Finance Costs | C82: 0.02
B84: Margins | C84: 0.075

Sheet Al LT Cables (3 x 50)
B1: =#REF! -> #REF! | C1: =SUM(D67:D72) -> 729.90387
B2: ="Cost Sheet for"&" "&C6&" Core"&" "&C9&" sq.mm"&" "&C10&" Cable" -> Cost Sheet for 3 Core 50 sq.mm Aluminium Cable
B4: Data Inputs
B6: No. of cores | C6: 3
B7: Shape of the core | C7: Sector shaped
B8: Conductor
B9: Conductor Size (in sq. mm) | C9: 50 | D9: sq. mm
B10: Conductor Material | C10: Aluminium | L10: =2*L9 -> 0
B11: Angle - Main | C11: =IF(C7="Sector shaped", (360/C6),360) -> 120
B12: Angle - Main | C12: =IF(C7="Sector shaped",360-C11*3,0) -> 0
B13: Conductor Radius | C13: =SQRT((C9*(360/C11))/PI()) -> 6.909883 | D13: mm
B14: Density of Conductor | C14: =VLOOKUP(C10,Density1,2,0) -> 2.7 | D14: g/cm3
B16: Insulation
B17: Material | C17: XLPE
B18: Nominal thickness of insulation | C18: 1
B19: Calculated radius over insulation | C19: =IF(C7="Circular", C13+C18,C13+2*C18) -> 8.909883 | D19: mm
B20: Density of Conductor | C20: =VLOOKUP(C17,Density,2,0) -> 0.93 | D20: g/cm3
B22: PVC Filler
B23: Filler Type | C23: PVC
B24: Area below inner sheath | C24: =PI()*((C31/2)^2) -> 311.02553 | D24: mm2
B25: Area till insulation | C25: =IF(C6=3.5,((C11/360)*PI()*(C19^2)*3)+((C12/360)*PI()*(C19^2)),(C11/360)*PI()*(C19^2)*C6) -> 249.39852 | D25: mm2
B26: Density | C26: =VLOOKUP(C23,Density,2,0) -> 1.35 | D26: g/cm3
B28: Inner Sheath
B29: Material | C29: PVC
B30: Minimum Thickness | C30: 0.3 | D30: mm
B31: Calculated diameter below innersheath | C31: =C37-2*C30 -> 19.9 | D31: mm
B32: Density of Conductor | C32: =VLOOKUP(C29,Density,2,0) -> 1.35 | D32: g/cm3
B34: Armour
B35: Material | C35: Unarmored
B36: Thickness of armour | C36: 0 | D36: mm
B37: Calculated diameter below armor | C37: =C43-2*C36 -> 20.5 | D37: mm
B38: Density of Conductor | C38: =VLOOKUP(C35,Armordensity,2,0) -> 0 | D38: g/cm3
B40: Outer Sheath
B41: Material | C41: PVC
B42: Minimum Thickness | C42: 2 | D42: mm
B43: Calculated diameter below outersheath | C43: =C46-(2*C42) -> 20.5 | D43: mm
B44: Density of Conductor | C44: =VLOOKUP(C41,Density,2,0) -> 1.35 | D44: g/cm3
B46: Overall OD of Cable | C46: 24.5
A48: ="COST SHEET FOR "&C6 & " CORE "&C9&" SQMM "&C10&" CABLE" -> COST SHEET FOR 3 CORE 50 SQMM Aluminium CABLE
A50: ASSUMPTIONS | G50: CALCULATION - SCENARIO 1
B52: Wastage Assumptions | H52: Material Cost Estimation | J52: Loading | K52: %
B53: =C10 -> Aluminium | C53: 0.02 | H53: ="Cost of"&" "&C10 -> Cost of Aluminium | L53: Rs | M53: =D67*C60 -> 53351.865
B54: Steel | C54: 0.02 | H54: Cost of PVC | L54: Rs | M54: =IF(C17="PVC",(D68+D69+D70+D72)*C61,(D69+D70+D72)*C61) -> 16670.571
B55: PVC | C55: 0.025 | H55: Cost of Steel | L55: Rs | M55: =D71*C62 -> 0
B56: XLPE | C56: 0.025 | H56: Cost of XLPE | L56: Rs | M56: =IF(C17="XLPE",D68*C63,0) -> 8536.1753
H57: Material Cost per Km | L57: Rs | M57: =M53+M54+M55+M56 -> 78558.611
B58: Price Assumptions
B59: Material | C59: Rs/Kg | H59: Other Costs as a % of Total Cost
B60: =C10 -> Aluminium | C60: =VLOOKUP(B60,'Data Input'!$M$3:$N$6,2,0) -> 129.15 | H60: Other Manufacturing Costs | L60: Rs | M60: =C78/$C$77*$M$57 -> 4621.0948
B61: PVC | C61: =VLOOKUP(B61,'Data Input'!$M$3:$N$6,2,0) -> 75.075 | H61: Energy Cost | L61: Rs | M61: =M57/C77*C79 -> 2772.6569
B62: Steel Wire | C62: =VLOOKUP(B62,'Data Input'!$M$3:$N$6,2,0) -> 42 | H62: Labour Cost | L62: Rs | M62: =$M$57/$C$77*C80 -> 1848.4379
B63: XLPE | C63: =(1+E63)*C61 -> 90.09 | D63: 20% over PVC | E63: 0.2 | H63: Administrative and Other Expenses | L63: Rs | M63: =$M$57/$C$77*C81 -> 2772.6569
H64: Overheads and Finance Costs | L64: Rs | M64: =$M$57/$C$77*C82 -> 1848.4379
B65: Material Composition Estimates per Km of Cable | H65: Total Costs | L65: Rs | M65: =SUM(M60:M64)+M57 -> 92421.896
B66: =C6&" core"&" "&C9&" sq.mm"&" "&C10&" cable" -> 3 core 50 sq.mm Aluminium cable | C66: Used in Cable (Kg) | D66: Including Wastage (Kg)
B67: ="Weight of"&" "&C10 -> Weight of Aluminium | C67: =(C9*10^-3*C14*10^3*IF(C6=3.5,3,C6))+(C9*10^-3*C14*10^3*IF(C6=3.5,1,0)) -> 405 | D67: =C67*(1+C53) -> 413.1 | H67: Special Construction costs
B68: Weight of Insulation | C68: =IF(C6=3.5,((C11/360)*PI()*(C19^2-C13^2)*C20*3)+((C12/360)*PI()*(C19^2-C13^2)*C20),(C11/360)*PI()*(C19^2-C13^2)*C20*C6) -> 92.440625 | D68: =C68*(1+C55) -> 94.75164 | H68: FRLS PVC inner sheath construction cost | J68: Y | K68: 0.025 | L68: Rs | M68: =IF(J68="Y",K68*$M$65,0) -> 2310.5474
B69: Weight of Inner Sheath | C69: =PI()*($C$37^2-$C$31^2)/4*$C$32 -> 25.701369 | D69: =C69*(1+C55) -> 26.343904 | H69: FRLS PVC outer sheath construction cost | J69: Y | K69: 0.025 | L69: Rs | M69: =IF(J69="Y",K69*$M$65,0) -> 2310.5474
B70: Weight of Outer Sheath | C70: =PI()*($C$46^2-$C$43^2)/4*$C$44 -> 190.85175 | D70: =C70*(1+C55) -> 195.62305 | H70: LSZH Inner sheath construction cost | J70: N | K70: 0.1 | L70: Rs | M70: =IF(J70="Y",K70*$M$65,0) -> 0
B71: Weight of Armour | C71: =PI()*($C$43^2-$C$37^2)/4*$C$38 -> 0 | D71: =C71*(1+C54) -> 0 | H71: LSZH outersheath construction cost | J71: N | K71: 0.1 | L71: Rs | M71: =IF(J71="Y",K71*$M$65,0) -> 0
B72: Weight of PVC Filler | C72: =(C24-C25)*C26/1000 -> 0.083196457 | D72: =C72*(1+C55) -> 0.085276369 | H72: Oxygen Index(Outer sheath) | J72: N | K72: 0.025 | L72: Rs | M72: =IF(J72="Y",K72*$M$65,0) -> 0
H73: HRPVC Inner Sheath | J73: N | K73: 0.02 | L73: Rs | M73: =IF(J73="Y",K73*$M$65,0) -> 0
H74: HRPVC Outer Sheath | J74: N | K74: 0.02 | L74: Rs | M74: =IF(J74="Y",K74*$M$65,0) -> 0
H75: Extruded PVC Inner sheath- Upto 50 sq.mm | J75: N | K75: 0.03 | L75: Rs | M75: =IF(J75="Y",K75*$M$65,0) -> 0
B76: Costs as a % of Material Cost | C76: % | H76: Extruded PVC Inner sheath-70 sq.mm | J76: N | K76: 0.025 | L76: Rs | M76: =IF(J76="Y",K76*$M$65,0) -> 0
B77: Material Costs | C77: 0.85 | H77: Stranding of Conductor | J77: N | K77: 0.015 | L77: Rs | M77: =IF(J77="Y",K77*$M$65,0) -> 0
B78: Other Manufacturing expenses | C78: 0.05 | H78: Total Cable Costs | L78: Rs | M78: =M65+SUM(M68:M77) -> 97042.99
B79: Energy Costs | C79: 0.03
B80: Labour Costs | C80: 0.02 | H80: Selling Price | M80: =M78*(1+C84) -> 104321.21
B81: Administrative and Other expenses | C81: 0.03
B82: Overheads and Finance Costs | C82: 0.02
B84: Margins | C84: 0.075

Sheet Al LT Cables (3 x 70)
B1: =#REF! -> #REF! | C1: =SUM(D67:D72) -> 993.42732
B2: ="Cost Sheet for"&" "&C6&" Core"&" "&C9&" sq.mm"&" "&C10&" Cable" -> Cost Sheet for 3 Core 70 sq.mm Aluminium Cable
B4: Data Inputs
B6: No. of cores | C6: 3
B7: Shape of the core | C7: Sector shaped
B8: Conductor
B9: Conductor Size (in sq. mm) | C9: 70 | D9: sq. mm
B10: Conductor Material | C10: Aluminium | L10: =2*L9 -> 0
B11: Angle - Main | C11: =IF(C7="Sector shaped", (360/C6),360) -> 120
B12: Angle - Main | C12: =IF(C7="Sector shaped",360-C11*3,0) -> 0
B13: Conductor Radius | C13: =SQRT((C9*(360/C11))/PI()) -> 8.1758838 | D13: mm
B14: Density of Conductor | C14: =VLOOKUP(C10,Density1,2,0) -> 2.7 | D14: g/cm3
B16: Insulation
B17: Material | C17: XLPE
B18: Nominal thickness of insulation | C18: 1.1
B19: Calculated radius over insulation | C19: =IF(C7="Circular", C13+C18,C13+2*C18) -> 10.375884 | D19: mm
B20: Density of Conductor | C20: =VLOOKUP(C17,Density,2,0) -> 0.93 | D20: g/cm3
B22: PVC Filler
B23: Filler Type | C23: PVC
B24: Area below inner sheath | C24: =PI()*((C31/2)^2) -> 426.38481 | D24: mm2
B25: Area till insulation | C25: =IF(C6=3.5,((C11/360)*PI()*(C19^2)*3)+((C12/360)*PI()*(C19^2)),(C11/360)*PI()*(C19^2)*C6) -> 338.22061 | D25: mm2
B26: Density | C26: =VLOOKUP(C23,Density,2,0) -> 1.35 | D26: g/cm3
B28: Inner Sheath
B29: Material | C29: PVC
B30: Minimum Thickness | C30: 0.4 | D30: mm
B31: Calculated diameter below innersheath | C31: =C37-2*C30 -> 23.3 | D31: mm
B32: Density of Conductor | C32: =VLOOKUP(C29,Density,2,0) -> 1.35 | D32: g/cm3
B34: Armour
B35: Material | C35: Unarmored
B36: Thickness of armour | C36: 0 | D36: mm
B37: Calculated diameter below armor | C37: =C43-2*C36 -> 24.1 | D37: mm
B38: Density of Conductor | C38: =VLOOKUP(C35,Armordensity,2,0) -> 0 | D38: g/cm3
B40: Outer Sheath
B41: Material | C41: PVC
B42: Minimum Thickness | C42: 2.2 | D42: mm
B43: Calculated diameter below outersheath | C43: =C46-(2*C42) -> 24.1 | D43: mm
B44: Density of Conductor | C44: =VLOOKUP(C41,Density,2,0) -> 1.35 | D44: g/cm3
B46: Overall OD of Cable | C46: 28.5
A48: ="COST SHEET FOR "&C6 & " CORE "&C9&" SQMM "&C10&" CABLE" -> COST SHEET FOR 3 CORE 70 SQMM Aluminium CABLE
A50: ASSUMPTIONS | G50: CALCULATION - SCENARIO 1
B52: Wastage Assumptions | H52: Material Cost Estimation | J52: Loading | K52: %
B53: =C10 -> Aluminium | C53: 0.02 | H53: ="Cost of"&" "&C10 -> Cost of Aluminium | L53: Rs | M53: =D67*C60 -> 74692.611
B54: Steel | C54: 0.02 | H54: Cost of PVC | L54: Rs | M54: =IF(C17="PVC",(D68+D69+D70+D72)*C61,(D69+D70+D72)*C61) -> 21986.541
B55: PVC | C55: 0.025 | H55: Cost of Steel | L55: Rs | M55: =D71*C62 -> 0
B56: XLPE | C56: 0.025 | H56: Cost of XLPE | L56: Rs | M56: =IF(C17="XLPE",D68*C63,0) -> 11011.367
H57: Material Cost per Km | L57: Rs | M57: =M53+M54+M55+M56 -> 107690.52
B58: Price Assumptions
B59: Material | C59: Rs/Kg | H59: Other Costs as a % of Total Cost
B60: =C10 -> Aluminium | C60: =VLOOKUP(B60,'Data Input'!$M$3:$N$6,2,0) -> 129.15 | H60: Other Manufacturing Costs | L60: Rs | M60: =C78/$C$77*$M$57 -> 6334.7364
B61: PVC | C61: =VLOOKUP(B61,'Data Input'!$M$3:$N$6,2,0) -> 75.075 | H61: Energy Cost | L61: Rs | M61: =M57/C77*C79 -> 3800.8419
B62: Steel Wire | C62: =VLOOKUP(B62,'Data Input'!$M$3:$N$6,2,0) -> 42 | H62: Labour Cost | L62: Rs | M62: =$M$57/$C$77*C80 -> 2533.8946
B63: XLPE | C63: =(1+E63)*C61 -> 90.09 | D63: 20% over PVC | E63: 0.2 | H63: Administrative and Other Expenses | L63: Rs | M63: =$M$57/$C$77*C81 -> 3800.8419
H64: Overheads and Finance Costs | L64: Rs | M64: =$M$57/$C$77*C82 -> 2533.8946
B65: Material Composition Estimates per Km of Cable | H65: Total Costs | L65: Rs | M65: =SUM(M60:M64)+M57 -> 126694.73
B66: =C6&" core"&" "&C9&" sq.mm"&" "&C10&" cable" -> 3 core 70 sq.mm Aluminium cable | C66: Used in Cable (Kg) | D66: Including Wastage (Kg)
B67: ="Weight of"&" "&C10 -> Weight of Aluminium | C67: =(C9*10^-3*C14*10^3*IF(C6=3.5,3,C6))+(C9*10^-3*C14*10^3*IF(C6=3.5,1,0)) -> 567 | D67: =C67*(1+C53) -> 578.34 | H67: Special Construction costs
B68: Weight of Insulation | C68: =IF(C6=3.5,((C11/360)*PI()*(C19^2-C13^2)*C20*3)+((C12/360)*PI()*(C19^2-C13^2)*C20),(C11/360)*PI()*(C19^2-C13^2)*C20*C6) -> 119.24517 | D68: =C68*(1+C55) -> 122.2263 | H68: FRLS PVC inner sheath construction cost | J68: Y | K68: 0.025 | L68: Rs | M68: =IF(J68="Y",K68*$M$65,0) -> 3167.3682
B69: Weight of Inner Sheath | C69: =PI()*($C$37^2-$C$31^2)/4*$C$32 -> 40.206103 | D69: =C69*(1+C55) -> 41.211255 | H69: FRLS PVC outer sheath construction cost | J69: Y | K69: 0.025 | L69: Rs | M69: =IF(J69="Y",K69*$M$65,0) -> 3167.3682
B70: Weight of Outer Sheath | C70: =PI()*($C$46^2-$C$43^2)/4*$C$44 -> 245.39294 | D70: =C70*(1+C55) -> 251.52777 | H70: LSZH Inner sheath construction cost | J70: N | K70: 0.1 | L70: Rs | M70: =IF(J70="Y",K70*$M$65,0) -> 0
B71: Weight of Armour | C71: =PI()*($C$43^2-$C$37^2)/4*$C$38 -> 0 | D71: =C71*(1+C54) -> 0 | H71: LSZH outersheath construction cost | J71: N | K71: 0.1 | L71: Rs | M71: =IF(J71="Y",K71*$M$65,0) -> 0
B72: Weight of PVC Filler | C72: =(C24-C25)*C26/1000 -> 0.11902166 | D72: =C72*(1+C55) -> 0.12199721 | H72: Oxygen Index(Outer sheath) | J72: N | K72: 0.025 | L72: Rs | M72: =IF(J72="Y",K72*$M$65,0) -> 0
H73: HRPVC Inner Sheath | J73: N | K73: 0.02 | L73: Rs | M73: =IF(J73="Y",K73*$M$65,0) -> 0
H74: HRPVC Outer Sheath | J74: N | K74: 0.02 | L74: Rs | M74: =IF(J74="Y",K74*$M$65,0) -> 0
H75: Extruded PVC Inner sheath- Upto 50 sq.mm | J75: N | K75: 0.03 | L75: Rs | M75: =IF(J75="Y",K75*$M$65,0) -> 0
B76: Costs as a % of Material Cost | C76: % | H76: Extruded PVC Inner sheath-70 sq.mm | J76: N | K76: 0.025 | L76: Rs | M76: =IF(J76="Y",K76*$M$65,0) -> 0
B77: Material Costs | C77: 0.85 | H77: Stranding of Conductor | J77: N | K77: 0.015 | L77: Rs | M77: =IF(J77="Y",K77*$M$65,0) -> 0
B78: Other Manufacturing expenses | C78: 0.05 | H78: Total Cable Costs | L78: Rs | M78: =M65+SUM(M68:M77) -> 133029.47
B79: Energy Costs | C79: 0.03
B80: Labour Costs | C80: 0.02 | H80: Selling Price | M80: =M78*(1+C84) -> 143006.68
B81: Administrative and Other expenses | C81: 0.03
B82: Overheads and Finance Costs | C82: 0.02
B84: Margins | C84: 0.075

Sheet Al LT Cables (3 x 95)
B1: =#REF! -> #REF! | C1: =SUM(D67:D72) -> 1246.0098
B2: ="Cost Sheet for"&" "&C6&" Core"&" "&C9&" sq.mm"&" "&C10&" Cable" -> Cost Sheet for 3 Core 95 sq.mm Aluminium Cable
B4: Data Inputs
B6: No. of cores | C6: 3
B7: Shape of the core | C7: Sector shaped
B8: Conductor
B9: Conductor Size (in sq. mm) | C9: 95 | D9: sq. mm
B10: Conductor Material | C10: Aluminium | L10: =2*L9 -> 0
B11: Angle - Main | C11: =IF(C7="Sector shaped", (360/C6),360) -> 120
B12: Angle - Main | C12: =IF(C7="Sector shaped",360-C11*3,0) -> 0
B13: Conductor Radius | C13: =SQRT((C9*(360/C11))/PI()) -> 9.5246164 | D13: mm
B14: Density of Conductor | C14: =VLOOKUP(C10,Density1,2,0) -> 2.7 | D14: g/cm3
B16: Insulation
B17: Material | C17: XLPE
B18: Nominal thickness of insulation | C18: 1.1
B19: Calculated radius over insulation | C19: =IF(C7="Circular", C13+C18,C13+2*C18) -> 11.724616 | D19: mm
B20: Density of Conductor | C20: =VLOOKUP(C17,Density,2,0) -> 0.93 | D20: g/cm3
B22: PVC Filler
B23: Filler Type | C23: PVC
B24: Area below inner sheath | C24: =PI()*((C31/2)^2) -> 522.79243 | D24: mm2
B25: Area till insulation | C25: =IF(C6=3.5,((C11/360)*PI()*(C19^2)*3)+((C12/360)*PI()*(C19^2)),(C11/360)*PI()*(C19^2)*C6) -> 431.86415 | D25: mm2
B26: Density | C26: =VLOOKUP(C23,Density,2,0) -> 1.35 | D26: g/cm3
B28: Inner Sheath
B29: Material | C29: PVC
B30: Minimum Thickness | C30: 0.4 | D30: mm
B31: Calculated diameter below innersheath | C31: =C37-2*C30 -> 25.8 | D31: mm
B32: Density of Conductor | C32: =VLOOKUP(C29,Density,2,0) -> 1.35 | D32: g/cm3
B34: Armour
B35: Material | C35: Unarmored
B36: Thickness of armour | C36: 0 | D36: mm
B37: Calculated diameter below armor | C37: =C43-2*C36 -> 26.6 | D37: mm
B38: Density of Conductor | C38: =VLOOKUP(C35,Armordensity,2,0) -> 0 | D38: g/cm3
B40: Outer Sheath
B41: Material | C41: PVC
B42: Minimum Thickness | C42: 2.2 | D42: mm
B43: Calculated diameter below outersheath | C43: =C46-(2*C42) -> 26.6 | D43: mm
B44: Density of Conductor | C44: =VLOOKUP(C41,Density,2,0) -> 1.35 | D44: g/cm3
B46: Overall OD of Cable | C46: 31
A48: ="COST SHEET FOR "&C6 & " CORE "&C9&" SQMM "&C10&" CABLE" -> COST SHEET FOR 3 CORE 95 SQMM Aluminium CABLE
A50: ASSUMPTIONS | G50: CALCULATION - SCENARIO 1
B52: Wastage Assumptions | H52: Material Cost Estimation | J52: Loading | K52: %
B53: =C10 -> Aluminium | C53: 0.02 | H53: ="Cost of"&" "&C10 -> Cost of Aluminium | L53: Rs | M53: =D67*C60 -> 101368.54
B54: Steel | C54: 0.02 | H54: Cost of PVC | L54: Rs | M54: =IF(C17="PVC",(D68+D69+D70+D72)*C61,(D69+D70+D72)*C61) -> 24108.197
B55: PVC | C55: 0.025 | H55: Cost of Steel | L55: Rs | M55: =D71*C62 -> 0
B56: XLPE | C56: 0.025 | H56: Cost of XLPE | L56: Rs | M56: =IF(C17="XLPE",D68*C63,0) -> 12612.443
H57: Material Cost per Km | L57: Rs | M57: =M53+M54+M55+M56 -> 138089.18
B58: Price Assumptions
B59: Material | C59: Rs/Kg | H59: Other Costs as a % of Total Cost
B60: =C10 -> Aluminium | C60: =VLOOKUP(B60,'Data Input'!$M$3:$N$6,2,0) -> 129.15 | H60: Other Manufacturing Costs | L60: Rs | M60: =C78/$C$77*$M$57 -> 8122.8931
B61: PVC | C61: =VLOOKUP(B61,'Data Input'!$M$3:$N$6,2,0) -> 75.075 | H61: Energy Cost | L61: Rs | M61: =M57/C77*C79 -> 4873.7359
B62: Steel Wire | C62: =VLOOKUP(B62,'Data Input'!$M$3:$N$6,2,0) -> 42 | H62: Labour Cost | L62: Rs | M62: =$M$57/$C$77*C80 -> 3249.1573
B63: XLPE | C63: =(1+E63)*C61 -> 90.09 | D63: 20% over PVC | E63: 0.2 | H63: Administrative and Other Expenses | L63: Rs | M63: =$M$57/$C$77*C81 -> 4873.7359
H64: Overheads and Finance Costs | L64: Rs | M64: =$M$57/$C$77*C82 -> 3249.1573
B65: Material Composition Estimates per Km of Cable | H65: Total Costs | L65: Rs | M65: =SUM(M60:M64)+M57 -> 162457.86
B66: =C6&" core"&" "&C9&" sq.mm"&" "&C10&" cable" -> 3 core 95 sq.mm Aluminium cable | C66: Used in Cable (Kg) | D66: Including Wastage (Kg)
B67: ="Weight of"&" "&C10 -> Weight of Aluminium | C67: =(C9*10^-3*C14*10^3*IF(C6=3.5,3,C6))+(C9*10^-3*C14*10^3*IF(C6=3.5,1,0)) -> 769.5 | D67: =C67*(1+C53) -> 784.89 | H67: Special Construction costs
B68: Weight of Insulation | C68: =IF(C6=3.5,((C11/360)*PI()*(C19^2-C13^2)*C20*3)+((C12/360)*PI()*(C19^2-C13^2)*C20),(C11/360)*PI()*(C19^2-C13^2)*C20*C6) -> 136.58366 | D68: =C68*(1+C55) -> 139.99825 | H68: FRLS PVC inner sheath construction cost | J68: Y | K68: 0.025 | L68: Rs | M68: =IF(J68="Y",K68*$M$65,0) -> 4061.4466
B69: Weight of Inner Sheath | C69: =PI()*($C$37^2-$C$31^2)/4*$C$32 -> 44.447253 | D69: =C69*(1+C55) -> 45.558434 | H69: FRLS PVC outer sheath construction cost | J69: Y | K69: 0.025 | L69: Rs | M69: =IF(J69="Y",K69*$M$65,0) -> 4061.4466
B70: Weight of Outer Sheath | C70: =PI()*($C$46^2-$C$43^2)/4*$C$44 -> 268.71927 | D70: =C70*(1+C55) -> 275.43725 | H70: LSZH Inner sheath construction cost | J70: N | K70: 0.1 | L70: Rs | M70: =IF(J70="Y",K70*$M$65,0) -> 0
B71: Weight of Armour | C71: =PI()*($C$43^2-$C$37^2)/4*$C$38 -> 0 | D71: =C71*(1+C54) -> 0 | H71: LSZH outersheath construction cost | J71: N | K71: 0.1 | L71: Rs | M71: =IF(J71="Y",K71*$M$65,0) -> 0
B72: Weight of PVC Filler | C72: =(C24-C25)*C26/1000 -> 0.12275318 | D72: =C72*(1+C55) -> 0.12582201 | H72: Oxygen Index(Outer sheath) | J72: N | K72: 0.025 | L72: Rs | M72: =IF(J72="Y",K72*$M$65,0) -> 0
H73: HRPVC Inner Sheath | J73: N | K73: 0.02 | L73: Rs | M73: =IF(J73="Y",K73*$M$65,0) -> 0
H74: HRPVC Outer Sheath | J74: N | K74: 0.02 | L74: Rs | M74: =IF(J74="Y",K74*$M$65,0) -> 0
H75: Extruded PVC Inner sheath- Upto 50 sq.mm | J75: N | K75: 0.03 | L75: Rs | M75: =IF(J75="Y",K75*$M$65,0) -> 0
B76: Costs as a % of Material Cost | C76: % | H76: Extruded PVC Inner sheath-70 sq.mm | J76: N | K76: 0.025 | L76: Rs | M76: =IF(J76="Y",K76*$M$65,0) -> 0
B77: Material Costs | C77: 0.85 | H77: Stranding of Conductor | J77: N | K77: 0.015 | L77: Rs | M77: =IF(J77="Y",K77*$M$65,0) -> 0
B78: Other Manufacturing expenses | C78: 0.05 | H78: Total Cable Costs | L78: Rs | M78: =M65+SUM(M68:M77) -> 170580.76
B79: Energy Costs | C79: 0.03
B80: Labour Costs | C80: 0.02 | H80: Selling Price | M80: =M78*(1+C84) -> 183374.31
B81: Administrative and Other expenses | C81: 0.03
B82: Overheads and Finance Costs | C82: 0.02
B84: Margins | C84: 0.075

Sheet Al LT Cables (3 x 120)
B1: =#REF! -> #REF! | C1: =SUM(D67:D72) -> 1517.6253
B2: ="Cost Sheet for"&" "&C6&" Core"&" "&C9&" sq.mm"&" "&C10&" Cable" -> Cost Sheet for 3 Core 120 sq.mm Aluminium Cable
B4: Data Inputs
B6: No. of cores | C6: 3
B7: Shape of the core | C7: Sector shaped
B8: Conductor
B9: Conductor Size (in sq. mm) | C9: 120 | D9: sq. mm
B10: Conductor Material | C10: Aluminium | L10: =2*L9 -> 0
B11: Angle - Main | C11: =IF(C7="Sector shaped", (360/C6),360) -> 120
B12: Angle - Main | C12: =IF(C7="Sector shaped",360-C11*3,0) -> 0
B13: Conductor Radius | C13: =SQRT((C9*(360/C11))/PI()) -> 10.704745 | D13: mm
B14: Density of Conductor | C14: =VLOOKUP(C10,Density1,2,0) -> 2.7 | D14: g/cm3
B16: Insulation
B17: Material | C17: XLPE
B18: Nominal thickness of insulation | C18: 1.2
B19: Calculated radius over insulation | C19: =IF(C7="Circular", C13+C18,C13+2*C18) -> 13.104745 | D19: mm
B20: Density of Conductor | C20: =VLOOKUP(C17,Density,2,0) -> 0.93 | D20: g/cm3
B22: PVC Filler
B23: Filler Type | C23: PVC
B24: Area below inner sheath | C24: =PI()*((C31/2)^2) -> 651.44065 | D24: mm2
B25: Area till insulation | C25: =IF(C6=3.5,((C11/360)*PI()*(C19^2)*3)+((C12/360)*PI()*(C19^2)),(C11/360)*PI()*(C19^2)*C6) -> 539.51932 | D25: mm2
B26: Density | C26: =VLOOKUP(C23,Density,2,0) -> 1.35 | D26: g/cm3
B28: Inner Sheath
B29: Material | C29: PVC
B30: Minimum Thickness | C30: 0.4 | D30: mm
B31: Calculated diameter below innersheath | C31: =C37-2*C30 -> 28.8 | D31: mm
B32: Density of Conductor | C32: =VLOOKUP(C29,Density,2,0) -> 1.35 | D32: g/cm3
B34: Armour
B35: Material | C35: Unarmored
B36: Thickness of armour | C36: 0 | D36: mm
B37: Calculated diameter below armor | C37: =C43-2*C36 -> 29.6 | D37: mm
B38: Density of Conductor | C38: =VLOOKUP(C35,Armordensity,2,0) -> 0 | D38: g/cm3
B40: Outer Sheath
B41: Material | C41: PVC
B42: Minimum Thickness | C42: 2.2 | D42: mm
B43: Calculated diameter below outersheath | C43: =C46-(2*C42) -> 29.6 | D43: mm
B44: Density of Conductor | C44: =VLOOKUP(C41,Density,2,0) -> 1.35 | D44: g/cm3
B46: Overall OD of Cable | C46: 34
A48: ="COST SHEET FOR "&C6 & " CORE "&C9&" SQMM "&C10&" CABLE" -> COST SHEET FOR 3 CORE 120 SQMM Aluminium CABLE
A50: ASSUMPTIONS | G50: CALCULATION - SCENARIO 1
B52: Wastage Assumptions | H52: Material Cost Estimation | J52: Loading | K52: %
B53: =C10 -> Aluminium | C53: 0.02 | H53: ="Cost of"&" "&C10 -> Cost of Aluminium | L53: Rs | M53: =D67*C60 -> 128044.48
B54: Steel | C54: 0.02 | H54: Cost of PVC | L54: Rs | M54: =IF(C17="PVC",(D68+D69+D70+D72)*C61,(D69+D70+D72)*C61) -> 26656.021
B55: PVC | C55: 0.025 | H55: Cost of Steel | L55: Rs | M55: =D71*C62 -> 0
B56: XLPE | C56: 0.025 | H56: Cost of XLPE | L56: Rs | M56: =IF(C17="XLPE",D68*C63,0) -> 15416.813
H57: Material Cost per Km | L57: Rs | M57: =M53+M54+M55+M56 -> 170117.31
B58: Price Assumptions
B59: Material | C59: Rs/Kg | H59: Other Costs as a % of Total Cost
B60: =C10 -> Aluminium | C60: =VLOOKUP(B60,'Data Input'!$M$3:$N$6,2,0) -> 129.15 | H60: Other Manufacturing Costs | L60: Rs | M60: =C78/$C$77*$M$57 -> 10006.901
B61: PVC | C61: =VLOOKUP(B61,'Data Input'!$M$3:$N$6,2,0) -> 75.075 | H61: Energy Cost | L61: Rs | M61: =M57/C77*C79 -> 6004.1403
B62: Steel Wire | C62: =VLOOKUP(B62,'Data Input'!$M$3:$N$6,2,0) -> 42 | H62: Labour Cost | L62: Rs | M62: =$M$57/$C$77*C80 -> 4002.7602
B63: XLPE | C63: =(1+E63)*C61 -> 90.09 | D63: 20% over PVC | E63: 0.2 | H63: Administrative and Other Expenses | L63: Rs | M63: =$M$57/$C$77*C81 -> 6004.1403
H64: Overheads and Finance Costs | L64: Rs | M64: =$M$57/$C$77*C82 -> 4002.7602
B65: Material Composition Estimates per Km of Cable | H65: Total Costs | L65: Rs | M65: =SUM(M60:M64)+M57 -> 200138.01
B66: =C6&" core"&" "&C9&" sq.mm"&" "&C10&" cable" -> 3 core 120 sq.mm Aluminium cable | C66: Used in Cable (Kg) | D66: Including Wastage (Kg)
B67: ="Weight of"&" "&C10 -> Weight of Aluminium | C67: =(C9*10^-3*C14*10^3*IF(C6=3.5,3,C6))+(C9*10^-3*C14*10^3*IF(C6=3.5,1,0)) -> 972 | D67: =C67*(1+C53) -> 991.44 | H67: Special Construction costs
B68: Weight of Insulation | C68: =IF(C6=3.5,((C11/360)*PI()*(C19^2-C13^2)*C20*3)+((C12/360)*PI()*(C19^2-C13^2)*C20),(C11/360)*PI()*(C19^2-C13^2)*C20*C6) -> 166.95297 | D68: =C68*(1+C55) -> 171.12679 | H68: FRLS PVC inner sheath construction cost | J68: Y | K68: 0.025 | L68: Rs | M68: =IF(J68="Y",K68*$M$65,0) -> 5003.4503
B69: Weight of Inner Sheath | C69: =PI()*($C$37^2-$C$31^2)/4*$C$32 -> 49.536633 | D69: =C69*(1+C55) -> 50.775049 | H69: FRLS PVC outer sheath construction cost | J69: Y | K69: 0.025 | L69: Rs | M69: =IF(J69="Y",K69*$M$65,0) -> 5003.4503
B70: Weight of Outer Sheath | C70: =PI()*($C$46^2-$C$43^2)/4*$C$44 -> 296.71086 | D70: =C70*(1+C55) -> 304.12863 | H70: LSZH Inner sheath construction cost | J70: N | K70: 0.1 | L70: Rs | M70: =IF(J70="Y",K70*$M$65,0) -> 0
B71: Weight of Armour | C71: =PI()*($C$43^2-$C$37^2)/4*$C$38 -> 0 | D71: =C71*(1+C54) -> 0 | H71: LSZH outersheath construction cost | J71: N | K71: 0.1 | L71: Rs | M71: =IF(J71="Y",K71*$M$65,0) -> 0
B72: Weight of PVC Filler | C72: =(C24-C25)*C26/1000 -> 0.1510938 | D72: =C72*(1+C55) -> 0.15487114 | H72: Oxygen Index(Outer sheath) | J72: N | K72: 0.025 | L72: Rs | M72: =IF(J72="Y",K72*$M$65,0) -> 0
H73: HRPVC Inner Sheath | J73: N | K73: 0.02 | L73: Rs | M73: =IF(J73="Y",K73*$M$65,0) -> 0
H74: HRPVC Outer Sheath | J74: N | K74: 0.02 | L74: Rs | M74: =IF(J74="Y",K74*$M$65,0) -> 0
H75: Extruded PVC Inner sheath- Upto 50 sq.mm | J75: N | K75: 0.03 | L75: Rs | M75: =IF(J75="Y",K75*$M$65,0) -> 0
B76: Costs as a % of Material Cost | C76: % | H76: Extruded PVC Inner sheath-70 sq.mm | J76: N | K76: 0.025 | L76: Rs | M76: =IF(J76="Y",K76*$M$65,0) -> 0
B77: Material Costs | C77: 0.85 | H77: Stranding of Conductor | J77: N | K77: 0.015 | L77: Rs | M77: =IF(J77="Y",K77*$M$65,0) -> 0
B78: Other Manufacturing expenses | C78: 0.05 | H78: Total Cable Costs | L78: Rs | M78: =M65+SUM(M68:M77) -> 210144.91
B79: Energy Costs | C79: 0.03
B80: Labour Costs | C80: 0.02 | H80: Selling Price | M80: =M78*(1+C84) -> 225905.78
B81: Administrative and Other expenses | C81: 0.03
B82: Overheads and Finance Costs | C82: 0.02
B84: Margins | C84: 0.075

Sheet Al LT Cables (3 x 150)
B1: =#REF! -> #REF! | C1: =SUM(D67:D72) -> 1906.1699
B2: ="Cost Sheet for"&" "&C6&" Core"&" "&C9&" sq.mm"&" "&C10&" Cable" -> Cost Sheet for 3 Core 150 sq.mm Aluminium Cable
B4: Data Inputs
B6: No. of cores | C6: 3
B7: Shape of the core | C7: Sector shaped
B8: Conductor
B9: Conductor Size (in sq. mm) | C9: 150 | D9: sq. mm
B10: Conductor Material | C10: Aluminium | L10: =2*L9 -> 0
B11: Angle - Main | C11: =IF(C7="Sector shaped", (360/C6),360) -> 120
B12: Angle - Main | C12: =IF(C7="Sector shaped",360-C11*3,0) -> 0
B13: Conductor Radius | C13: =SQRT((C9*(360/C11))/PI()) -> 11.968268 | D13: mm
B14: Density of Conductor | C14: =VLOOKUP(C10,Density1,2,0) -> 2.7 | D14: g/cm3
B16: Insulation
B17: Material | C17: XLPE
B18: Nominal thickness of insulation | C18: 1.4
B19: Calculated radius over insulation | C19: =IF(C7="Circular", C13+C18,C13+2*C18) -> 14.768268 | D19: mm
B20: Density of Conductor | C20: =VLOOKUP(C17,Density,2,0) -> 0.93 | D20: g/cm3
B22: PVC Filler
B23: Filler Type | C23: PVC
B24: Area below inner sheath | C24: =PI()*((C31/2)^2) -> 814.33223 | D24: mm2
B25: Area till insulation | C25: =IF(C6=3.5,((C11/360)*PI()*(C19^2)*3)+((C12/360)*PI()*(C19^2)),(C11/360)*PI()*(C19^2)*C6) -> 685.18686 | D25: mm2
B26: Density | C26: =VLOOKUP(C23,Density,2,0) -> 1.35 | D26: g/cm3
B28: Inner Sheath
B29: Material | C29: PVC
B30: Minimum Thickness | C30: 0.5 | D30: mm
B31: Calculated diameter below innersheath | C31: =C37-2*C30 -> 32.2 | D31: mm
B32: Density of Conductor | C32: =VLOOKUP(C29,Density,2,0) -> 1.35 | D32: g/cm3
B34: Armour
B35: Material | C35: Unarmored
B36: Thickness of armour | C36: 0 | D36: mm
B37: Calculated diameter below armor | C37: =C43-2*C36 -> 33.2 | D37: mm
B38: Density of Conductor | C38: =VLOOKUP(C35,Armordensity,2,0) -> 0 | D38: g/cm3
B40: Outer Sheath
B41: Material | C41: PVC
B42: Minimum Thickness | C42: 2.4 | D42: mm
B43: Calculated diameter below outersheath | C43: =C46-(2*C42) -> 33.2 | D43: mm
B44: Density of Conductor | C44: =VLOOKUP(C41,Density,2,0) -> 1.35 | D44: g/cm3
B46: Overall OD of Cable | C46: 38
A48: ="COST SHEET FOR "&C6 & " CORE "&C9&" SQMM "&C10&" CABLE" -> COST SHEET FOR 3 CORE 150 SQMM Aluminium CABLE
A50: ASSUMPTIONS | G50: CALCULATION - SCENARIO 1
B52: Wastage Assumptions | H52: Material Cost Estimation | J52: Loading | K52: %
B53: =C10 -> Aluminium | C53: 0.02 | H53: ="Cost of"&" "&C10 -> Cost of Aluminium | L53: Rs | M53: =D67*C60 -> 160055.6
B54: Steel | C54: 0.02 | H54: Cost of PVC | L54: Rs | M54: =IF(C17="PVC",(D68+D69+D70+D72)*C61,(D69+D70+D72)*C61) -> 33234.054
B55: PVC | C55: 0.025 | H55: Cost of Steel | L55: Rs | M55: =D71*C62 -> 0
B56: XLPE | C56: 0.025 | H56: Cost of XLPE | L56: Rs | M56: =IF(C17="XLPE",D68*C63,0) -> 20197.446
H57: Material Cost per Km | L57: Rs | M57: =M53+M54+M55+M56 -> 213487.09
B58: Price Assumptions
B59: Material | C59: Rs/Kg | H59: Other Costs as a % of Total Cost
B60: =C10 -> Aluminium | C60: =VLOOKUP(B60,'Data Input'!$M$3:$N$6,2,0) -> 129.15 | H60: Other Manufacturing Costs | L60: Rs | M60: =C78/$C$77*$M$57 -> 12558.064
B61: PVC | C61: =VLOOKUP(B61,'Data Input'!$M$3:$N$6,2,0) -> 75.075 | H61: Energy Cost | L61: Rs | M61: =M57/C77*C79 -> 7534.8386
B62: Steel Wire | C62: =VLOOKUP(B62,'Data Input'!$M$3:$N$6,2,0) -> 42 | H62: Labour Cost | L62: Rs | M62: =$M$57/$C$77*C80 -> 5023.2258
B63: XLPE | C63: =(1+E63)*C61 -> 90.09 | D63: 20% over PVC | E63: 0.2 | H63: Administrative and Other Expenses | L63: Rs | M63: =$M$57/$C$77*C81 -> 7534.8386
H64: Overheads and Finance Costs | L64: Rs | M64: =$M$57/$C$77*C82 -> 5023.2258
B65: Material Composition Estimates per Km of Cable | H65: Total Costs | L65: Rs | M65: =SUM(M60:M64)+M57 -> 251161.29
B66: =C6&" core"&" "&C9&" sq.mm"&" "&C10&" cable" -> 3 core 150 sq.mm Aluminium cable | C66: Used in Cable (Kg) | D66: Including Wastage (Kg)
B67: ="Weight of"&" "&C10 -> Weight of Aluminium | C67: =(C9*10^-3*C14*10^3*IF(C6=3.5,3,C6))+(C9*10^-3*C14*10^3*IF(C6=3.5,1,0)) -> 1215 | D67: =C67*(1+C53) -> 1239.3 | H67: Special Construction costs
B68: Weight of Insulation | C68: =IF(C6=3.5,((C11/360)*PI()*(C19^2-C13^2)*C20*3)+((C12/360)*PI()*(C19^2-C13^2)*C20),(C11/360)*PI()*(C19^2-C13^2)*C20*C6) -> 218.72378 | D68: =C68*(1+C55) -> 224.19188 | H68: FRLS PVC inner sheath construction cost | J68: Y | K68: 0.025 | L68: Rs | M68: =IF(J68="Y",K68*$M$65,0) -> 6279.0322
B69: Weight of Inner Sheath | C69: =PI()*($C$37^2-$C$31^2)/4*$C$32 -> 69.342804 | D69: =C69*(1+C55) -> 71.076374 | H69: FRLS PVC outer sheath construction cost | J69: Y | K69: 0.025 | L69: Rs | M69: =IF(J69="Y",K69*$M$65,0) -> 6279.0322
B70: Weight of Outer Sheath | C70: =PI()*($C$46^2-$C$43^2)/4*$C$44 -> 362.36386 | D70: =C70*(1+C55) -> 371.42296 | H70: LSZH Inner sheath construction cost | J70: N | K70: 0.1 | L70: Rs | M70: =IF(J70="Y",K70*$M$65,0) -> 0
B71: Weight of Armour | C71: =PI()*($C$43^2-$C$37^2)/4*$C$38 -> 0 | D71: =C71*(1+C54) -> 0 | H71: LSZH outersheath construction cost | J71: N | K71: 0.1 | L71: Rs | M71: =IF(J71="Y",K71*$M$65,0) -> 0
B72: Weight of PVC Filler | C72: =(C24-C25)*C26/1000 -> 0.17434625 | D72: =C72*(1+C55) -> 0.17870491 | H72: Oxygen Index(Outer sheath) | J72: N | K72: 0.025 | L72: Rs | M72: =IF(J72="Y",K72*$M$65,0) -> 0
H73: HRPVC Inner Sheath | J73: N | K73: 0.02 | L73: Rs | M73: =IF(J73="Y",K73*$M$65,0) -> 0
H74: HRPVC Outer Sheath | J74: N | K74: 0.02 | L74: Rs | M74: =IF(J74="Y",K74*$M$65,0) -> 0
H75: Extruded PVC Inner sheath- Upto 50 sq.mm | J75: N | K75: 0.03 | L75: Rs | M75: =IF(J75="Y",K75*$M$65,0) -> 0
B76: Costs as a % of Material Cost | C76: % | H76: Extruded PVC Inner sheath-70 sq.mm | J76: N | K76: 0.025 | L76: Rs | M76: =IF(J76="Y",K76*$M$65,0) -> 0
B77: Material Costs | C77: 0.85 | H77: Stranding of Conductor | J77: N | K77: 0.015 | L77: Rs | M77: =IF(J77="Y",K77*$M$65,0) -> 0
B78: Other Manufacturing expenses | C78: 0.05 | H78: Total Cable Costs | L78: Rs | M78: =M65+SUM(M68:M77) -> 263719.35
B79: Energy Costs | C79: 0.03
B80: Labour Costs | C80: 0.02 | H80: Selling Price | M80: =M78*(1+C84) -> 283498.3
B81: Administrative and Other expenses | C81: 0.03
B82: Overheads and Finance Costs | C82: 0.02
B84: Margins | C84: 0.075

Sheet Al LT Cables (3 x 185)
B1: =#REF! -> #REF! | C1: =SUM(D67:D72) -> 2338.3193
B2: ="Cost Sheet for"&" "&C6&" Core"&" "&C9&" sq.mm"&" "&C10&" Cable" -> Cost Sheet for 3 Core 185 sq.mm Aluminium Cable
B4: Data Inputs
B6: No. of cores | C6: 3
B7: Shape of the core | C7: Sector shaped
B8: Conductor
B9: Conductor Size (in sq. mm) | C9: 185 | D9: sq. mm
B10: Conductor Material | C10: Aluminium | L10: =2*L9 -> 0
B11: Angle - Main | C11: =IF(C7="Sector shaped", (360/C6),360) -> 120
B12: Angle - Main | C12: =IF(C7="Sector shaped",360-C11*3,0) -> 0
B13: Conductor Radius | C13: =SQRT((C9*(360/C11))/PI()) -> 13.291425 | D13: mm
B14: Density of Conductor | C14: =VLOOKUP(C10,Density1,2,0) -> 2.7 | D14: g/cm3
B16: Insulation
B17: Material | C17: XLPE
B18: Nominal thickness of insulation | C18: 1.6
B19: Calculated radius over insulation | C19: =IF(C7="Circular", C13+C18,C13+2*C18) -> 16.491425 | D19: mm
B20: Density of Conductor | C20: =VLOOKUP(C17,Density,2,0) -> 0.93 | D20: g/cm3
B22: PVC Filler
B23: Filler Type | C23: PVC
B24: Area below inner sheath | C24: =PI()*((C31/2)^2) -> 1006.5977 | D24: mm2
B25: Area till insulation | C25: =IF(C6=3.5,((C11/360)*PI()*(C19^2)*3)+((C12/360)*PI()*(C19^2)),(C11/360)*PI()*(C19^2)*C6) -> 854.40987 | D25: mm2
B26: Density | C26: =VLOOKUP(C23,Density,2,0) -> 1.35 | D26: g/cm3
B28: Inner Sheath
B29: Material | C29: PVC
B30: Minimum Thickness | C30: 0.5 | D30: mm
B31: Calculated diameter below innersheath | C31: =C37-2*C30 -> 35.8 | D31: mm
B32: Density of Conductor | C32: =VLOOKUP(C29,Density,2,0) -> 1.35 | D32: g/cm3
B34: Armour
B35: Material | C35: Unarmored
B36: Thickness of armour | C36: 0 | D36: mm
B37: Calculated diameter below armor | C37: =C43-2*C36 -> 36.8 | D37: mm
B38: Density of Conductor | C38: =VLOOKUP(C35,Armordensity,2,0) -> 0 | D38: g/cm3
B40: Outer Sheath
B41: Material | C41: PVC
B42: Minimum Thickness | C42: 2.6 | D42: mm
B43: Calculated diameter below outersheath | C43: =C46-(2*C42) -> 36.8 | D43: mm
B44: Density of Conductor | C44: =VLOOKUP(C41,Density,2,0) -> 1.35 | D44: g/cm3
B46: Overall OD of Cable | C46: 42
A48: ="COST SHEET FOR "&C6 & " CORE "&C9&" SQMM "&C10&" CABLE" -> COST SHEET FOR 3 CORE 185 SQMM Aluminium CABLE
A50: ASSUMPTIONS | G50: CALCULATION - SCENARIO 1
B52: Wastage Assumptions | H52: Material Cost Estimation | J52: Loading | K52: %
B53: =C10 -> Aluminium | C53: 0.02 | H53: ="Cost of"&" "&C10 -> Cost of Aluminium | L53: Rs | M53: =D67*C60 -> 197401.9
B54: Steel | C54: 0.02 | H54: Cost of PVC | L54: Rs | M54: =IF(C17="PVC",(D68+D69+D70+D72)*C61,(D69+D70+D72)*C61) -> 39372.099
B55: PVC | C55: 0.025 | H55: Cost of Steel | L55: Rs | M55: =D71*C62 -> 0
B56: XLPE | C56: 0.025 | H56: Cost of XLPE | L56: Rs | M56: =IF(C17="XLPE",D68*C63,0) -> 25712.808
H57: Material Cost per Km | L57: Rs | M57: =M53+M54+M55+M56 -> 262486.81
B58: Price Assumptions
B59: Material | C59: Rs/Kg | H59: Other Costs as a % of Total Cost
B60: =C10 -> Aluminium | C60: =VLOOKUP(B60,'Data Input'!$M$3:$N$6,2,0) -> 129.15 | H60: Other Manufacturing Costs | L60: Rs | M60: =C78/$C$77*$M$57 -> 15440.4
B61: PVC | C61: =VLOOKUP(B61,'Data Input'!$M$3:$N$6,2,0) -> 75.075 | H61: Energy Cost | L61: Rs | M61: =M57/C77*C79 -> 9264.2403
B62: Steel Wire | C62: =VLOOKUP(B62,'Data Input'!$M$3:$N$6,2,0) -> 42 | H62: Labour Cost | L62: Rs | M62: =$M$57/$C$77*C80 -> 6176.1602
B63: XLPE | C63: =(1+E63)*C61 -> 90.09 | D63: 20% over PVC | E63: 0.2 | H63: Administrative and Other Expenses | L63: Rs | M63: =$M$57/$C$77*C81 -> 9264.2403
H64: Overheads and Finance Costs | L64: Rs | M64: =$M$57/$C$77*C82 -> 6176.1602
B65: Material Composition Estimates per Km of Cable | H65: Total Costs | L65: Rs | M65: =SUM(M60:M64)+M57 -> 308808.01
B66: =C6&" core"&" "&C9&" sq.mm"&" "&C10&" cable" -> 3 core 185 sq.mm Aluminium cable | C66: Used in Cable (Kg) | D66: Including Wastage (Kg)
B67: ="Weight of"&" "&C10 -> Weight of Aluminium | C67: =(C9*10^-3*C14*10^3*IF(C6=3.5,3,C6))+(C9*10^-3*C14*10^3*IF(C6=3.5,1,0)) -> 1498.5 | D67: =C67*(1+C53) -> 1528.47 | H67: Special Construction costs
B68: Weight of Insulation | C68: =IF(C6=3.5,((C11/360)*PI()*(C19^2-C13^2)*C20*3)+((C12/360)*PI()*(C19^2-C13^2)*C20),(C11/360)*PI()*(C19^2-C13^2)*C20*C6) -> 278.45118 | D68: =C68*(1+C55) -> 285.41246 | H68: FRLS PVC inner sheath construction cost | J68: Y | K68: 0.025 | L68: Rs | M68: =IF(J68="Y",K68*$M$65,0) -> 7720.2002
B69: Weight of Inner Sheath | C69: =PI()*($C$37^2-$C$31^2)/4*$C$32 -> 76.976874 | D69: =C69*(1+C55) -> 78.901296 | H69: FRLS PVC outer sheath construction cost | J69: Y | K69: 0.025 | L69: Rs | M69: =IF(J69="Y",K69*$M$65,0) -> 7720.2002
B70: Weight of Outer Sheath | C70: =PI()*($C$46^2-$C$43^2)/4*$C$44 -> 434.46341 | D70: =C70*(1+C55) -> 445.325 | H70: LSZH Inner sheath construction cost | J70: N | K70: 0.1 | L70: Rs | M70: =IF(J70="Y",K70*$M$65,0) -> 0
B71: Weight of Armour | C71: =PI()*($C$43^2-$C$37^2)/4*$C$38 -> 0 | D71: =C71*(1+C54) -> 0 | H71: LSZH outersheath construction cost | J71: N | K71: 0.1 | L71: Rs | M71: =IF(J71="Y",K71*$M$65,0) -> 0
B72: Weight of PVC Filler | C72: =(C24-C25)*C26/1000 -> 0.20545357 | D72: =C72*(1+C55) -> 0.21058991 | H72: Oxygen Index(Outer sheath) | J72: N | K72: 0.025 | L72: Rs | M72: =IF(J72="Y",K72*$M$65,0) -> 0
H73: HRPVC Inner Sheath | J73: N | K73: 0.02 | L73: Rs | M73: =IF(J73="Y",K73*$M$65,0) -> 0
H74: HRPVC Outer Sheath | J74: N | K74: 0.02 | L74: Rs | M74: =IF(J74="Y",K74*$M$65,0) -> 0
H75: Extruded PVC Inner sheath- Upto 50 sq.mm | J75: N | K75: 0.03 | L75: Rs | M75: =IF(J75="Y",K75*$M$65,0) -> 0
B76: Costs as a % of Material Cost | C76: % | H76: Extruded PVC Inner sheath-70 sq.mm | J76: N | K76: 0.025 | L76: Rs | M76: =IF(J76="Y",K76*$M$65,0) -> 0
B77: Material Costs | C77: 0.85 | H77: Stranding of Conductor | J77: N | K77: 0.015 | L77: Rs | M77: =IF(J77="Y",K77*$M$65,0) -> 0
B78: Other Manufacturing expenses | C78: 0.05 | H78: Total Cable Costs | L78: Rs | M78: =M65+SUM(M68:M77) -> 324248.41
B79: Energy Costs | C79: 0.03
B80: Labour Costs | C80: 0.02 | H80: Selling Price | M80: =M78*(1+C84) -> 348567.04
B81: Administrative and Other expenses | C81: 0.03
B82: Overheads and Finance Costs | C82: 0.02
B84: Margins | C84: 0.075

Sheet Al LT Cables (3 x 240)
B1: =#REF! -> #REF! | C1: =SUM(D67:D72) -> 2977.9094
B2: ="Cost Sheet for"&" "&C6&" Core"&" "&C9&" sq.mm"&" "&C10&" Cable" -> Cost Sheet for 3 Core 240 sq.mm Aluminium Cable
B4: Data Inputs
B6: No. of cores | C6: 3
B7: Shape of the core | C7: Sector shaped
B8: Conductor
B9: Conductor Size (in sq. mm) | C9: 240 | D9: sq. mm
B10: Conductor Material | C10: Aluminium | L10: =2*L9 -> 0
B11: Angle - Main | C11: =IF(C7="Sector shaped", (360/C6),360) -> 120
B12: Angle - Main | C12: =IF(C7="Sector shaped",360-C11*3,0) -> 0
B13: Conductor Radius | C13: =SQRT((C9*(360/C11))/PI()) -> 15.138795 | D13: mm
B14: Density of Conductor | C14: =VLOOKUP(C10,Density1,2,0) -> 2.7 | D14: g/cm3
B16: Insulation
B17: Material | C17: XLPE
B18: Nominal thickness of insulation | C18: 1.7
B19: Calculated radius over insulation | C19: =IF(C7="Circular", C13+C18,C13+2*C18) -> 18.538795 | D19: mm
B20: Density of Conductor | C20: =VLOOKUP(C17,Density,2,0) -> 0.93 | D20: g/cm3
B22: PVC Filler
B23: Filler Type | C23: PVC
B24: Area below inner sheath | C24: =PI()*((C31/2)^2) -> 1301.0042 | D24: mm2
B25: Area till insulation | C25: =IF(C6=3.5,((C11/360)*PI()*(C19^2)*3)+((C12/360)*PI()*(C19^2)),(C11/360)*PI()*(C19^2)*C6) -> 1079.7243 | D25: mm2
B26: Density | C26: =VLOOKUP(C23,Density,2,0) -> 1.35 | D26: g/cm3
B28: Inner Sheath
B29: Material | C29: PVC
B30: Minimum Thickness | C30: 0.6 | D30: mm
B31: Calculated diameter below innersheath | C31: =C37-2*C30 -> 40.7 | D31: mm
B32: Density of Conductor | C32: =VLOOKUP(C29,Density,2,0) -> 1.35 | D32: g/cm3
B34: Armour
B35: Material | C35: Unarmored
B36: Thickness of armour | C36: 0 | D36: mm
B37: Calculated diameter below armor | C37: =C43-2*C36 -> 41.9 | D37: mm
B38: Density of Conductor | C38: =VLOOKUP(C35,Armordensity,2,0) -> 0 | D38: g/cm3
B40: Outer Sheath
B41: Material | C41: PVC
B42: Minimum Thickness | C42: 2.8 | D42: mm
B43: Calculated diameter below outersheath | C43: =C46-(2*C42) -> 41.9 | D43: mm
B44: Density of Conductor | C44: =VLOOKUP(C41,Density,2,0) -> 1.35 | D44: g/cm3
B46: Overall OD of Cable | C46: 47.5
A48: ="COST SHEET FOR "&C6 & " CORE "&C9&" SQMM "&C10&" CABLE" -> COST SHEET FOR 3 CORE 240 SQMM Aluminium CABLE
A50: ASSUMPTIONS | G50: CALCULATION - SCENARIO 1
B52: Wastage Assumptions | H52: Material Cost Estimation | J52: Loading | K52: %
B53: =C10 -> Aluminium | C53: 0.02 | H53: ="Cost of"&" "&C10 -> Cost of Aluminium | L53: Rs | M53: =D67*C60 -> 256088.95
B54: Steel | C54: 0.02 | H54: Cost of PVC | L54: Rs | M54: =IF(C17="PVC",(D68+D69+D70+D72)*C61,(D69+D70+D72)*C61) -> 48958.073
B55: PVC | C55: 0.025 | H55: Cost of Steel | L55: Rs | M55: =D71*C62 -> 0
B56: XLPE | C56: 0.025 | H56: Cost of XLPE | L56: Rs | M56: =IF(C17="XLPE",D68*C63,0) -> 30892.51
H57: Material Cost per Km | L57: Rs | M57: =M53+M54+M55+M56 -> 335939.54
B58: Price Assumptions
B59: Material | C59: Rs/Kg | H59: Other Costs as a % of Total Cost
B60: =C10 -> Aluminium | C60: =VLOOKUP(B60,'Data Input'!$M$3:$N$6,2,0) -> 129.15 | H60: Other Manufacturing Costs | L60: Rs | M60: =C78/$C$77*$M$57 -> 19761.149
B61: PVC | C61: =VLOOKUP(B61,'Data Input'!$M$3:$N$6,2,0) -> 75.075 | H61: Energy Cost | L61: Rs | M61: =M57/C77*C79 -> 11856.689
B62: Steel Wire | C62: =VLOOKUP(B62,'Data Input'!$M$3:$N$6,2,0) -> 42 | H62: Labour Cost | L62: Rs | M62: =$M$57/$C$77*C80 -> 7904.4597
B63: XLPE | C63: =(1+E63)*C61 -> 90.09 | D63: 20% over PVC | E63: 0.2 | H63: Administrative and Other Expenses | L63: Rs | M63: =$M$57/$C$77*C81 -> 11856.689
H64: Overheads and Finance Costs | L64: Rs | M64: =$M$57/$C$77*C82 -> 7904.4597
B65: Material Composition Estimates per Km of Cable | H65: Total Costs | L65: Rs | M65: =SUM(M60:M64)+M57 -> 395222.98
B66: =C6&" core"&" "&C9&" sq.mm"&" "&C10&" cable" -> 3 core 240 sq.mm Aluminium cable | C66: Used in Cable (Kg) | D66: Including Wastage (Kg)
B67: ="Weight of"&" "&C10 -> Weight of Aluminium | C67: =(C9*10^-3*C14*10^3*IF(C6=3.5,3,C6))+(C9*10^-3*C14*10^3*IF(C6=3.5,1,0)) -> 1944 | D67: =C67*(1+C53) -> 1982.88 | H67: Special Construction costs
B68: Weight of Insulation | C68: =IF(C6=3.5,((C11/360)*PI()*(C19^2-C13^2)*C20*3)+((C12/360)*PI()*(C19^2-C13^2)*C20),(C11/360)*PI()*(C19^2-C13^2)*C20*C6) -> 334.54362 | D68: =C68*(1+C55) -> 342.90721 | H68: FRLS PVC inner sheath construction cost | J68: Y | K68: 0.025 | L68: Rs | M68: =IF(J68="Y",K68*$M$65,0) -> 9880.5746
B69: Weight of Inner Sheath | C69: =PI()*($C$37^2-$C$31^2)/4*$C$32 -> 105.0957 | D69: =C69*(1+C55) -> 107.72309 | H69: FRLS PVC outer sheath construction cost | J69: Y | K69: 0.025 | L69: Rs | M69: =IF(J69="Y",K69*$M$65,0) -> 9880.5746
B70: Weight of Outer Sheath | C70: =PI()*($C$46^2-$C$43^2)/4*$C$44 -> 530.82234 | D70: =C70*(1+C55) -> 544.0929 | H70: LSZH Inner sheath construction cost | J70: N | K70: 0.1 | L70: Rs | M70: =IF(J70="Y",K70*$M$65,0) -> 0
B71: Weight of Armour | C71: =PI()*($C$43^2-$C$37^2)/4*$C$38 -> 0 | D71: =C71*(1+C54) -> 0 | H71: LSZH outersheath construction cost | J71: N | K71: 0.1 | L71: Rs | M71: =IF(J71="Y",K71*$M$65,0) -> 0
B72: Weight of PVC Filler | C72: =(C24-C25)*C26/1000 -> 0.29872784 | D72: =C72*(1+C55) -> 0.30619604 | H72: Oxygen Index(Outer sheath) | J72: N | K72: 0.025 | L72: Rs | M72: =IF(J72="Y",K72*$M$65,0) -> 0
H73: HRPVC Inner Sheath | J73: N | K73: 0.02 | L73: Rs | M73: =IF(J73="Y",K73*$M$65,0) -> 0
H74: HRPVC Outer Sheath | J74: N | K74: 0.02 | L74: Rs | M74: =IF(J74="Y",K74*$M$65,0) -> 0
H75: Extruded PVC Inner sheath- Upto 50 sq.mm | J75: N | K75: 0.03 | L75: Rs | M75: =IF(J75="Y",K75*$M$65,0) -> 0
B76: Costs as a % of Material Cost | C76: % | H76: Extruded PVC Inner sheath-70 sq.mm | J76: N | K76: 0.025 | L76: Rs | M76: =IF(J76="Y",K76*$M$65,0) -> 0
B77: Material Costs | C77: 0.85 | H77: Stranding of Conductor | J77: N | K77: 0.015 | L77: Rs | M77: =IF(J77="Y",K77*$M$65,0) -> 0
B78: Other Manufacturing expenses | C78: 0.05 | H78: Total Cable Costs | L78: Rs | M78: =M65+SUM(M68:M77) -> 414984.13
B79: Energy Costs | C79: 0.03
B80: Labour Costs | C80: 0.02 | H80: Selling Price | M80: =M78*(1+C84) -> 446107.94
B81: Administrative and Other expenses | C81: 0.03
B82: Overheads and Finance Costs | C82: 0.02
B84: Margins | C84: 0.075

Sheet Al LT Cables (4 x 6)
B1: =#REF! -> #REF! | C1: =SUM(D67:D72) -> 222.11213
B2: ="Cost Sheet for"&" "&C6&" Core"&" "&C9&" sq.mm"&" "&C10&" Cable" -> Cost Sheet for 4 Core 6 sq.mm Aluminium Cable
B4: Data Inputs
B6: No. of cores | C6: 4
B7: Shape of the core | C7: Sector shaped
B8: Conductor
B9: Conductor Size (in sq. mm) | C9: 6 | D9: sq. mm
B10: Conductor Material | C10: Aluminium | L10: =2*L9 -> 0
B11: Angle - Main | C11: =IF(C7="Sector shaped", (360/C6),360) -> 90
B12: Angle - Main | C12: =IF(C7="Sector shaped",360-C11*3,0) -> 90
B13: Conductor Radius | C13: =SQRT((C9*(360/C11))/PI()) -> 2.7639532 | D13: mm
B14: Density of Conductor | C14: =VLOOKUP(C10,Density1,2,0) -> 2.7 | D14: g/cm3
B16: Insulation
B17: Material | C17: XLPE
B18: Nominal thickness of insulation | C18: 0.7
B19: Calculated radius over insulation | C19: =IF(C7="Circular", C13+C18,C13+2*C18) -> 4.1639532 | D19: mm
B20: Density of Conductor | C20: =VLOOKUP(C17,Density,2,0) -> 0.93 | D20: g/cm3
B22: PVC Filler
B23: Filler Type | C23: PVC
B24: Area below inner sheath | C24: =PI()*((C31/2)^2) -> 109.35884 | D24: mm2
B25: Area till insulation | C25: =IF(C6=3.5,((C11/360)*PI()*(C19^2)*3)+((C12/360)*PI()*(C19^2)),(C11/360)*PI()*(C19^2)*C6) -> 54.470524 | D25: mm2
B26: Density | C26: =VLOOKUP(C23,Density,2,0) -> 1.35 | D26: g/cm3
B28: Inner Sheath
B29: Material | C29: PVC
B30: Minimum Thickness | C30: 0.3 | D30: mm
B31: Calculated diameter below innersheath | C31: =C37-2*C30 -> 11.8 | D31: mm
B32: Density of Conductor | C32: =VLOOKUP(C29,Density,2,0) -> 1.35 | D32: g/cm3
B34: Armour
B35: Material | C35: Unarmored
B36: Thickness of armour | C36: 0 | D36: mm
B37: Calculated diameter below armor | C37: =C43-2*C36 -> 12.4 | D37: mm
B38: Density of Conductor | C38: =VLOOKUP(C35,Armordensity,2,0) -> 0 | D38: g/cm3
B40: Outer Sheath
B41: Material | C41: PVC
B42: Minimum Thickness | C42: 1.8 | D42: mm
B43: Calculated diameter below outersheath | C43: =C46-(2*C42) -> 12.4 | D43: mm
B44: Density of Conductor | C44: =VLOOKUP(C41,Density,2,0) -> 1.35 | D44: g/cm3
B46: Overall OD of Cable | C46: 16
A48: ="COST SHEET FOR "&C6 & " CORE "&C9&" SQMM "&C10&" CABLE" -> COST SHEET FOR 4 CORE 6 SQMM Aluminium CABLE
A50: ASSUMPTIONS | G50: CALCULATION - SCENARIO 1
B52: Wastage Assumptions | H52: Material Cost Estimation | J52: Loading | K52: %
B53: =C10 -> Aluminium | C53: 0.02 | H53: ="Cost of"&" "&C10 -> Cost of Aluminium | L53: Rs | M53: =D67*C60 -> 8536.2984
B54: Steel | C54: 0.02 | H54: Cost of PVC | L54: Rs | M54: =IF(C17="PVC",(D68+D69+D70+D72)*C61,(D69+D70+D72)*C61) -> 9532.2804
B55: PVC | C55: 0.025 | H55: Cost of Steel | L55: Rs | M55: =D71*C62 -> 0
B56: XLPE | C56: 0.025 | H56: Cost of XLPE | L56: Rs | M56: =IF(C17="XLPE",D68*C63,0) -> 2616.7566
H57: Material Cost per Km | L57: Rs | M57: =M53+M54+M55+M56 -> 20685.335
B58: Price Assumptions
B59: Material | C59: Rs/Kg | H59: Other Costs as a % of Total Cost
B60: =C10 -> Aluminium | C60: =VLOOKUP(B60,'Data Input'!$M$3:$N$6,2,0) -> 129.15 | H60: Other Manufacturing Costs | L60: Rs | M60: =C78/$C$77*$M$57 -> 1216.7844
B61: PVC | C61: =VLOOKUP(B61,'Data Input'!$M$3:$N$6,2,0) -> 75.075 | H61: Energy Cost | L61: Rs | M61: =M57/C77*C79 -> 730.07066
B62: Steel Wire | C62: =VLOOKUP(B62,'Data Input'!$M$3:$N$6,2,0) -> 42 | H62: Labour Cost | L62: Rs | M62: =$M$57/$C$77*C80 -> 486.71377
B63: XLPE | C63: =(1+E63)*C61 -> 90.09 | D63: 20% over PVC | E63: 0.2 | H63: Administrative and Other Expenses | L63: Rs | M63: =$M$57/$C$77*C81 -> 730.07066
H64: Overheads and Finance Costs | L64: Rs | M64: =$M$57/$C$77*C82 -> 486.71377
B65: Material Composition Estimates per Km of Cable | H65: Total Costs | L65: Rs | M65: =SUM(M60:M64)+M57 -> 24335.689
B66: =C6&" core"&" "&C9&" sq.mm"&" "&C10&" cable" -> 4 core 6 sq.mm Aluminium cable | C66: Used in Cable (Kg) | D66: Including Wastage (Kg)
B67: ="Weight of"&" "&C10 -> Weight of Aluminium | C67: =(C9*10^-3*C14*10^3*IF(C6=3.5,3,C6))+(C9*10^-3*C14*10^3*IF(C6=3.5,1,0)) -> 64.8 | D67: =C67*(1+C53) -> 66.096 | H67: Special Construction costs
B68: Weight of Insulation | C68: =IF(C6=3.5,((C11/360)*PI()*(C19^2-C13^2)*C20*3)+((C12/360)*PI()*(C19^2-C13^2)*C20),(C11/360)*PI()*(C19^2-C13^2)*C20*C6) -> 28.337587 | D68: =C68*(1+C55) -> 29.046027 | H68: FRLS PVC inner sheath construction cost | J68: Y | K68: 0.025 | L68: Rs | M68: =IF(J68="Y",K68*$M$65,0) -> 608.39222
B69: Weight of Inner Sheath | C69: =PI()*($C$37^2-$C$31^2)/4*$C$32 -> 15.395375 | D69: =C69*(1+C55) -> 15.780259 | H69: FRLS PVC outer sheath construction cost | J69: Y | K69: 0.025 | L69: Rs | M69: =IF(J69="Y",K69*$M$65,0) -> 608.39222
B70: Weight of Outer Sheath | C70: =PI()*($C$46^2-$C$43^2)/4*$C$44 -> 108.4038 | D70: =C70*(1+C55) -> 111.11389 | H70: LSZH Inner sheath construction cost | J70: N | K70: 0.1 | L70: Rs | M70: =IF(J70="Y",K70*$M$65,0) -> 0
B71: Weight of Armour | C71: =PI()*($C$43^2-$C$37^2)/4*$C$38 -> 0 | D71: =C71*(1+C54) -> 0 | H71: LSZH outersheath construction cost | J71: N | K71: 0.1 | L71: Rs | M71: =IF(J71="Y",K71*$M$65,0) -> 0
B72: Weight of PVC Filler | C72: =(C24-C25)*C26/1000 -> 0.074099227 | D72: =C72*(1+C55) -> 0.075951708 | H72: Oxygen Index(Outer sheath) | J72: N | K72: 0.025 | L72: Rs | M72: =IF(J72="Y",K72*$M$65,0) -> 0
H73: HRPVC Inner Sheath | J73: N | K73: 0.02 | L73: Rs | M73: =IF(J73="Y",K73*$M$65,0) -> 0
H74: HRPVC Outer Sheath | J74: N | K74: 0.02 | L74: Rs | M74: =IF(J74="Y",K74*$M$65,0) -> 0
H75: Extruded PVC Inner sheath- Upto 50 sq.mm | J75: N | K75: 0.03 | L75: Rs | M75: =IF(J75="Y",K75*$M$65,0) -> 0
B76: Costs as a % of Material Cost | C76: % | H76: Extruded PVC Inner sheath-70 sq.mm | J76: N | K76: 0.025 | L76: Rs | M76: =IF(J76="Y",K76*$M$65,0) -> 0
B77: Material Costs | C77: 0.85 | H77: Stranding of Conductor | J77: N | K77: 0.015 | L77: Rs | M77: =IF(J77="Y",K77*$M$65,0) -> 0
B78: Other Manufacturing expenses | C78: 0.05 | H78: Total Cable Costs | L78: Rs | M78: =M65+SUM(M68:M77) -> 25552.473
B79: Energy Costs | C79: 0.03
B80: Labour Costs | C80: 0.02 | H80: Selling Price | M80: =M78*(1+C84) -> 27468.909
B81: Administrative and Other expenses | C81: 0.03
B82: Overheads and Finance Costs | C82: 0.02
B84: Margins | C84: 0.075

Sheet Al LT Cables (4 x 10)
B1: =#REF! -> #REF! | C1: =SUM(D67:D72) -> 291.20219
B2: ="Cost Sheet for"&" "&C6&" Core"&" "&C9&" sq.mm"&" "&C10&" Cable" -> Cost Sheet for 4 Core 10 sq.mm Aluminium Cable
B4: Data Inputs
B6: No. of cores | C6: 4
B7: Shape of the core | C7: Sector shaped
B8: Conductor
B9: Conductor Size (in sq. mm) | C9: 10 | D9: sq. mm
B10: Conductor Material | C10: Aluminium | L10: =2*L9 -> 0
B11: Angle - Main | C11: =IF(C7="Sector shaped", (360/C6),360) -> 90
B12: Angle - Main | C12: =IF(C7="Sector shaped",360-C11*3,0) -> 90
B13: Conductor Radius | C13: =SQRT((C9*(360/C11))/PI()) -> 3.5682482 | D13: mm
B14: Density of Conductor | C14: =VLOOKUP(C10,Density1,2,0) -> 2.7 | D14: g/cm3
B16: Insulation
B17: Material | C17: XLPE
B18: Nominal thickness of insulation | C18: 0.7
B19: Calculated radius over insulation | C19: =IF(C7="Circular", C13+C18,C13+2*C18) -> 4.9682482 | D19: mm
B20: Density of Conductor | C20: =VLOOKUP(C17,Density,2,0) -> 0.93 | D20: g/cm3
B22: PVC Filler
B23: Filler Type | C23: PVC
B24: Area below inner sheath | C24: =PI()*((C31/2)^2) -> 149.57123 | D24: mm2
B25: Area till insulation | C25: =IF(C6=3.5,((C11/360)*PI()*(C19^2)*3)+((C12/360)*PI()*(C19^2)),(C11/360)*PI()*(C19^2)*C6) -> 77.545472 | D25: mm2
B26: Density | C26: =VLOOKUP(C23,Density,2,0) -> 1.35 | D26: g/cm3
B28: Inner Sheath
B29: Material | C29: PVC
B30: Minimum Thickness | C30: 0.3 | D30: mm
B31: Calculated diameter below innersheath | C31: =C37-2*C30 -> 13.8 | D31: mm
B32: Density of Conductor | C32: =VLOOKUP(C29,Density,2,0) -> 1.35 | D32: g/cm3
B34: Armour
B35: Material | C35: Unarmored
B36: Thickness of armour | C36: 0 | D36: mm
B37: Calculated diameter below armor | C37: =C43-2*C36 -> 14.4 | D37: mm
B38: Density of Conductor | C38: =VLOOKUP(C35,Armordensity,2,0) -> 0 | D38: g/cm3
B40: Outer Sheath
B41: Material | C41: PVC
B42: Minimum Thickness | C42: 1.8 | D42: mm
B43: Calculated diameter below outersheath | C43: =C46-(2*C42) -> 14.4 | D43: mm
B44: Density of Conductor | C44: =VLOOKUP(C41,Density,2,0) -> 1.35 | D44: g/cm3
B46: Overall OD of Cable | C46: 18
A48: ="COST SHEET FOR "&C6 & " CORE "&C9&" SQMM "&C10&" CABLE" -> COST SHEET FOR 4 CORE 10 SQMM Aluminium CABLE
A50: ASSUMPTIONS | G50: CALCULATION - SCENARIO 1
B52: Wastage Assumptions | H52: Material Cost Estimation | J52: Loading | K52: %
B53: =C10 -> Aluminium | C53: 0.02 | H53: ="Cost of"&" "&C10 -> Cost of Aluminium | L53: Rs | M53: =D67*C60 -> 14227.164
B54: Steel | C54: 0.02 | H54: Cost of PVC | L54: Rs | M54: =IF(C17="PVC",(D68+D69+D70+D72)*C61,(D69+D70+D72)*C61) -> 10904.791
B55: PVC | C55: 0.025 | H55: Cost of Steel | L55: Rs | M55: =D71*C62 -> 0
B56: XLPE | C56: 0.025 | H56: Cost of XLPE | L56: Rs | M56: =IF(C17="XLPE",D68*C63,0) -> 3224.3411
H57: Material Cost per Km | L57: Rs | M57: =M53+M54+M55+M56 -> 28356.296
B58: Price Assumptions
B59: Material | C59: Rs/Kg | H59: Other Costs as a % of Total Cost
B60: =C10 -> Aluminium | C60: =VLOOKUP(B60,'Data Input'!$M$3:$N$6,2,0) -> 129.15 | H60: Other Manufacturing Costs | L60: Rs | M60: =C78/$C$77*$M$57 -> 1668.0174
B61: PVC | C61: =VLOOKUP(B61,'Data Input'!$M$3:$N$6,2,0) -> 75.075 | H61: Energy Cost | L61: Rs | M61: =M57/C77*C79 -> 1000.8105
B62: Steel Wire | C62: =VLOOKUP(B62,'Data Input'!$M$3:$N$6,2,0) -> 42 | H62: Labour Cost | L62: Rs | M62: =$M$57/$C$77*C80 -> 667.20698
B63: XLPE | C63: =(1+E63)*C61 -> 90.09 | D63: 20% over PVC | E63: 0.2 | H63: Administrative and Other Expenses | L63: Rs | M63: =$M$57/$C$77*C81 -> 1000.8105
H64: Overheads and Finance Costs | L64: Rs | M64: =$M$57/$C$77*C82 -> 667.20698
B65: Material Composition Estimates per Km of Cable | H65: Total Costs | L65: Rs | M65: =SUM(M60:M64)+M57 -> 33360.349
B66: =C6&" core"&" "&C9&" sq.mm"&" "&C10&" cable" -> 4 core 10 sq.mm Aluminium cable | C66: Used in Cable (Kg) | D66: Including Wastage (Kg)
B67: ="Weight of"&" "&C10 -> Weight of Aluminium | C67: =(C9*10^-3*C14*10^3*IF(C6=3.5,3,C6))+(C9*10^-3*C14*10^3*IF(C6=3.5,1,0)) -> 108 | D67: =C67*(1+C53) -> 110.16 | H67: Special Construction costs
B68: Weight of Insulation | C68: =IF(C6=3.5,((C11/360)*PI()*(C19^2-C13^2)*C20*3)+((C12/360)*PI()*(C19^2-C13^2)*C20),(C11/360)*PI()*(C19^2-C13^2)*C20*C6) -> 34.917289 | D68: =C68*(1+C55) -> 35.790222 | H68: FRLS PVC inner sheath construction cost | J68: Y | K68: 0.025 | L68: Rs | M68: =IF(J68="Y",K68*$M$65,0) -> 834.00872
B69: Weight of Inner Sheath | C69: =PI()*($C$37^2-$C$31^2)/4*$C$32 -> 17.940065 | D69: =C69*(1+C55) -> 18.388566 | H69: FRLS PVC outer sheath construction cost | J69: Y | K69: 0.025 | L69: Rs | M69: =IF(J69="Y",K69*$M$65,0) -> 834.00872
B70: Weight of Outer Sheath | C70: =PI()*($C$46^2-$C$43^2)/4*$C$44 -> 123.67194 | D70: =C70*(1+C55) -> 126.76373 | H70: LSZH Inner sheath construction cost | J70: N | K70: 0.1 | L70: Rs | M70: =IF(J70="Y",K70*$M$65,0) -> 0
B71: Weight of Armour | C71: =PI()*($C$43^2-$C$37^2)/4*$C$38 -> 0 | D71: =C71*(1+C54) -> 0 | H71: LSZH outersheath construction cost | J71: N | K71: 0.1 | L71: Rs | M71: =IF(J71="Y",K71*$M$65,0) -> 0
B72: Weight of PVC Filler | C72: =(C24-C25)*C26/1000 -> 0.097234768 | D72: =C72*(1+C55) -> 0.099665637 | H72: Oxygen Index(Outer sheath) | J72: N | K72: 0.025 | L72: Rs | M72: =IF(J72="Y",K72*$M$65,0) -> 0
H73: HRPVC Inner Sheath | J73: N | K73: 0.02 | L73: Rs | M73: =IF(J73="Y",K73*$M$65,0) -> 0
H74: HRPVC Outer Sheath | J74: N | K74: 0.02 | L74: Rs | M74: =IF(J74="Y",K74*$M$65,0) -> 0
H75: Extruded PVC Inner sheath- Upto 50 sq.mm | J75: N | K75: 0.03 | L75: Rs | M75: =IF(J75="Y",K75*$M$65,0) -> 0
B76: Costs as a % of Material Cost | C76: % | H76: Extruded PVC Inner sheath-70 sq.mm | J76: N | K76: 0.025 | L76: Rs | M76: =IF(J76="Y",K76*$M$65,0) -> 0
B77: Material Costs | C77: 0.85 | H77: Stranding of Conductor | J77: N | K77: 0.015 | L77: Rs | M77: =IF(J77="Y",K77*$M$65,0) -> 0
B78: Other Manufacturing expenses | C78: 0.05 | H78: Total Cable Costs | L78: Rs | M78: =M65+SUM(M68:M77) -> 35028.366
B79: Energy Costs | C79: 0.03
B80: Labour Costs | C80: 0.02 | H80: Selling Price | M80: =M78*(1+C84) -> 37655.494
B81: Administrative and Other expenses | C81: 0.03
B82: Overheads and Finance Costs | C82: 0.02
B84: Margins | C84: 0.075

Sheet Al LT Cables (4 x 16)
B1: =#REF! -> #REF! | C1: =SUM(D67:D72) -> 374.33992
B2: ="Cost Sheet for"&" "&C6&" Core"&" "&C9&" sq.mm"&" "&C10&" Cable" -> Cost Sheet for 4 Core 16 sq.mm Aluminium Cable
B4: Data Inputs
B6: No. of cores | C6: 4
B7: Shape of the core | C7: Sector shaped
B8: Conductor
B9: Conductor Size (in sq. mm) | C9: 16 | D9: sq. mm
B10: Conductor Material | C10: Aluminium | L10: =2*L9 -> 0
B11: Angle - Main | C11: =IF(C7="Sector shaped", (360/C6),360) -> 90
B12: Angle - Main | C12: =IF(C7="Sector shaped",360-C11*3,0) -> 90
B13: Conductor Radius | C13: =SQRT((C9*(360/C11))/PI()) -> 4.5135167 | D13: mm
B14: Density of Conductor | C14: =VLOOKUP(C10,Density1,2,0) -> 2.7 | D14: g/cm3
B16: Insulation
B17: Material | C17: XLPE
B18: Nominal thickness of insulation | C18: 0.7
B19: Calculated radius over insulation | C19: =IF(C7="Circular", C13+C18,C13+2*C18) -> 5.9135167 | D19: mm
B20: Density of Conductor | C20: =VLOOKUP(C17,Density,2,0) -> 0.93 | D20: g/cm3
B22: PVC Filler
B23: Filler Type | C23: PVC
B24: Area below inner sheath | C24: =PI()*((C31/2)^2) -> 172.03361 | D24: mm2
B25: Area till insulation | C25: =IF(C6=3.5,((C11/360)*PI()*(C19^2)*3)+((C12/360)*PI()*(C19^2)),(C11/360)*PI()*(C19^2)*C6) -> 109.86049 | D25: mm2
B26: Density | C26: =VLOOKUP(C23,Density,2,0) -> 1.35 | D26: g/cm3
B28: Inner Sheath
B29: Material | C29: PVC
B30: Minimum Thickness | C30: 0.3 | D30: mm
B31: Calculated diameter below innersheath | C31: =C37-2*C30 -> 14.8 | D31: mm
B32: Density of Conductor | C32: =VLOOKUP(C29,Density,2,0) -> 1.35 | D32: g/cm3
B34: Armour
B35: Material | C35: Unarmored
B36: Thickness of armour | C36: 0 | D36: mm
B37: Calculated diameter below armor | C37: =C43-2*C36 -> 15.4 | D37: mm
B38: Density of Conductor | C38: =VLOOKUP(C35,Armordensity,2,0) -> 0 | D38: g/cm3
B40: Outer Sheath
B41: Material | C41: PVC
B42: Minimum Thickness | C42: 1.8 | D42: mm
B43: Calculated diameter below outersheath | C43: =C46-(2*C42) -> 15.4 | D43: mm
B44: Density of Conductor | C44: =VLOOKUP(C41,Density,2,0) -> 1.35 | D44: g/cm3
B46: Overall OD of Cable | C46: 19
A48: ="COST SHEET FOR "&C6 & " CORE "&C9&" SQMM "&C10&" CABLE" -> COST SHEET FOR 4 CORE 16 SQMM Aluminium CABLE
A50: ASSUMPTIONS | G50: CALCULATION - SCENARIO 1
